Workbook

Sheet 表紙
B1: 三菱ケミカルグループ（4188） シナリオ財務モデル
B2: 作成 2026-10-30。単位は億円（株数・1株指標を除く）。年度＝翌年3月期（2026年度＝2027年3月期）
B4: 目的
B5: ・会社予算（2026年度）を起点に、SM 本体は会社計画経路（切替で保守経路）とし、半導体材料（合成石英・リソマックス）・Zoox 向け CFRP・石化の再編（丸善千葉停止、水島停止、分社化と他社との合併）の上振れと下振れを数式で積み上げ、2029年度の中期経営計画の達成可否を JSR なし（ケースA）と JSR あり（ケースB）で比べる。 | H5: DESIGN
B6: ・入力は「前提」シートだけ。合併年度（2028／2029）、BM 公正価値の求め方、Zoox 単価、合成石英・リソマックスの基準売上は前提シートで切り替えられる。 | H6: DESIGN
B8: 2029年度の中計達成状況（中計判定シートの数式参照）
B9: 指標 | C9: 目標 | D9: ケースA | E9: ケースB | F9: 判定A | G9: 判定B
B10: =中計判定!B5&"（"&中計判定!C5&"）" -> 売上収益（億円） | C10: =中計判定!D5 -> 45060 | D10: =中計判定!E5 -> 36452.356 | E10: =中計判定!F5 -> 36452.356 | F10: =中計判定!I5 -> 未達 | G10: =中計判定!J5 -> 未達
B11: =中計判定!B6&"（"&中計判定!C6&"）" -> コア営業利益（億円） | C11: =中計判定!D6 -> 4600 | D11: =中計判定!E6 -> 4101.4401 | E11: =中計判定!F6 -> 4234.8575 | F11: =中計判定!I6 -> 未達 | G11: =中計判定!J6 -> 未達
B12: =中計判定!B7&"（"&中計判定!C7&"）" -> EPS（円） | C12: =中計判定!D7 -> 152 | D12: =中計判定!E7 -> 132.74552 | E12: =中計判定!F7 -> 140.03707 | F12: =中計判定!I7 -> 未達 | G12: =中計判定!J7 -> 未達
B13: =中計判定!B8&"（"&中計判定!C8&"）" -> ROIC（%） | C13: =中計判定!D8 -> 0.07 | D13: =中計判定!E8 -> 0.06803135 | E13: =中計判定!F8 -> 0.067379141 | F13: =中計判定!I8 -> 未達 | G13: =中計判定!J8 -> 未達
B14: =中計判定!B9&"（"&中計判定!C9&"）" -> ネットD/E（以下）（倍） | C14: =中計判定!D9 -> 0.8 | D14: =中計判定!E9 -> 0.54899901 | E14: =中計判定!F9 -> 0.67249423 | F14: =中計判定!I9 -> 達成 | G14: =中計判定!J9 -> 達成
B15: ="・ケースA は5項目中"&中計判定!I10&"項目、ケースB は"&中計判定!J10&"項目を達成。JSR コール："&中計判定!F16&"。BM 合併年度："&中計判定!E17&"年度" -> ・ケースA は5項目中1項目、ケースB は1項目を達成。JSR コール：未到達（44.9%で据え置き）。BM 合併年度：2028年度
B17: 主要前提（前提シートの値）
B18: 前提 | C18: 値 | D18: 単位
B19: BM の合併年度（期首） | C19: =前提!$D$25 -> 2028 | D19: 年度
B20: BM 合弁株式の公正価値（1＝倍率法、2＝簿価） | C20: =前提!$D$26 -> 1 | D20: 番号
B21: 合弁 EV の EV/EBITDA 倍率 | C21: =前提!$D$107 -> 6 | D21: 倍
B22: Zoox 1台あたり売上 | C22: =前提!$D$27 -> 1000 | D22: 万円
B23: Zoox 台数（2027年度以降） | C23: =前提!F10 -> 2500 | D23: 台
B24: 合成石英 2026年度売上（基準） | C24: =前提!$D$28 -> 70 | D24: 億円
B25: リソマックス 2026年度売上（基準） | C25: =前提!$D$29 -> 120 | D25: 億円
B26: WFE 成長率（2027年度） | C26: =前提!F9 -> 0.218 | D26: %
B27: SM 本体の基礎コア利益率（2029年度） | C27: =前提!H7 -> 0.088 | D27: %
B28: MMA&D コア営業利益（2029年度） | C28: =前提!H11 -> 160 | D28: 億円
B29: 産業ガス コア営業利益（2029年度） | C29: =前提!H15 -> 2370 | D29: 億円
B30: 税率（会社予想当期利益に較正） | C30: =前提!$D$122 -> 0.27 | D30: %
B31: 金融費用率 | C31: =前提!$D$121 -> 0.02 | D31: %
B32: JSR 株式価値（報道、二次） | C32: =前提!$D$135 -> 10000 | D32: 億円
B33: SM 本体の基礎経路（1＝会社計画、2＝保守） | C33: =前提!$D$30 -> 1 | D33: 番号
B34: 持分法利益の二重課税を除く（1＝除く） | C34: =前提!$D$32 -> 1 | D34: 番号
B35: JSR 第1段の取得比率 | C35: =前提!$D$138 -> 0.2 | D35: %
B36: JSR 持分法の上限 | C36: =前提!$D$139 -> 0.49 | D36: %
B37: JSR 取得の余力の基準（ネットD/E） | C37: =前提!$D$145 -> 0.8 | D37: 倍
B38: ハイブリッド債で調達（1＝する） | C38: =前提!$D$33 -> 0 | D38: 番号
B40: 読むときの注意
B41: ・2027年度の EPS 低下は、非経常▲400（分社化費用込み）と炭素撤退期の BM 赤字（▲120）による。 | H41: DESIGN
B42: ・合併時の除外損（BM の連結除外）は、実務上は合併前の減損として先行計上されうる。計上年度と区分がずれる可能性がある。 | H42: DIR2
B43: ・BM の公正価値（中間 EBITDA×6倍）は資産規模6,000と見合わない。この差そのものが減損リスクである。 | H43: DIR2
B44: ・JSR の取得（ケースB）は、20%取得後、期首ごとにネットD/E 0.8 の余力の範囲で49%まで買い増し、余力が残り代金＋JSR 純有利子負債を上回った年度に全額取得する。ハイブリッド債の扱いは会社で未確認（切替の既定は使わない）。 | H44: DIR2
B46: ・本ブックは公開情報と仮定に基づく試算で、投資の勧誘や将来の業績の保証を目的としない。

Sheet 前提
B1: 前提（入力はこのシートだけ）
B2: 単位は億円（株数・株価・1株指標を除く）。年度＝翌年3月期（2026年度＝2027年3月期）。青字＝入力。区分：一次／二次／推計／仮定／設計（設計書が置いた値）／切替
B4: 年度別の前提
B5: 項目 | C5: 単位 | D5: 2025年度 | E5: 2026年度 | F5: 2027年度 | G5: 2028年度 | H5: 2029年度 | I5: 2030年度 | J5: 出典ID | K5: 区分 | L5: 備考
B6: 年度（数値） | C6: 年度 | D6: 2025 | E6: 2026 | F6: 2027 | G6: 2028 | H6: 2029 | I6: 2030 | K6: — | L6: 数式の年度判定に使う
B7: SM 本体の基礎コア利益率 | C7: % | E7: 0.073 | F7: 0.078 | G7: 0.083 | H7: 0.088 | I7: 0.09 | J7: DESIGN,M01,M02 | K7: 設計 | L7: 会社中計（新区分2029年度 15,700/1,550、9.9%）より保守的。2026年度は会社予算の900（7.28%）を使い、7.3%は参考表示
B8: ウエハ出荷面積の成長率 | C8: % | F8: 0.06 | G8: 0.06 | H8: 0.05 | I8: 0.05 | J8: SEMI-WAFER,RS-SEMI | K8: 二次 | L8: SEMI 2026-10（2026→29年 年+5.7%）を設計書が年別に配分
B9: WFE（前工程装置）の成長率 | C9: % | F9: 0.218 | G9: 0.141 | H9: 0.05 | I9: 0.03 | J9: SEMI-WFE,DESIGN | K9: 一次（2027〜28）／仮定（2029〜30） | L9: 2027・2028年は SEMI 年央予測。2029・2030年は仮定
B10: Zoox 向け台数 | C10: 台 | E10: 1500 | F10: 2500 | G10: 2500 | H10: 2500 | I10: 2500 | J10: NHTSA-555,QA01,DESIGN | K10: 仮定（上限は二次） | L10: 2026年度1,500台は会社予算に含まれると仮定。2027年度以降は NHTSA 免除上限の年2,500台
B11: MMA&D コア営業利益 | C11: 億円 | E11: 110 | F11: 120 | G11: 140 | H11: 160 | I11: 170 | J11: M03,M08,M42,QA02,DESIGN | K11: 一次（2026）／設計 | L11: 根拠は下の注記（MMA&D）
B12: BM 基礎コア営業利益（市況・稼働率改善前） | C12: 億円 | E12: -50 | F12: -150 | G12: -110 | H12: -90 | I12: -80 | J12: M03,M36,DESIGN | K12: 一次（2026）／設計 | L12: 2028年度で炭素撤退が完了
B13: BM 売上の増減（炭素撤退） | C13: 億円 | F13: -500 | G13: -500 | J13: M36,DESIGN | K13: 設計 | L13: 炭素の下期撤退で2027年度▲500、2028年度▲500
B14: BM 売上の成長率（2029年度以降） | C14: % | H14: -0.02 | I14: -0.02 | J14: DESIGN | K14: 設計
B15: 産業ガス コア営業利益 | C15: 億円 | E15: 2050 | F15: 2150 | G15: 2260 | H15: 2370 | I15: 2480 | J15: M03,G02,DESIGN | K15: 一次（2026）／設計 | L15: 日本酸素 NI2030 の2,500〜2,750より保守的
B16: その他 コア営業利益 | C16: 億円 | E16: 40 | F16: 0 | G16: 0 | H16: 0 | I16: 0 | J16: M03,DESIGN | K16: 一次（2026）／設計
B17: 非経常損益（分社化費用・合併除外損益を除く） | C17: 億円 | E17: -50 | F17: -350 | G17: -400 | H17: -300 | I17: -300 | J17: M03,DESIGN | K17: 一次（2026）／設計 | L17: 設計書の2027年度▲400は分社化費用▲50込み。ここでは▲350＋分社化費用（下の単一値）に分けた
B18: 設備投資（BM 控除前。合併年度以降▲280） | C18: 億円 | E18: 3391 | F18: 3300 | G18: 3200 | H18: 3000 | I18: 3000 | J18: M03,DESIGN | K18: 一次（2026）／設計 | L18: 合併年度以降は BM 分を控除（単一値）
B19: 減価償却（2028年度以降は BM 分を除いた後の値） | C19: 億円 | E19: 2794 | F19: 2850 | G19: 2600 | H19: 2650 | I19: 2700 | J19: M03,DESIGN,DIR2 | K19: 一次（2026）／設計 | L19: 2028年度以降の列は BM 控除後。合併年度を2029にすると、2028年度に BM 分270を足し戻す
B20: JSR コア営業利益（基礎、フォトレジスト上振れ前） | C20: 億円 | E20: 600 | F20: 680 | G20: 760 | H20: 840 | I20: 920 | J20: JSR-YUHO,DESIGN | K20: 設計 | L20: 2025年度 405＋減損116＝521から成長。2030年までにコア1,000の目標を8%割引
B21: 注1：MMA&D の経路（110→170）の根拠：中国の能力が年16%増（2021〜25年）で需要を上回る。欧州撤退で生産が中国へ移り、地域分断で約30%シェアの事業モデルが崩れたと会社自身が認める（M08）。ルイジアナ新工場は長期契約が取れず2025年1月に中止（M42）。価格は紛争前1,400ドル弱→足元1,600〜1,700ドルだが中東要因の一時性が高い（QA02・QA01）。サウジ停止・台湾売却で当社能力も縮む。中計の MMA 450（利益率14%）には遠い。
B23: 切替（感応度・シナリオ）
B24: 項目 | C24: 単位 | D24: 値 | J24: 出典ID | K24: 区分 | L24: 備考
B25: BM の他社との合併年度（期首。2028 または 2029） | C25: 年度 | D25: 2028 | J25: DESIGN | K25: 切替 | L25: IF で連結範囲・持分法・除外損益・設備投資控除が切り替わる
B26: BM 合弁株式の公正価値の求め方（1＝倍率法、2＝簿価） | C26: 番号 | D26: 1 | J26: DESIGN | K26: 切替 | L26: 2＝簿価は再測定損益ゼロの比較用（追加の仮定）
B27: Zoox 1台あたり売上 | C27: 万円 | D27: 1000 | J27: RS-ZOOX,M01,DESIGN | K27: 推計 | L27: 幅600〜1,600万円。1Q のサブセグメント増収+102億円と生産ペースからの逆算
B28: 合成石英 2026年度売上（基準） | C28: 億円 | D28: 70 | J28: RS-SEMI,DESIGN | K28: 仮定 | L28: 開示なし。推計幅30〜150
B29: リソマックス 2026年度売上（基準） | C29: 億円 | D29: 120 | J29: RS-SEMI,DESIGN | K29: 仮定 | L29: 開示なし。幅60〜200
B30: SM 本体の基礎経路（1＝会社計画、2＝保守経路） | C30: 番号 | D30: 1 | J30: DIR2,M01,M02 | K30: 切替 | L30: 会社計画：2029年度 15,700/1,550 へ線形。保守：+4%/年・利益率7.8〜9.0%
B31: JSR 全額取得年度の上書き（0＝自動判定） | C31: 年度 | D31: 0 | J31: DIR2 | K31: 切替（追加） | L31: 0 以外を入れるとその年度の期首に残り全株を取得（比較用）
B32: 持分法利益への法人税の二重課税を除く（1＝除く、0＝設計書の当初式） | C32: 番号 | D32: 1 | J32: DIR2 | K32: 切替 | L32: 持分法利益は税後の値なので連結の27%を掛けない。ROIC の分子も（コア−持分法）×(1−30%)＋持分法
B33: JSR 取得資金をハイブリッド債で一部調達（0＝しない、1＝する） | C33: 番号 | D33: 0 | J33: DIR2 | K33: 切替（仮定） | L33: 会社のハイブリッド債の扱い（発行有無・資本性評価）は未確認（M01・M03・M24・M15 を検索して記載なし）
B34: 2026年度 会社予算（セグメント、M03 p20）
B35: 項目 | C35: 単位 | D35: 値 | J35: 出典ID | K35: 区分 | L35: 備考
B36: スペシャリティ（SM）売上 | C36: 億円 | D36: 12370 | J36: M03 | K36: 一次
B37: スペシャリティ（SM）コア営業利益 | C37: 億円 | D37: 900 | J37: M03 | K37: 一次
B38: MMA&D 売上 | C38: 億円 | D38: 3490 | J38: M03 | K38: 一次
B39: ベーシック（BM）売上 | C39: 億円 | D39: 6830 | J39: M03 | K39: 一次
B40: その他 売上 | C40: 億円 | D40: 1590 | J40: M03 | K40: 一次
B41: 産業ガス 売上 | C41: 億円 | D41: 13720 | J41: M03 | K41: 一次
B42: 会社予算 売上合計 | C42: 億円 | D42: 38000 | J42: M03 | K42: 一次 | L42: 検証用
B43: 会社予算 コア営業利益合計 | C43: 億円 | D43: 3050 | J43: M03 | K43: 一次 | L43: 検証用
B44: 会社予想 EPS（2026年度） | C44: 円 | D44: 93.5 | J44: M03 | K44: 一次 | L44: 検証用（±5%）
B45: 会社予想 親会社当期利益（2026年度） | C45: 億円 | D45: 1270 | J45: M03 | K45: 一次 | L45: 税率27%の較正先
B46: スペシャリティ（SM）本体・その他・産業ガス・MMA&D
B47: 項目 | C47: 単位 | D47: 値 | J47: 出典ID | K47: 区分 | L47: 備考
B48: SM 本体の売上成長率（保守経路） | C48: %/年 | D48: 0.04 | J48: DESIGN | K48: 設計
B49: SM 会社計画 売上（終点年度） | C49: 億円 | D49: 15700 | J49: M02,M01 | K49: 一次 | L49: 新区分の中計（2029年度）
B50: SM 会社計画 コア営業利益（終点年度） | C50: 億円 | D50: 1550 | J50: M01 | K50: 一次 | L50: M01 p23：900→1,090→1,290→1,550。ここでは指示どおり線形（1,117・1,333）
B51: SM 会社計画の終点年度 | C51: 年度 | D51: 2029 | J51: M01,DIR2 | K51: 一次 | L51: 2026年度から線形
B52: SM 会社計画経路：終点後の売上成長率 | C52: %/年 | D52: 0.04 | J52: DIR2 | K52: 指示
B53: SM 会社計画経路：終点後のコア利益率 | C53: % | D53: 0.1 | J53: DIR2 | K53: 指示
B54: MMA&D 売上成長率 | C54: %/年 | D54: 0.01 | J54: DESIGN | K54: 設計
B55: その他 売上成長率 | C55: %/年 | D55: 0 | J55: DESIGN | K55: 仮定（追加） | L55: 設計書に記載なし。横ばいと置いた
B56: 産業ガス 売上成長率 | C56: %/年 | D56: 0.04 | J56: DESIGN | K56: 設計
B57: 合成石英（D_半導体）
B58: 項目 | C58: 単位 | D58: 値 | J58: 出典ID | K58: 区分 | L58: 備考
B59: 合成石英 コア利益率（参考表示） | C59: % | D59: 0.2 | J59: DESIGN | K59: 仮定
B60: 会社計画経路の成長率（2026→29、棒高さ1.60→2.00倍） | C60: %/年 | D60: 0.077 | J60: M02,RS-SEMI | K60: 一次（計測値） | L60: 2024→29年 +15%/年（2026年説明会 p36）
B61: 需要：WFE 成長に掛ける係数（新規ファブ立上げ分） | C61: 倍 | D61: 0.25 | J61: DESIGN | K61: 仮定
B62: 能力指数 2026年度（完売＝需要指数の基準も1） | C62: 指数 | D62: 1 | J62: QA01,RS-SEMI | K62: 一次 | L62: 現有能力でフル販売
B63: 能力：小改良による増分 | C63: 指数 | D63: 0.05 | J63: DESIGN | K63: 仮定
B64: 能力：小改良の開始年度 | C64: 年度 | D64: 2027 | J64: DESIGN | K64: 仮定
B65: 能力：福岡の増強（+35%） | C65: 指数 | D65: 0.35 | J65: M02,RS-SEMI | K65: 一次
B66: 能力：増強の稼働年度（2028年9月） | C66: 年度 | D66: 2028 | J66: M02,RS-SEMI | K66: 一次
B67: 能力：稼働年度に効く割合 | C67: 倍 | D67: 0.5 | J67: DESIGN | K67: 仮定 | L67: 9月稼働で半年分
B68: 合成石英の価格上昇率 | C68: %/年 | D68: 0.04 | J68: DESIGN | K68: 仮定 | L68: 完売・Tier1
B69: 合成石英の限界利益率（上振れ分） | C69: % | D69: 0.45 | J69: DESIGN | K69: 仮定 | L69: 固定費吸収
B70: リソマックス（D_半導体）
B71: 項目 | C71: 単位 | D71: 値 | J71: 出典ID | K71: 区分 | L71: 備考
B72: リソマックス 利益率（参考表示） | C72: % | D72: 0.15 | J72: DESIGN | K72: 仮定
B73: 会社計画経路の成長率 | C73: %/年 | D73: 0.07 | J73: RS-SEMI,DESIGN | K73: 設計 | L73: 会社の半導体材料市場前提6〜8%
B74: EUV・先端ミックスの上乗せ | C74: %pt/年 | D74: 0.03 | J74: M43,DESIGN | K74: 仮定（開始年度は一次） | L74: 福岡 EUV 新設が2027年度
B75: EUV ミックス上乗せの開始年度 | C75: 年度 | D75: 2027 | J75: M03,RS-SEMI | K75: 一次 | L75: 投資計画表で FY27 欄
B76: WFE 成長に掛ける係数 | C76: 倍 | D76: 0.2 | J76: DESIGN | K76: 仮定
B77: リソマックスの限界利益率（上振れ分） | C77: % | D77: 0.35 | J77: DESIGN | K77: 仮定
B78: Zoox 向け CFRP（D_Zoox）
B79: 項目 | C79: 単位 | D79: 値 | J79: 出典ID | K79: 区分 | L79: 備考
B80: 会社予算に含まれる台数（基準） | C80: 台 | D80: 1500 | J80: DESIGN | K80: 仮定
B81: 上振れの利益率 | C81: % | D81: 0.15 | J81: DESIGN | K81: 仮定
B82: ベーシック（BM、D_石化）
B83: 項目 | C83: 単位 | D83: 値 | J83: 出典ID | K83: 区分 | L83: 備考
B84: 当社持分エチレン能力（非定修年） | C84: 千t | D84: 848 | J84: RS-PC | K84: 推計（一次から） | L84: 鹿島564＋水島567×50%
B85: 2025年度 基礎化学品売上 | C85: 億円 | D85: 5743 | J85: M03,RS-PC | K85: 一次
B86: 2025年度 生産推計 | C86: 千t | D86: 611 | J86: RS-PC,DESIGN | K86: 推計
B87: 限界利益率（原料・仕入・用役控除） | C87: % | D87: 0.0635 | J87: R01,RS-PC | K87: 推計（代替） | L87: 代替宣言：MCG は未開示。クラサス単体の原価明細で代用（ナフサ下落期・誘導品構成の違い・定修年不明が劣化点）
B88: 丸善千葉停止による国内稼働率の上昇 | C88: %pt | D88: 6 | J88: J02,RS-PC | K88: 推計 | L88: 71%→77%（生産一定の機械計算）
B89: 丸善効果の開始年度 | C89: 年度 | D89: 2027 | J89: RS-PC,DESIGN | K89: 設計
B90: 水島の固定費（1基の目安） | C90: 億円 | D90: 160 | J90: R01,RS-PC | K90: 推計（代替） | L90: 代替宣言：クラサス固定費約159億円で代用
B91: 水島の当社持分 | C91: % | D91: 0.5 | J91: RS-PC | K91: 一次
B92: 残存設備の稼働率上昇 | C92: %pt | D92: 4 | J92: DESIGN | K92: 仮定
B93: 水島停止による持分能力の減少率 | C93: % | D93: 0.07 | J93: RS-PC,DIR2 | K93: 推計（一次から） | L93: 848→789千t。限界利益減＝持分能力×減少率×売上/千t×限界利益率（設計書の▲22は他パラメータと不整合のため式に変更）
B94: 水島停止の年度 | C94: 年度 | D94: 2030 | J94: RS-PC,DESIGN | K94: 設計
B95: 分社化・合併（分社化・合併シート）
B96: 項目 | C96: 単位 | D96: 値 | J96: 出典ID | K96: 区分 | L96: 備考
B97: 分社化の年度（会社分割で子会社化と仮定） | C97: 年度 | D97: 2027 | J97: M07,DESIGN | K97: 一次（時期）／仮定（手法） | L97: 連結 BS は不変
B98: 分社化の一時費用（非経常） | C98: 億円 | D98: -50 | J98: DESIGN | K98: 仮定
B99: 切り出し BS：資産 | C99: 億円 | D99: 6000 | J99: RS-SEG,DESIGN | K99: 仮定 | L99: 2025年度 BM&P セグメント資産6,999から炭素分を控除
B100: 切り出し BS：営業負債 | C100: 億円 | D100: 700 | J100: DESIGN | K100: 仮定
B101: 切り出し BS：配分する有利子負債（合弁へ移る） | C101: 億円 | D101: 500 | J101: DESIGN | K101: 仮定
B102: 合弁の当社持分 | C102: % | D102: 0.5 | J102: DESIGN | K102: 仮定 | L102: 持分法
...

Sheet D_半導体
B1: D_半導体（合成石英・リソマックス）
B2: 上振れは「会社計画経路に対する増分」。2026年度は計画と同じ（上振れゼロ）
B4: 項目 | C4: 単位 | D4: 2025年度 | E4: 2026年度 | F4: 2027年度 | G4: 2028年度 | H4: 2029年度 | I4: 2030年度 | J4: 出所・算式
B5: 合成石英
B6: ウエハ出荷面積の成長率 | C6: % | F6: =前提!F8 -> 0.06 | G6: =前提!G8 -> 0.06 | H6: =前提!H8 -> 0.05 | I6: =前提!I8 -> 0.05 | J6: SEMI-WAFER
B7: WFE の成長率 | C7: % | F7: =前提!F9 -> 0.218 | G7: =前提!G9 -> 0.141 | H7: =前提!H9 -> 0.05 | I7: =前提!I9 -> 0.03 | J7: SEMI-WFE（2029〜30は仮定）
B8: 需要の成長率 | C8: % | F8: =F6+前提!$D$61*F7 -> 0.1145 | G8: =G6+前提!$D$61*G7 -> 0.09525 | H8: =H6+前提!$D$61*H7 -> 0.0625 | I8: =I6+前提!$D$61*I7 -> 0.0575 | J8: ウエハ面積成長＋係数×WFE 成長
B9: 需要指数（2026年度＝1） | C9: 指数 | E9: =前提!$D$62 -> 1 | F9: =E9*(1+F8) -> 1.1145 | G9: =F9*(1+G8) -> 1.2206561 | H9: =G9*(1+H8) -> 1.2969471 | I9: =H9*(1+I8) -> 1.3715216 | J9: 前年×(1＋需要の成長率)
B10: 能力指数 | C10: 指数 | E10: =前提!$D$62+IF(前提!E$6>=前提!$D$64,前提!$D$63,0)+IF(前提!E$6=前提!$D$66,前提!$D$65*前提!$D$67,IF(前提!E$6>前提!$D$66,前提!$D$65,0)) -> 1 | F10: =前提!$D$62+IF(前提!F$6>=前提!$D$64,前提!$D$63,0)+IF(前提!F$6=前提!$D$66,前提!$D$65*前提!$D$67,IF(前提!F$6>前提!$D$66,前提!$D$65,0)) -> 1.05 | G10: =前提!$D$62+IF(前提!G$6>=前提!$D$64,前提!$D$63,0)+IF(前提!G$6=前提!$D$66,前提!$D$65*前提!$D$67,IF(前提!G$6>前提!$D$66,前提!$D$65,0)) -> 1.225 | H10: =前提!$D$62+IF(前提!H$6>=前提!$D$64,前提!$D$63,0)+IF(前提!H$6=前提!$D$66,前提!$D$65*前提!$D$67,IF(前提!H$6>前提!$D$66,前提!$D$65,0)) -> 1.4 | I10: =前提!$D$62+IF(前提!I$6>=前提!$D$64,前提!$D$63,0)+IF(前提!I$6=前提!$D$66,前提!$D$65*前提!$D$67,IF(前提!I$6>前提!$D$66,前提!$D$65,0)) -> 1.4 | J10: 2026＝1.00、小改良＋0.05、2028年9月稼働の+0.35は初年度半分
B11: 数量指数 | C11: 指数 | E11: =MIN(E9,E10) -> 1 | F11: =MIN(F9,F10) -> 1.05 | G11: =MIN(G9,G10) -> 1.2206561 | H11: =MIN(H9,H10) -> 1.2969471 | I11: =MIN(I9,I10) -> 1.3715216 | J11: MIN(需要, 能力)
B12: 価格指数 | C12: 指数 | E12: =(1+前提!$D$68)^(前提!E$6-前提!E$6) -> 1 | F12: =(1+前提!$D$68)^(前提!F$6-前提!E$6) -> 1.04 | G12: =(1+前提!$D$68)^(前提!G$6-前提!E$6) -> 1.0816 | H12: =(1+前提!$D$68)^(前提!H$6-前提!E$6) -> 1.124864 | I12: =(1+前提!$D$68)^(前提!I$6-前提!E$6) -> 1.1698586 | J12: +4%/年
B13: 当社経路の売上 | C13: 億円 | E13: =前提!$D$28*E11*E12 -> 70 | F13: =前提!$D$28*F11*F12 -> 76.44 | G13: =前提!$D$28*G11*G12 -> 92.418317 | H13: =前提!$D$28*H11*H12 -> 102.12224 | I13: =前提!$D$28*I11*I12 -> 112.31404 | J13: 基準売上×数量指数×価格指数
B14: 会社計画経路の売上 | C14: 億円 | E14: =前提!$D$28*(1+前提!$D$60)^(前提!E$6-前提!E$6) -> 70 | F14: =前提!$D$28*(1+前提!$D$60)^(前提!F$6-前提!E$6) -> 75.39 | G14: =前提!$D$28*(1+前提!$D$60)^(前提!G$6-前提!E$6) -> 81.19503 | H14: =前提!$D$28*(1+前提!$D$60)^(前提!H$6-前提!E$6) -> 87.447047 | I14: =前提!$D$28*(1+前提!$D$60)^(前提!I$6-前提!E$6) -> 94.18047 | J14: M02 p36（+7.7%/年）
B15: 上振れ売上（当社−計画） | C15: 億円 | E15: =E13-E14 -> 0 | F15: =F13-F14 -> 1.05 | G15: =G13-G14 -> 11.223287 | H15: =H13-H14 -> 14.675192 | I15: =I13-I14 -> 18.133569
B16: 上振れコア利益（限界利益率） | C16: 億円 | E16: =E15*前提!$D$69 -> 0 | F16: =F15*前提!$D$69 -> 0.4725 | G16: =G15*前提!$D$69 -> 5.0504789 | H16: =H15*前提!$D$69 -> 6.6038366 | I16: =I15*前提!$D$69 -> 8.1601062 | J16: 売上差×45%
B17: 取り逃し需要（能力超過分の売上） | C17: 億円 | E17: =MAX(0,E9-E10)*前提!$D$28*E12 -> 0 | F17: =MAX(0,F9-F10)*前提!$D$28*F12 -> 4.6956 | G17: =MAX(0,G9-G10)*前提!$D$28*G12 -> 0 | H17: =MAX(0,H9-H10)*前提!$D$28*H12 -> 0 | I17: =MAX(0,I9-I10)*前提!$D$28*I12 -> 0
B18: 参考：当社経路のコア利益（利益率20%） | C18: 億円 | E18: =E13*前提!$D$59 -> 14 | F18: =F13*前提!$D$59 -> 15.288 | G18: =G13*前提!$D$59 -> 18.483663 | H18: =H13*前提!$D$59 -> 20.424448 | I18: =I13*前提!$D$59 -> 22.462808
B20: リソマックス
B21: EUV・先端ミックスの上乗せ | C21: % | F21: =IF(前提!F$6>=前提!$D$75,前提!$D$74,0) -> 0.03 | G21: =IF(前提!G$6>=前提!$D$75,前提!$D$74,0) -> 0.03 | H21: =IF(前提!H$6>=前提!$D$75,前提!$D$74,0) -> 0.03 | I21: =IF(前提!I$6>=前提!$D$75,前提!$D$74,0) -> 0.03 | J21: 2027年度から+3pt（福岡 EUV 新設）
B22: 当社経路の成長率 | C22: % | F22: =F6+F21+前提!$D$76*F7 -> 0.1336 | G22: =G6+G21+前提!$D$76*G7 -> 0.1182 | H22: =H6+H21+前提!$D$76*H7 -> 0.09 | I22: =I6+I21+前提!$D$76*I7 -> 0.086 | J22: ウエハ面積成長＋ミックス＋0.20×WFE 成長
B23: 当社経路の売上 | C23: 億円 | E23: =前提!$D$29 -> 120 | F23: =E23*(1+F22) -> 136.032 | G23: =F23*(1+G22) -> 152.11098 | H23: =G23*(1+H22) -> 165.80097 | I23: =H23*(1+I22) -> 180.05985
B24: 会社計画経路の売上 | C24: 億円 | E24: =前提!$D$29*(1+前提!$D$73)^(前提!E$6-前提!E$6) -> 120 | F24: =前提!$D$29*(1+前提!$D$73)^(前提!F$6-前提!E$6) -> 128.4 | G24: =前提!$D$29*(1+前提!$D$73)^(前提!G$6-前提!E$6) -> 137.388 | H24: =前提!$D$29*(1+前提!$D$73)^(前提!H$6-前提!E$6) -> 147.00516 | I24: =前提!$D$29*(1+前提!$D$73)^(前提!I$6-前提!E$6) -> 157.29552 | J24: +7%/年
B25: 上振れ売上（当社−計画） | C25: 億円 | E25: =E23-E24 -> 0 | F25: =F23-F24 -> 7.632 | G25: =G23-G24 -> 14.722982 | H25: =H23-H24 -> 18.795811 | I25: =I23-I24 -> 22.764333
B26: 上振れコア利益（限界利益率） | C26: 億円 | E26: =E25*前提!$D$77 -> 0 | F26: =F25*前提!$D$77 -> 2.6712 | G26: =G25*前提!$D$77 -> 5.1530438 | H26: =H25*前提!$D$77 -> 6.5785338 | I26: =I25*前提!$D$77 -> 7.9675166 | J26: 売上差×35%
B27: 参考：当社経路のコア利益（利益率15%） | C27: 億円 | E27: =E23*前提!$D$72 -> 18 | F27: =F23*前提!$D$72 -> 20.4048 | G27: =G23*前提!$D$72 -> 22.816647 | H27: =H23*前提!$D$72 -> 24.870146 | I27: =I23*前提!$D$72 -> 27.008978
B28: 注1：合成石英・リソマックスの売上と利益は会社の開示が無い。基準売上（70・120）は感応度用の仮定で、前提シートで変えられる。
B29: 注2：WFE とウエハ面積は暦年の値を年度に当てている（設計書どおり）。

Sheet D_Zoox
B1: D_Zoox（Zoox 向け CFRP）
B2: 上振れ＝(台数−会社予算に含まれる1,500台)×1台売上
B4: 項目 | C4: 単位 | D4: 2025年度 | E4: 2026年度 | F4: 2027年度 | G4: 2028年度 | H4: 2029年度 | I4: 2030年度 | J4: 出所・算式
B5: 台数 | C5: 台 | E5: =前提!E10 -> 1500 | F5: =前提!F10 -> 2500 | G5: =前提!G10 -> 2500 | H5: =前提!H10 -> 2500 | I5: =前提!I10 -> 2500 | J5: NHTSA-555（上限）・仮定
B6: 会社予算に含まれる台数 | C6: 台 | E6: =前提!$D$80 -> 1500 | F6: =前提!$D$80 -> 1500 | G6: =前提!$D$80 -> 1500 | H6: =前提!$D$80 -> 1500 | I6: =前提!$D$80 -> 1500 | J6: 仮定
B7: 1台あたり売上 | C7: 億円/台 | E7: =前提!$D$27/10000 -> 0.1 | F7: =前提!$D$27/10000 -> 0.1 | G7: =前提!$D$27/10000 -> 0.1 | H7: =前提!$D$27/10000 -> 0.1 | I7: =前提!$D$27/10000 -> 0.1 | J7: 1,000万円（推計）
B8: 参考：Zoox 向け売上 | C8: 億円 | E8: =E5*E7 -> 150 | F8: =F5*F7 -> 250 | G8: =G5*G7 -> 250 | H8: =H5*H7 -> 250 | I8: =I5*I7 -> 250
B9: 上振れ売上 | C9: 億円 | E9: =(E5-E6)*E7 -> 0 | F9: =(F5-F6)*F7 -> 100 | G9: =(G5-G6)*G7 -> 100 | H9: =(H5-H6)*H7 -> 100 | I9: =(I5-I6)*I7 -> 100
B10: 上振れコア利益 | C10: 億円 | E10: =E9*前提!$D$81 -> 0 | F10: =F9*前提!$D$81 -> 15 | G10: =G9*前提!$D$81 -> 15 | H10: =H9*前提!$D$81 -> 15 | I10: =I9*前提!$D$81 -> 15 | J10: 売上差×15%
B11: 注1：年2,500台は工場能力ではなく NHTSA の免除上限（二次。年か累計かは一次で未確定）。

Sheet D_石化
B1: D_石化（ベーシック、当社単体ベース＝合併前）
B2: 丸善千葉停止・水島停止の効果を基礎経路に足す。合併後の連結範囲は「分社化・合併」シート
B4: 項目 | C4: 単位 | D4: 2025年度 | E4: 2026年度 | F4: 2027年度 | G4: 2028年度 | H4: 2029年度 | I4: 2030年度 | J4: 出所・算式
B5: 基礎コア営業利益 | C5: 億円 | E5: =前提!E12 -> -50 | F5: =前提!F12 -> -150 | G5: =前提!G12 -> -110 | H5: =前提!H12 -> -90 | I5: =前提!I12 -> -80 | J5: 設計
B6: 売上/千t（2025年度） | C6: 億円/千t | E6: =前提!$D$85/前提!$D$86 -> 9.3993453 | F6: =前提!$D$85/前提!$D$86 -> 9.3993453 | G6: =前提!$D$85/前提!$D$86 -> 9.3993453 | H6: =前提!$D$85/前提!$D$86 -> 9.3993453 | I6: =前提!$D$85/前提!$D$86 -> 9.3993453 | J6: 5,743÷611
B7: 稼働率1ptあたり利益 | C7: 億円/pt | E7: =前提!$D$84*0.01*E6*前提!$D$87 -> 5.0613595 | F7: =前提!$D$84*0.01*F6*前提!$D$87 -> 5.0613595 | G7: =前提!$D$84*0.01*G6*前提!$D$87 -> 5.0613595 | H7: =前提!$D$84*0.01*H6*前提!$D$87 -> 5.0613595 | I7: =前提!$D$84*0.01*I6*前提!$D$87 -> 5.0613595 | J7: 848千t×1%×売上/千t×限界利益率6.35%
B8: 丸善千葉停止（稼働率+6pt） | C8: 億円 | E8: =IF(前提!E$6>=前提!$D$89,前提!$D$88*E7,0) -> 0 | F8: =IF(前提!F$6>=前提!$D$89,前提!$D$88*F7,0) -> 30.368157 | G8: =IF(前提!G$6>=前提!$D$89,前提!$D$88*G7,0) -> 30.368157 | H8: =IF(前提!H$6>=前提!$D$89,前提!$D$88*H7,0) -> 30.368157 | I8: =IF(前提!I$6>=前提!$D$89,前提!$D$88*I7,0) -> 30.368157 | J8: 2027年度から
B9: 水島停止：固定費削減 | C9: 億円 | E9: =IF(前提!E$6>=前提!$D$94,前提!$D$90*前提!$D$91,0) -> 0 | F9: =IF(前提!F$6>=前提!$D$94,前提!$D$90*前提!$D$91,0) -> 0 | G9: =IF(前提!G$6>=前提!$D$94,前提!$D$90*前提!$D$91,0) -> 0 | H9: =IF(前提!H$6>=前提!$D$94,前提!$D$90*前提!$D$91,0) -> 0 | I9: =IF(前提!I$6>=前提!$D$94,前提!$D$90*前提!$D$91,0) -> 80 | J9: 160×50%
B10: 水島停止：残存設備の稼働率上昇 | C10: 億円 | E10: =IF(前提!E$6>=前提!$D$94,前提!$D$92*E7,0) -> 0 | F10: =IF(前提!F$6>=前提!$D$94,前提!$D$92*F7,0) -> 0 | G10: =IF(前提!G$6>=前提!$D$94,前提!$D$92*G7,0) -> 0 | H10: =IF(前提!H$6>=前提!$D$94,前提!$D$92*H7,0) -> 0 | I10: =IF(前提!I$6>=前提!$D$94,前提!$D$92*I7,0) -> 20.245438 | J10: +4pt×1pt利益
B11: 水島停止：能力減による限界利益減 | C11: 億円 | E11: =IF(前提!E$6>=前提!$D$94,-前提!$D$84*前提!$D$93*E6*前提!$D$87,0) -> 0 | F11: =IF(前提!F$6>=前提!$D$94,-前提!$D$84*前提!$D$93*F6*前提!$D$87,0) -> 0 | G11: =IF(前提!G$6>=前提!$D$94,-前提!$D$84*前提!$D$93*G6*前提!$D$87,0) -> 0 | H11: =IF(前提!H$6>=前提!$D$94,-前提!$D$84*前提!$D$93*H6*前提!$D$87,0) -> 0 | I11: =IF(前提!I$6>=前提!$D$94,-前提!$D$84*前提!$D$93*I6*前提!$D$87,0) -> -35.429516 | J11: −848千t×7%×売上/千t×6.35%
B12: 水島停止の効果 計 | C12: 億円 | E12: =E9+E10+E11 -> 0 | F12: =F9+F10+F11 -> 0 | G12: =G9+G10+G11 -> 0 | H12: =H9+H10+H11 -> 0 | I12: =I9+I10+I11 -> 64.815922
B13: BM コア営業利益（当社単体ベース） | C13: 億円 | E13: =E5+E8+E12 -> -50 | F13: =F5+F8+F12 -> -119.63184 | G13: =G5+G8+G12 -> -79.631843 | H13: =H5+H8+H12 -> -59.631843 | I13: =I5+I8+I12 -> 15.184078
B14: BM 売上（当社単体ベース） | C14: 億円 | E14: =前提!$D$39 -> 6830 | F14: =E14*(1+前提!F14)+前提!F13 -> 6330 | G14: =F14*(1+前提!G14)+前提!G13 -> 5830 | H14: =G14*(1+前提!H14)+前提!H13 -> 5713.4 | I14: =H14*(1+前提!I14)+前提!I13 -> 5599.132 | J14: 2027・2028年度は炭素撤退で各▲500、以後▲2%/年
B15: 注1：限界利益率・固定費はクラサス単体の原価明細で代用（MCG は未開示。代替宣言は前提シート）。
B16: 注2：合併後は、この単体ベースの BM コアが合弁利益の算定に使われる（合弁利益＝単体 BM コア×2＋統合効果）。

Sheet D_JSR
B1: D_JSR（ケースBのみ）
B2: 取得年度の下期に20%を取得（持分法）。2028〜30年度の各期首に、余力の範囲で49%まで追加取得（コール）。49%到達後、余力が残り株式の代金＋JSR 純有利子負債以上になった最初の年度に全額取得（連結）。満たさなければ49%で据え置き
B4: 項目 | C4: 単位 | D4: 2025年度 | E4: 2026年度 | F4: 2027年度 | G4: 2028年度 | H4: 2029年度 | I4: 2030年度 | J4: 出所・算式
B5: JSR の業績とフォトレジスト上振れ
B6: JSR 売上（基礎） | C6: 億円 | E6: =前提!$D$149*(1+前提!$D$150)^(前提!E$6-前提!D$6) -> 4715.49 | F6: =前提!$D$149*(1+前提!$D$150)^(前提!F$6-前提!D$6) -> 5045.5743 | G6: =前提!$D$149*(1+前提!$D$150)^(前提!G$6-前提!D$6) -> 5398.7645 | H6: =前提!$D$149*(1+前提!$D$150)^(前提!H$6-前提!D$6) -> 5776.678 | I6: =前提!$D$149*(1+前提!$D$150)^(前提!I$6-前提!D$6) -> 6181.0455 | J6: 4,407×1.07^n
B7: 電子材料売上（基礎、+10%/年） | C7: 億円 | E7: =前提!$D$153*(1+前提!$D$154)^(前提!E$6-前提!D$6) -> 2156 | F7: =前提!$D$153*(1+前提!$D$154)^(前提!F$6-前提!D$6) -> 2371.6 | G7: =前提!$D$153*(1+前提!$D$154)^(前提!G$6-前提!D$6) -> 2608.76 | H7: =前提!$D$153*(1+前提!$D$154)^(前提!H$6-前提!D$6) -> 2869.636 | I7: =前提!$D$153*(1+前提!$D$154)^(前提!I$6-前提!D$6) -> 3156.5996
B8: 電子材料の当社経路の成長率 | C8: % | E8: =前提!$D$154 -> 0.1 | F8: =前提!F8+前提!$D$155*前提!F9+前提!$D$156 -> 0.1563 | G8: =前提!G8+前提!$D$155*前提!G9+前提!$D$156 -> 0.12935 | H8: =前提!H8+前提!$D$155*前提!H9+前提!$D$156 -> 0.0875 | I8: =前提!I8+前提!$D$155*前提!I9+前提!$D$156 -> 0.0805 | J8: ウエハ面積＋0.35×WFE＋EUV 2pt（2026は基礎と同じ）
B9: 電子材料売上（当社経路） | C9: 億円 | E9: =前提!$D$153*(1+E8) -> 2156 | F9: =E9*(1+F8) -> 2492.9828 | G9: =F9*(1+G8) -> 2815.4501 | H9: =G9*(1+H8) -> 3061.802 | I9: =H9*(1+I8) -> 3308.2771
B10: 電子材料の上振れ売上 | C10: 億円 | E10: =E9-E7 -> 0 | F10: =F9-F7 -> 121.3828 | G10: =G9-G7 -> 206.69013 | H10: =H9-H7 -> 192.16601 | I10: =I9-I7 -> 151.67747
B11: フォトレジスト上振れ（コア） | C11: 億円 | E11: =E10*前提!$D$157 -> 0 | F11: =F10*前提!$D$157 -> 36.41484 | G11: =G10*前提!$D$157 -> 62.007038 | H11: =H10*前提!$D$157 -> 57.649803 | I11: =I10*前提!$D$157 -> 45.503242 | J11: 差分×30%
B12: JSR コア営業利益（基礎） | C12: 億円 | E12: =前提!E20 -> 600 | F12: =前提!F20 -> 680 | G12: =前提!G20 -> 760 | H12: =前提!H20 -> 840 | I12: =前提!I20 -> 920
B13: JSR コア営業利益（上振れ込み） | C13: 億円 | E13: =E12+E11 -> 600 | F13: =F12+F11 -> 716.41484 | G13: =G12+G11 -> 822.00704 | H13: =H12+H11 -> 897.6498 | I13: =I12+I11 -> 965.50324
B14: JSR 売上（上振れ込み） | C14: 億円 | E14: =E6+E10 -> 4715.49 | F14: =F6+F10 -> 5166.9571 | G14: =G6+G10 -> 5605.4546 | H14: =H6+H10 -> 5968.844 | I14: =I6+I10 -> 6332.723 | J14: 上振れ売上も加える（追加の仮定）
B16: 取得の判定（期首、前期末のケースB の BS で判定）
B17: 第1段 取得年度フラグ | E17: =IF(前提!E$6=前提!$D$140,1,0) -> 0 | F17: =IF(前提!F$6=前提!$D$140,1,0) -> 1 | G17: =IF(前提!G$6=前提!$D$140,1,0) -> 0 | H17: =IF(前提!H$6=前提!$D$140,1,0) -> 0 | I17: =IF(前提!I$6=前提!$D$140,1,0) -> 0
B18: 保有フラグ | E18: =IF(前提!E$6>=前提!$D$140,1,0) -> 0 | F18: =IF(前提!F$6>=前提!$D$140,1,0) -> 1 | G18: =IF(前提!G$6>=前提!$D$140,1,0) -> 1 | H18: =IF(前提!H$6>=前提!$D$140,1,0) -> 1 | I18: =IF(前提!I$6>=前提!$D$140,1,0) -> 1
B19: コール行使可能期間フラグ（各期首） | E19: =IF(AND(前提!E$6>=前提!$D$143,前提!E$6<=前提!$D$144),1,0) -> 0 | F19: =IF(AND(前提!F$6>=前提!$D$143,前提!F$6<=前提!$D$144),1,0) -> 0 | G19: =IF(AND(前提!G$6>=前提!$D$143,前提!G$6<=前提!$D$144),1,0) -> 1 | H19: =IF(AND(前提!H$6>=前提!$D$143,前提!H$6<=前提!$D$144),1,0) -> 1 | I19: =IF(AND(前提!I$6>=前提!$D$143,前提!I$6<=前提!$D$144),1,0) -> 1
B20: 行使価格（100%分の株式価値） | C20: 億円 | E20: =前提!$D$135*(1+前提!$D$142)^MAX(0,前提!E$6-前提!$D$140) -> 10000 | F20: =前提!$D$135*(1+前提!$D$142)^MAX(0,前提!F$6-前提!$D$140) -> 10000 | G20: =前提!$D$135*(1+前提!$D$142)^MAX(0,前提!G$6-前提!$D$140) -> 10300 | H20: =前提!$D$135*(1+前提!$D$142)^MAX(0,前提!H$6-前提!$D$140) -> 10609 | I20: =前提!$D$135*(1+前提!$D$142)^MAX(0,前提!I$6-前提!$D$140) -> 10927.27 | J20: 1兆×(1+3%)^経過年数
B21: ハイブリッド債で調達する比率 | C21: % | E21: =前提!$D$33*前提!$D$146 -> 0 | F21: =前提!$D$33*前提!$D$146 -> 0 | G21: =前提!$D$33*前提!$D$146 -> 0 | H21: =前提!$D$33*前提!$D$146 -> 0 | I21: =前提!$D$33*前提!$D$146 -> 0 | J21: 切替0なら0%
B22: 取得額のうち資本扱いになる割合 | C22: % | E22: =E21*前提!$D$147 -> 0 | F22: =F21*前提!$D$147 -> 0 | G22: =G21*前提!$D$147 -> 0 | H22: =H21*前提!$D$147 -> 0 | I22: =I21*前提!$D$147 -> 0
B23: 0.8 の余力（0.8×前期末親会社持分−前期末純有利子負債） | C23: 億円 | E23: =前提!$D$145*連結BS!D45-連結BS!D44 -> -554.4 | F23: =前提!$D$145*連結BS!E45-連結BS!E44 -> 757.14679 | G23: =前提!$D$145*連結BS!F45-連結BS!F44 -> 31.108804 | H23: =前提!$D$145*連結BS!G45-連結BS!G44 -> 276.97324 | I23: =前提!$D$145*連結BS!H45-連結BS!H44 -> 2402.7571 | J23: ハイブリッド債があれば資本性調整後の値で計算
B24: 余力で取得できる額 | C24: 億円 | E24: =MAX(0,E23)/(1-(1+前提!$D$145)*E22) -> 0 | F24: =MAX(0,F23)/(1-(1+前提!$D$145)*F22) -> 757.14679 | G24: =MAX(0,G23)/(1-(1+前提!$D$145)*G22) -> 31.108804 | H24: =MAX(0,H23)/(1-(1+前提!$D$145)*H22) -> 276.97324 | I24: =MAX(0,I23)/(1-(1+前提!$D$145)*I22) -> 2402.7571 | J24: 余力÷(1−(1+0.8)×資本扱い割合)。切替0なら余力そのもの
B25: 全額取得の自動判定（49%到達済み・余力≧残り代金＋JSR 純有利子負債） | E25: =IF(AND(E19=1,N(D29)=0,N(D28)>=前提!$D$139-0.000001,E23>=(1-N(D28))*E20*(1-(1+前提!$D$145)*E22)+前提!$D$136),1,0) -> 0 | F25: =IF(AND(F19=1,N(E29)=0,N(E28)>=前提!$D$139-0.000001,F23>=(1-N(E28))*F20*(1-(1+前提!$D$145)*F22)+前提!$D$136),1,0) -> 0 | G25: =IF(AND(G19=1,N(F29)=0,N(F28)>=前提!$D$139-0.000001,G23>=(1-N(F28))*G20*(1-(1+前提!$D$145)*G22)+前提!$D$136),1,0) -> 0 | H25: =IF(AND(H19=1,N(G29)=0,N(G28)>=前提!$D$139-0.000001,H23>=(1-N(G28))*H20*(1-(1+前提!$D$145)*H22)+前提!$D$136),1,0) -> 0 | I25: =IF(AND(I19=1,N(H29)=0,N(H28)>=前提!$D$139-0.000001,I23>=(1-N(H28))*I20*(1-(1+前提!$D$145)*I22)+前提!$D$136),1,0) -> 0
B26: 全額取得（期首、連結開始） | E26: =IF(前提!$D$31>0,IF(AND(前提!E$6=前提!$D$31,N(D29)=0,N(D28)>0),1,0),E25) -> 0 | F26: =IF(前提!$D$31>0,IF(AND(前提!F$6=前提!$D$31,N(E29)=0,N(E28)>0),1,0),F25) -> 0 | G26: =IF(前提!$D$31>0,IF(AND(前提!G$6=前提!$D$31,N(F29)=0,N(F28)>0),1,0),G25) -> 0 | H26: =IF(前提!$D$31>0,IF(AND(前提!H$6=前提!$D$31,N(G29)=0,N(G28)>0),1,0),H25) -> 0 | I26: =IF(前提!$D$31>0,IF(AND(前提!I$6=前提!$D$31,N(H29)=0,N(H28)>0),1,0),I25) -> 0 | J26: 前提の上書きが0なら自動判定
B27: 追加取得の持分（期首、49%まで） | C27: % | E27: =IF(AND(E19=1,N(D29)=0,E26=0,N(D28)>0),MIN(MAX(0,前提!$D$139-N(D28)),E24/E20),0) -> 0 | F27: =IF(AND(F19=1,N(E29)=0,F26=0,N(E28)>0),MIN(MAX(0,前提!$D$139-N(E28)),F24/F20),0) -> 0 | G27: =IF(AND(G19=1,N(F29)=0,G26=0,N(F28)>0),MIN(MAX(0,前提!$D$139-N(F28)),G24/G20),0) -> 0.0030202722 | H27: =IF(AND(H19=1,N(G29)=0,H26=0,N(G28)>0),MIN(MAX(0,前提!$D$139-N(G28)),H24/H20),0) -> 0.026107385 | I27: =IF(AND(I19=1,N(H29)=0,I26=0,N(H28)>0),MIN(MAX(0,前提!$D$139-N(H28)),I24/I20),0) -> 0.21988631 | J27: MIN(49%−前期末持分, 取得できる額÷行使価格)
B28: 持分比率（期末） | C28: % | E28: =IF(E26=1,1,N(D28)+E17*前提!$D$138+E27) -> 0 | F28: =IF(F26=1,1,N(E28)+F17*前提!$D$138+F27) -> 0.2 | G28: =IF(G26=1,1,N(F28)+G17*前提!$D$138+G27) -> 0.20302027 | H28: =IF(H26=1,1,N(G28)+H17*前提!$D$138+H27) -> 0.22912766 | I28: =IF(I26=1,1,N(H28)+I17*前提!$D$138+I27) -> 0.44901397
B29: 連結フラグ | E29: =MAX(N(D29),E26) -> 0 | F29: =MAX(N(E29),F26) -> 0 | G29: =MAX(N(F29),G26) -> 0 | H29: =MAX(N(G29),H26) -> 0 | I29: =MAX(N(H29),I26) -> 0
B31: 支払額と資金調達
B32: 第1段の取得額（下期） | C32: 億円 | E32: =E17*前提!$D$138*E20 -> 0 | F32: =F17*前提!$D$138*F20 -> 2000 | G32: =G17*前提!$D$138*G20 -> 0 | H32: =H17*前提!$D$138*H20 -> 0 | I32: =I17*前提!$D$138*I20 -> 0 | J32: 1兆×20%
B33: 追加取得額（期首） | C33: 億円 | E33: =E27*E20 -> 0 | F33: =F27*F20 -> 0 | G33: =G27*G20 -> 31.108804 | H33: =H27*H20 -> 276.97324 | I33: =I27*I20 -> 2402.7571
B34: 全額取得の代金（期首、残り株式） | C34: 億円 | E34: =E26*(1-N(D28))*E20 -> 0 | F34: =F26*(1-N(E28))*F20 -> 0 | G34: =G26*(1-N(F28))*G20 -> 0 | H34: =H26*(1-N(G28))*H20 -> 0 | I34: =I26*(1-N(H28))*I20 -> 0
B35: 持分法投資への払込（第1段＋追加取得） | C35: 億円 | E35: =E32+E33 -> 0 | F35: =F32+F33 -> 2000 | G35: =G32+G33 -> 31.108804 | H35: =H32+H33 -> 276.97324 | I35: =I32+I33 -> 2402.7571
B36: 支払額 計 | C36: 億円 | E36: =E35+E34 -> 0 | F36: =F35+F34 -> 2000 | G36: =G35+G34 -> 31.108804 | H36: =H35+H34 -> 276.97324 | I36: =I35+I34 -> 2402.7571
B37: うちハイブリッド債による調達 | C37: 億円 | E37: =E36*E21 -> 0 | F37: =F36*F21 -> 0 | G37: =G36*G21 -> 0 | H37: =H36*H21 -> 0 | I37: =I36*I21 -> 0
B38: ハイブリッド債の残高（期末） | C38: 億円 | E38: =N(D38)+E37 -> 0 | F38: =N(E38)+F37 -> 0 | G38: =N(F38)+G37 -> 0 | H38: =N(G38)+H37 -> 0 | I38: =N(H38)+I37 -> 0
B39: ハイブリッド債の上乗せ金利 | C39: 億円 | E39: =前提!$D$148*(N(D38)+E21*(E33+E34+E32*前提!$D$141)) -> 0 | F39: =前提!$D$148*(N(E38)+F21*(F33+F34+F32*前提!$D$141)) -> 0 | G39: =前提!$D$148*(N(F38)+G21*(G33+G34+G32*前提!$D$141)) -> 0 | H39: =前提!$D$148*(N(G38)+H21*(H33+H34+H32*前提!$D$141)) -> 0 | I39: =前提!$D$148*(N(H38)+I21*(I33+I34+I32*前提!$D$141)) -> 0
B41: 持分法期間と連結後
B42: 持分法期間フラグ | E42: =E18*(1-E29) -> 0 | F42: =F18*(1-F29) -> 1 | G42: =G18*(1-G29) -> 1 | H42: =H18*(1-H29) -> 1 | I42: =I18*(1-I29) -> 1
B43: 期間係数（取得年度は下期のみ） | C43: 倍 | E43: =IF(E17=1,前提!$D$141,1) -> 1 | F43: =IF(F17=1,前提!$D$141,1) -> 0.5 | G43: =IF(G17=1,前提!$D$141,1) -> 1 | H43: =IF(H17=1,前提!$D$141,1) -> 1 | I43: =IF(I17=1,前提!$D$141,1) -> 1
B44: 当社持分法利益（持分×(コア−金融費用100)×(1−27%)） | C44: 億円 | E44: =E42*E43*E28*(E13-前提!$D$158)*(1-前提!$D$159) -> 0 | F44: =F42*F43*F28*(F13-前提!$D$158)*(1-前提!$D$159) -> 44.998283 | G44: =G42*G43*G28*(G13-前提!$D$158)*(1-前提!$D$159) -> 107.00491 | H44: =H42*H43*H28*(H13-前提!$D$158)*(1-前提!$D$159) -> 133.41745 | I44: =I42*I43*I28*(I13-前提!$D$158)*(1-前提!$D$159) -> 283.69482 | J44: 期首取得なので期末持分を通年に当てる
B45: 持分法投資の振替（連結時、前期末残高） | C45: 億円 | E45: =E26*N(D46) -> 0 | F45: =F26*N(E46) -> 0 | G45: =G26*N(F46) -> 0 | H45: =H26*N(G46) -> 0 | I45: =I26*N(H46) -> 0
B46: JSR 持分法投資の残高 | C46: 億円 | E46: =N(D46)+E35+E44-E45 -> 0 | F46: =N(E46)+F35+F44-F45 -> 2044.9983 | G46: =N(F46)+G35+G44-G45 -> 2183.112 | H46: =N(G46)+H35+H44-H45 -> 2593.5027 | I46: =N(H46)+I35+I44-I45 -> 5279.9546
B47: JSR 連結売上 | C47: 億円 | E47: =E29*E14 -> 0 | F47: =F29*F14 -> 0 | G47: =G29*G14 -> 0 | H47: =H29*H14 -> 0 | I47: =I29*I14 -> 0
B48: JSR 連結コア営業利益 | C48: 億円 | E48: =E29*E13 -> 0 | F48: =F29*F13 -> 0 | G48: =G29*G13 -> 0 | H48: =H29*H13 -> 0 | I48: =I29*I13 -> 0
B49: のれん（全額取得年度、累計取得対価−JSR 純資産） | C49: 億円 | E49: =E26*(SUM($E36:E36)-前提!$D$137) -> 0 | F49: =F26*(SUM($E36:F36)-前提!$D$137) -> 0 | G49: =G26*(SUM($E36:G36)-前提!$D$137) -> 0 | H49: =H26*(SUM($E36:H36)-前提!$D$137) -> 0 | I49: =I26*(SUM($E36:I36)-前提!$D$137) -> 0 | J49: 参考表示
B51: 出力
B52: 持分比率 | C52: % | E52: =E28 -> 0 | F52: =F28 -> 0.2 | G52: =G28 -> 0.20302027 | H52: =H28 -> 0.22912766 | I52: =I28 -> 0.44901397
B53: 支払額 | C53: 億円 | E53: =E36 -> 0 | F53: =F36 -> 2000 | G53: =G36 -> 31.108804 | H53: =H36 -> 276.97324 | I53: =I36 -> 2402.7571
B54: 持分法利益／連結コア | C54: 億円 | E54: =E44+E48 -> 0 | F54: =F44+F48 -> 44.998283 | G54: =G44+G48 -> 107.00491 | H54: =H44+H48 -> 133.41745 | I54: =I44+I48 -> 283.69482
B55: 0.8 の余力（期首） | C55: 億円 | E55: =E23 -> -554.4 | F55: =F23 -> 757.14679 | G55: =G23 -> 31.108804 | H55: =H23 -> 276.97324 | I55: =I23 -> 2402.7571
B56: JSR による増益：コア営業利益（B−A） | C56: 億円 | E56: =連結PL!E52 -> 0 | F56: =連結PL!F52 -> 44.998283 | G56: =連結PL!G52 -> 107.00491 | H56: =連結PL!H52 -> 133.41745 | I56: =連結PL!I52 -> 283.69482
B57: JSR による増益：親会社当期利益（B−A） | C57: 億円 | E57: =連結PL!E53 -> 0 | F57: =連結PL!F53 -> 30.398283 | G57: =連結PL!G53 -> 77.137559 | H57: =連結PL!H53 -> 99.070229 | I57: =連結PL!I53 -> 213.25963
B58: JSR による増益：EPS（B−A） | C58: 円 | E58: =連結PL!E54 -> 0 | F58: =連結PL!F54 -> 2.2373065 | G58: =連結PL!G54 -> 5.6773062 | H58: =連結PL!H54 -> 7.2915455 | I58: =連結PL!I54 -> 15.695859
B59: ネットD/E（ケースA） | C59: 倍 | E59: =連結BS!E21 -> 0.75895837 | F59: =連結BS!F21 -> 0.6946446 | G59: =連結BS!G21 -> 0.67048468 | H59: =連結BS!H21 -> 0.54899901 | I59: =連結BS!I21 -> 0.42829163
B60: ネットD/E（ケースB） | C60: 倍 | E60: =連結BS!E46 -> 0.75895837 | F60: =連結BS!F46 -> 0.79838117 | G60: =連結BS!G46 -> 0.78426964 | H60: =連結BS!H46 -> 0.67249423 | I60: =連結BS!I46 -> 0.6667913
B62: 全額取得（連結）の年度 | D62: =IF(SUM($E$26:$I$26)=0,"未到達（"&TEXT(MAX($E$28:$I$28),"0.0%")&"で据え置き）",SUMPRODUCT($E$26:$I$26,前提!$E$6:$I$6)) -> 未到達（44.9%で据え置き）
B64: 注1：JSR の純有利子負債（3,434）は連結時まで一定と置いた。持分法期間の金融費用は設計どおり年100。
B65: 注2：連結時の既存持分の再測定損益は計上していない。のれんは償却しない（IFRS）。
B66: 注3：ハイブリッド債の会社での扱い（発行有無・資本性）は未確認で、比率・資本性・上乗せ金利はすべて仮定。

Sheet セグメント
B1: セグメント（ケースA＝JSRなし）
B2: 2026年度は会社予算（M03 p20）。SM は基礎経路（既定＝会社計画）に上振れ（会社計画比の増分）を足す
B4: 項目 | C4: 単位 | D4: 2025年度 | E4: 2026年度 | F4: 2027年度 | G4: 2028年度 | H4: 2029年度 | I4: 2030年度 | J4: 出所・算式
B5: スペシャリティ（SM）
B6: 保守経路：売上 | C6: 億円 | E6: =前提!$D$36 -> 12370 | F6: =E6*(1+前提!$D$48) -> 12864.8 | G6: =F6*(1+前提!$D$48) -> 13379.392 | H6: =G6*(1+前提!$D$48) -> 13914.568 | I6: =H6*(1+前提!$D$48) -> 14471.15 | J6: 2026＝会社予算、以後+4%/年
B7: 保守経路：コア営業利益 | C7: 億円 | E7: =前提!$D$37 -> 900 | F7: =F6*前提!F7 -> 1003.4544 | G7: =G6*前提!G7 -> 1110.4895 | H7: =H6*前提!H7 -> 1224.482 | I7: =I6*前提!I7 -> 1302.4035 | J7: 利益率7.8→9.0%
B8: 会社計画経路：売上 | C8: 億円 | E8: =前提!$D$36 -> 12370 | F8: =IF(前提!F$6<=前提!$D$51,前提!$D$36+(前提!$D$49-前提!$D$36)*(前提!F$6-前提!E$6)/(前提!$D$51-前提!E$6),E8*(1+前提!$D$52)) -> 13480 | G8: =IF(前提!G$6<=前提!$D$51,前提!$D$36+(前提!$D$49-前提!$D$36)*(前提!G$6-前提!E$6)/(前提!$D$51-前提!E$6),F8*(1+前提!$D$52)) -> 14590 | H8: =IF(前提!H$6<=前提!$D$51,前提!$D$36+(前提!$D$49-前提!$D$36)*(前提!H$6-前提!E$6)/(前提!$D$51-前提!E$6),G8*(1+前提!$D$52)) -> 15700 | I8: =IF(前提!I$6<=前提!$D$51,前提!$D$36+(前提!$D$49-前提!$D$36)*(前提!I$6-前提!E$6)/(前提!$D$51-前提!E$6),H8*(1+前提!$D$52)) -> 16328 | J8: 12,370→15,700（2029）を線形、以後+4%
B9: 会社計画経路：コア営業利益 | C9: 億円 | E9: =前提!$D$37 -> 900 | F9: =IF(前提!F$6<=前提!$D$51,前提!$D$37+(前提!$D$50-前提!$D$37)*(前提!F$6-前提!E$6)/(前提!$D$51-前提!E$6),F8*前提!$D$53) -> 1116.6667 | G9: =IF(前提!G$6<=前提!$D$51,前提!$D$37+(前提!$D$50-前提!$D$37)*(前提!G$6-前提!E$6)/(前提!$D$51-前提!E$6),G8*前提!$D$53) -> 1333.3333 | H9: =IF(前提!H$6<=前提!$D$51,前提!$D$37+(前提!$D$50-前提!$D$37)*(前提!H$6-前提!E$6)/(前提!$D$51-前提!E$6),H8*前提!$D$53) -> 1550 | I9: =IF(前提!I$6<=前提!$D$51,前提!$D$37+(前提!$D$50-前提!$D$37)*(前提!I$6-前提!E$6)/(前提!$D$51-前提!E$6),I8*前提!$D$53) -> 1632.8 | J9: 900→1,550（2029）を線形、以後利益率10.0%
B10: SM 本体 基礎売上（選択した経路） | C10: 億円 | E10: =IF(前提!$D$30=1,E8,E6) -> 12370 | F10: =IF(前提!$D$30=1,F8,F6) -> 13480 | G10: =IF(前提!$D$30=1,G8,G6) -> 14590 | H10: =IF(前提!$D$30=1,H8,H6) -> 15700 | I10: =IF(前提!$D$30=1,I8,I6) -> 16328 | J10: 前提の切替（1＝会社計画）
B11: SM 本体 基礎コア営業利益（選択した経路） | C11: 億円 | E11: =IF(前提!$D$30=1,E9,E7) -> 900 | F11: =IF(前提!$D$30=1,F9,F7) -> 1116.6667 | G11: =IF(前提!$D$30=1,G9,G7) -> 1333.3333 | H11: =IF(前提!$D$30=1,H9,H7) -> 1550 | I11: =IF(前提!$D$30=1,I9,I7) -> 1632.8
B12: SM 本体 基礎コア利益率 | C12: % | E12: =E11/E10 -> 0.072756669 | F12: =F11/F10 -> 0.082838773 | G12: =G11/G10 -> 0.091386795 | H12: =H11/H10 -> 0.098726115 | I12: =I11/I10 -> 0.1
B13: 上振れ売上：合成石英 | C13: 億円 | E13: =D_半導体!E15 -> 0 | F13: =D_半導体!F15 -> 1.05 | G13: =D_半導体!G15 -> 11.223287 | H13: =D_半導体!H15 -> 14.675192 | I13: =D_半導体!I15 -> 18.133569
B14: 上振れ売上：リソマックス | C14: 億円 | E14: =D_半導体!E25 -> 0 | F14: =D_半導体!F25 -> 7.632 | G14: =D_半導体!G25 -> 14.722982 | H14: =D_半導体!H25 -> 18.795811 | I14: =D_半導体!I25 -> 22.764333
B15: 上振れ売上：Zoox | C15: 億円 | E15: =D_Zoox!E9 -> 0 | F15: =D_Zoox!F9 -> 100 | G15: =D_Zoox!G9 -> 100 | H15: =D_Zoox!H9 -> 100 | I15: =D_Zoox!I9 -> 100
B16: 上振れコア：合成石英 | C16: 億円 | E16: =D_半導体!E16 -> 0 | F16: =D_半導体!F16 -> 0.4725 | G16: =D_半導体!G16 -> 5.0504789 | H16: =D_半導体!H16 -> 6.6038366 | I16: =D_半導体!I16 -> 8.1601062
B17: 上振れコア：リソマックス | C17: 億円 | E17: =D_半導体!E26 -> 0 | F17: =D_半導体!F26 -> 2.6712 | G17: =D_半導体!G26 -> 5.1530438 | H17: =D_半導体!H26 -> 6.5785338 | I17: =D_半導体!I26 -> 7.9675166
B18: 上振れコア：Zoox | C18: 億円 | E18: =D_Zoox!E10 -> 0 | F18: =D_Zoox!F10 -> 15 | G18: =D_Zoox!G10 -> 15 | H18: =D_Zoox!H10 -> 15 | I18: =D_Zoox!I10 -> 15
B19: SM 売上 | C19: 億円 | E19: =E10+E13+E14+E15 -> 12370 | F19: =F10+F13+F14+F15 -> 13588.682 | G19: =G10+G13+G14+G15 -> 14715.946 | H19: =H10+H13+H14+H15 -> 15833.471 | I19: =I10+I13+I14+I15 -> 16468.898
B20: SM コア営業利益 | C20: 億円 | E20: =E11+E16+E17+E18 -> 900 | F20: =F11+F16+F17+F18 -> 1134.8104 | G20: =G11+G16+G17+G18 -> 1358.5369 | H20: =H11+H16+H17+H18 -> 1578.1824 | I20: =I11+I16+I17+I18 -> 1663.9276
B22: MMA&D・ベーシック・その他・産業ガス
B23: MMA&D 売上 | C23: 億円 | E23: =前提!$D$38 -> 3490 | F23: =E23*(1+前提!$D$54) -> 3524.9 | G23: =F23*(1+前提!$D$54) -> 3560.149 | H23: =G23*(1+前提!$D$54) -> 3595.7505 | I23: =H23*(1+前提!$D$54) -> 3631.708
B24: MMA&D コア営業利益 | C24: 億円 | E24: =前提!E11 -> 110 | F24: =前提!F11 -> 120 | G24: =前提!G11 -> 140 | H24: =前提!H11 -> 160 | I24: =前提!I11 -> 170
B25: BM 売上（連結範囲） | C25: 億円 | E25: =分社化・合併!E30 -> 6830 | F25: =分社化・合併!F30 -> 6330 | G25: =分社化・合併!G30 -> 0 | H25: =分社化・合併!H30 -> 0 | I25: =分社化・合併!I30 -> 0 | J25: 合併後はゼロ
B26: BM コア営業利益（連結範囲） | C26: 億円 | E26: =分社化・合併!E31 -> -50 | F26: =分社化・合併!F31 -> -119.63184 | G26: =分社化・合併!G31 -> 0 | H26: =分社化・合併!H31 -> 0 | I26: =分社化・合併!I31 -> 0
B27: BM 合弁の持分法利益（コアに含む） | C27: 億円 | E27: =分社化・合併!E34 -> 0 | F27: =分社化・合併!F34 -> 0 | G27: =分社化・合併!G34 -> -55.74229 | H27: =分社化・合併!H34 -> -6.7422902 | I27: =分社化・合併!I34 -> 45.628855
B28: その他 売上 | C28: 億円 | E28: =前提!$D$40 -> 1590 | F28: =E28*(1+前提!$D$55) -> 1590 | G28: =F28*(1+前提!$D$55) -> 1590 | H28: =G28*(1+前提!$D$55) -> 1590 | I28: =H28*(1+前提!$D$55) -> 1590 | J28: 成長率は仮定（0%）
B29: その他 コア営業利益 | C29: 億円 | E29: =前提!E16 -> 40 | F29: =前提!F16 -> 0 | G29: =前提!G16 -> 0 | H29: =前提!H16 -> 0 | I29: =前提!I16 -> 0
B30: 産業ガス 売上 | C30: 億円 | E30: =前提!$D$41 -> 13720 | F30: =E30*(1+前提!$D$56) -> 14268.8 | G30: =F30*(1+前提!$D$56) -> 14839.552 | H30: =G30*(1+前提!$D$56) -> 15433.134 | I30: =H30*(1+前提!$D$56) -> 16050.459
B31: 産業ガス コア営業利益 | C31: 億円 | E31: =前提!E15 -> 2050 | F31: =前提!F15 -> 2150 | G31: =前提!G15 -> 2260 | H31: =前提!H15 -> 2370 | I31: =前提!I15 -> 2480
B33: 連結（ケースA）
B34: 売上収益 計 | C34: 億円 | E34: =E19+E23+E25+E28+E30 -> 38000 | F34: =F19+F23+F25+F28+F30 -> 39302.382 | G34: =G19+G23+G25+G28+G30 -> 34705.647 | H34: =H19+H23+H25+H28+H30 -> 36452.356 | I34: =I19+I23+I25+I28+I30 -> 37741.065
B35: コア営業利益 計 | C35: 億円 | E35: =E20+E24+E26+E27+E29+E31 -> 3050 | F35: =F20+F24+F26+F27+F29+F31 -> 3285.1785 | G35: =G20+G24+G26+G27+G29+G31 -> 3702.7946 | H35: =H20+H24+H26+H27+H29+H31 -> 4101.4401 | I35: =I20+I24+I26+I27+I29+I31 -> 4359.5565
B36: コア営業利益率 | C36: % | E36: =E35/E34 -> 0.080263158 | F36: =F35/F34 -> 0.083587263 | G36: =G35/G34 -> 0.10669141 | H36: =H35/H34 -> 0.11251509 | I36: =I35/I34 -> 0.11551228
B38: 上振れの内訳（コア営業利益への寄与）
B39: 合成石英 | C39: 億円 | E39: =E16 -> 0 | F39: =F16 -> 0.4725 | G39: =G16 -> 5.0504789 | H39: =H16 -> 6.6038366 | I39: =I16 -> 8.1601062
B40: リソマックス | C40: 億円 | E40: =E17 -> 0 | F40: =F17 -> 2.6712 | G40: =G17 -> 5.1530438 | H40: =H17 -> 6.5785338 | I40: =I17 -> 7.9675166
B41: Zoox | C41: 億円 | E41: =E18 -> 0 | F41: =F18 -> 15 | G41: =G18 -> 15 | H41: =H18 -> 15 | I41: =I18 -> 15
B42: 丸善千葉停止 | C42: 億円 | E42: =D_石化!E8*IF(分社化・合併!E6=1,前提!$D$102*前提!$D$103*(1-前提!$D$105),1) -> 0 | F42: =D_石化!F8*IF(分社化・合併!F6=1,前提!$D$102*前提!$D$103*(1-前提!$D$105),1) -> 30.368157 | G42: =D_石化!G8*IF(分社化・合併!G6=1,前提!$D$102*前提!$D$103*(1-前提!$D$105),1) -> 21.25771 | H42: =D_石化!H8*IF(分社化・合併!H6=1,前提!$D$102*前提!$D$103*(1-前提!$D$105),1) -> 21.25771 | I42: =D_石化!I8*IF(分社化・合併!I6=1,前提!$D$102*前提!$D$103*(1-前提!$D$105),1) -> 21.25771 | J42: 合併後は持分法経由（×50%×2×(1−30%)）
B43: 水島停止 | C43: 億円 | E43: =D_石化!E12*IF(分社化・合併!E6=1,前提!$D$102*前提!$D$103*(1-前提!$D$105),1) -> 0 | F43: =D_石化!F12*IF(分社化・合併!F6=1,前提!$D$102*前提!$D$103*(1-前提!$D$105),1) -> 0 | G43: =D_石化!G12*IF(分社化・合併!G6=1,前提!$D$102*前提!$D$103*(1-前提!$D$105),1) -> 0 | H43: =D_石化!H12*IF(分社化・合併!H6=1,前提!$D$102*前提!$D$103*(1-前提!$D$105),1) -> 0 | I43: =D_石化!I12*IF(分社化・合併!I6=1,前提!$D$102*前提!$D$103*(1-前提!$D$105),1) -> 45.371145 | J43: 同上
B44: 合併統合効果 | C44: 億円 | E44: =分社化・合併!E32*前提!$D$102*(1-前提!$D$105) -> 0 | F44: =分社化・合併!F32*前提!$D$102*(1-前提!$D$105) -> 0 | G44: =分社化・合併!G32*前提!$D$102*(1-前提!$D$105) -> 0 | H44: =分社化・合併!H32*前提!$D$102*(1-前提!$D$105) -> 35 | I44: =分社化・合併!I32*前提!$D$102*(1-前提!$D$105) -> 35 | J44: 当社持分50%×(1−30%)
B45: 上振れ 計 | C45: 億円 | E45: =E39+E40+E41+E42+E43+E44 -> 0 | F45: =F39+F40+F41+F42+F43+F44 -> 48.511857 | G45: =G39+G40+G41+G42+G43+G44 -> 46.461233 | H45: =H39+H40+H41+H42+H43+H44 -> 84.44008 | I45: =I39+I40+I41+I42+I43+I44 -> 132.75648

Sheet 連結PL
B1: 連結PL（ケースA＝JSRなし／ケースB＝JSRあり）
B2: 当期利益＝(コア＋非経常−金融費用)×(1−27%)＋合併除外損益×(1−30%)−非支配株主利益
B4: 項目 | C4: 単位 | D4: 2025年度 | E4: 2026年度 | F4: 2027年度 | G4: 2028年度 | H4: 2029年度 | I4: 2030年度 | J4: 出所・算式
B5: ケースA（JSRなし＝本体）
B6: 売上収益 | C6: 億円 | D6: =前提!$D$132 -> 37040 | E6: =セグメント!E34 -> 38000 | F6: =セグメント!F34 -> 39302.382 | G6: =セグメント!G34 -> 34705.647 | H6: =セグメント!H34 -> 36452.356 | I6: =セグメント!I34 -> 37741.065 | J6: 2025年度は実績（運転資本の計算用）
B7: コア営業利益 | C7: 億円 | E7: =セグメント!E35 -> 3050 | F7: =セグメント!F35 -> 3285.1785 | G7: =セグメント!G35 -> 3702.7946 | H7: =セグメント!H35 -> 4101.4401 | I7: =セグメント!I35 -> 4359.5565
B8: うち持分法利益 | C8: 億円 | E8: =セグメント!E27 -> 0 | F8: =セグメント!F27 -> 0 | G8: =セグメント!G27 -> -55.74229 | H8: =セグメント!H27 -> -6.7422902 | I8: =セグメント!I27 -> 45.628855
B9: 非経常損益（分社化・合併以外） | C9: 億円 | E9: =前提!E17 -> -50 | F9: =前提!F17 -> -350 | G9: =前提!G17 -> -400 | H9: =前提!H17 -> -300 | I9: =前提!I17 -> -300
B10: 分社化の一時費用 | C10: 億円 | E10: =分社化・合併!E9 -> 0 | F10: =分社化・合併!F9 -> -50 | G10: =分社化・合併!G9 -> 0 | H10: =分社化・合併!H9 -> 0 | I10: =分社化・合併!I9 -> 0
B11: 合併除外損益（税前） | C11: 億円 | E11: =分社化・合併!E23 -> 0 | F11: =分社化・合併!F23 -> 0 | G11: =分社化・合併!G23 -> -3852.4537 | H11: =分社化・合併!H23 -> 0 | I11: =分社化・合併!I23 -> 0
B12: 期首純有利子負債（期首取引後） | C12: 億円 | E12: =連結BS!D16-分社化・合併!E26 -> 14648 | F12: =連結BS!E16-分社化・合併!F26 -> 14001.465 | G12: =連結BS!F16-分社化・合併!G26 -> 12827.725 | H12: =連結BS!G16-分社化・合併!H26 -> 11733.496 | I12: =連結BS!H16-分社化・合併!I26 -> 10251.112 | J12: 合併の負債移転は期首
B13: 金融費用 | C13: 億円 | E13: =E12*前提!$D$121 -> 292.96 | F13: =F12*前提!$D$121 -> 280.02929 | G13: =G12*前提!$D$121 -> 256.5545 | H13: =H12*前提!$D$121 -> 234.66991 | I13: =I12*前提!$D$121 -> 205.02224 | J13: 期首純有利子負債×2.0%
B14: 税前利益（除外損益を除く） | C14: 億円 | E14: =E7+E9+E10-E13 -> 2707.04 | F14: =F7+F9+F10-F13 -> 2605.1492 | G14: =G7+G9+G10-G13 -> 3046.2401 | H14: =H7+H9+H10-H13 -> 3566.7702 | I14: =I7+I9+I10-I13 -> 3854.5342
B15: 法人税等（27%） | C15: 億円 | E15: =-E14*前提!$D$122 -> -730.9008 | F15: =-F14*前提!$D$122 -> -703.39029 | G15: =-G14*前提!$D$122 -> -822.48482 | H15: =-H14*前提!$D$122 -> -963.02795 | I15: =-I14*前提!$D$122 -> -1040.7242
B16: 持分法利益の二重課税の戻し（切替） | C16: 億円 | E16: =前提!$D$32*E8*前提!$D$122 -> 0 | F16: =前提!$D$32*F8*前提!$D$122 -> 0 | G16: =前提!$D$32*G8*前提!$D$122 -> -15.050418 | H16: =前提!$D$32*H8*前提!$D$122 -> -1.8204184 | I16: =前提!$D$32*I8*前提!$D$122 -> 12.319791 | J16: 既定0＝設計どおり
B17: 合併除外損益（税後30%） | C17: 億円 | E17: =E11*(1-前提!$D$108) -> 0 | F17: =F11*(1-前提!$D$108) -> 0 | G17: =G11*(1-前提!$D$108) -> -2696.7176 | H17: =H11*(1-前提!$D$108) -> 0 | I17: =I11*(1-前提!$D$108) -> 0
B18: 当期利益（非支配含む） | C18: 億円 | E18: =E14+E15+E16+E17 -> 1976.1392 | F18: =F14+F15+F16+F17 -> 1901.7589 | G18: =G14+G15+G16+G17 -> -488.01279 | H18: =H14+H15+H16+H17 -> 2601.9218 | I18: =I14+I15+I16+I17 -> 2826.1298
B19: 日本酸素 当期利益 | C19: 億円 | E19: =前提!$D$114*セグメント!E31/セグメント!$E$31 -> 1310 | F19: =前提!$D$114*セグメント!F31/セグメント!$E$31 -> 1373.9024 | G19: =前提!$D$114*セグメント!G31/セグメント!$E$31 -> 1444.1951 | H19: =前提!$D$114*セグメント!H31/セグメント!$E$31 -> 1514.4878 | I19: =前提!$D$114*セグメント!I31/セグメント!$E$31 -> 1584.7805 | J19: 2026＝1,310、以後コア比例
B20: 非支配株主利益 | C20: 億円 | E20: =前提!$D$115*E19+前提!$D$117 -> 697.271 | F20: =前提!$D$115*F19+前提!$D$117 -> 728.8452 | G20: =前提!$D$115*G19+前提!$D$117 -> 763.57681 | H20: =前提!$D$115*H19+前提!$D$117 -> 798.30842 | I20: =前提!$D$115*I19+前提!$D$117 -> 833.04004 | J20: 49.41%×日本酸素＋その他50
B21: 親会社の所有者に帰属する当期利益 | C21: 億円 | E21: =E18-E20 -> 1278.8682 | F21: =F18-F20 -> 1172.9137 | G21: =G18-G20 -> -1251.5896 | H21: =H18-H20 -> 1803.6134 | I21: =I18-I20 -> 1993.0897
B22: EPS | C22: 円 | E22: =E21/前提!$D$124*100 -> 94.124398 | F22: =F21/前提!$D$124*100 -> 86.326175 | G22: =G21/前提!$D$124*100 -> -92.1167 | H22: =H21/前提!$D$124*100 -> 132.74552 | I22: =I21/前提!$D$124*100 -> 146.69094 | J22: ÷1,358.7百万株
B23: 配当（親会社株主） | C23: 億円 | E23: =MAX(前提!$D$125*前提!$D$124/100,前提!$D$126*E21) -> 447.60387 | F23: =MAX(前提!$D$125*前提!$D$124/100,前提!$D$126*F21) -> 434.784 | G23: =MAX(前提!$D$125*前提!$D$124/100,前提!$D$126*G21) -> 434.784 | H23: =MAX(前提!$D$125*前提!$D$124/100,前提!$D$126*H21) -> 631.26468 | I23: =MAX(前提!$D$125*前提!$D$124/100,前提!$D$126*I21) -> 697.58141 | J23: MAX(32円×株数, 35%×当期利益)
B24: 配当（非支配株主） | C24: 億円 | E24: =前提!$D$118*E19/$E$19 -> 141 | F24: =前提!$D$118*F19/$E$19 -> 147.87805 | G24: =前提!$D$118*G19/$E$19 -> 155.4439 | H24: =前提!$D$118*H19/$E$19 -> 163.00976 | I24: =前提!$D$118*I19/$E$19 -> 170.57561 | J24: 2026＝141、以後当期利益比例
B25: ROIC | C25: % | E25: =((E7-前提!$D$32*E8)*(1-前提!$D$123)+前提!$D$32*E8)/AVERAGE(連結BS!D20,連結BS!E20) -> 0.048894436 | F25: =((F7-前提!$D$32*F8)*(1-前提!$D$123)+前提!$D$32*F8)/AVERAGE(連結BS!E20,連結BS!F20) -> 0.051841602 | G25: =((G7-前提!$D$32*G8)*(1-前提!$D$123)+前提!$D$32*G8)/AVERAGE(連結BS!F20,連結BS!G20) -> 0.059412302 | H25: =((H7-前提!$D$32*H8)*(1-前提!$D$123)+前提!$D$32*H8)/AVERAGE(連結BS!G20,連結BS!H20) -> 0.06803135 | I25: =((I7-前提!$D$32*I8)*(1-前提!$D$123)+前提!$D$32*I8)/AVERAGE(連結BS!H20,連結BS!I20) -> 0.072188341 | J25: （コア−持分法）×(1−30%)＋持分法、÷(資本合計＋有利子負債)の期首期末平均（切替0なら設計書当初式）
B26: ネットD/E | C26: 倍 | E26: =連結BS!E21 -> 0.75895837 | F26: =連結BS!F21 -> 0.6946446 | G26: =連結BS!G21 -> 0.67048468 | H26: =連結BS!H21 -> 0.54899901 | I26: =連結BS!I21 -> 0.42829163 | J26: 純有利子負債÷親会社持分（B はハイブリッド債の資本性調整後）
B28: ケースB（JSRあり）
B29: 売上収益 | C29: 億円 | D29: =D6 -> 37040 | E29: =E6+D_JSR!E47 -> 38000 | F29: =F6+D_JSR!F47 -> 39302.382 | G29: =G6+D_JSR!G47 -> 34705.647 | H29: =H6+D_JSR!H47 -> 36452.356 | I29: =I6+D_JSR!I47 -> 37741.065 | J29: ケースA＋JSR 連結売上
B30: コア営業利益 | C30: 億円 | E30: =E7+D_JSR!E44+D_JSR!E48 -> 3050 | F30: =F7+D_JSR!F44+D_JSR!F48 -> 3330.1768 | G30: =G7+D_JSR!G44+D_JSR!G48 -> 3809.7995 | H30: =H7+D_JSR!H44+D_JSR!H48 -> 4234.8575 | I30: =I7+D_JSR!I44+D_JSR!I48 -> 4643.2513 | J30: ケースA＋JSR 持分法利益＋JSR 連結コア
B31: うち持分法利益 | C31: 億円 | E31: =E8+D_JSR!E44 -> 0 | F31: =F8+D_JSR!F44 -> 44.998283 | G31: =G8+D_JSR!G44 -> 51.262617 | H31: =H8+D_JSR!H44 -> 126.67516 | I31: =I8+D_JSR!I44 -> 329.32368
B32: 非経常損益（分社化・合併以外） | C32: 億円 | E32: =前提!E17 -> -50 | F32: =前提!F17 -> -350 | G32: =前提!G17 -> -400 | H32: =前提!H17 -> -300 | I32: =前提!I17 -> -300
B33: 分社化の一時費用 | C33: 億円 | E33: =分社化・合併!E9 -> 0 | F33: =分社化・合併!F9 -> -50 | G33: =分社化・合併!G9 -> 0 | H33: =分社化・合併!H9 -> 0 | I33: =分社化・合併!I9 -> 0
B34: 合併除外損益（税前） | C34: 億円 | E34: =分社化・合併!E23 -> 0 | F34: =分社化・合併!F23 -> 0 | G34: =分社化・合併!G23 -> -3852.4537 | H34: =分社化・合併!H23 -> 0 | I34: =分社化・合併!I23 -> 0
B35: 期首純有利子負債（期首取引後） | C35: 億円 | E35: =連結BS!D38-分社化・合併!E26+D_JSR!E33+D_JSR!E34+D_JSR!E26*前提!$D$136 -> 14648 | F35: =連結BS!E38-分社化・合併!F26+D_JSR!F33+D_JSR!F34+D_JSR!F26*前提!$D$136 -> 14001.465 | G35: =連結BS!F38-分社化・合併!G26+D_JSR!G33+D_JSR!G34+D_JSR!G26*前提!$D$136 -> 14873.434 | H35: =連結BS!G38-分社化・合併!H26+D_JSR!H33+D_JSR!H34+D_JSR!H26*前提!$D$136 -> 14086.045 | I35: =連結BS!H38-分社化・合併!I26+D_JSR!I33+D_JSR!I34+D_JSR!I26*前提!$D$136 -> 15075.441 | J35: JSR の追加取得・全額取得は期首（代金＋連結時の JSR 純有利子負債）
B36: 金融費用 | C36: 億円 | E36: =E35*前提!$D$121+D_JSR!E32*前提!$D$121*前提!$D$141+D_JSR!E39 -> 292.96 | F36: =F35*前提!$D$121+D_JSR!F32*前提!$D$121*前提!$D$141+D_JSR!F39 -> 300.02929 | G36: =G35*前提!$D$121+D_JSR!G32*前提!$D$121*前提!$D$141+D_JSR!G39 -> 297.46868 | H36: =H35*前提!$D$121+D_JSR!H32*前提!$D$121*前提!$D$141+D_JSR!H39 -> 281.7209 | I36: =I35*前提!$D$121+D_JSR!I32*前提!$D$121*前提!$D$141+D_JSR!I39 -> 301.50881 | J36: ＋第1段取得（下期）の半年分＋ハイブリッド債の上乗せ金利
B37: 税前利益（除外損益を除く） | C37: 億円 | E37: =E30+E32+E33-E36 -> 2707.04 | F37: =F30+F32+F33-F36 -> 2630.1475 | G37: =G30+G32+G33-G36 -> 3112.3308 | H37: =H30+H32+H33-H36 -> 3653.1366 | I37: =I30+I32+I33-I36 -> 4041.7425
B38: 法人税等（27%） | C38: 億円 | E38: =-E37*前提!$D$122 -> -730.9008 | F38: =-F37*前提!$D$122 -> -710.13983 | G38: =-G37*前提!$D$122 -> -840.32931 | H38: =-H37*前提!$D$122 -> -986.34689 | I38: =-I37*前提!$D$122 -> -1091.2705
B39: 持分法利益の二重課税の戻し（切替） | C39: 億円 | E39: =前提!$D$32*E31*前提!$D$122 -> 0 | F39: =前提!$D$32*F31*前提!$D$122 -> 12.149536 | G39: =前提!$D$32*G31*前提!$D$122 -> 13.840907 | H39: =前提!$D$32*H31*前提!$D$122 -> 34.202293 | I39: =前提!$D$32*I31*前提!$D$122 -> 88.917393 | J39: 既定0＝設計どおり
B40: 合併除外損益（税後30%） | C40: 億円 | E40: =E34*(1-前提!$D$108) -> 0 | F40: =F34*(1-前提!$D$108) -> 0 | G40: =G34*(1-前提!$D$108) -> -2696.7176 | H40: =H34*(1-前提!$D$108) -> 0 | I40: =I34*(1-前提!$D$108) -> 0
B41: 当期利益（非支配含む） | C41: 億円 | E41: =E37+E38+E39+E40 -> 1976.1392 | F41: =F37+F38+F39+F40 -> 1932.1572 | G41: =G37+G38+G39+G40 -> -410.87523 | H41: =H37+H38+H39+H40 -> 2700.992 | I41: =I37+I38+I39+I40 -> 3039.3894
B42: 日本酸素 当期利益 | C42: 億円 | E42: =E19 -> 1310 | F42: =F19 -> 1373.9024 | G42: =G19 -> 1444.1951 | H42: =H19 -> 1514.4878 | I42: =I19 -> 1584.7805
B43: 非支配株主利益 | C43: 億円 | E43: =E20 -> 697.271 | F43: =F20 -> 728.8452 | G43: =G20 -> 763.57681 | H43: =H20 -> 798.30842 | I43: =I20 -> 833.04004
B44: 親会社の所有者に帰属する当期利益 | C44: 億円 | E44: =E41-E43 -> 1278.8682 | F44: =F41-F43 -> 1203.312 | G44: =G41-G43 -> -1174.452 | H44: =H41-H43 -> 1902.6836 | I44: =I41-I43 -> 2206.3494
B45: EPS | C45: 円 | E45: =E44/前提!$D$124*100 -> 94.124398 | F45: =F44/前提!$D$124*100 -> 88.563482 | G45: =G44/前提!$D$124*100 -> -86.439394 | H45: =H44/前提!$D$124*100 -> 140.03707 | I45: =I44/前提!$D$124*100 -> 162.38679 | J45: ÷1,358.7百万株
B46: 配当（親会社株主） | C46: 億円 | E46: =MAX(前提!$D$125*前提!$D$124/100,前提!$D$126*E44) -> 447.60387 | F46: =MAX(前提!$D$125*前提!$D$124/100,前提!$D$126*F44) -> 434.784 | G46: =MAX(前提!$D$125*前提!$D$124/100,前提!$D$126*G44) -> 434.784 | H46: =MAX(前提!$D$125*前提!$D$124/100,前提!$D$126*H44) -> 665.93926 | I46: =MAX(前提!$D$125*前提!$D$124/100,前提!$D$126*I44) -> 772.22228 | J46: MAX(32円×株数, 35%×当期利益)
B47: 配当（非支配株主） | C47: 億円 | E47: =E24 -> 141 | F47: =F24 -> 147.87805 | G47: =G24 -> 155.4439 | H47: =H24 -> 163.00976 | I47: =I24 -> 170.57561
B48: ROIC | C48: % | E48: =((E30-前提!$D$32*E31)*(1-前提!$D$123)+前提!$D$32*E31)/AVERAGE(連結BS!D42,連結BS!E42) -> 0.048894436 | F48: =((F30-前提!$D$32*F31)*(1-前提!$D$123)+前提!$D$32*F31)/AVERAGE(連結BS!E42,連結BS!F42) -> 0.051665104 | G48: =((G30-前提!$D$32*G31)*(1-前提!$D$123)+前提!$D$32*G31)/AVERAGE(連結BS!F42,連結BS!G42) -> 0.059003233 | H48: =((H30-前提!$D$32*H31)*(1-前提!$D$123)+前提!$D$32*H31)/AVERAGE(連結BS!G42,連結BS!H42) -> 0.067379141 | I48: =((I30-前提!$D$32*I31)*(1-前提!$D$123)+前提!$D$32*I31)/AVERAGE(連結BS!H42,連結BS!I42) -> 0.072177757 | J48: （コア−持分法）×(1−30%)＋持分法、÷(資本合計＋有利子負債)の期首期末平均（切替0なら設計書当初式）
B49: ネットD/E | C49: 倍 | E49: =連結BS!E46 -> 0.75895837 | F49: =連結BS!F46 -> 0.79838117 | G49: =連結BS!G46 -> 0.78426964 | H49: =連結BS!H46 -> 0.67249423 | I49: =連結BS!I46 -> 0.6667913 | J49: 純有利子負債÷親会社持分（B はハイブリッド債の資本性調整後）
B51: JSR による差（B−A）
B52: コア営業利益の差 | C52: 億円 | E52: =E30-E7 -> 0 | F52: =F30-F7 -> 44.998283 | G52: =G30-G7 -> 107.00491 | H52: =H30-H7 -> 133.41745 | I52: =I30-I7 -> 283.69482
B53: 親会社当期利益の差 | C53: 億円 | E53: =E44-E21 -> 0 | F53: =F44-F21 -> 30.398283 | G53: =G44-G21 -> 77.137559 | H53: =H44-H21 -> 99.070229 | I53: =I44-I21 -> 213.25963
B54: EPS の差 | C54: 円 | E54: =E45-E22 -> 0 | F54: =F45-F22 -> 2.2373065 | G54: =G45-G22 -> 5.6773062 | H54: =H45-H22 -> 7.2915455 | I54: =I45-I22 -> 15.695859
B55: 注1：持分法利益（合弁・JSR とも税後）はコア営業利益に含むが、連結の27%は掛けない（既定。切替0で設計書の当初式＝二重課税に戻る）。
B56: 注2：金融費用は期首取引（合併の負債移転・JSR の期首取得）後の期首純有利子負債に掛ける。
B57: 注3：2027年度の EPS 低下は、非経常▲400（分社化費用込み）と炭素撤退期の BM 赤字（▲120）による。
B58: 注4：2028年度の合併除外損は、実務上は合併前の減損として先行計上されうる。BM の公正価値（EBITDA×6倍）が資産規模6,000と見合わないこと自体が減損リスクである。

Sheet 連結BS
B1: 連結BS（簡略：正味営業資産＝親会社持分＋非支配持分＋純有利子負債）
B2: 2025年度＝2026年3月末実績。純有利子負債は BS の差額で求め、連結CF の積み上げと一致するかを検証シートで確認
B4: 項目 | C4: 単位 | D4: 2025年度末 | E4: 2026年度 | F4: 2027年度 | G4: 2028年度 | H4: 2029年度 | I4: 2030年度 | J4: 出所・算式
B5: ケースA（JSRなし）
B6: ＋設備投資 | C6: 億円 | E6: =連結CF!E6 -> 3391 | F6: =連結CF!F6 -> 3300 | G6: =連結CF!G6 -> 2920 | H6: =連結CF!H6 -> 2720 | I6: =連結CF!I6 -> 2720
B7: −減価償却 | C7: 億円 | E7: =-連結CF!E7 -> -2794 | F7: =-連結CF!F7 -> -2850 | G7: =-連結CF!G7 -> -2600 | H7: =-連結CF!H7 -> -2650 | I7: =-連結CF!I7 -> -2700
B8: ＋運転資本の増加 | C8: 億円 | E8: =連結CF!E9 -> 144 | F8: =連結CF!F9 -> 195.3573 | G8: =連結CF!G9 -> 259.98979 | H8: =連結CF!H9 -> 262.00625 | I8: =連結CF!I9 -> 193.30647
B9: −合併で連結から外れる BM 正味営業資産 | C9: 億円 | E9: =-分社化・合併!E25 -> 0 | F9: =-分社化・合併!F25 -> 0 | G9: =-分社化・合併!G25 -> -5300 | H9: =-分社化・合併!H25 -> 0 | I9: =-分社化・合併!I25 -> 0
B10: ＋合弁株式（公正価値） | C10: 億円 | E10: =分社化・合併!E27 -> 0 | F10: =分社化・合併!F27 -> 0 | G10: =分社化・合併!G27 -> 947.54626 | H10: =分社化・合併!H27 -> 0 | I10: =分社化・合併!I27 -> 0
B11: ＋持分法損益の積み上げ | C11: 億円 | E11: =連結PL!E8 -> 0 | F11: =連結PL!F8 -> 0 | G11: =連結PL!G8 -> -55.74229 | H11: =連結PL!H8 -> -6.7422902 | I11: =連結PL!I8 -> 45.628855
B12: ＋繰延税金資産（合併除外損の税効果、非資金） | C12: 億円 | E12: =-連結PL!E11*前提!$D$108 -> 0 | F12: =-連結PL!F11*前提!$D$108 -> 0 | G12: =-連結PL!G11*前提!$D$108 -> 1155.7361 | H12: =-連結PL!H11*前提!$D$108 -> 0 | I12: =-連結PL!I11*前提!$D$108 -> 0
B13: 正味営業資産 | C13: 億円 | D13: =前提!$D$127+前提!$D$128+前提!$D$129 -> 38795 | E13: =D13+E6+E7+E8+E9+E10+E11+E12 -> 39536 | F13: =E13+F6+F7+F8+F9+F10+F11+F12 -> 40181.357 | G13: =F13+G6+G7+G8+G9+G10+G11+G12 -> 37508.887 | H13: =G13+H6+H7+H8+H9+H10+H11+H12 -> 37834.151 | I13: =H13+I6+I7+I8+I9+I10+I11+I12 -> 38093.086
B14: 親会社の所有者に帰属する持分 | C14: 億円 | D14: =前提!$D$127 -> 17617 | E14: =D14+連結PL!E21-連結PL!E23 -> 18448.264 | F14: =E14+連結PL!F21-連結PL!F23 -> 19186.394 | G14: =F14+連結PL!G21-連結PL!G23 -> 17500.02 | H14: =G14+連結PL!H21-連結PL!H23 -> 18672.369 | I14: =H14+連結PL!I21-連結PL!I23 -> 19967.878
B15: 非支配持分 | C15: 億円 | D15: =前提!$D$128 -> 6530 | E15: =D15+連結PL!E20-連結PL!E24 -> 7086.271 | F15: =E15+連結PL!F20-連結PL!F24 -> 7667.2381 | G15: =F15+連結PL!G20-連結PL!G24 -> 8275.3711 | H15: =G15+連結PL!H20-連結PL!H24 -> 8910.6697 | I15: =H15+連結PL!I20-連結PL!I24 -> 9573.1342
B16: 純有利子負債（BS 差額） | C16: 億円 | D16: =D13-D14-D15 -> 14648 | E16: =E13-E14-E15 -> 14001.465 | F16: =F13-F14-F15 -> 13327.725 | G16: =G13-G14-G15 -> 11733.496 | H16: =H13-H14-H15 -> 10251.112 | I16: =I13-I14-I15 -> 8552.0748
B17: 現金及び現金同等物 | C17: 億円 | D17: =前提!$D$130 -> 4500 | E17: =前提!$D$130 -> 4500 | F17: =前提!$D$130 -> 4500 | G17: =前提!$D$130 -> 4500 | H17: =前提!$D$130 -> 4500 | I17: =前提!$D$130 -> 4500
B18: 有利子負債（純有利子負債＋現金） | C18: 億円 | D18: =D16+D17 -> 19148 | E18: =E16+E17 -> 18501.465 | F18: =F16+F17 -> 17827.725 | G18: =G16+G17 -> 16233.496 | H18: =H16+H17 -> 14751.112 | I18: =I16+I17 -> 13052.075
B19: 資本合計 | C19: 億円 | D19: =D14+D15 -> 24147 | E19: =E14+E15 -> 25534.535 | F19: =F14+F15 -> 26853.632 | G19: =G14+G15 -> 25775.392 | H19: =H14+H15 -> 27583.039 | I19: =I14+I15 -> 29541.012
B20: 投下資本（資本合計＋有利子負債） | C20: 億円 | D20: =D19+D18 -> 43295 | E20: =E19+E18 -> 44036 | F20: =F19+F18 -> 44681.357 | G20: =G19+G18 -> 42008.887 | H20: =H19+H18 -> 42334.151 | I20: =I19+I18 -> 42593.086
B21: ネットD/E | C21: 倍 | D21: =D16/D14 -> 0.8314696 | E21: =E16/E14 -> 0.75895837 | F21: =F16/F14 -> 0.6946446 | G21: =G16/G14 -> 0.67048468 | H21: =H16/H14 -> 0.54899901 | I21: =I16/I14 -> 0.42829163
B22: 均衡差（正味営業資産−資本合計−純有利子負債） | C22: 億円 | D22: =D13-D19-D16 -> 0 | E22: =E13-E19-E16 -> 0 | F22: =F13-F19-F16 -> 0 | G22: =G13-G19-G16 -> 0 | H22: =H13-H19-H16 -> 0 | I22: =I13-I19-I16 -> 0
B24: ケースB（JSRあり）
B25: ＋設備投資 | C25: 億円 | E25: =連結CF!E28 -> 3391 | F25: =連結CF!F28 -> 3300 | G25: =連結CF!G28 -> 2920 | H25: =連結CF!H28 -> 2720 | I25: =連結CF!I28 -> 2720
B26: −減価償却 | C26: 億円 | E26: =-連結CF!E29 -> -2794 | F26: =-連結CF!F29 -> -2850 | G26: =-連結CF!G29 -> -2600 | H26: =-連結CF!H29 -> -2650 | I26: =-連結CF!I29 -> -2700
B27: ＋運転資本の増加 | C27: 億円 | E27: =連結CF!E31 -> 144 | F27: =連結CF!F31 -> 195.3573 | G27: =連結CF!G31 -> 259.98979 | H27: =連結CF!H31 -> 262.00625 | I27: =連結CF!I31 -> 193.30647
B28: −合併で連結から外れる BM 正味営業資産 | C28: 億円 | E28: =-分社化・合併!E25 -> 0 | F28: =-分社化・合併!F25 -> 0 | G28: =-分社化・合併!G25 -> -5300 | H28: =-分社化・合併!H25 -> 0 | I28: =-分社化・合併!I25 -> 0
B29: ＋合弁株式（公正価値） | C29: 億円 | E29: =分社化・合併!E27 -> 0 | F29: =分社化・合併!F27 -> 0 | G29: =分社化・合併!G27 -> 947.54626 | H29: =分社化・合併!H27 -> 0 | I29: =分社化・合併!I27 -> 0
B30: ＋持分法損益の積み上げ | C30: 億円 | E30: =連結PL!E31 -> 0 | F30: =連結PL!F31 -> 44.998283 | G30: =連結PL!G31 -> 51.262617 | H30: =連結PL!H31 -> 126.67516 | I30: =連結PL!I31 -> 329.32368
B31: ＋繰延税金資産（合併除外損の税効果、非資金） | C31: 億円 | E31: =-連結PL!E34*前提!$D$108 -> 0 | F31: =-連結PL!F34*前提!$D$108 -> 0 | G31: =-連結PL!G34*前提!$D$108 -> 1155.7361 | H31: =-連結PL!H34*前提!$D$108 -> 0 | I31: =-連結PL!I34*前提!$D$108 -> 0
B32: ＋JSR 株式の取得（持分法の期間） | C32: 億円 | E32: =D_JSR!E35 -> 0 | F32: =D_JSR!F35 -> 2000 | G32: =D_JSR!G35 -> 31.108804 | H32: =D_JSR!H35 -> 276.97324 | I32: =D_JSR!I35 -> 2402.7571
B33: −JSR 持分法投資の振替（連結時） | C33: 億円 | E33: =-D_JSR!E45 -> 0 | F33: =-D_JSR!F45 -> 0 | G33: =-D_JSR!G45 -> 0 | H33: =-D_JSR!H45 -> 0 | I33: =-D_JSR!I45 -> 0
B34: ＋JSR 連結（純資産・のれん・取込負債） | C34: 億円 | E34: =D_JSR!E45+D_JSR!E34+D_JSR!E26*前提!$D$136 -> 0 | F34: =D_JSR!F45+D_JSR!F34+D_JSR!F26*前提!$D$136 -> 0 | G34: =D_JSR!G45+D_JSR!G34+D_JSR!G26*前提!$D$136 -> 0 | H34: =D_JSR!H45+D_JSR!H34+D_JSR!H26*前提!$D$136 -> 0 | I34: =D_JSR!I45+D_JSR!I34+D_JSR!I26*前提!$D$136 -> 0
B35: 正味営業資産 | C35: 億円 | D35: =前提!$D$127+前提!$D$128+前提!$D$129 -> 38795 | E35: =D35+E25+E26+E27+E28+E29+E30+E31+E32+E33+E34 -> 39536 | F35: =E35+F25+F26+F27+F28+F29+F30+F31+F32+F33+F34 -> 42226.356 | G35: =F35+G25+G26+G27+G28+G29+G30+G31+G32+G33+G34 -> 39691.999 | H35: =G35+H25+H26+H27+H28+H29+H30+H31+H32+H33+H34 -> 40427.654 | I35: =H35+I25+I26+I27+I28+I29+I30+I31+I32+I33+I34 -> 43373.041
B36: 親会社の所有者に帰属する持分 | C36: 億円 | D36: =前提!$D$127 -> 17617 | E36: =D36+連結PL!E44-連結PL!E46 -> 18448.264 | F36: =E36+連結PL!F44-連結PL!F46 -> 19216.792 | G36: =F36+連結PL!G44-連結PL!G46 -> 17607.556 | H36: =G36+連結PL!H44-連結PL!H46 -> 18844.301 | I36: =H36+連結PL!I44-連結PL!I46 -> 20278.428
B37: 非支配持分 | C37: 億円 | D37: =前提!$D$128 -> 6530 | E37: =D37+連結PL!E43-連結PL!E47 -> 7086.271 | F37: =E37+連結PL!F43-連結PL!F47 -> 7667.2381 | G37: =F37+連結PL!G43-連結PL!G47 -> 8275.3711 | H37: =G37+連結PL!H43-連結PL!H47 -> 8910.6697 | I37: =H37+連結PL!I43-連結PL!I47 -> 9573.1342
B38: 純有利子負債（BS 差額） | C38: 億円 | D38: =D35-D36-D37 -> 14648 | E38: =E35-E36-E37 -> 14001.465 | F38: =F35-F36-F37 -> 15342.325 | G38: =G35-G36-G37 -> 13809.072 | H38: =H35-H36-H37 -> 12672.683 | I38: =I35-I36-I37 -> 13521.479
B39: 現金及び現金同等物 | C39: 億円 | D39: =前提!$D$130 -> 4500 | E39: =前提!$D$130 -> 4500 | F39: =前提!$D$130 -> 4500 | G39: =前提!$D$130 -> 4500 | H39: =前提!$D$130 -> 4500 | I39: =前提!$D$130 -> 4500
B40: 有利子負債（純有利子負債＋現金） | C40: 億円 | D40: =D38+D39 -> 19148 | E40: =E38+E39 -> 18501.465 | F40: =F38+F39 -> 19842.325 | G40: =G38+G39 -> 18309.072 | H40: =H38+H39 -> 17172.683 | I40: =I38+I39 -> 18021.479
B41: 資本合計 | C41: 億円 | D41: =D36+D37 -> 24147 | E41: =E36+E37 -> 25534.535 | F41: =F36+F37 -> 26884.031 | G41: =G36+G37 -> 25882.927 | H41: =H36+H37 -> 27754.97 | I41: =I36+I37 -> 29851.562
B42: 投下資本（資本合計＋有利子負債） | C42: 億円 | D42: =D41+D40 -> 43295 | E42: =E41+E40 -> 44036 | F42: =F41+F40 -> 46726.356 | G42: =G41+G40 -> 44191.999 | H42: =H41+H40 -> 44927.654 | I42: =I41+I40 -> 47873.041
B43: うちハイブリッド債の残高（純有利子負債に含む） | C43: 億円 | D43: =N(D_JSR!D38) -> 0 | E43: =N(D_JSR!E38) -> 0 | F43: =N(D_JSR!F38) -> 0 | G43: =N(D_JSR!G38) -> 0 | H43: =N(D_JSR!H38) -> 0 | I43: =N(D_JSR!I38) -> 0
B44: 純有利子負債（ハイブリッド債の資本性を控除） | C44: 億円 | D44: =D38-前提!$D$147*D43 -> 14648 | E44: =E38-前提!$D$147*E43 -> 14001.465 | F44: =F38-前提!$D$147*F43 -> 15342.325 | G44: =G38-前提!$D$147*G43 -> 13809.072 | H44: =H38-前提!$D$147*H43 -> 12672.683 | I44: =I38-前提!$D$147*I43 -> 13521.479
B45: 親会社持分（ハイブリッド債の資本性を加算） | C45: 億円 | D45: =D36+前提!$D$147*D43 -> 17617 | E45: =E36+前提!$D$147*E43 -> 18448.264 | F45: =F36+前提!$D$147*F43 -> 19216.792 | G45: =G36+前提!$D$147*G43 -> 17607.556 | H45: =H36+前提!$D$147*H43 -> 18844.301 | I45: =I36+前提!$D$147*I43 -> 20278.428
B46: ネットD/E（資本性調整後） | C46: 倍 | D46: =D44/D45 -> 0.8314696 | E46: =E44/E45 -> 0.75895837 | F46: =F44/F45 -> 0.79838117 | G46: =G44/G45 -> 0.78426964 | H46: =H44/H45 -> 0.67249423 | I46: =I44/I45 -> 0.6667913 | J46: ハイブリッド切替0なら通常の定義と同じ
B47: 均衡差（正味営業資産−資本合計−純有利子負債） | C47: 億円 | D47: =D35-D41-D38 -> 0 | E47: =E35-E41-E38 -> 0 | F47: =F35-F41-F38 -> 0 | G47: =G35-G41-G38 -> 0 | H47: =H35-H41-H38 -> 0 | I47: =I35-I41-I38 -> 0
B49: 注1：正味営業資産の各増減は連結CF・分社化・合併・D_JSR の行を参照する。2025年度末は M03 p13 の実績。

Sheet 連結CF
B1: 連結CF（現金一定、借入増減で調整）
B2: 純有利子負債（CF 由来）＝期首＋借入増減＋非資金の負債増減
B4: 項目 | C4: 単位 | D4: 2025年度 | E4: 2026年度 | F4: 2027年度 | G4: 2028年度 | H4: 2029年度 | I4: 2030年度 | J4: 出所・算式
B5: ケースA（JSRなし）
B6: 設備投資（金額） | C6: 億円 | E6: =前提!E18+分社化・合併!E36 -> 3391 | F6: =前提!F18+分社化・合併!F36 -> 3300 | G6: =前提!G18+分社化・合併!G36 -> 2920 | H6: =前提!H18+分社化・合併!H36 -> 2720 | I6: =前提!I18+分社化・合併!I36 -> 2720 | J6: 合併年度以降は BM 分▲280
B7: 減価償却（金額） | C7: 億円 | E7: =前提!E19+分社化・合併!E37 -> 2794 | F7: =前提!F19+分社化・合併!F37 -> 2850 | G7: =前提!G19+分社化・合併!G37 -> 2600 | H7: =前提!H19+分社化・合併!H37 -> 2650 | I7: =前提!I19+分社化・合併!I37 -> 2700 | J7: 列は2028年度以降 BM 控除後。合併が2029年度なら2028年度に+270
B8: 前年売上（同一連結範囲） | C8: 億円 | E8: =連結PL!D6-分社化・合併!E7*N(D_石化!D14) -> 37040 | F8: =連結PL!E6-分社化・合併!F7*N(D_石化!E14) -> 38000 | G8: =連結PL!F6-分社化・合併!G7*N(D_石化!F14) -> 32972.382 | H8: =連結PL!G6-分社化・合併!H7*N(D_石化!G14) -> 34705.647 | I8: =連結PL!H6-分社化・合併!I7*N(D_石化!H14) -> 36452.356 | J8: 合併初年度は前年の BM 売上を除いて比べる
B9: 運転資本の増加 | C9: 億円 | E9: =前提!$D$131*(連結PL!E6-E8) -> 144 | F9: =前提!$D$131*(連結PL!F6-F8) -> 195.3573 | G9: =前提!$D$131*(連結PL!G6-G8) -> 259.98979 | H9: =前提!$D$131*(連結PL!H6-H8) -> 262.00625 | I9: =前提!$D$131*(連結PL!I6-I8) -> 193.30647 | J9: 売上増分×15%
B10: 当期利益（非支配含む） | C10: 億円 | E10: =連結PL!E18 -> 1976.1392 | F10: =連結PL!F18 -> 1901.7589 | G10: =連結PL!G18 -> -488.01279 | H10: =連結PL!H18 -> 2601.9218 | I10: =連結PL!I18 -> 2826.1298
B11: 減価償却 | C11: 億円 | E11: =E7 -> 2794 | F11: =F7 -> 2850 | G11: =G7 -> 2600 | H11: =H7 -> 2650 | I11: =I7 -> 2700
B12: 非資金の非経常（合併除外損益の戻し、税後） | C12: 億円 | E12: =-連結PL!E17 -> 0 | F12: =-連結PL!F17 -> 0 | G12: =-連結PL!G17 -> 2696.7176 | H12: =-連結PL!H17 -> 0 | I12: =-連結PL!I17 -> 0 | J12: 税効果は繰延税金資産（BS）で受け、現金の税負担減とはしない
B13: 持分法損益（非資金） | C13: 億円 | E13: =-連結PL!E8 -> 0 | F13: =-連結PL!F8 -> 0 | G13: =-連結PL!G8 -> 55.74229 | H13: =-連結PL!H8 -> 6.7422902 | I13: =-連結PL!I8 -> -45.628855
B14: 運転資本の増加 | C14: 億円 | E14: =-E9 -> -144 | F14: =-F9 -> -195.3573 | G14: =-G9 -> -259.98979 | H14: =-H9 -> -262.00625 | I14: =-I9 -> -193.30647
B15: 営業CF | C15: 億円 | E15: =E10+E11+E12+E13+E14 -> 4626.1392 | F15: =F10+F11+F12+F13+F14 -> 4556.4016 | G15: =G10+G11+G12+G13+G14 -> 4604.4573 | H15: =H10+H11+H12+H13+H14 -> 4996.6578 | I15: =I10+I11+I12+I13+I14 -> 5287.1945
B16: 設備投資 | C16: 億円 | E16: =-E6 -> -3391 | F16: =-F6 -> -3300 | G16: =-G6 -> -2920 | H16: =-H6 -> -2720 | I16: =-I6 -> -2720
B17: 投資CF | C17: 億円 | E17: =E16 -> -3391 | F17: =F16 -> -3300 | G17: =G16 -> -2920 | H17: =H16 -> -2720 | I17: =I16 -> -2720
B18: フリーCF | C18: 億円 | E18: =E15+E17 -> 1235.1392 | F18: =F15+F17 -> 1256.4016 | G18: =G15+G17 -> 1684.4573 | H18: =H15+H17 -> 2276.6578 | I18: =I15+I17 -> 2567.1945
B19: 配当（親会社株主） | C19: 億円 | E19: =-連結PL!E23 -> -447.60387 | F19: =-連結PL!F23 -> -434.784 | G19: =-連結PL!G23 -> -434.784 | H19: =-連結PL!H23 -> -631.26468 | I19: =-連結PL!I23 -> -697.58141
B20: 配当（非支配株主） | C20: 億円 | E20: =-連結PL!E24 -> -141 | F20: =-連結PL!F24 -> -147.87805 | G20: =-連結PL!G24 -> -155.4439 | H20: =-連結PL!H24 -> -163.00976 | I20: =-連結PL!I24 -> -170.57561
B21: 借入の増減（現金一定） | C21: 億円 | E21: =-(E18+E19+E20) -> -646.53533 | F21: =-(F18+F19+F20) -> -673.73959 | G21: =-(G18+G19+G20) -> -1094.2294 | H21: =-(H18+H19+H20) -> -1482.3834 | I21: =-(I18+I19+I20) -> -1699.0374
B22: 財務CF | C22: 億円 | E22: =E19+E20+E21 -> -1235.1392 | F22: =F19+F20+F21 -> -1256.4016 | G22: =G19+G20+G21 -> -1684.4573 | H22: =H19+H20+H21 -> -2276.6578 | I22: =I19+I20+I21 -> -2567.1945
B23: 現金の増減 | C23: 億円 | E23: =E15+E17+E22 -> 0 | F23: =F15+F17+F22 -> 0 | G23: =G15+G17+G22 -> 0 | H23: =H15+H17+H22 -> 0 | I23: =I15+I17+I22 -> 0
B24: 非資金：合弁へ移る有利子負債 | C24: 億円 | E24: =-分社化・合併!E26 -> 0 | F24: =-分社化・合併!F26 -> 0 | G24: =-分社化・合併!G26 -> -500 | H24: =-分社化・合併!H26 -> 0 | I24: =-分社化・合併!I26 -> 0
B25: 純有利子負債（CF 由来） | C25: 億円 | D25: =前提!$D$129 -> 14648 | E25: =D25+E21+E24 -> 14001.465 | F25: =E25+F21+F24 -> 13327.725 | G25: =F25+G21+G24 -> 11733.496 | H25: =G25+H21+H24 -> 10251.112 | I25: =H25+I21+I24 -> 8552.0748
B27: ケースB（JSRあり）
B28: 設備投資（金額） | C28: 億円 | E28: =E6+D_JSR!E29*前提!$D$152 -> 3391 | F28: =F6+D_JSR!F29*前提!$D$152 -> 3300 | G28: =G6+D_JSR!G29*前提!$D$152 -> 2920 | H28: =H6+D_JSR!H29*前提!$D$152 -> 2720 | I28: =I6+D_JSR!I29*前提!$D$152 -> 2720 | J28: ＋JSR 連結後300
B29: 減価償却（金額） | C29: 億円 | E29: =E7+D_JSR!E29*前提!$D$151 -> 2794 | F29: =F7+D_JSR!F29*前提!$D$151 -> 2850 | G29: =G7+D_JSR!G29*前提!$D$151 -> 2600 | H29: =H7+D_JSR!H29*前提!$D$151 -> 2650 | I29: =I7+D_JSR!I29*前提!$D$151 -> 2700 | J29: ＋JSR 492
B30: 前年売上（同一連結範囲） | C30: 億円 | E30: =連結PL!D29-分社化・合併!E7*N(D_石化!D14)+D_JSR!E26*N(D_JSR!D14) -> 37040 | F30: =連結PL!E29-分社化・合併!F7*N(D_石化!E14)+D_JSR!F26*N(D_JSR!E14) -> 38000 | G30: =連結PL!F29-分社化・合併!G7*N(D_石化!F14)+D_JSR!G26*N(D_JSR!F14) -> 32972.382 | H30: =連結PL!G29-分社化・合併!H7*N(D_石化!G14)+D_JSR!H26*N(D_JSR!G14) -> 34705.647 | I30: =連結PL!H29-分社化・合併!I7*N(D_石化!H14)+D_JSR!I26*N(D_JSR!H14) -> 36452.356 | J30: 全額取得年度は前年の JSR 売上を足して比べる
B31: 運転資本の増加 | C31: 億円 | E31: =前提!$D$131*(連結PL!E29-E30) -> 144 | F31: =前提!$D$131*(連結PL!F29-F30) -> 195.3573 | G31: =前提!$D$131*(連結PL!G29-G30) -> 259.98979 | H31: =前提!$D$131*(連結PL!H29-H30) -> 262.00625 | I31: =前提!$D$131*(連結PL!I29-I30) -> 193.30647 | J31: 売上増分×15%
B32: 当期利益（非支配含む） | C32: 億円 | E32: =連結PL!E41 -> 1976.1392 | F32: =連結PL!F41 -> 1932.1572 | G32: =連結PL!G41 -> -410.87523 | H32: =連結PL!H41 -> 2700.992 | I32: =連結PL!I41 -> 3039.3894
B33: 減価償却 | C33: 億円 | E33: =E29 -> 2794 | F33: =F29 -> 2850 | G33: =G29 -> 2600 | H33: =H29 -> 2650 | I33: =I29 -> 2700
B34: 非資金の非経常（合併除外損益の戻し、税後） | C34: 億円 | E34: =-連結PL!E40 -> 0 | F34: =-連結PL!F40 -> 0 | G34: =-連結PL!G40 -> 2696.7176 | H34: =-連結PL!H40 -> 0 | I34: =-連結PL!I40 -> 0 | J34: 税効果は繰延税金資産（BS）で受け、現金の税負担減とはしない
B35: 持分法損益（非資金） | C35: 億円 | E35: =-連結PL!E31 -> 0 | F35: =-連結PL!F31 -> -44.998283 | G35: =-連結PL!G31 -> -51.262617 | H35: =-連結PL!H31 -> -126.67516 | I35: =-連結PL!I31 -> -329.32368
B36: 運転資本の増加 | C36: 億円 | E36: =-E31 -> -144 | F36: =-F31 -> -195.3573 | G36: =-G31 -> -259.98979 | H36: =-H31 -> -262.00625 | I36: =-I31 -> -193.30647
B37: 営業CF | C37: 億円 | E37: =E32+E33+E34+E35+E36 -> 4626.1392 | F37: =F32+F33+F34+F35+F36 -> 4541.8016 | G37: =G32+G33+G34+G35+G36 -> 4574.59 | H37: =H32+H33+H34+H35+H36 -> 4962.3106 | I37: =I32+I33+I34+I35+I36 -> 5216.7593
B38: 設備投資 | C38: 億円 | E38: =-E28 -> -3391 | F38: =-F28 -> -3300 | G38: =-G28 -> -2920 | H38: =-H28 -> -2720 | I38: =-I28 -> -2720
B39: JSR 株式の取得（第1段・追加取得） | C39: 億円 | E39: =-D_JSR!E35 -> 0 | F39: =-D_JSR!F35 -> -2000 | G39: =-D_JSR!G35 -> -31.108804 | H39: =-D_JSR!H35 -> -276.97324 | I39: =-D_JSR!I35 -> -2402.7571
B40: JSR 全額取得（残り株式） | C40: 億円 | E40: =-D_JSR!E34 -> 0 | F40: =-D_JSR!F34 -> 0 | G40: =-D_JSR!G34 -> 0 | H40: =-D_JSR!H34 -> 0 | I40: =-D_JSR!I34 -> 0
B41: 投資CF | C41: 億円 | E41: =E38+E39+E40 -> -3391 | F41: =F38+F39+F40 -> -5300 | G41: =G38+G39+G40 -> -2951.1088 | H41: =H38+H39+H40 -> -2996.9732 | I41: =I38+I39+I40 -> -5122.7571
B42: フリーCF | C42: 億円 | E42: =E37+E41 -> 1235.1392 | F42: =F37+F41 -> -758.19836 | G42: =G37+G41 -> 1623.4812 | H42: =H37+H41 -> 1965.3374 | I42: =I37+I41 -> 94.002184
B43: 配当（親会社株主） | C43: 億円 | E43: =-連結PL!E46 -> -447.60387 | F43: =-連結PL!F46 -> -434.784 | G43: =-連結PL!G46 -> -434.784 | H43: =-連結PL!H46 -> -665.93926 | I43: =-連結PL!I46 -> -772.22228
B44: 配当（非支配株主） | C44: 億円 | E44: =-連結PL!E47 -> -141 | F44: =-連結PL!F47 -> -147.87805 | G44: =-連結PL!G47 -> -155.4439 | H44: =-連結PL!H47 -> -163.00976 | I44: =-連結PL!I47 -> -170.57561
B45: 借入の増減（現金一定） | C45: 億円 | E45: =-(E42+E43+E44) -> -646.53533 | F45: =-(F42+F43+F44) -> 1340.8604 | G45: =-(G42+G43+G44) -> -1033.2533 | H45: =-(H42+H43+H44) -> -1136.3884 | I45: =-(I42+I43+I44) -> 848.79571
B46: 財務CF | C46: 億円 | E46: =E43+E44+E45 -> -1235.1392 | F46: =F43+F44+F45 -> 758.19836 | G46: =G43+G44+G45 -> -1623.4812 | H46: =H43+H44+H45 -> -1965.3374 | I46: =I43+I44+I45 -> -94.002184
B47: 現金の増減 | C47: 億円 | E47: =E37+E41+E46 -> 0 | F47: =F37+F41+F46 -> 0 | G47: =G37+G41+G46 -> 0 | H47: =H37+H41+H46 -> 0 | I47: =I37+I41+I46 -> 0
B48: 非資金：合弁へ移る有利子負債 | C48: 億円 | E48: =-分社化・合併!E26 -> 0 | F48: =-分社化・合併!F26 -> 0 | G48: =-分社化・合併!G26 -> -500 | H48: =-分社化・合併!H26 -> 0 | I48: =-分社化・合併!I26 -> 0
B49: 非資金：JSR 純有利子負債の取込 | C49: 億円 | E49: =D_JSR!E26*前提!$D$136 -> 0 | F49: =D_JSR!F26*前提!$D$136 -> 0 | G49: =D_JSR!G26*前提!$D$136 -> 0 | H49: =D_JSR!H26*前提!$D$136 -> 0 | I49: =D_JSR!I26*前提!$D$136 -> 0
B50: 純有利子負債（CF 由来） | C50: 億円 | D50: =前提!$D$129 -> 14648 | E50: =D50+E45+E48+E49 -> 14001.465 | F50: =E50+F45+F48+F49 -> 15342.325 | G50: =F50+G45+G48+G49 -> 13809.072 | H50: =G50+H45+H48+H49 -> 12672.683 | I50: =H50+I45+I48+I49 -> 13521.479
B52: 注1：合併除外損益は税後の金額を非資金として戻す。税効果（30%）は繰延税金資産として正味営業資産に計上し、現金の税負担減とはしない（追加の仮定）。
B53: 注2：持分法の投資先（合弁・JSR）は配当を出さないと仮定。

Sheet 分社化・合併
B1: 分社化・合併（BM の切り出しと持分法化）
B2: 分社化（2027年度、会社分割で子会社化と仮定）は連結 BS 不変。合併（期首）で BM を連結除外し、合弁株式を公正価値で計上
B4: 項目 | C4: 単位 | D4: 2025年度 | E4: 2026年度 | F4: 2027年度 | G4: 2028年度 | H4: 2029年度 | I4: 2030年度 | J4: 出所・算式
B5: 年度判定
B6: 合併後フラグ（1＝持分法） | E6: =IF(前提!E$6>=前提!$D$25,1,0) -> 0 | F6: =IF(前提!F$6>=前提!$D$25,1,0) -> 0 | G6: =IF(前提!G$6>=前提!$D$25,1,0) -> 1 | H6: =IF(前提!H$6>=前提!$D$25,1,0) -> 1 | I6: =IF(前提!I$6>=前提!$D$25,1,0) -> 1 | J6: 前提の合併年度で切替
B7: 合併初年度フラグ | E7: =IF(前提!E$6=前提!$D$25,1,0) -> 0 | F7: =IF(前提!F$6=前提!$D$25,1,0) -> 0 | G7: =IF(前提!G$6=前提!$D$25,1,0) -> 1 | H7: =IF(前提!H$6=前提!$D$25,1,0) -> 0 | I7: =IF(前提!I$6=前提!$D$25,1,0) -> 0
B8: 分社化年度フラグ | E8: =IF(前提!E$6=前提!$D$97,1,0) -> 0 | F8: =IF(前提!F$6=前提!$D$97,1,0) -> 1 | G8: =IF(前提!G$6=前提!$D$97,1,0) -> 0 | H8: =IF(前提!H$6=前提!$D$97,1,0) -> 0 | I8: =IF(前提!I$6=前提!$D$97,1,0) -> 0
B9: 分社化の一時費用（非経常） | C9: 億円 | E9: =E8*前提!$D$98 -> 0 | F9: =F8*前提!$D$98 -> -50 | G9: =G8*前提!$D$98 -> 0 | H9: =H8*前提!$D$98 -> 0 | I9: =I8*前提!$D$98 -> 0
B11: 切り出し BS（2025年度末ベース、仮定）
B12: 資産 | C12: 億円 | D12: =前提!$D$99 -> 6000 | J12: BM&P セグメント資産6,999から炭素分を控除
B13: 営業負債 | C13: 億円 | D13: =前提!$D$100 -> 700
B14: 配分する有利子負債 | C14: 億円 | D14: =前提!$D$101 -> 500
B15: 純資産 | C15: 億円 | D15: =D12-D13-D14 -> 4800
B16: 正味営業資産（資産−営業負債） | C16: 億円 | D16: =D12-D13 -> 5300
B18: 合弁の公正価値と除外損益
B19: BM の中間 EBITDA（2026〜30年度のコア平均＋減価償却） | C19: 億円 | D19: =AVERAGE(D_石化!$E$13:$I$13)+前提!$D$106 -> 241.25771 | J19: 「中間」は5年平均と解釈（追加の仮定）
B20: 合弁 EV（2×中間EBITDA×倍率） | C20: 億円 | D20: =前提!$D$103*D19*前提!$D$107 -> 2895.0925
B21: 合弁株式の公正価値（倍率法：50%×EV−配分負債） | C21: 億円 | D21: =前提!$D$102*D20-D14 -> 947.54626
B22: 合弁株式の計上額（切替後） | C22: 億円 | D22: =IF(前提!$D$26=1,D21,D15) -> 947.54626 | J22: 1＝倍率法、2＝簿価
B23: 合併除外損益（税前、非経常） | C23: 億円 | E23: =E7*($D$22-$D$15) -> 0 | F23: =F7*($D$22-$D$15) -> 0 | G23: =G7*($D$22-$D$15) -> -3852.4537 | H23: =H7*($D$22-$D$15) -> 0 | I23: =I7*($D$22-$D$15) -> 0 | J23: IFRS10：残存持分の再測定。公正価値−除外純資産
B24: 合併除外損益（税後、税効果30%） | C24: 億円 | E24: =E23*(1-前提!$D$108) -> 0 | F24: =F23*(1-前提!$D$108) -> 0 | G24: =G23*(1-前提!$D$108) -> -2696.7176 | H24: =H23*(1-前提!$D$108) -> 0 | I24: =I23*(1-前提!$D$108) -> 0
B25: 連結から外れる正味営業資産 | C25: 億円 | E25: =E7*$D$16 -> 0 | F25: =F7*$D$16 -> 0 | G25: =G7*$D$16 -> 5300 | H25: =H7*$D$16 -> 0 | I25: =I7*$D$16 -> 0
B26: 合弁へ移る有利子負債（非資金） | C26: 億円 | E26: =E7*$D$14 -> 0 | F26: =F7*$D$14 -> 0 | G26: =G7*$D$14 -> 500 | H26: =H7*$D$14 -> 0 | I26: =I7*$D$14 -> 0
B27: 合弁株式の計上 | C27: 億円 | E27: =E7*$D$22 -> 0 | F27: =F7*$D$22 -> 0 | G27: =G7*$D$22 -> 947.54626 | H27: =H7*$D$22 -> 0 | I27: =I7*$D$22 -> 0
B29: 連結範囲と持分法利益
B30: 連結に含める BM 売上 | C30: 億円 | E30: =D_石化!E14*(1-E6) -> 6830 | F30: =D_石化!F14*(1-F6) -> 6330 | G30: =D_石化!G14*(1-G6) -> 0 | H30: =D_石化!H14*(1-H6) -> 0 | I30: =D_石化!I14*(1-I6) -> 0
B31: 連結に含める BM コア営業利益 | C31: 億円 | E31: =D_石化!E13*(1-E6) -> -50 | F31: =D_石化!F13*(1-F6) -> -119.63184 | G31: =D_石化!G13*(1-G6) -> 0 | H31: =D_石化!H13*(1-H6) -> 0 | I31: =D_石化!I13*(1-I6) -> 0
B32: 統合効果（初年度0、2年目以降） | C32: 億円 | E32: =IF(前提!E$6>前提!$D$25,前提!$D$104,0) -> 0 | F32: =IF(前提!F$6>前提!$D$25,前提!$D$104,0) -> 0 | G32: =IF(前提!G$6>前提!$D$25,前提!$D$104,0) -> 0 | H32: =IF(前提!H$6>前提!$D$25,前提!$D$104,0) -> 100 | I32: =IF(前提!I$6>前提!$D$25,前提!$D$104,0) -> 100
B33: 合弁の利益（当社 BM コア×2＋統合効果） | C33: 億円 | E33: =E6*(前提!$D$103*D_石化!E13+E32) -> 0 | F33: =F6*(前提!$D$103*D_石化!F13+F32) -> 0 | G33: =G6*(前提!$D$103*D_石化!G13+G32) -> -159.26369 | H33: =H6*(前提!$D$103*D_石化!H13+H32) -> -19.263686 | I33: =I6*(前提!$D$103*D_石化!I13+I32) -> 130.36816
B34: 当社持分法利益（50%×合弁利益×(1−30%)、コアに含む） | C34: 億円 | E34: =前提!$D$102*E33*(1-前提!$D$105) -> 0 | F34: =前提!$D$102*F33*(1-前提!$D$105) -> 0 | G34: =前提!$D$102*G33*(1-前提!$D$105) -> -55.74229 | H34: =前提!$D$102*H33*(1-前提!$D$105) -> -6.7422902 | I34: =前提!$D$102*I33*(1-前提!$D$105) -> 45.628855
B35: 合弁株式の残高（配当なし、持分法損益を積み上げ） | C35: 億円 | E35: =N(D35)+E27+E34 -> 0 | F35: =N(E35)+F27+F34 -> 0 | G35: =N(F35)+G27+G34 -> 891.80397 | H35: =N(G35)+H27+H34 -> 885.06168 | I35: =N(H35)+I27+I34 -> 930.69053
B36: 設備投資の控除（BM 分） | C36: 億円 | E36: =-E6*前提!$D$109 -> 0 | F36: =-F6*前提!$D$109 -> 0 | G36: =-G6*前提!$D$109 -> -280 | H36: =-H6*前提!$D$109 -> -280 | I36: =-I6*前提!$D$109 -> -280
B37: 減価償却の調整（列は2028年度以降 BM 控除後。合併前の年度は BM 分を足し戻す） | C37: 億円 | E37: =(1-E6)*IF(前提!E$6>=前提!$D$111,前提!$D$110,0) -> 0 | F37: =(1-F6)*IF(前提!F$6>=前提!$D$111,前提!$D$110,0) -> 0 | G37: =(1-G6)*IF(前提!G$6>=前提!$D$111,前提!$D$110,0) -> 0 | H37: =(1-H6)*IF(前提!H$6>=前提!$D$111,前提!$D$110,0) -> 0 | I37: =(1-I6)*IF(前提!I$6>=前提!$D$111,前提!$D$110,0) -> 0
B38: 注1：合弁は配当を出さないと仮定し、持分法損益は合弁株式の残高に積み上げる（CF では非資金として控除）。
B39: 注2：合弁へ移る有利子負債500は純有利子負債を非資金で減らす。除外純資産4,800＝正味営業資産5,300−移転負債500。
B40: 注3：切り出し BS は合併年度にかかわらず2025年度末ベースで一定と置いた。
B41: 注4：合併時の除外損は、実務上は合併前の減損として先行計上されうる（計上年度と区分がずれる）。
B42: 注5：BM の公正価値（中間 EBITDA×6倍から算出した合弁株式）は資産規模6,000と見合わない。この差そのものが減損リスクである。

Sheet 中計判定
B1: 中計判定（2029年度）
B2: 目標は M03 p37〜38・M15 p25（一次）。ケースA＝JSRなし、ケースB＝JSRあり
B4: 指標 | C4: 単位 | D4: 目標 | E4: ケースA | F4: ケースB | G4: A−目標 | H4: B−目標 | I4: 判定A | J4: 判定B
B5: 売上収益 | C5: 億円 | D5: =前提!$D$162 -> 45060 | E5: =連結PL!H6 -> 36452.356 | F5: =連結PL!H29 -> 36452.356 | G5: =E5-D5 -> -8607.6444 | H5: =F5-D5 -> -8607.6444 | I5: =IF(E5>=D5,"達成","未達") -> 未達 | J5: =IF(F5>=D5,"達成","未達") -> 未達
B6: コア営業利益 | C6: 億円 | D6: =前提!$D$163 -> 4600 | E6: =連結PL!H7 -> 4101.4401 | F6: =連結PL!H30 -> 4234.8575 | G6: =E6-D6 -> -498.55992 | H6: =F6-D6 -> -365.14247 | I6: =IF(E6>=D6,"達成","未達") -> 未達 | J6: =IF(F6>=D6,"達成","未達") -> 未達
B7: EPS | C7: 円 | D7: =前提!$D$164 -> 152 | E7: =連結PL!H22 -> 132.74552 | F7: =連結PL!H45 -> 140.03707 | G7: =E7-D7 -> -19.25448 | H7: =F7-D7 -> -11.962935 | I7: =IF(E7>=D7,"達成","未達") -> 未達 | J7: =IF(F7>=D7,"達成","未達") -> 未達
B8: ROIC | C8: % | D8: =前提!$D$165 -> 0.07 | E8: =連結PL!H25 -> 0.06803135 | F8: =連結PL!H48 -> 0.067379141 | G8: =E8-D8 -> -0.0019686503 | H8: =F8-D8 -> -0.0026208593 | I8: =IF(E8>=D8,"達成","未達") -> 未達 | J8: =IF(F8>=D8,"達成","未達") -> 未達
B9: ネットD/E（以下） | C9: 倍 | D9: =前提!$D$166 -> 0.8 | E9: =連結PL!H26 -> 0.54899901 | F9: =連結PL!H49 -> 0.67249423 | G9: =E9-D9 -> -0.25100099 | H9: =F9-D9 -> -0.12750577 | I9: =IF(E9<=D9,"達成","未達") -> 達成 | J9: =IF(F9<=D9,"達成","未達") -> 達成
B10: 達成項目数（5項目中） | I10: =COUNTIF(I5:I9,"達成") -> 1 | J10: =COUNTIF(J5:J9,"達成") -> 1
B12: 補足
B13: BM を合併で外したことによる2029年度の売上減 | C13: 億円 | E13: =-分社化・合併!H6*D_石化!H14 -> -5713.4
B14: JSR 連結による2029年度の売上増（ケースB） | C14: 億円 | F14: =D_JSR!H47 -> 0
B15: 参考：JSR を全額連結した場合の2029年度売上（上振れ込み） | C15: 億円 | F15: =D_JSR!H14 -> 5968.844
B16: JSR 全額取得（連結）の年度 | F16: =D_JSR!D62 -> 未到達（44.9%で据え置き）
B17: BM 合併年度（前提の切替） | C17: 年度 | E17: =前提!$D$25 -> 2028
B18: =IF(SUM(D_JSR!$E$26:$I$26)=0,"・JSR は2030年度までに全額取得に至らず連結されない（2029年度の持分"&TEXT(D_JSR!H28,"0.0%")&"、持分法利益"&TEXT(D_JSR!H44,"#,##0")&"億円）","・JSR を連結した年度の JSR 売上は"&TEXT(SUMPRODUCT(D_JSR!$E$26:$I$26,D_JSR!$E$14:$I$14),"#,##0")&"億円") -> ・JSR は2030年度までに全額取得に至らず連結されない（2029年度の持分22.9%、持分法利益133億円）
B19: 注1：BM を合併で外すと2029年度の売上は上の金額だけ減る。
B20: 注2：2027年度の EPS 低下は、非経常▲400（分社化費用込み）と炭素撤退期の BM 赤字による。
B21: 注3：合併時の除外損は、実務上は合併前の減損として先行計上されうる。BM の公正価値（EBITDA×6倍）が資産規模6,000と見合わないこと自体が減損リスクである。

Sheet 日本酸素_持分法換算
B1: 日本酸素_持分法換算（参考：本体の会計は連結のまま）
B2: 日本酸素を持分法（50.59%）で見た場合の化学事業のみの売上・コアと当社取込利益（ケースA）
B4: 項目 | C4: 単位 | D4: 2025年度 | E4: 2026年度 | F4: 2027年度 | G4: 2028年度 | H4: 2029年度 | I4: 2030年度 | J4: 出所・算式
B5: 連結売上（ケースA） | C5: 億円 | E5: =連結PL!E6 -> 38000 | F5: =連結PL!F6 -> 39302.382 | G5: =連結PL!G6 -> 34705.647 | H5: =連結PL!H6 -> 36452.356 | I5: =連結PL!I6 -> 37741.065
B6: −産業ガス売上 | C6: 億円 | E6: =-セグメント!E30 -> -13720 | F6: =-セグメント!F30 -> -14268.8 | G6: =-セグメント!G30 -> -14839.552 | H6: =-セグメント!H30 -> -15433.134 | I6: =-セグメント!I30 -> -16050.459
B7: 化学事業のみの売上 | C7: 億円 | E7: =E5+E6 -> 24280 | F7: =F5+F6 -> 25033.582 | G7: =G5+G6 -> 19866.095 | H7: =H5+H6 -> 21019.221 | I7: =I5+I6 -> 21690.606
B8: 連結コア営業利益（ケースA） | C8: 億円 | E8: =連結PL!E7 -> 3050 | F8: =連結PL!F7 -> 3285.1785 | G8: =連結PL!G7 -> 3702.7946 | H8: =連結PL!H7 -> 4101.4401 | I8: =連結PL!I7 -> 4359.5565
B9: −産業ガス コア | C9: 億円 | E9: =-セグメント!E31 -> -2050 | F9: =-セグメント!F31 -> -2150 | G9: =-セグメント!G31 -> -2260 | H9: =-セグメント!H31 -> -2370 | I9: =-セグメント!I31 -> -2480
B10: 化学事業のみのコア営業利益 | C10: 億円 | E10: =E8+E9 -> 1000 | F10: =F8+F9 -> 1135.1785 | G10: =G8+G9 -> 1442.7946 | H10: =H8+H9 -> 1731.4401 | I10: =I8+I9 -> 1879.5565
B11: 化学事業のみのコア利益率 | C11: % | E11: =E10/E7 -> 0.041186161 | F11: =F10/F7 -> 0.045346228 | G11: =G10/G7 -> 0.072625976 | H11: =H10/H7 -> 0.08237413 | I11: =I10/I7 -> 0.086653019
B12: 日本酸素 当期利益 | C12: 億円 | E12: =連結PL!E19 -> 1310 | F12: =連結PL!F19 -> 1373.9024 | G12: =連結PL!G19 -> 1444.1951 | H12: =連結PL!H19 -> 1514.4878 | I12: =連結PL!I19 -> 1584.7805
B13: 当社取込利益（50.59%×日本酸素当期利益） | C13: 億円 | E13: =前提!$D$116*E12 -> 662.729 | F13: =前提!$D$116*F12 -> 695.05724 | G13: =前提!$D$116*G12 -> 730.61831 | H13: =前提!$D$116*H12 -> 766.17938 | I13: =前提!$D$116*I12 -> 801.74045
B14: 参考：化学のみコア＋日本酸素取込 | C14: 億円 | E14: =E10+E13 -> 1662.729 | F14: =F10+F13 -> 1830.2358 | G14: =G10+G13 -> 2173.4129 | H14: =H10+H13 -> 2497.6195 | I14: =I10+I13 -> 2681.2969

Sheet 出典
B1: 出典
B2: 出典ID は前提シートの出典ID列と対応。「※二次」は報道・転載
B4: 出典ID | C4: 資料名（使用箇所） | D4: 発行者 | E4: 公表日 | F4: URL・保存先 | G4: 区分
B5: M03 | C5: 2026年3月期 決算説明（p20 セグメント別予想、p13 連結財政状態、p35〜36 設備投資・減価償却、p37〜39 中計目標と経営指標算定式） | D5: 三菱ケミカルグループ | E5: 2026-05-13 | F5: https://www.mcgc.com/ir/pdf/02626/02884.pdf | G5: 一次
B6: M01 | C6: 2027年3月期 第1四半期 決算説明（p22 炭素繊維サブセグメント、p23 SM・コンポジット経路） | D6: 三菱ケミカルグループ | E6: 2026-07-31 | F6: https://www.mcgc.com/ir/pdf/02722/02959.pdf | G6: 一次
B7: M02 | C7: 事業戦略説明会2026（p36 合成石英 売上CAGR+15%・FY28生産開始） | D7: 三菱ケミカルグループ | E7: 2026-05-25 | F7: https://www.mcgc.com/ir/pdf/02652/02900.pdf | G7: 一次
B8: M15 | C8: IR Day 2025（p25 キャピタルアロケーション・ネットD/E 0.8以下、p21 MMA能力・シェア約30%） | D8: 三菱ケミカルグループ | E8: 2025-12-18 | F8: https://www.mcgc.com/ir/pdf/02499/02739.pdf | G8: 一次
B9: M08 | C9: MMA&D 事業責任者説明（欧州撤退・中国へ生産移転・地域分断で従来モデルが崩れた） | D9: 三菱ケミカルグループ | E9: 2026-09 | F9: https://www.mcgc.com/ir/hub/feature/2026/mma-derivatives.html | G9: 一次
B10: M42 | C10: 米国ルイジアナ州 MMA 新設の検討中止（英語版、2025-01-07）。注：data/shared/mcgc_ir の manifest.json では M42 は別文書（事業戦略説明会2025 質疑）として登録されており ID が衝突している。ここでは plan_bs_mma の用法（ディスク上の M42.pdf の中身）に従う | D10: 三菱ケミカルグループ | E10: 2025-01-07 | F10: https://www.mcgc.com/english/ir/pdf/02170/02474.pdf | G10: 一次
B11: M24 | C11: 2027年3月期 第1四半期 決算短信（p2 株式数、p8 連結財政状態計算書） | D11: 三菱ケミカルグループ | E11: 2026-08-07 | F11: https://www.mcgc.com/ir/pdf/02720/02957.pdf | G11: 一次
B12: M26 | C12: 2026年3月期 決算短信〔IFRS〕（セグメント資産・持分法損益） | D12: 三菱ケミカルグループ | E12: 2026-05-13 | F12: https://www.mcgc.com/ir/pdf/02624/02882.pdf | G12: 一次
B13: M36 | C13: コークス及び炭素材の事業撤退 | D13: 三菱ケミカルグループ | E13: 2026-02-02 | F13: https://www.mcgc.com/ir/pdf/02533/02781.pdf | G13: 一次
B14: M07 | C14: 石油化学事業の分社化の検討開始 | D14: 三菱ケミカルグループ | E14: 2026-05-25 | F14: https://www2.jpx.co.jp/disc/41880/140120260525545853.pdf | G14: 一次
B15: M43 | C15: リソマックス 生産能力増強（福岡）ニュースリリース | D15: 三菱ケミカルグループ | E15: 2024-06-12 | F15: https://www.mcgc.com/news_release/01981.html | G15: 一次
... B36: DIR2 | C36: 司令塔の修正指示（2026-10-30、v2：二重課税の除去・減価償却の扱い・水島の能力減の式・SM 会社計画経路・JSR 取得構造・ハイブリッド債） | D36: 0055 司令塔 | E36: 2026-10-30 | F36: 司令塔メッセージ（ワーカー宛て） | G36: 一次
B37: 注1：mcgc_ir の M01〜M43 は D:\開発用フォルダ\data\shared\mcgc_ir\（manifest.json＋_meta.yaml）。内部調査メモは D:\開発用フォルダ\data\projects\0055_equity-research-workbook\4188_20261022\research\。

Sheet 検証
B1: 検証
B2: 許容差：金額は0.01億円、EPS は会社予想の±5%。判定は PASS／FAIL
B4: 検査項目 | C4: 値 | D4: 基準 | E4: 差 | F4: 判定 | G4: 内容
B5: BS 均衡（ケースA）：|正味営業資産−資本合計−純有利子負債| の最大値 | C5: =MAX(ABS(MIN(連結BS!$D$22:$I$22)),ABS(MAX(連結BS!$D$22:$I$22))) -> 0 | D5: =0 -> 0 | E5: =C5-D5 -> 0 | F5: =IF(ABS(E5)<=0.01,"PASS","FAIL") -> PASS | G5: 純有利子負債を BS の差額で求めているため恒等的に0（構造の確認）
B6: CF 由来の純有利子負債＝BS の純有利子負債（ケースA、2025〜30年度の差の絶対値合計） | C6: =ABS(連結CF!D25-連結BS!D16)+ABS(連結CF!E25-連結BS!E16)+ABS(連結CF!F25-連結BS!F16)+ABS(連結CF!G25-連結BS!G16)+ABS(連結CF!H25-連結BS!H16)+ABS(連結CF!I25-連結BS!I16) -> 2.5465852e-11 | D6: =0 -> 0 | E6: =C6-D6 -> 2.5465852e-11 | F6: =IF(ABS(E6)<=0.01,"PASS","FAIL") -> PASS | G6: 実質の検査：利益・配当・非資金項目・取得の流れが BS と整合するか
B7: 現金の増減＝0（ケースA、2026〜30年度の絶対値合計） | C7: =ABS(連結CF!E23)+ABS(連結CF!F23)+ABS(連結CF!G23)+ABS(連結CF!H23)+ABS(連結CF!I23) -> 0 | D7: =0 -> 0 | E7: =C7-D7 -> 0 | F7: =IF(ABS(E7)<=0.01,"PASS","FAIL") -> PASS | G7: 現金一定の仮定
B8: BS 均衡（ケースB）：|正味営業資産−資本合計−純有利子負債| の最大値 | C8: =MAX(ABS(MIN(連結BS!$D$47:$I$47)),ABS(MAX(連結BS!$D$47:$I$47))) -> 0 | D8: =0 -> 0 | E8: =C8-D8 -> 0 | F8: =IF(ABS(E8)<=0.01,"PASS","FAIL") -> PASS | G8: 純有利子負債を BS の差額で求めているため恒等的に0（構造の確認）
B9: CF 由来の純有利子負債＝BS の純有利子負債（ケースB、2025〜30年度の差の絶対値合計） | C9: =ABS(連結CF!D50-連結BS!D38)+ABS(連結CF!E50-連結BS!E38)+ABS(連結CF!F50-連結BS!F38)+ABS(連結CF!G50-連結BS!G38)+ABS(連結CF!H50-連結BS!H38)+ABS(連結CF!I50-連結BS!I38) -> 2.7284841e-11 | D9: =0 -> 0 | E9: =C9-D9 -> 2.7284841e-11 | F9: =IF(ABS(E9)<=0.01,"PASS","FAIL") -> PASS | G9: 実質の検査：利益・配当・非資金項目・取得の流れが BS と整合するか
B10: 現金の増減＝0（ケースB、2026〜30年度の絶対値合計） | C10: =ABS(連結CF!E47)+ABS(連結CF!F47)+ABS(連結CF!G47)+ABS(連結CF!H47)+ABS(連結CF!I47) -> 0 | D10: =0 -> 0 | E10: =C10-D10 -> 0 | F10: =IF(ABS(E10)<=0.01,"PASS","FAIL") -> PASS | G10: 現金一定の仮定
B11: 2026年度 売上＝会社予算 | C11: =連結PL!E6 -> 38000 | D11: =前提!$D$42 -> 38000 | E11: =C11-D11 -> 0 | F11: =IF(ABS(E11)<=0.01,"PASS","FAIL") -> PASS | G11: M03 p20
B12: 2026年度 コア営業利益＝会社予算 | C12: =連結PL!E7 -> 3050 | D12: =前提!$D$43 -> 3050 | E12: =C12-D12 -> 0 | F12: =IF(ABS(E12)<=0.01,"PASS","FAIL") -> PASS | G12: M03 p20
B13: 2026年度 セグメント別：SM 売上・コアが会社予算（合計の差） | C13: =ABS(セグメント!E19-前提!$D$36)+ABS(セグメント!E20-前提!$D$37) -> 0 | D13: =0 -> 0 | E13: =C13-D13 -> 0 | F13: =IF(ABS(E13)<=0.01,"PASS","FAIL") -> PASS | G13: 上振れは2026年度ゼロ
B14: 2026年度 ケースA の EPS が会社予想の±5%以内 | C14: =連結PL!E22 -> 94.124398 | D14: =前提!$D$44 -> 93.5 | E14: =C14-D14 -> 0.62439832 | F14: =IF(ABS(C14/D14-1)<=0.05,"PASS","FAIL") -> PASS | G14: 会社予想93.5円
B15: 2026年度 ケースA の親会社当期利益（参考：会社予想1,270との比） | C15: =連結PL!E21 -> 1278.8682 | D15: =前提!$D$45 -> 1270 | E15: =C15-D15 -> 8.8682 | F15: =IF(ABS(C15/D15-1)<=0.05,"PASS","FAIL") -> PASS | G15: 税率27%の較正
B16: ケースB−ケースA：2026年度は差がない（JSR は2027年度から） | C16: =ABS(連結PL!E52)+ABS(連結PL!E53) -> 0 | D16: =0 -> 0 | E16: =C16-D16 -> 0 | F16: =IF(ABS(E16)<=0.01,"PASS","FAIL") -> PASS
B17: セグメント合計＝連結PL（コア、2026〜30年度の差の絶対値合計） | C17: =ABS(セグメント!E35-連結PL!E7)+ABS(セグメント!F35-連結PL!F7)+ABS(セグメント!G35-連結PL!G7)+ABS(セグメント!H35-連結PL!H7)+ABS(セグメント!I35-連結PL!I7) -> 0 | D17: =0 -> 0 | E17: =C17-D17 -> 0 | F17: =IF(ABS(E17)<=0.01,"PASS","FAIL") -> PASS
B18: 合併除外損益は合併初年度だけ（計上年度の数） | C18: =COUNTIF(分社化・合併!$E$23:$I$23,"<>0") -> 1 | D18: =IF(ABS(分社化・合併!D22-分社化・合併!D15)>0,1,0) -> 1 | E18: =C18-D18 -> 0 | F18: =IF(ABS(E18)<=0,"PASS","FAIL") -> PASS
B19: JSR の全額取得は高々1回 | C19: =SUM(D_JSR!$E$26:$I$26) -> 0 | D19: =MIN(1,SUM(D_JSR!$E$26:$I$26)) -> 0 | E19: =C19-D19 -> 0 | F19: =IF(ABS(E19)<=0,"PASS","FAIL") -> PASS
B20: JSR 連結前の持分は49%以下（超過分の最大値） | C20: =MAX(0,SUMPRODUCT(MAX(D_JSR!$E$28:$I$28*(1-D_JSR!$E$29:$I$29))-前提!$D$139)) -> 0 | D20: =0 -> 0 | E20: =C20-D20 -> 0 | F20: =IF(ABS(E20)<=0.000001,"PASS","FAIL") -> PASS
B21: ケースB のネットD/E（ハイブリッド切替0のとき）≦0.8：各年度の最大値 | C21: =MAX(連結BS!$E$46:$I$46) -> 0.79838117 | D21: =前提!$D$145 -> 0.8 | E21: =C21-D21 -> -0.0016188344 | F21: =IF(OR(前提!$D$33<>0,C21<=D21),"PASS","FAIL") -> PASS | G21: 切替が1のときは参考表示（判定は PASS）
B22: 持分法の取得額は余力以内（追加取得額−余力で取得できる額の最大値） | C22: =SUMPRODUCT(MAX(D_JSR!$E$33:$I$33-D_JSR!$E$24:$I$24)) -> 0 | D22: =0 -> 0 | E22: =C22-D22 -> 0 | F22: =IF(C22<=0.001,"PASS","FAIL") -> PASS | G22: ≦0なら PASS
B23: 合成石英の数量指数は能力以下 | C23: =MAX(D_半導体!$E$11:$I$11)-MAX(D_半導体!$E$10:$I$10) -> -0.028478407 | D23: =0 -> 0 | E23: =C23-D23 -> -0.028478407 | F23: =IF(E23<=0,"PASS","FAIL") -> PASS | G23: 数量≦能力（差≦0なら PASS）
B24: 数式エラーの数：前提 | C24: =SUMPRODUCT(--ISERROR(前提!A1:L220)) -> 0 | D24: =0 -> 0 | E24: =C24-D24 -> 0 | F24: =IF(ABS(E24)<=0,"PASS","FAIL") -> PASS
B25: 数式エラーの数：D_半導体 | C25: =SUMPRODUCT(--ISERROR(D_半導体!A1:L220)) -> 0 | D25: =0 -> 0 | E25: =C25-D25 -> 0 | F25: =IF(ABS(E25)<=0,"PASS","FAIL") -> PASS
B26: 数式エラーの数：D_Zoox | C26: =SUMPRODUCT(--ISERROR(D_Zoox!A1:L220)) -> 0 | D26: =0 -> 0 | E26: =C26-D26 -> 0 | F26: =IF(ABS(E26)<=0,"PASS","FAIL") -> PASS
B27: 数式エラーの数：D_石化 | C27: =SUMPRODUCT(--ISERROR(D_石化!A1:L220)) -> 0 | D27: =0 -> 0 | E27: =C27-D27 -> 0 | F27: =IF(ABS(E27)<=0,"PASS","FAIL") -> PASS
B28: 数式エラーの数：D_JSR | C28: =SUMPRODUCT(--ISERROR(D_JSR!A1:L220)) -> 0 | D28: =0 -> 0 | E28: =C28-D28 -> 0 | F28: =IF(ABS(E28)<=0,"PASS","FAIL") -> PASS
B29: 数式エラーの数：セグメント | C29: =SUMPRODUCT(--ISERROR(セグメント!A1:L220)) -> 0 | D29: =0 -> 0 | E29: =C29-D29 -> 0 | F29: =IF(ABS(E29)<=0,"PASS","FAIL") -> PASS
B30: 数式エラーの数：連結PL | C30: =SUMPRODUCT(--ISERROR(連結PL!A1:L220)) -> 0 | D30: =0 -> 0 | E30: =C30-D30 -> 0 | F30: =IF(ABS(E30)<=0,"PASS","FAIL") -> PASS
B31: 数式エラーの数：連結BS | C31: =SUMPRODUCT(--ISERROR(連結BS!A1:L220)) -> 0 | D31: =0 -> 0 | E31: =C31-D31 -> 0 | F31: =IF(ABS(E31)<=0,"PASS","FAIL") -> PASS
B32: 数式エラーの数：連結CF | C32: =SUMPRODUCT(--ISERROR(連結CF!A1:L220)) -> 0 | D32: =0 -> 0 | E32: =C32-D32 -> 0 | F32: =IF(ABS(E32)<=0,"PASS","FAIL") -> PASS
B33: 数式エラーの数：分社化・合併 | C33: =SUMPRODUCT(--ISERROR(分社化・合併!A1:L220)) -> 0 | D33: =0 -> 0 | E33: =C33-D33 -> 0 | F33: =IF(ABS(E33)<=0,"PASS","FAIL") -> PASS
B34: 数式エラーの数：中計判定 | C34: =SUMPRODUCT(--ISERROR(中計判定!A1:L220)) -> 0 | D34: =0 -> 0 | E34: =C34-D34 -> 0 | F34: =IF(ABS(E34)<=0,"PASS","FAIL") -> PASS
B35: 数式エラーの数：日本酸素_持分法換算 | C35: =SUMPRODUCT(--ISERROR(日本酸素_持分法換算!A1:L220)) -> 0 | D35: =0 -> 0 | E35: =C35-D35 -> 0 | F35: =IF(ABS(E35)<=0,"PASS","FAIL") -> PASS
B36: 数式エラーの数：表紙 | C36: =SUMPRODUCT(--ISERROR(表紙!A1:L220)) -> 0 | D36: =0 -> 0 | E36: =C36-D36 -> 0 | F36: =IF(ABS(E36)<=0,"PASS","FAIL") -> PASS
B38: FAIL の数 | C38: =COUNTIF(F5:F36,"FAIL") -> 0
B40: 注1：EPS の検査は設計書の「会社予想（約93.5円）と±5%以内」。数式エラーは各シートの A1:L220 を ISERROR で数える。
B41: 注2：再計算は erw.recalc（Excel COM）で行い、全シートの数式エラーもブック外で検査した。
