Workbook
Name ERW_DCF_PRICE: 計算_DCF!$C$53
Name ERW_EXPECTED: 計算_シナリオ!$D$8
Name ERW_FCF1: 計算_DCF!$C$41
Name ERW_FM_CHECKS: データ_整合検査!$D$6:$K$11
Name ERW_FM_OP1: '3_Forecast'!$I$14
Name ERW_LIVE: 検証!$F$18:$F$29
Name ERW_LIVE_LABELS: 検証!$B$18:$B$29
Name ERW_PRICE_BASE: 計算_シナリオ!$C$67
Name ERW_PRICE_BEAR: 計算_シナリオ!$C$189
Name ERW_PRICE_BULL: 計算_シナリオ!$C$128
Name ERW_REV1: 計算_DCF!$C$33
Name ERW_SCEN: '2_投資判断'!$C$4
Name ERW_SENS1: 計算_DCF!$E$66
Name ERW_SENS2: 計算_DCF!$E$76
Name ERW_TARGET: '2_投資判断'!$C$150

Sheet 表紙
B2: 企業調査レポート
B4: Texas Instruments（TXN）
B6: 証券コード | C6: TXN
B7: 基準日 | C7: 2026-10-23
B8: 作成日 | C8: 2026-10-24
B9: レーティング | C9: ='2_投資判断'!$C$8 -> 回避
B10: 目標株価 | C10: ='2_投資判断'!$C$12 -> 128.72754
B11: 現在株価 | C11: ='2_投資判断'!$C$11 -> 279.5
B12: 上昇余地 | C12: ='2_投資判断'!$C$12/'2_投資判断'!$C$11-1 -> -0.53943637
B14: 作成:
B16: 目次
B17: シート | C17: 内容
B18: 1_企業分析 | C18: 企業概要・株価とバリュエーション推移・類似企業比較・事業内容（セグメント構成比・主力製品と世界シェア）・社長の来歴・SWOT・関連市況
B19: 2_投資判断 | C19: 投資判断・市場の注目点・伸びる点と懸念点・目標株価と倍率翻訳・DCF の要約と感応度
B20: 3_Summary | C20: 業績予想：主要財務の要約（0054 財務モデル）
B21: 3_PL | C21: 業績予想：損益計算書
B22: 3_BS | C22: 業績予想：貸借対照表
B23: 3_CF | C23: 業績予想：キャッシュフロー計算書
B24: 3_セグメント売上 | C24: 業績予想：セグメント別売上
B25: 3_地域別売上 | C25: 業績予想：地域別売上
B26: 3_Forecast | C26: 業績予想：3期予測の計算
B27: 3_Assumptions | C27: 業績予想の前提（シナリオ別入力を含む）
B28: 計算_DCF | C28: 計算：WACC・DCF・感応度表・SOTP の計算過程
... B37: 検証 | C37: 検証：再計算・数式・静的検査の結果と計算上の取り扱い
B39: 本資料は情報提供を目的として作成したもので、投資勧誘や投資助言ではありません。

Sheet 1_企業分析
B1: TXN Texas Instruments 企業分析
B2: 基準日 2026-10-23／決算期末 12月／出所列の ID は「出典」シートを参照
B4: ① 企業概要 | M4: 出所
B5: 項目 | C5: 内容 | K5: 備考
B6: 社名／ティッカー／上場市場 | C6: Texas Instruments Incorporated（TI、デラウェア州法人）／TXN／Nasdaq Global Select Market | K6: SEC CIK 0000097476。アナログ・組込みプロセッサ半導体の設計・製造・販売 | M6: F1-S1,F1-S4
B7: 本社・設立 | C7: 米国テキサス州ダラス（12500 TI Boulevard）。30か国超で設計・製造・販売拠点を持つ。事業開始は1930年 | K7: 2025年12月31日時点。10-K Item 1 の記載 | M7: F1-S1,F1-S4
B8: 従業員数 | C8: 約33,000人（約90%が R&D・営業・製造）。2025年の離職率10.1% | K8: 2025年12月31日時点 | M8: F1-S1
B9: 決算期 | C9: 12月（暦年） | K9: 直近四半期は2026年7〜9月期（Q3'26）。決算発表は2026-10-21引け後 | M9: F1-S1
B10: 事業の一言 | C10: 電源・信号処理などのアナログ半導体（売上の約79%）と、マイコン・プロセッサなどの組込みプロセッサ（約15%）を、300mmウエハーの自社工場で作り、80%超を直販する。顧客10万社超、製品8万点超 | K10: FY2025。売上構成はアナログ$14,006M・組込み$2,697M・その他$979M（その他にDLP・電卓・ASIC） | M10: F1-S1
B11: 直近通期業績（FY2025：2025年12月期） | C11: 売上高$17,682M（前年比+13.0%）、営業利益$6,023M（営業利益率34.1%）、純利益$5,001M、希薄化後EPS $5.45 | K11: 粗利率57.0%（前年58.1%）。営業利益にはリストラ費用等$117M（150mm工場2拠点閉鎖計画・ASIC関連のれん減損を含む）を含む | M11: F1-S1
B12: 直近四半期（Q3'26：2026年7〜9月期） | C12: 売上高$6,055M（前年同期比+28%、前期比+11%）、粗利率64.2%（前年同期57.4%）、営業利益$2,874M（営業利益率47.5%、前年同期35.1%、営業利益+73%）、純利益$2,425M、EPS $2.62 | K12: 粗利率・営業利益率は売上・粗利・営業利益から算出（推定ではなく算術）。EPSには会社ガイダンス外の$0.01のマイナス（離散税項目）を含む。Q4'26ガイダンス：売上$5.80〜6.30B、EPS $2.45〜2.79（レンジ中央の売上$6.05B） | M12: F1-S2,F1-S6
B13: セグメント別（Q3'26） | C13: アナログ売上$4,911M（前年比+32%、営業利益率51.0%）、組込み$858M（+21%、26.5%）、その他$286M（-6%） | K13: 営業利益率はセグメント営業利益÷売上から算出。アナログ営業利益$2,505M、組込み$227M、その他$142M（買収費用・リストラ費用を含む） | M13: F1-S2
B14: 最終市場構成（FY2025、10-K） | C14: 産業33%、車載33%、パーソナルエレクトロニクス21%、データセンター9%、通信機器3%（ほかに電卓が約1%） | K14: FY2025推計売上比。2025年に市場区分を組み替え済み（データセンターを独立区分化） | M14: F1-S1
B15: 最終市場の直近動向（Q3'26） | C15: 産業は前年比+40%超で約4年ぶりのピーク更新、車載は+10%台半ば、データセンターは約+95%で売上の約13%、パーソナルエレクトロニクスはほぼ横ばい、通信機器は前年比・前期比とも増 | K15: （二次・未確認）の部分：具体的な伸び率と構成比13%は決算コール書き起こし（二次）の記載。TI公式の決算リリースは『産業・車載・データセンターで広範な成長』とのみ記載 | M15: F1-S6,F1-S2
B16: 地域別売上（顧客本社所在地ベース、FY2025） | C16: 米国38%($6,763M)、中国21%($3,781M)、欧州・中東・アフリカ21%($3,747M、うちドイツ顧客10%)、アジア他11%、日本7%($1,173M)、その他2%。出荷先ベースでは中国向けが約50% | K16: 顧客本社が米国外の売上は約60%。中国比率は本社所在地ベース（約20〜21%）と出荷先ベース（約50%）で大きく異なる点に注意 | M16: F1-S1
B17: 配当 | C17: 四半期配当$1.42（Q3'26宣言額）から$1.52へ7%増額予定（年換算$6.08）、23年連続の増配。支払日2026-11-10、基準日2026-10-30 | K17: 増額は10月の取締役会での正式宣言が条件（9/17付8-K）。直近12か月の配当支払$5,174M・自社株買い$636M、合計還元$5,810M。会社方針は長期にフリーキャッシュフローの全額還元 | M17: F1-S4,F1-S2
B18: 係属中のM&A：Silicon Labs（SLAB）買収 | C18: 1株$231現金、企業価値約$7.5B、2027年上期の完了見込み。約1,200製品の無線接続製品群を獲得し、完了後3年以内に年$450M規模の製造・運営シナジーを見込む。連結数値には未反映 | K18: 資金は手元資金と負債（2026年6月に最大$5Bの364日つなぎ融資枠を設定、6/30時点で未借入）。SLAB株主総会は2026-04-30に承認（二次）、米HSRは2026-05-22に待機期間満了（SLAB 8-K、ミラー経由）、中国など他の規制承認の状況は未確認 | M18: F1-S5,F1-S3,F1-S7
B37: 図1：1930年創業・8万品目・顧客10万社超（TI at a glance）（出所：会社資料 3） | M37: F7-S1
B39: ② 株価・バリュエーション推移 | M39: 出所
B40: 現在値と過去レンジ（月次）
B41: 指標 | C41: 現在値 | D41: 最小 | E41: 中央値 | F41: 最大 | G41: 現在の位置 | H41: 観測数
B42: 株価（ドル、調整後月末） | C42: =IF(ISNUMBER(データ_株価!$C$6),データ_株価!$C$6,"n.a.") -> 279.5 | D42: =IF(COUNT(データ_株価!$H$5:$H$65)=0,"n.a.",MIN(データ_株価!$H$5:$H$65)) -> 131.5218 | E42: =IF(COUNT(データ_株価!$H$5:$H$65)=0,"n.a.",MEDIAN(データ_株価!$H$5:$H$65)) -> 165.1917 | F42: =IF(COUNT(データ_株価!$H$5:$H$65)=0,"n.a.",MAX(データ_株価!$H$5:$H$65)) -> 304.1229 | G42: =IF(AND(COUNT(データ_株価!$H$5:$H$65)>0,ISNUMBER(C42)),COUNTIF(データ_株価!$H$5:$H$65,"<="&C42)/COUNT(データ_株価!$H$5:$H$65),"n.a.") -> 0.95081967 | H42: =COUNT(データ_株価!$H$5:$H$65) -> 61
B43: PER（実績） | C43: =IF(ISNUMBER(データ_株価!$N$65),データ_株価!$N$65,"n.a.") -> 36.251621 | D43: =IF(COUNT(データ_株価!$N$5:$N$65)=0,"n.a.",MIN(データ_株価!$N$5:$N$65)) -> 16.837527 | E43: =IF(COUNT(データ_株価!$N$5:$N$65)=0,"n.a.",MEDIAN(データ_株価!$N$5:$N$65)) -> 27.522621 | F43: =IF(COUNT(データ_株価!$N$5:$N$65)=0,"n.a.",MAX(データ_株価!$N$5:$N$65)) -> 52.342464 | G43: =IF(AND(COUNT(データ_株価!$N$5:$N$65)>0,ISNUMBER(C43)),COUNTIF(データ_株価!$N$5:$N$65,"<="&C43)/COUNT(データ_株価!$N$5:$N$65),"n.a.") -> 0.7704918 | H43: =COUNT(データ_株価!$N$5:$N$65) -> 61
B44: PBR | C44: =IF(ISNUMBER(データ_株価!$C$15),データ_株価!$C$15,"n.a.") -> 13.304807 | D44: =IF(COUNT(データ_株価!$O$5:$O$65)=0,"n.a.",MIN(データ_株価!$O$5:$O$65)) -> 7.7550393 | E44: =IF(COUNT(データ_株価!$O$5:$O$65)=0,"n.a.",MEDIAN(データ_株価!$O$5:$O$65)) -> 10.658502 | F44: =IF(COUNT(データ_株価!$O$5:$O$65)=0,"n.a.",MAX(データ_株価!$O$5:$O$65)) -> 16.581068 | G44: =IF(AND(COUNT(データ_株価!$O$5:$O$65)>0,ISNUMBER(C44)),COUNTIF(データ_株価!$O$5:$O$65,"<="&C44)/COUNT(データ_株価!$O$5:$O$65),"n.a.") -> 0.85245902 | H44: =COUNT(データ_株価!$O$5:$O$65) -> 61
B45: 配当利回り（実績TTM） | C45: =IF(ISNUMBER(データ_株価!$C$16),データ_株価!$C$16,"n.a.") -> 0.020322004 | D45: =IF(COUNT(データ_株価!$P$5:$P$65)=0,"n.a.",MIN(データ_株価!$P$5:$P$65)) -> 0.018188956 | E45: =IF(COUNT(データ_株価!$P$5:$P$65)=0,"n.a.",MEDIAN(データ_株価!$P$5:$P$65)) -> 0.026570526 | F45: =IF(COUNT(データ_株価!$P$5:$P$65)=0,"n.a.",MAX(データ_株価!$P$5:$P$65)) -> 0.034927119 | G45: =IF(AND(COUNT(データ_株価!$P$5:$P$65)>0,ISNUMBER(C45)),COUNTIF(データ_株価!$P$5:$P$65,"<="&C45)/COUNT(データ_株価!$P$5:$P$65),"n.a.") -> 0.081967213 | H45: =COUNT(データ_株価!$P$5:$P$65) -> 61
B46: EV/EBITDA | C46: =IF(ISNUMBER(データ_株価!$C$17),データ_株価!$C$17,"n.a.") -> 24.487152 | D46: =IF(COUNT(データ_株価!$Q$5:$Q$65)=0,"n.a.",MIN(データ_株価!$Q$5:$Q$65)) -> 12.750617 | E46: =IF(COUNT(データ_株価!$Q$5:$Q$65)=0,"n.a.",MEDIAN(データ_株価!$Q$5:$Q$65)) -> 20.140637 | F46: =IF(COUNT(データ_株価!$Q$5:$Q$65)=0,"n.a.",MAX(データ_株価!$Q$5:$Q$65)) -> 33.615565 | G46: =IF(AND(COUNT(データ_株価!$Q$5:$Q$65)>0,ISNUMBER(C46)),COUNTIF(データ_株価!$Q$5:$Q$65,"<="&C46)/COUNT(データ_株価!$Q$5:$Q$65),"n.a.") -> 0.68852459 | H46: =COUNT(データ_株価!$Q$5:$Q$65) -> 61
B47: 注1：現在値はスナップショット（PER 実績は月次の最新値）。現在の位置は月次観測のうち現在値以下の割合
B48: 注2：会社予想 EPS が開示されないため PER（予想）は掲載しない。PER・配当利回りは実績 TTM
B50: 株式の概要
B51: 項目 | C51: 値
B52: 時価総額（百万ドル） | C52: =IF(ISNUMBER(データ_株価!$C$9),データ_株価!$C$9/1000000,"n.a.") -> 255252.73
B53: 売買代金 60日平均（百万ドル） | C53: =IF(ISNUMBER(データ_株価!$C$10),データ_株価!$C$10/1000000,"n.a.") -> 1676.2836
B54: 売買代金 60日平均（億円、円換算） | C54: =IF(ISNUMBER(データ_株価!$C$11),データ_株価!$C$11/100000000,"n.a.") -> 2648.528
B55: 発行済株式数（百万株、自己株控除後） | C55: =IF(ISNUMBER(データ_株価!$C$7),データ_株価!$C$7/1000000,"n.a.") -> 913.24769
B56: 純有利子負債（百万ドル） | C56: =IF(ISNUMBER(データ_株価!$C$12),データ_株価!$C$12/1000000,"n.a.") -> 5413
B73: 出所：Yahoo Finance（yfinance）・SEC EDGAR より作成
B90: 出所：Yahoo Finance（yfinance）・SEC EDGAR より作成
B92: ・過去5年の株価は3局面。2021-10-21の終値$201.29(5年窓の起点付近の高値)から下落し、2023-10-30に$140.50(同-30%)、2025-04-21に$145.61まで調整。その後2026年に急回復し、2026-06-22の終値$332.28が窓内の最高値。2026-10-22の$279.50は最高値比約-16%。 | M92: F4-S4 ※二次
B93: ・2026年の上昇は決算で段階的に起きた。2025年末$173.49→Q1決算翌日(4/23)に+19.4%→6月高値。7月決算後(7/23)は-3.1%で下落基調となり、2026-09-01に$253.34(高値比-24%)まで調整、10月に$280台へ戻した。2026年初来は10/22時点で約+61%。 | M93: F4-S4 ※二次
B94: ・直近の決算反応は非対称。Q3'26は売上・EPS・Q4ガイダンスのいずれもコンセンサス超え(売上$6,055M対約$5.92B、EPS$2.62対約$2.42、Q4中央値も上回る)だったが、10/22は-1.81%で出来高は直前20日平均の約2.5倍。7月(Q2)も-3.1%と、期待が高い局面でビートが売りで返される傾向がある。 | M94: F4-S1,F4-S4,F4-S10
B95: ・PERは過去数年のレンジ上端圏。年末終値÷通期EPS(10-K)は2023末24.1倍、2024末36.1倍、2025末31.8倍(司令塔計算)。現在は直近4四半期EPS$7.71(Q4'25 $1.27+Q1 $1.68+Q2 $2.14+Q3 $2.62)で約36倍と、2024年末と並ぶ水準。予想PERは約28倍(第三者、二次・未確認)。2023〜25年は減益局面でEPSが低くPERが高く出やすかった点に注意。 | M95: F4-S17,F4-S4,F4-S1,F4-S20,F4-S10
B96: ・EV/EBITDAはQ3年率換算で約19倍(司令塔の粗推計)。時価総額約$255B(株価$279.50×発行済約914M株)に純債務約$5.4Bを加えEV約$261B、Q3の営業利益$2,874M+減価償却等$576M=$3,450Mの4倍($13.8B)で割った値。過去5年のEV/EBITDAレンジは未取得で、現在値の相対位置は判定できない。 | M96: F4-S1,F4-S4
B97: ・FCF利回りは低い。直近12か月のTI定義FCF$8,422M(CHIPS法の受取を含む)を時価総額約$255Bで割ると約3.3%、CHIPS受取$1,104Mを除くと約2.9%(司令塔計算)。2024〜25年の大型設備投資期に比べFCFは大きく改善したが、株価は回復をかなり織り込んでいる。 | M97: F4-S1,F4-S4
B99: ③ 類似企業比較 | M99: 出所
B100: コード | C100: 社名 | D100: 株価（ドル） | E100: 時価総額（百万ドル） | F100: PER（実績TTM） | G100: PBR | H100: ROE | I100: 営業利益率 | J100: 売上成長率 | K100: EV/EBITDA | L100: 配当利回り（実績TTM）
B101: =データ_類似企業!B5 -> TXN | C101: =データ_類似企業!C5 -> Texas Instruments（対象） | D101: =データ_類似企業!D5 -> 279.5 | E101: =IF(ISNUMBER(データ_類似企業!E5),データ_類似企業!E5/1000000,"n.a.") -> 255252.73 | F101: =データ_類似企業!F5 -> 36.251621 | G101: =データ_類似企業!G5 -> 13.304807 | H101: =データ_類似企業!H5 -> 0.39724115 | I101: =データ_類似企業!I5 -> 0.40763748 | J101: =データ_類似企業!J5 -> 0.20271053 | K101: =データ_類似企業!K5 -> 24.487152 | L101: =データ_類似企業!L5 -> 0.020322004 | M101: market.json
B102: =データ_類似企業!B6 -> ADI | C102: =データ_類似企業!C6 -> ANALOG DEVICES INC | D102: =データ_類似企業!D6 -> 385.76001 | E102: =IF(ISNUMBER(データ_類似企業!E6),データ_類似企業!E6/1000000,"n.a.") -> 186925.98 | F102: =データ_類似企業!F6 -> 45.814728 | G102: =データ_類似企業!G6 -> 5.5714152 | H102: =データ_類似企業!H6 -> 0.12227095 | I102: =データ_類似企業!I6 -> 0.35549467 | J102: =データ_類似企業!J6 -> 0.33648002 | K102: =データ_類似企業!K6 -> 36.171556 | L102: =データ_類似企業!L6 -> 0.010835753 | M102: Yahoo Finance（yfinance）・SEC EDGAR
B103: =データ_類似企業!B7 -> MCHP | C103: =データ_類似企業!C7 -> MICROCHIP TECHNOLOGY INC | D103: =データ_類似企業!D7 -> 74.519997 | E103: =IF(ISNUMBER(データ_類似企業!E7),データ_類似企業!E7/1000000,"n.a.") -> 40465.006 | F103: =データ_類似企業!F7 -> 109.58823 | G103: =データ_類似企業!G7 -> 6.2726718 | H103: =データ_類似企業!H7 -> 0.071896063 | I103: =データ_類似企業!I7 -> 0.15516467 | J103: =データ_類似企業!J7 -> 0.2092875 | K103: =データ_類似企業!K7 -> 30.995445 | L103: =データ_類似企業!L7 -> 0.024422975 | M103: Yahoo Finance（yfinance）・SEC EDGAR
B104: =データ_類似企業!B8 -> NXPI | C104: =データ_類似企業!C8 -> NXP Semiconductors N.V. | D104: =データ_類似企業!D8 -> 237.78999 | E104: =IF(ISNUMBER(データ_類似企業!E8),データ_類似企業!E8/1000000,"n.a.") -> 60035.096 | F104: =データ_類似企業!F8 -> 22.755023 | G104: =データ_類似企業!G8 -> 5.4941975 | H104: =データ_類似企業!H8 -> 0.26203763 | I104: =データ_類似企業!I8 -> 0.30352755 | J104: =データ_類似企業!J8 -> 0.023695529 | K104: =データ_類似企業!K8 -> 15.126559 | L104: =データ_類似企業!L8 -> 0.017057068 | M104: Yahoo Finance（yfinance）・SEC EDGAR
B105: =データ_類似企業!B9 -> ON | C105: =データ_類似企業!C9 -> ON SEMICONDUCTOR CORP | D105: =データ_類似企業!D9 -> 73.230003 | E105: =IF(ISNUMBER(データ_類似企業!E9),データ_類似企業!E9/1000000,"n.a.") -> 28509.299 | F105: =データ_類似企業!F9 -> 47.245163 | G105: =データ_類似企業!G9 -> 3.9493674 | H105: =データ_類似企業!H9 -> 0.083142584 | I105: =データ_類似企業!I9 -> 0.10805447 | J105: =データ_類似企業!J9 -> -0.03141214 | K105: =データ_類似企業!K9 -> 19.946679 | L105: =データ_類似企業!L9 -> n.a. | M105: Yahoo Finance（yfinance）・SEC EDGAR
B106: =データ_類似企業!B10 -> STM | C106: =データ_類似企業!C10 -> STMicroelectronics N.V. | D106: =データ_類似企業!D10 -> 44.09 | E106: =IF(ISNUMBER(データ_類似企業!E10),データ_類似企業!E10/1000000,"n.a.") -> 39185.788 | F106: =データ_類似企業!F10 -> n.a. | G106: =データ_類似企業!G10 -> 2.1979912 | H106: =データ_類似企業!H10 -> n.a. | I106: =データ_類似企業!I10 -> n.a. | J106: =データ_類似企業!J10 -> n.a. | K106: =データ_類似企業!K10 -> n.a. | L106: =データ_類似企業!L10 -> 0.0081651168 | M106: Yahoo Finance（yfinance）・SEC EDGAR
B107: =データ_類似企業!B11 -> MPWR | C107: =データ_類似企業!C11 -> MONOLITHIC POWER SYSTEMS, INC. | D107: =データ_類似企業!D11 -> 1167.9301 | E107: =IF(ISNUMBER(データ_類似企業!E11),データ_類似企業!E11/1000000,"n.a.") -> 57395.587 | F107: =データ_類似企業!F11 -> 71.345758 | G107: =データ_類似企業!G11 -> 14.734105 | H107: =データ_類似企業!H11 -> 0.22572879 | I107: =データ_類似企業!I11 -> 0.28723484 | J107: =データ_類似企業!J11 -> 0.28666322 | K107: =データ_類似企業!K11 -> n.a. | L107: =データ_類似企業!L11 -> 0.0060962555 | M107: Yahoo Finance（yfinance）・SEC EDGAR
B108: 類似企業 中央値（対象除く） | D108: =IF(COUNT(D102:D107)=0,"n.a.",MEDIAN(D102:D107)) -> 156.15499 | E108: =IF(COUNT(E102:E107)=0,"n.a.",MEDIAN(E102:E107)) -> 48930.296 | F108: =IF(COUNT(F102:F107)=0,"n.a.",MEDIAN(F102:F107)) -> 47.245163 | G108: =IF(COUNT(G102:G107)=0,"n.a.",MEDIAN(G102:G107)) -> 5.5328064 | H108: =IF(COUNT(H102:H107)=0,"n.a.",MEDIAN(H102:H107)) -> 0.12227095 | I108: =IF(COUNT(I102:I107)=0,"n.a.",MEDIAN(I102:I107)) -> 0.28723484 | J108: =IF(COUNT(J102:J107)=0,"n.a.",MEDIAN(J102:J107)) -> 0.2092875 | K108: =IF(COUNT(K102:K107)=0,"n.a.",MEDIAN(K102:K107)) -> 25.471062 | L108: =IF(COUNT(L102:L107)=0,"n.a.",MEDIAN(L102:L107)) -> 0.010835753
B109: 注1：対象企業の ROE・営業利益率・売上成長率は market.json snapshot に無ければ n.a.
B128: 出所：Yahoo Finance（yfinance）・SEC EDGAR（各社 SEC 開示・株価）より作成
B130: ・ピア選定は事業構成の近さ順。1) ADI＝高性能アナログ・ミックスドシグナルの純度が最も高く、最終市場も産業49%・車載25%・通信16%（FQ3'26、2026年8月1日終了）でTXNと重なる。製造は自社ファブに外部ファウンドリを併用（既知・2026-10-05）。2) MCHP＝アナログ＋組込み（MCU）の混成で、TXNのAnalog/Embedded構成に最も似るIDM。3) NXPI＝車載・産業の混成信号とプロセッサ。ファブライト寄りで製造モデルは異なる。4) STM＝アナログ・パワー・MCUのIDMで産業・車載が主力。5) ON＝パワー／SiC中心で車載・産業が重なるが、アナログ比率は低い。6) MPWR＝ファブレスの電源IC専業で、AIデータセンター電源の競合・比較軸として採用。TXNの比率はAnalog 81%（売上$4,911M/$6,055M、2026年7〜9月期）。 | M130: F2-S1,F2-S2
B131: ・Infineon（FY26 Q3＝2026年4〜6月期、売上€4.172B・前年比約+13%、粗利率40.8%）とRenesas（2026年4〜6月期、IFRS粗利率58.6%）は事業の近さでは有力なピアだが、米ドル建ての上場が無く、会計基準・決算期も異なるため codes に入れない。参考点としてのみ散布図に載せる（二次・未確認）。 | M131: F2-S11,F2-S12,F2-S13 ※二次
B132: ・最新期の成長と粗利率は全社で改善した。TXN（2026年7〜9月期）は売上$6,055M・前年比+28%、粗利率64.2%（前年同期57.4%、売上総利益÷売上で当方算出）。前期比は売上+11%、粗利率は約+2.8%pt。ADI（FQ3'26）は+40%・GAAP粗利率67.3%（調整後72.5%）、MCHP（FQ1'27＝2026年6月30日終了）は+38.0%・63.2%、MPWR（2026年4〜6月期）は+47.6%・55.2%、NXPI（同）は+19%・57.3%、STM（同）は+26.0%・34.8%、ON（同）は+9%・38.4%。粗利率はアナログ専業・混成（TXN・ADI・MCHP）が60%超、パワー／IDM（STM・ON）は30%台と二極化している。 | M132: F2-S1,F2-S2,F2-S3,F2-S4,F2-S5,F2-S6,F2-S7
B133: ・未発表のため直前四半期を使う会社が多い点に注意。NXPI・STM・ON・MPWRの2026年7〜9月期は未発表（STMは2026-10-29予定）で、散布図は直前四半期（4〜6月期）の値。ADI・MCHPも決算期がずれる（ADIは8月1日終了、MCHPは6月30日終了）。期間が揃わないため、順位の比較は参考値にとどめる。 | M133: F2-S2,F2-S3,F2-S4,F2-S5,F2-S6,F2-S7,F2-S14
B134: ・粗利率の二極化は価格と稼働率の差から来る。TXNは粗利率改善の要因として売上増・価格・ミックスを挙げ、アナログ価格は2026年上期は前年並み、下期に動きが出たと説明した（二次・未確認）。ADI・TXNの値上げ（ADIは2026年2月と9月13日の2回、TXNは4月1日と10月1日の通知）は流通・報道ベースで、割合は情報源により幅がある（二次・未確認）。STMはP&Dセグメントが営業赤字（Q2'26 -$99M）で、未稼働費用は$37M（前年$103M）まで減少した。 | M134: F2-S8,F2-S9,F2-S6
B135: ・アナログ市場の順位はTXN首位、ADI第2位が通説（市場調査サイトでTXN約18〜19%、ADI約13.5%、情報源間で不一致のため二次・未確認）。TXNは同業との差を300mm内製で作る。既知（2026-10-17）：300mmで未パッケージのチップが約40%安いと10-Kに記載し、Sherman SM1が2025-12に生産開始。ただし新規として、Infineonが2026-07に€5BのDresden 300mm fabを開所しており（二次）、原価優位は競合に追われ始めている。 | M135: F2-S15,F2-S12,F2-S16 ※二次
B136: ・中国の国産化の脅威は、法的・価格面とも未解決。中国商務部は2025-09-13に米国産の汎用インターフェースIC・ゲートドライバIC（40nm以上）の反ダンピング調査を開始し、期限は2026-09-13（最長6か月延長可）。期限後の裁定または延長の有無は今回確認できていない（未取得）。TXNは2026年7〜9月期の決算説明で、自動車売上が前年比で中十%台の伸び（米国と中国が牽引）、中国事業は全社より速く伸びたと述べたとされる（二次・未確認）。 | M136: F2-S10,F2-S8 ※二次
B137: ・需給はタイト。TXNは設備投資を2026年$2〜3B（上限寄り）とし、後工程の装置リードタイムが延びていると述べた（二次・未確認）。ADI等のオペアンプ・基準ICは納期60週超との流通情報もある（二次・未確認）。TXNの売上のうちデータセンターは前年比約+95%・全社の約13%、産業は前年比+40%超で過去ピーク超え（二次・未確認）。ピアのAI関連は、STMが2026年のAIデータセンター売上$1B超、MPWRのEnterprise Dataが前年比+164.3%、ADIのCommunicationsが+84%（FQ3'26）で、TXNの追い風は個社固有でなく業界全体の波。 | M137: F2-S8,F2-S9,F2-S6,F2-S7,F2-S2
B139: ④ 事業内容・ビジネスモデル | M139: 出所
B140: セグメント | C140: 事業内容 | H140: 収益モデル | K140: 売上構成比 | L140: 営業利益率
B141: Analog（アナログ） | C141: Power（バッテリー管理、DC/DCスイッチングレギュレータ、AC/DC・絶縁電源、パワースイッチ、リニアレギュレータ、マルチフェーズコントローラ等）とSignal Chain（アンプ、データコンバータ、インターフェース、モータードライバ、クロック、ロジック、センサー）を、産業機器・車載・データセンター・パーソナルエレクトロニクス・通信機器の設計者と製造者に売る。 | H141: 利益を決めるのは、需要（工場稼働率）、製品ミックス、価格、300mm移行による製造コストの4つ。自社工場の固定費が重く、稼働率が上がると増収分の大半が粗利に落ちる（Q3'26の前期比の限界粗利率は約90%と会社説明、二次）。300mmの未パッケージのチップは200mmより約40%安い（会社説明）。2026年下期は価格が小幅に上昇、2027年の価格交渉は進行中（コール、二次）。償却費の増加は利益率の逆風。 | K141: =データ_セグメント!C5 -> 0.792 | L141: =データ_セグメント!D5 -> 0.386 | M141: F1-S1,F1-S2,F1-S6
B142: Embedded Processing（組込みプロセッサ） | C142: マイコン、プロセッサ、無線接続、レーダー製品を、主に産業機器と車載の顧客に売る。顧客が自社のソフトウェア資産を載せるため、世代をまたぐ乗り換えが起きにくい。Silicon Labs買収で無線接続製品群が加わる予定（完了前）。 | H142: 利益を決めるのは、工場稼働率（特にLFAB＝購入した稼働中のファブ）と製造コストの償却負担、売上の回復。FY2025は製造コスト増で営業利益率が11.3%に低下したが、LFABの稼働が上がるにつれ組込みが製造コスト低減の恩恵を受ける、と会社は説明している。顧客のソフトウェア資産による囲い込みで製品寿命が長い。Q3'26の営業利益率は26.5%まで回復。 | K142: =データ_セグメント!C6 -> 0.153 | L142: =データ_セグメント!D6 -> 0.113 | M142: F1-S1,F1-S2,F1-S3
B143: Other（その他） | C143: DLP（高精細画像を投影する製品）、電卓、特定顧客向けのカスタム半導体（ASIC）。このセグメントには買収・統合・リストラ費用や全社項目も含まれる。 | H143: 売上は小さく、利益は製品利益よりも費用項目（FY2025はリストラ費用等$117M、2024年は物件売却益を含む$124Mのクレジット）で振れる。Q3'26はSilicon Labs関連の買収費用$7Mを含む。 | K143: =データ_セグメント!C7 -> 0.055 | L143: =データ_セグメント!D7 -> 0.314 | M143: F1-S1,F1-S2
B162: 出所：会社資料、The Motley Fool資料より作成（元データは データ_セグメント） | M162: F1-S1,F1-S2,F1-S3,F1-S6
B163: 注1：利益構成比は会社開示のセグメント利益からの算出（調整額を除くセグメント合計に対する比率。赤字セグメントは負）
B164: ・300mm内製の構造的コスト優位：未パッケージのチップは200mmウエハー品より約40%安いと会社が説明（自己申告）。Richardson・Sherman（テキサス）とLehi（ユタ）の300mm新工場の立ち上げを進め、150mm工場2拠点の閉鎖を計画。製造は大半を内製し、足りない分だけ外部ファウンドリを使う。 | M164: F1-S1,F1-S3
B165: ・固定費レバレッジ：自社工場の固定費が重く、稼働率が上がると利益率が跳ね、下がると逆に減益が増幅される。Q3'26は粗利率64.2%（前年同期57.4%）、営業利益率47.5%（同35.1%）と、売上+28%に対し営業利益+73%。 | M165: F1-S2,F1-S3
B166: ・直販中心の販売網：FY2025の売上の80%超が直販（TI.com含む）で、顧客は10万社超、売上の約半分は上位50社の外側。注文対応・在庫プログラムなどに投資し、顧客の設計案件への接触を増やす。流通業者は世界1社と一部地域のみを選択肢として提供。 | M166: F1-S1
B167: ・広い製品ポートフォリオと製品寿命：8万点超の製品で産業・車載・データセンター・パーソナルエレクトロニクス・通信機器をカバーし、特定の用途や顧客への依存を抑える。新製品が単期の売上に与える影響は小さく、息の長い製品が積み上がる構造（会社説明）。 | M167: F1-S1,F1-S3
B168: ・在庫の先行構築戦略：用途が広く陳腐化リスクの低い製品は需要に先行して作り置き、リードタイムの競争力を保つ。在庫は$4,672M（2026-09-30）で前年同月$4,829Mより減少、在庫日数は194日（前期比-2日、コール）。 | M168: F1-S1,F1-S2,F1-S6
B169: ・設備投資サイクルとフリーキャッシュフロー：2016〜2025年の10年間で約$24Bを設備投資に配分。6年間の高水準の投資局面は終盤で、2026年の設備投資は$2〜3Bの見込み（コール：高めの水準に寄る）。直近12か月の設備投資$2,578M（前年$4,817M）、FCF$8,422M（売上比40.6%、前年同期$2,415M）。FCFにはCHIPS法の助成金受取$1,104M（直近12か月）を含み、営業CFにもCHIPS法の投資税額控除の現金効果$469Mが含まれる。 | M169: F1-S1,F1-S2,F1-S6
B170: ・地域製造の分散と地政学：北米・アジア・日本・欧州でウエハー製造と組立・テスト拠点を自社運営し、複数拠点・複数工程で供給継続性を確保。『地政学的に頼れる生産能力』を顧客への売りにする。マレーシアの後工程拠点を立ち上げ中（コール、二次）。中国は本社所在地ベースで売上の約21%、出荷先ベースで約50%と、地政学・競合（中国国産化）の影響を受けやすい。 | M170: F1-S1,F1-S6
B171: ・経営指標と還元：長期の『1株あたりFCFの成長』を最重要指標とし、FCFの全額を長期に配当と自社株買いで還元する方針。23年連続増配、直近12か月の還元$5,810M。Silicon Labs買収（約$7.5B現金）は完了後の純債務増加と還元余力の要点。 | M171: F1-S1,F1-S4,F1-S2,F1-S5
B193: 図2：2025年の売上$17.68B（アナログ$14.01B・組込み$2.70B・その他$979M）と最終市場構成、設備投資$4.6B・R&D$2.1B（出所：会社資料 3） | M193: F7-S1
B209: 図3：製造拠点15か所・従業員約3.3万人・主要な製造／設計拠点（2025年12月末）（出所：会社資料 3） | M209: F7-S1
B233: 図4：TI自身が示す4つの競争優位（製造・技術／製品の幅／販売チャネル／多様性と長寿命性）→FCF/株の成長最大化（出所：会社資料 3） | M233: F7-S2
B234: 主力製品と世界シェア
B235: 製品 | C235: セグメント | E235: 用途 | J235: 順位 | K235: 世界シェア
B236: アナログ全体（Omdia『Power & Analog』定義） | C236: アナログ | E236: 電源管理・信号処理・インタフェース等の主力。TIアナログ売上は2025年$14.01B（売上の約79%） | J236: 1位 | K236: 世界1位・約11.4%（2023年売上、Omdia定義はパワートランジスタ等を含み、TIのAnalogセグメントとは範囲が異なる。二次・未確認） | M236: F7-S3,F7-S4
B237: 電源管理IC（バッテリー管理・DC/DC・AC/DC・リニア・パワースイッチ等） | C237: アナログ（Power） | E237: 電子機器内の電圧変換・分配・保護。車載・産業・データセンターで使う | J237: n.a. | K237: シェア開示なし（TIは製品別売上を開示せず、信頼できる第三者推計も見つからず） | M237: F7-S3
B238: シグナルチェーン（アンプ・データコンバータ・インタフェース・モータードライブ・クロック・ロジック・センシング） | C238: アナログ（Signal Chain） | E238: 実世界の信号を検知・調整・変換してデジタル処理側へ渡す | J238: n.a. | K238: シェア開示なし（同上） | M238: F7-S3
B239: マイコン（MSP430・C2000等） | C239: 組込みプロセッシング | E239: 家電・工具・産業・車載の制御。顧客が自社ソフトを積み上げるため設計の継続期間が長い | J239: n.a. | K239: 全体シェア開示なし（車載向けは次行を参照） | M239: F7-S3
B240: 車載マイコン | C240: 組込みプロセッシング | E240: 車載の制御用。TIの最終市場で車載は売上の33%（2025年） | J240: 4位 | K240: 世界4位・8.4%（2024年、TechInsights調査の報道。二次・未確認） | M240: F7-S5,F7-S1
B241: プロセッサ・ミリ波レーダー・無線接続 | C241: 組込みプロセッシング | E241: 組込み向けの演算、車載・産業のレーダー、無線通信。Silicon Labs買収は完了前（2027年上期見込み）で、連結に含まない | J241: n.a. | K241: シェア開示なし | M241: F7-S3,F7-S2
B242: DLP・電卓・カスタムASIC | C242: その他 | E242: DLPは主に高精細映像の投影用。その他の売上は2025年$979M | J242: n.a. | K242: シェア開示なし（外部推計の一次・信頼できる二次を今回は確認できず） | M242: F7-S3,F7-S1
B243: 注1：シェアは各出所の定義（数量・金額、対象市場の範囲、年）による。異なる出所のシェアは直接比較できない
B268: 図5：買収予定のSilicon Labsの用途例（産業向けが売上の約85%、2025年。組込み無線の主な最終用途）（出所：会社資料 5） | M268: F7-S2
B270: ⑤ 社長の来歴 | M270: 出所
B271: 項目 | C271: 内容
B272: 氏名 | C272: Haviv Ilan（ハビブ・イラン）
B273: 役職 | C273: 会長兼社長兼CEO（Chairman, President and CEO）
B274: 生年 | C274: 1968〜69年頃（推定: 8-K・委任状の年齢 52歳[2020-08]、54歳[2023-01]、57歳[2026-03] から逆算）
B275: 就任 | C275: CEO 2023-04-01 就任、会長兼務 2026-01-01（Templeton 氏の退任 2025-12-31 を受けて）
B277: 年 | C277: 経歴・出来事
B278: 1999頃 | C278: TI入社（2020-08時点で社歴21年とされる）。入社時期の月日は未確認 | M278: F3-S1
...

Sheet 2_投資判断
B1: TXN Texas Instruments 投資判断・目標株価
B2: 基準日 2026-10-23／金額は百万ドル（株価はドル）／計算過程は 計算_DCF・計算_シナリオ を参照
B4: シナリオ切替（1=base, 2=bull, 3=bear） | C4: 1 | D4: =CHOOSE(C4,"base","bull","bear") -> base | E4: 表示中シナリオ（切替セル）のDCF理論株価 | I4: =計算_DCF!$C$53 -> 128.72754
B6: ① 投資判断 | N6: 出所
B7: 項目 | C7: 値
B8: レーティング | C8: 回避
B9: 確信度（1〜5） | C9: 3
B10: 投資期間 | C10: 6〜18か月（2027年1月の Q4 決算・2月の資本管理説明会から、2027年後半のサイクル判定まで）
B11: 現在株価（2026-10-22） | C11: =データ_株価!$C$6 -> 279.5
B12: 目標株価（＝DCF理論株価 base） | C12: ='2_投資判断'!$C$150 -> 128.72754
B13: 上昇余地 | C13: ='2_投資判断'!$C$150/'2_投資判断'!$C$11-1 -> -0.53943637
B14: 確率加重期待値（base/bull/bear、各0ドル下限） | C14: =計算_シナリオ!$D$8 -> 128.8847
B15: 期待値ベースの上昇余地 | C15: =計算_シナリオ!$D$8/'2_投資判断'!$C$11-1 -> -0.53887408
B16: 注1：目標株価は base の DCF理論株価（シナリオ切替に依存しない）。切替は 3_Assumptions の上書き仮定と 計算_DCF に連動
B17: 注2：確率加重は各シナリオを0ドルで下限処理（株主の有限責任）。シナリオ表の理論株価は下限処理前の値
B18: 投資判断の要旨
B19: ・事業の質は高く、Q3'26 は売上 +28%・営業利益率 47.5% と回復は本物。ただし株価 $279.50 は直近12か月 EPS の約36倍・EV/EBITDA 24.5倍。米10年国債 5.13% を前提にした DCF は base $129・bull $173・bear $85（確率加重 $129）で、WACC を 8% まで下げても base は約 $179 にとどまる。逆DCFでは、現在株価は base の業績なら WACC 約 6.4%（β1.2 なら ERP 約1.1% 相当）を必要とし、2028年 +13%・粗利率 65% が続く強い業績パスでも約 8.2% を要する。市場は強い業績と低い割引率を同時に織り込んでおり、どちらか一方が外れれば下値余地が大きい。新規の買いは見送り、既存保有は下記の条件で縮小を検討する。なお「回避」は DCF の前提の幅には頑健だが、倍率法（PER 30倍）を採れば逆転するため、評価方法の選択には依存する。投資助言ではない。
B20: 反証条件（これが起きたら判断を撤回）
B21: ・【回避が誤りとなる条件 → Buy 再検討】株価が bull シナリオの理論株価（約 $173）以下に下落（現値比 約 −38%。実質的には見送りに近い条件）。 | N21: S2-S4 ※二次
B22: ・【再評価を起動（いずれか1つ、期限 2027年1月の Q4 決算日）】FQ1'27 売上ガイダンス中央値が $6.3B 以上。 | N22: F6-S1
B23: ・【同上】2027年の値上げを中位一桁%以上と開示。 | N23: F6-S4,F4-S2 ※二次
B24: ・【同上】粗利率 64% 以上を2四半期続けて維持（bull の粗利率前提が実現）。 | N24: F1-S2
B25: ・【前提の反証】米10年国債が 5% を超えたまま、TXN の EV/EBITDA が 20倍超で4四半期続き、業績が base 並みなら、市場の割引率は当方の想定（β1.2・ERP 4.2%）より構造的に低い。β・ERP の組合せを見直して DCF を再計算する。 | N25: S2-S1,S2-S2,S2-S4
B26: ・【既存保有者の売却を急ぐ条件（いずれか1つ）】FQ1'27 売上ガイダンス中央値が $5.6B 未満、在庫日数が2四半期連続で上昇し 210日超、または粗利率が2四半期連続で低下し 60% 割れ。 | N26: F6-S1,F6-S4
B27: ・【同上】補助金除き FCF の直近12か月売上比が 25% 割れ、または配当が補助金除き FCF の 100% 超。 | N27: F6-S1
B28: ・【同上】中国商務部が反ダンピング調査で暫定措置・延長を公告、または米中の停止措置が 2027-01-10 に延長されず失効。 | N28: F6-S7,F6-S13
B29: カタリスト
B30: 時期 | C30: イベント
B31: 2026-10-29 | C31: STMicroelectronics Q3 決算（受注・book-to-bill でダブルオーダーの程度を確認）
B32: 2026-10 下旬〜11 上旬 | C32: NXP（流通在庫週数）・Microchip の決算
B33: 2026-11 中旬 | C33: ADI FQ4'26 決算（需要と値上げの外部確認。日付未確認）
B34: 2026-12 | C34: WSTS 秋季予測（アナログ 2027年の成長率）
B35: 2027-01-10 | C35: 米中の関税・非関税措置の停止期限（反ダンピング調査の分岐点）
B36: 2027-01 下旬 | C36: Q4'26 決算と 2027年の価格交渉結果の開示（日付未確認）
B37: 2027-02 | C37: 資本管理説明会・2027年設備投資の設定（日付未確認）
B38: 2027 上期 | C38: Silicon Labs 買収の完了見込み（中国 SAMR の承認が条件）
B40: ② 市場の注目点（市場の見方と当社の見方） | N40: 出所
B41: テーマ | C41: 市場の見方 | H41: 当社の見方
B42: Q4'26ガイダンスと季節性（需要の強さ） | C42: Q4'26(10-12月期)売上ガイダンスは$5.80〜6.30B(中央値$6.05B)、EPSは$2.45〜2.79(中央値$2.62)。決算前のコンセンサスは売上約$5.73〜5.75B・EPS約$2.27〜2.29（二次・未確認）で、レンジ下限が市場予想を上回った。会社は「季節性を上回る」と説明し、理由にデータセンター、産業回復、車載を挙げた（二次の通話記録）。Q3'26実績は売上$6,055M(前年比+28%、前期比+11%)、EPS$2.62(税の離散項目で-$0.01)。ただしレンジ幅は$500Mと広く、中央値より下限が重要との指摘がある（二次）。 | H42: ガイダンスは市場予想を上回ったが、中央値は Q3 並み。前四半期比で横ばいを示した点を、成長の頭打ちの初期サインとみる。2027年の base は +7% と置き、FQ1'27 ガイダンス（1月）で確かめる。 | N42: F4-S1,F4-S2,F4-S10,F4-S11
B43: 粗利率と増分利益率（稼働率・300mm） | C43: Q3'26の粗利率は64.2%（粗利$3,887M÷売上$6,055M）、前期比+280bp。会社は主因を売上増とし、工場稼働、価格、製品・最終市場ミックスも寄与と説明した（二次の通話記録）。前期比の増分粗利率は約90%（Q2'26粗利率61.4%・売上$5,463Mは既知、司令塔計算）で、会社の長期目安75〜85%（二次）を上回る。Morgan Stanleyは粗利率のポジティブサプライズを指摘する一方、在庫水準が高くアナログの完全回復と呼ぶのは時期尚早とした（二次）。営業利益率は47.5%（営業利益$2,874M）。 | H43: 増分粗利率 約90% は稼働率の回復によるもので、毎期は続かない。減価償却が売上比 10% 超に増えたため、売上が下を向くと利益率の落ちも大きい。粗利率は 2027年 63% を上限に、2028年は 60.5% に戻すのが base。 | N43: F4-S1,F4-S2,F4-S3,F4-S8,F4-S20,F6-S5
B44: 値上げと2027年の価格交渉 | C44: 7月(Q2)コールでは、価格は上期据え置きで値上げを開始、Q3の増収の大半は数量で価格の寄与は小さいと説明（二次）。10月(Q3)コールでは、アナログ価格が2026年下期に改善、2027年向けの顧客別の年次価格交渉が進行中で、詳細は2027年1月の決算で開示する意向（二次）。通常は年1回の交渉だが、供給が急務の顧客向けに期央の値上げ機会があったとの説明もある（二次）。売上増に占める価格寄与の数値開示は確認できない。 | H44: 値上げの寄与はまだ小さい（二次の通話記録）。一方で半導体 PPI は前年比 −2.2% で、業界全体では価格の上昇を確認できない。値上げは bull シナリオの条件として扱い、base には入れない。 | N44: F4-S2,F4-S3,F4-S7,F4-S18,F8-S1
B45: データセンター・産業・車載の需要 | C45: Q3'26のデータセンター売上は前年比約+95%・前期比約+20%、売上の約13%（Q2'26は前年比約2倍・前期比約+20%）。産業は前年比+40%超で4年ぶりの過去最高水準、車載は前年比で10%台半ば（米国・中国が牽引）、パーソナルエレクトロニクスは前年比ほぼ横ばい（以上、二次の通話記録）。CEOはデータセンター需要の鈍化は見えず来年も成長が続くと述べた。顧客在庫は低く、車載で一部に供給逼迫があるがCOVID期ほどではない。リードタイムは小幅に延伸（二次）。セグメント別は、アナログ売上$4,911M(前年比+32%、営業利益$2,505M)、組込み$858M(同+21%、同$227M)（一次）。 | H45: データセンター・産業は本物の需要だが、半導体・電子部品の生産 +19.9% に対し製造業全体 +1.4%、中国の自動車生産 −8.7% と、部品の伸びが最終需要を上回る。補充需要が一巡した後の伸びが論点。 | N45: F4-S1,F4-S2,F4-S3,F4-S7,F5-S5,F5-S8
B46: 設備投資・FCF・在庫日数（300mm投資の回収） | C46: Q3'26の設備投資は$463M(前年同期$1,197M)。直近12か月(2026-09期)の設備投資は$2,578M、営業CFは$9,896M、TI定義のFCFは$8,422M（売上比40.6%、CHIPS法の受取$1,104Mを含む。ITC活用$469Mは営業CF側）（一次）。2026年の設備投資ガイダンスは$2〜3Bで、設備の納入時期次第で上限近辺になり得る（二次）。上限に近づく場合はQ4の投資がQ3の$463Mより増える計算（司令塔推定、1-3Q累計は未照合）。2027年の設備投資は2027年2月に設定する予定で、2027年以降用のクリーンルーム工事は確保済みとの説明（二次）。在庫は$4,672M、194日分（前期比-2日、通話記録）。純債務は有利子負債$13,555M(流動$650M+長期$12,905M)から現金$4,211M・短期投資$3,931Mを引いた約$5.4B（司令塔計算）。配当は$1.42→$1.52に7%増額(23年連続、基準日2026-10-30)（一次）。 | H46: FCF の回復は設備投資の減少が主因で、約2割は補助金。補助金除きでは売上比 33%。設備投資は 2027年に売上比 10%、2028年 9% まで下がる前提で、FCF の伸びはそこで止まる。 | N46: F4-S1,F4-S2,F4-S3,F4-S6,F6-S1
B47: 中国（売上比率・反ダンピング調査・競争） | C47: 通話では車載で中国が需要を牽引し、中国事業は全社平均より速く成長との説明（二次）。中国商務部は2025-09-13、TI・ADI・Broadcom・Onsemiなど米国産の40nm以上アナログIC（汎用インターフェース、ゲートドライバ）の反ダンピング調査を開始。通常の期限は2026-09-13、特別な場合は6か月延長で最長2027-03-13（検索要約、公告原文は未確認）。2026-10-23時点で延長・仮決定・終局の公告は確認できず、状況は未確認。TIの売上の地理は本社所在地ベースで中国約21%（既知、10-K FY2025）。 | H47: 未決着のまま法定期限を過ぎており、休戦期限 2027-01-10 が分岐点。影響は推定で営業利益の数%で、評価の主因ではないが、反証条件で監視する。 | N47: F4-S2,F4-S3,F4-S15,F4-S20,F6-S7,F6-S13
B48: Silicon Labs買収（資金・承認・完了時期） | C48: 2026-02-04発表、現金$231.00/株・EV約$7.5B、完了は2027年上期見込み（一次、10-Q）。2026-06に買収完了を条件とする364日つなぎ融資(delayed draw term loan)最大$5Bを設定し、2026-06-30時点の借入はなし（一次）。Silicon Labs株主は2026-04-30に承認、米HSRの待機は2026-05-22に失効（二次）。7月コールでは規制承認は計画通り進行、資金は手元資金と負債と説明（二次）。中国SAMRの決定は確認できない（中国売上比率の指摘は二次・未確認）。10月のQ3コールではSilicon Labsに関する新情報は確認できなかった。 | H48: 完了しても EPS は増えるが、ROIC は下がる見込み。不成立でも違約金 $499M で済むため TXN の下値への影響は限定的。DCF には含めていない。 | N48: F4-S5,F4-S7,F4-S13,F4-S14,F6-S17
B49: 決算後の株価反応とセルサイド評価（織り込み） | C49: 2026-10-22の終値は$279.50で前日比-1.81%、出来高13.87M株（直前20営業日平均5.52M株の約2.5倍）（二次データ）。決算前日の10-21は+2.47%($284.65)、10-23は取引途中で約+1.0%($282.34)。過去2回の反応は、4月(Q1)が+19.4%（4/23、$236.31→$282.23、出来高25.7M株）、7月(Q2)が-3.1%（7/23、$294.19→$284.99、出来高11.7M株）。セルサイド（二次・未確認）は決算後にJPMorgan(Overweight)$340→$365、Stifel(Buy)$360→$370、Rosenblatt(Buy)$350→$360、Barclays(Equal-Weight)$250→$280、Jefferies(Hold)$260→$300、Morgan Stanley(Underweight)$255→$278、Mizuho(Neutral)$305→$290。コンセンサス目標は約$303〜311、格付けはHold中心（16 Buy・10 Hold・4 Sell）。織り込み: 実績PER約36倍（直近4四半期EPS$7.71）、予想PER約28倍（第三者）。 | H49: 決算翌日の下落は、好決算でも上値を追わない局面であることを示す。セルサイドの目標（約 $300）は、base の 2027年 EPS の約30倍、または bull の 2028年 EPS の約22倍に当たり、DCF に直すと「強い業績パス（2028年 +13%・粗利率 65% 永続）× WACC 約 8%」に相当する。当方の base（$129）との差の約7割は業績の前提の差で、割引率の差は約2割。 | N49: F4-S4,F4-S8,F4-S9,F4-S10,F4-S11,F4-S12,S2-S1
B51: ③ 伸びる点・懸念点・TAM・強気/弱気の上振れ幅 | N51: 出所
B52: ［景気・市況］サイクルは拡張の中盤から後半の入口とみる（後半入りの確率は主観で約6割）
B53: ・TI の売上は底（2024年1〜3月期）から10四半期で +65% と前回の上昇局面（9四半期 +62%）並みに達し、Q3'26 は前回ピークを 15.5% 上回った。ISM 価格指数・電子部品の不足の長期化・部品生産と最終製造の乖離はダブルオーダーの兆候。一方、ISM の顧客在庫 41.6（少なすぎる状態が24か月連続）と多くの会社の流通在庫の薄さは、補充需要がまだ残ることを示す反対証拠である。サイクルの天井は事後にしか確定しないため、判定は確率付きとする。base は 2027年 +7%（WSTS アナログ 2027年 +6.6% と同水準）、2028年 +4% とし、2028年の利益率を中位循環の水準に戻す（予測ではなく正規化の仮定）。
B54: 根拠 | L54: 数値
B55: ・TI 四半期売上: 前回ピーク 2022年7〜9月期 $5,241M、底 2024年1〜3月期 $3,661M、2026年7〜9月期 $6,055M | L55: 底から +65%・10四半期 | N55: F5-S13,F5-S9
B56: ・米 ISM 製造業 2026年9月: 価格 77.9、電子部品の不足 19か月連続（過熱側）。顧客在庫 41.6（少なすぎる、24か月連続）は反対証拠 | L56: 価格 77.9 | N56: F5-S4
B57: ・米鉱工業生産 2026年9月 前年比: 半導体・電子部品 +19.9%、製造業全体 +1.4% | L57: +19.9% 対 +1.4% | N57: F5-S5
B58: ・NXP 流通在庫 9週→11週（前年比。11週が同社の目標水準かは未確認） | L58: 11週 | N58: F5-S14
B59: ・WSTS 春季予測 アナログ 2026年 +10.2%、2027年 +6.6% | L59: +6.6%（2027） | N59: F5-S1,F5-S2
B60: 監視KPI | C60: NXP 流通在庫（12週超で警戒）、ISM 顧客在庫（50接近で警戒）、各社 book-to-bill、TI 在庫日数（210日超で警戒）
B61: 連動する仮定 | C61: 売上成長率（全社共通の基準）、売上総利益率
B63: ［懸念］織り込み: 株価は bull 並みの業績と低い割引率を同時に織り込む
B64: ・株価 $279.50 は直近12か月 EPS $7.71 の 36.3倍、EV/EBITDA 24.5倍。WACC 9.79%（rf 5.13%・ERP 4.2%・β1.2）の DCF は base $129。逆DCFでは現在株価に必要な WACC は base 業績で約 6.4%、2028年 +13%・粗利率 65% 永続の強い業績パスでも約 8.2%。WACC 9.79% のままなら 2029〜35年に年約20%の成長が要る。セルサイド目標（約 $300、二次・未確認）との差 約 $151 を、監査時の強気業績パス（2028年 +13%・粗利率 65% 永続）で分解すると、業績パスの寄与が約7割（+$111）、WACC 9.8%→8.5% が +$32、g 4% が +$10 で、主因は割引率ではなく業績の前提。インプライド EV/EBITDA 9.3倍（2027年予想。直近12か月基準では 11.3倍）がピア・自社レンジの下限を下回るのは、ピア倍率が 2026年のピークに近い利益の直近12か月値であることと、自社の5年レンジが 10年債 0.6〜4.9% の時期に形成されたことによる。
B65: 根拠 | L65: 数値
B66: ・株価・PER・EV/EBITDA（2026-10-22、直近12か月） | L66: $279.50・36.3倍・24.5倍 | N66: S2-S4,F6-S22 ※二次
B67: ・米10年国債利回り 2026-10-21 | L67: 5.13% | N67: S2-S1
B68: ・米国インプライド ERP（2026-10-01） | L68: 4.20% | N68: S2-S2 ※二次
B69: ・β 自計測 5年月次 Blume 調整 1.24、2年週次 同 1.15 | L69: 採用 1.20 | N69: S2-S3 ※二次
B70: 監視KPI | C70: 米10年国債利回り、TI の業績が bull の前提（2027年 +16%・粗利率 65%）に近づくか
B72: ［懸念］FCF の質: 約2割は補助金。2027年以降は剥落していく
B73: ・直近12か月の TI 定義 FCF $8,422M には CHIPS 受取 $1,104M と投資税額控除の現金効果 $469M が入る。モデルの FCF は補助金を含めず、未回収の CHIPS 関連債権 $2,163M（2026-06-30）だけを株式価値に加算した。
B74: 根拠 | L74: 数値
B75: ・補助金除き FCF（営業CF−ITC 現金効果−設備投資） | L75: $6,849M（売上比 33.0%） | N75: F6-S1
B76: ・CHIPS 関連の受取債権（流動 $1,005M＋長期 $1,158M） | L76: $2,163M | N76: F6-S3
B77: ・CHIPS 控除による 2025年の売上原価押し下げ | L77: $353M（粗利率 約2pt） | N77: F6-S2
B78: 監視KPI | C78: 補助金除き FCF の売上比（25% 割れで警戒）、10-K FY2026 の CHIPS 関連債権
B79: 連動する仮定 | C79: 有形・無形の現金投資／売上
B81: ［成長］データセンター電源と産業の回復が成長を牽引
B82: ・Q3'26 はアナログ +32%・組込み +21%。データセンター向けは前年比 約+95% で売上の約13%（コール、二次・未確認）。800V 給電への移行はアナログ電源の搭載額を増やすが、ST・MPS・Infineon も同じ市場を狙う。base は 2026年のセグメント別実績見込み（9か月実績＋Q4 ガイダンス中央値）に合わせ、2027年以降は全社同率とした。
B83: 根拠 | L83: 数値
B84: ・Q3'26 セグメント売上（前年比） | L84: アナログ $4,911M（+32%）、組込み $858M（+21%）、その他 $286M（−6%） | N84: F1-S2
B85: ・データセンター売上 前年比 約+95%・売上の約13%（コール、二次・未確認） | L85: 約13% | N85: F1-S6,F4-S2 ※二次
B86: ・ST はデータセンター売上を 2026年 $1B 超、2027年 $2B を大きく超えると表明（競合） | L86: $1B 超 | N86: F5-S15
B87: 監視KPI | C87: データセンター比率（コールでの開示）、アナログ前年比
B88: 連動する仮定 | C88: 成長率加減：Analog、成長率加減：Embedded Processing、成長率加減：Other
B90: ［市場規模］アナログ市場は 2026年 約 $950〜1,120億。TI のシェアは 16〜19%
B91: ・WSTS 春季予測は 2026年 $95.4B（+10.2%）だが、上場大手の伸び（+20〜29%）から逆算すると $103.8〜111.8B。TI のシェアは 2021年 19%（二次）から 2025年 16.2% に低下しており、市場の伸びに対しシェア維持を前提とする。
B92: 根拠 | L92: 数値
B93: ・WSTS アナログ 2025年実績・2026年予測（トップダウン） | L93: $86.5B → $95.4B | N93: F5-S1,F5-S2
B94: ・上場6社の加重成長から逆算した 2026年（ボトムアップ） | L94: $103.8〜111.8B | N94: F5-S13,F5-S9
B95: ・TI アナログ ÷ WSTS アナログ（2025年） | L95: 16.2% | N95: F5-S10,F5-S2
B96: 監視KPI | C96: WSTS 秋季予測、TI アナログ成長率と同業比
B97: 連動する仮定 | C97: 売上成長率（全社共通の基準）
B99: ［懸念］固定費と利益率: 現在の 47.5% は前回ピーク（50.6%）に近い
B100: ・減価償却が売上比 10% 超に増え、売上が前回並みに 22% 落ちれば営業利益は 35〜39% 減る計算。DCF のターミナルは 2028年の利益率で固定されるため、base は 2028年の営業利益率を約 42%（2018〜19年の中位循環 40〜43% に近い水準）に戻す。
B101: 根拠 | L101: 数値
B102: ・減価償却 2022年 → 直近12か月 | L102: $925M → 約 $2,180M（売上比 4.6%→10.5%） | N102: F6-S5,F6-S1
B103: ・前回サイクル 2022→2024年 | L103: 売上 −21.9%・営業利益 −46.1% | N103: F6-S5
B104: ・Q3'26 営業利益率 | L104: 47.5% | N104: F1-S2
B105: 監視KPI | C105: 粗利率（2四半期連続低下・60% 割れで警戒）、増分粗利率
B106: 連動する仮定 | C106: 売上総利益率、販管費率、別建て研究開発費率
B108: ［懸念］資本配分: ROIC は 75%→22% に低下、報酬は FCF/株と連動しない
B109: ・300mm 投資で投下資本は約2.4倍になり、ROIC（自己算出）は 2021年 75% から 2025年 22%、直近12か月 約29%。会社は FCF/株を最重要指標とするが、賞与の指標は売上成長・営業利益率・TSR の同業比較。Silicon Labs（EV/売上 約9.6倍）は ROIC を希薄化させる見込み。
B110: 根拠 | L110: 数値
...

Sheet 3_Summary
C2: TEXAS INSTRUMENTS INC Summary
C4: USD 百万単位。年次・連結実績。n.a. = 未抽出／対象外
C5: 項目 | D5: 2021-12-31 A | E5: 2022-12-31 A | F5: 2023-12-31 A | G5: 2024-12-31 A | H5: 2025-12-31 A | I5: 2026-12-31 E | J5: 2027-12-31 E | K5: 2028-12-31 E
C6: 売上高 | D6: =IF(AND(ISNUMBER('3_PL'!D6)),'3_PL'!D6,"n.a.") -> 18344 | E6: =IF(AND(ISNUMBER('3_PL'!E6)),'3_PL'!E6,"n.a.") -> 20028 | F6: =IF(AND(ISNUMBER('3_PL'!F6)),'3_PL'!F6,"n.a.") -> 17519 | G6: =IF(AND(ISNUMBER('3_PL'!G6)),'3_PL'!G6,"n.a.") -> 15641 | H6: =IF(AND(ISNUMBER('3_PL'!H6)),'3_PL'!H6,"n.a.") -> 17682 | I6: ='3_Forecast'!I8 -> 22387.166 | J6: ='3_Forecast'!J8 -> 23954.268 | K6: ='3_Forecast'!K8 -> 24912.438
C7: 営業利益 | D7: =IF(AND(ISNUMBER('3_PL'!D12)),'3_PL'!D12,"n.a.") -> 8960 | E7: =IF(AND(ISNUMBER('3_PL'!E12)),'3_PL'!E12,"n.a.") -> 10140 | F7: =IF(AND(ISNUMBER('3_PL'!F12)),'3_PL'!F12,"n.a.") -> 7331 | G7: =IF(AND(ISNUMBER('3_PL'!G12)),'3_PL'!G12,"n.a.") -> 5465 | H7: =IF(AND(ISNUMBER('3_PL'!H12)),'3_PL'!H12,"n.a.") -> 6023 | I7: ='3_Forecast'!I14 -> 9850.353 | J7: ='3_Forecast'!J14 -> 10923.146 | K7: ='3_Forecast'!K14 -> 10537.961
C8: 親会社株主帰属利益 | D8: =IF(AND(ISNUMBER('3_PL'!D17)),'3_PL'!D17,"n.a.") -> 7769 | E8: =IF(AND(ISNUMBER('3_PL'!E17)),'3_PL'!E17,"n.a.") -> 8749 | F8: =IF(AND(ISNUMBER('3_PL'!F17)),'3_PL'!F17,"n.a.") -> 6510 | G8: =IF(AND(ISNUMBER('3_PL'!G17)),'3_PL'!G17,"n.a.") -> 4799 | H8: =IF(AND(ISNUMBER('3_PL'!H17)),'3_PL'!H17,"n.a.") -> 5001 | I8: ='3_Forecast'!I21 -> 8392.8707 | J8: ='3_Forecast'!J21 -> 9177.7763 | K8: ='3_Forecast'!K21 -> 8844.5916
C9: 総資産 | D9: =IF(AND(ISNUMBER('3_BS'!D12)),'3_BS'!D12,"n.a.") -> 24676 | E9: =IF(AND(ISNUMBER('3_BS'!E12)),'3_BS'!E12,"n.a.") -> 27207 | F9: =IF(AND(ISNUMBER('3_BS'!F12)),'3_BS'!F12,"n.a.") -> 32348 | G9: =IF(AND(ISNUMBER('3_BS'!G12)),'3_BS'!G12,"n.a.") -> 35509 | H9: =IF(AND(ISNUMBER('3_BS'!H12)),'3_BS'!H12,"n.a.") -> 34585 | I9: ='3_Forecast'!I56 -> 38069.217 | J9: ='3_Forecast'!J56 -> 42283.406 | K9: ='3_Forecast'!K56 -> 46223.555
C10: 資本合計（非支配持分含む） | D10: =IF(AND(ISNUMBER('3_BS'!D16)),'3_BS'!D16,"n.a.") -> 13333 | E10: =IF(AND(ISNUMBER('3_BS'!E16)),'3_BS'!E16,"n.a.") -> 14577 | F10: =IF(AND(ISNUMBER('3_BS'!F16)),'3_BS'!F16,"n.a.") -> 16897 | G10: =IF(AND(ISNUMBER('3_BS'!G16)),'3_BS'!G16,"n.a.") -> 16903 | H10: =IF(AND(ISNUMBER('3_BS'!H16)),'3_BS'!H16,"n.a.") -> 16273 | I10: ='3_Forecast'!I60 -> 19666.871 | J10: ='3_Forecast'!J60 -> 23845.647 | K10: ='3_Forecast'!K60 -> 27691.239
C11: 営業活動によるCF | D11: =IF(AND(ISNUMBER('3_CF'!D6)),'3_CF'!D6,"n.a.") -> 8756 | E11: =IF(AND(ISNUMBER('3_CF'!E6)),'3_CF'!E6,"n.a.") -> 8720 | F11: =IF(AND(ISNUMBER('3_CF'!F6)),'3_CF'!F6,"n.a.") -> 6420 | G11: =IF(AND(ISNUMBER('3_CF'!G6)),'3_CF'!G6,"n.a.") -> 6318 | H11: =IF(AND(ISNUMBER('3_CF'!H6)),'3_CF'!H6,"n.a.") -> 7153 | I11: ='3_Forecast'!I37 -> 10102.427 | J11: ='3_Forecast'!J37 -> 10970.419 | K11: ='3_Forecast'!K37 -> 10488.636
C12: 投資活動によるCF | D12: =IF(AND(ISNUMBER('3_CF'!D10)),'3_CF'!D10,"n.a.") -> -4095 | E12: =IF(AND(ISNUMBER('3_CF'!E10)),'3_CF'!E10,"n.a.") -> -3583 | F12: =IF(AND(ISNUMBER('3_CF'!F10)),'3_CF'!F10,"n.a.") -> -4362 | G12: =IF(AND(ISNUMBER('3_CF'!G10)),'3_CF'!G10,"n.a.") -> -3202 | H12: =IF(AND(ISNUMBER('3_CF'!H10)),'3_CF'!H10,"n.a.") -> -1439 | I12: ='3_Forecast'!I38 -> -2798.3958 | J12: ='3_Forecast'!J38 -> -2395.4268 | K12: ='3_Forecast'!K38 -> -2242.1194
C13: 財務活動によるCF | D13: =IF(AND(ISNUMBER('3_CF'!D12)),'3_CF'!D12,"n.a.") -> -3137 | E13: =IF(AND(ISNUMBER('3_CF'!E12)),'3_CF'!E12,"n.a.") -> -6718 | F13: =IF(AND(ISNUMBER('3_CF'!F12)),'3_CF'!F12,"n.a.") -> -2144 | G13: =IF(AND(ISNUMBER('3_CF'!G12)),'3_CF'!G12,"n.a.") -> -2880 | H13: =IF(AND(ISNUMBER('3_CF'!H12)),'3_CF'!H12,"n.a.") -> -5689 | I13: ='3_Forecast'!I45 -> -4999 | J13: ='3_Forecast'!J45 -> -4999 | K13: ='3_Forecast'!K45 -> -4999
C14: 現金同等物の期末残高（CF定義） | D14: =IF(AND(ISNUMBER('3_CF'!D16)),'3_CF'!D16,"n.a.") -> 4631 | E14: =IF(AND(ISNUMBER('3_CF'!E16)),'3_CF'!E16,"n.a.") -> 3050 | F14: =IF(AND(ISNUMBER('3_CF'!F16)),'3_CF'!F16,"n.a.") -> 2964 | G14: =IF(AND(ISNUMBER('3_CF'!G16)),'3_CF'!G16,"n.a.") -> 3200 | H14: =IF(AND(ISNUMBER('3_CF'!H16)),'3_CF'!H16,"n.a.") -> 3225 | I14: ='3_Forecast'!I48 -> 5530.0311 | J14: ='3_Forecast'!J48 -> 9106.0235 | K14: ='3_Forecast'!K48 -> 12353.54
C17: 営業利益率 | D17: =IF(AND(ISNUMBER('3_PL'!D12),ISNUMBER('3_PL'!D6),'3_PL'!D6<>0),'3_PL'!D12/'3_PL'!D6,"n.a.") -> 0.48844309 | E17: =IF(AND(ISNUMBER('3_PL'!E12),ISNUMBER('3_PL'!E6),'3_PL'!E6<>0),'3_PL'!E12/'3_PL'!E6,"n.a.") -> 0.50629119 | F17: =IF(AND(ISNUMBER('3_PL'!F12),ISNUMBER('3_PL'!F6),'3_PL'!F6<>0),'3_PL'!F12/'3_PL'!F6,"n.a.") -> 0.41845996 | G17: =IF(AND(ISNUMBER('3_PL'!G12),ISNUMBER('3_PL'!G6),'3_PL'!G6<>0),'3_PL'!G12/'3_PL'!G6,"n.a.") -> 0.34940221 | H17: =IF(AND(ISNUMBER('3_PL'!H12),ISNUMBER('3_PL'!H6),'3_PL'!H6<>0),'3_PL'!H12/'3_PL'!H6,"n.a.") -> 0.34062889 | I17: =IF(AND(ISNUMBER('3_Forecast'!I14),ISNUMBER('3_Forecast'!I8),'3_Forecast'!I8<>0),'3_Forecast'!I14/'3_Forecast'!I8,"n.a.") -> 0.44 | J17: =IF(AND(ISNUMBER('3_Forecast'!J14),ISNUMBER('3_Forecast'!J8),'3_Forecast'!J8<>0),'3_Forecast'!J14/'3_Forecast'!J8,"n.a.") -> 0.456 | K17: =IF(AND(ISNUMBER('3_Forecast'!K14),ISNUMBER('3_Forecast'!K8),'3_Forecast'!K8<>0),'3_Forecast'!K14/'3_Forecast'!K8,"n.a.") -> 0.423
C18: 純利益率 | D18: =IF(AND(ISNUMBER('3_PL'!D17),ISNUMBER('3_PL'!D6),'3_PL'!D6<>0),'3_PL'!D17/'3_PL'!D6,"n.a.") -> 0.42351723 | E18: =IF(AND(ISNUMBER('3_PL'!E17),ISNUMBER('3_PL'!E6),'3_PL'!E6<>0),'3_PL'!E17/'3_PL'!E6,"n.a.") -> 0.43683843 | F18: =IF(AND(ISNUMBER('3_PL'!F17),ISNUMBER('3_PL'!F6),'3_PL'!F6<>0),'3_PL'!F17/'3_PL'!F6,"n.a.") -> 0.37159655 | G18: =IF(AND(ISNUMBER('3_PL'!G17),ISNUMBER('3_PL'!G6),'3_PL'!G6<>0),'3_PL'!G17/'3_PL'!G6,"n.a.") -> 0.30682181 | H18: =IF(AND(ISNUMBER('3_PL'!H17),ISNUMBER('3_PL'!H6),'3_PL'!H6<>0),'3_PL'!H17/'3_PL'!H6,"n.a.") -> 0.28283 | I18: =IF(AND(ISNUMBER('3_Forecast'!I21),ISNUMBER('3_Forecast'!I8),'3_Forecast'!I8<>0),'3_Forecast'!I21/'3_Forecast'!I8,"n.a.") -> 0.37489652 | J18: =IF(AND(ISNUMBER('3_Forecast'!J21),ISNUMBER('3_Forecast'!J8),'3_Forecast'!J8<>0),'3_Forecast'!J21/'3_Forecast'!J8,"n.a.") -> 0.38313742 | K18: =IF(AND(ISNUMBER('3_Forecast'!K21),ISNUMBER('3_Forecast'!K8),'3_Forecast'!K8<>0),'3_Forecast'!K21/'3_Forecast'!K8,"n.a.") -> 0.35502714
C19: 営業CF / 売上高 | D19: =IF(AND(ISNUMBER('3_CF'!D6),ISNUMBER('3_PL'!D6),'3_PL'!D6<>0),'3_CF'!D6/'3_PL'!D6,"n.a.") -> 0.47732229 | E19: =IF(AND(ISNUMBER('3_CF'!E6),ISNUMBER('3_PL'!E6),'3_PL'!E6<>0),'3_CF'!E6/'3_PL'!E6,"n.a.") -> 0.43539045 | F19: =IF(AND(ISNUMBER('3_CF'!F6),ISNUMBER('3_PL'!F6),'3_PL'!F6<>0),'3_CF'!F6/'3_PL'!F6,"n.a.") -> 0.36645927 | G19: =IF(AND(ISNUMBER('3_CF'!G6),ISNUMBER('3_PL'!G6),'3_PL'!G6<>0),'3_CF'!G6/'3_PL'!G6,"n.a.") -> 0.40393837 | H19: =IF(AND(ISNUMBER('3_CF'!H6),ISNUMBER('3_PL'!H6),'3_PL'!H6<>0),'3_CF'!H6/'3_PL'!H6,"n.a.") -> 0.40453569 | I19: =IF(AND(ISNUMBER('3_Forecast'!I37),ISNUMBER('3_Forecast'!I8),'3_Forecast'!I8<>0),'3_Forecast'!I37/'3_Forecast'!I8,"n.a.") -> 0.45125975 | J19: =IF(AND(ISNUMBER('3_Forecast'!J37),ISNUMBER('3_Forecast'!J8),'3_Forecast'!J8<>0),'3_Forecast'!J37/'3_Forecast'!J8,"n.a.") -> 0.45797347 | K19: =IF(AND(ISNUMBER('3_Forecast'!K37),ISNUMBER('3_Forecast'!K8),'3_Forecast'!K8<>0),'3_Forecast'!K37/'3_Forecast'!K8,"n.a.") -> 0.42102004
C20: 売上高成長率 | D20: n.a. | E20: =IF(AND(ISNUMBER('3_PL'!E6),ISNUMBER('3_PL'!D6),'3_PL'!D6<>0),'3_PL'!E6/'3_PL'!D6-1,"n.a.") -> 0.091801134 | F20: =IF(AND(ISNUMBER('3_PL'!F6),ISNUMBER('3_PL'!E6),'3_PL'!E6<>0),'3_PL'!F6/'3_PL'!E6-1,"n.a.") -> -0.12527462 | G20: =IF(AND(ISNUMBER('3_PL'!G6),ISNUMBER('3_PL'!F6),'3_PL'!F6<>0),'3_PL'!G6/'3_PL'!F6-1,"n.a.") -> -0.1071979 | H20: =IF(AND(ISNUMBER('3_PL'!H6),ISNUMBER('3_PL'!G6),'3_PL'!G6<>0),'3_PL'!H6/'3_PL'!G6-1,"n.a.") -> 0.13049038 | I20: =IF(AND(ISNUMBER('3_Forecast'!I8),ISNUMBER('3_Forecast'!H8),'3_Forecast'!H8<>0),'3_Forecast'!I8/'3_Forecast'!H8-1,"n.a.") -> 0.2660992 | J20: =IF(AND(ISNUMBER('3_Forecast'!J8),ISNUMBER('3_Forecast'!I8),'3_Forecast'!I8<>0),'3_Forecast'!J8/'3_Forecast'!I8-1,"n.a.") -> 0.07 | K20: =IF(AND(ISNUMBER('3_Forecast'!K8),ISNUMBER('3_Forecast'!J8),'3_Forecast'!J8<>0),'3_Forecast'!K8/'3_Forecast'!J8-1,"n.a.") -> 0.04
C23: 対象と読み方
C24: TXN: 取得関連無形資産の残高はFY2021〜FY2025の10-K貸借対照表に独立表示なし、取得関連無形資産償却はFY2024・FY2025の10-K CF計算書に表示なし（該当行はn.a.のまま）。無形資産・D&Aは司令塔判断（案A）により資産計上ソフトウェアの表示値で代替。代替宣言：理想＝0054定義の無形資産・純粋D&A／10-K FY2021-25のBSに取得関連無形資産の行が無いことを確認済み／代替＝資産計上ソフトウェア（Capitalized software licenses）の表示値とその償却／バイアス＝無形資産の過小は軽微、償却率は有形中心の値になる
C25: 異なる年度のセグメント再編・会計基準変更は自動で組み替えない。比較値は出典の定義を確認。
C26: 年次連結実績。将来予測は別のモデル仮定で設定。会社予想と区別する。
C27: 財務整理用。投資助言ではありません。
C28: 予測3年は機械的初期仮定によるモデル予測E。会社予想ではありません。
C29: 未抽出の三表セル: 2。すべての空欄を未開示と解釈しない。
C30: 青字：原数値。緑字：他シート参照。黒字：計算・Summary。A：実績。
C31: BSの現預金とCFの現金同等物は範囲が異なる場合があります。差額をゼロに強制しません。

Sheet 3_PL
C2: TEXAS INSTRUMENTS INC PL
C4: USD 百万単位。年次・連結実績。n.a. = 未抽出／対象外
C5: 項目 | D5: 2021-12-31 A | E5: 2022-12-31 A | F5: 2023-12-31 A | G5: 2024-12-31 A | H5: 2025-12-31 A | I5: 2026-12-31 E | J5: 2027-12-31 E | K5: 2028-12-31 E
C6: 売上高 | D6: =IF(AND(ISNUMBER(データ_財務!F6)),データ_財務!F6/1000000,"n.a.") -> 18344 | E6: =IF(AND(ISNUMBER(データ_財務!F7)),データ_財務!F7/1000000,"n.a.") -> 20028 | F6: =IF(AND(ISNUMBER(データ_財務!F8)),データ_財務!F8/1000000,"n.a.") -> 17519 | G6: =IF(AND(ISNUMBER(データ_財務!F9)),データ_財務!F9/1000000,"n.a.") -> 15641 | H6: =IF(AND(ISNUMBER(データ_財務!F10)),データ_財務!F10/1000000,"n.a.") -> 17682 | I6: ='3_Forecast'!I8 -> 22387.166 | J6: ='3_Forecast'!J8 -> 23954.268 | K6: ='3_Forecast'!K8 -> 24912.438
C7: 売上原価 | D7: =IF(AND(ISNUMBER(データ_財務!F11)),データ_財務!F11/1000000,"n.a.") -> 5968 | E7: =IF(AND(ISNUMBER(データ_財務!F12)),データ_財務!F12/1000000,"n.a.") -> 6257 | F7: =IF(AND(ISNUMBER(データ_財務!F13)),データ_財務!F13/1000000,"n.a.") -> 6500 | G7: =IF(AND(ISNUMBER(データ_財務!F14)),データ_財務!F14/1000000,"n.a.") -> 6547 | H7: =IF(AND(ISNUMBER(データ_財務!F15)),データ_財務!F15/1000000,"n.a.") -> 7599 | I7: ='3_Forecast'!I9 -> 8507.1231 | J7: ='3_Forecast'!J9 -> 8863.079 | K7: ='3_Forecast'!K9 -> 9840.4131
C8: 売上総利益 | D8: =IF(AND(ISNUMBER(データ_財務!F16)),データ_財務!F16/1000000,"n.a.") -> 12376 | E8: =IF(AND(ISNUMBER(データ_財務!F17)),データ_財務!F17/1000000,"n.a.") -> 13771 | F8: =IF(AND(ISNUMBER(データ_財務!F18)),データ_財務!F18/1000000,"n.a.") -> 11019 | G8: =IF(AND(ISNUMBER(データ_財務!F19)),データ_財務!F19/1000000,"n.a.") -> 9094 | H8: =IF(AND(ISNUMBER(データ_財務!F20)),データ_財務!F20/1000000,"n.a.") -> 10083 | I8: ='3_Forecast'!I10 -> 13880.043 | J8: ='3_Forecast'!J10 -> 15091.189 | K8: ='3_Forecast'!K10 -> 15072.025
C9: 販売費及び一般管理費 | D9: =IF(AND(ISNUMBER(データ_財務!F21)),データ_財務!F21/1000000,"n.a.") -> 1666 | E9: =IF(AND(ISNUMBER(データ_財務!F22)),データ_財務!F22/1000000,"n.a.") -> 1704 | F9: =IF(AND(ISNUMBER(データ_財務!F23)),データ_財務!F23/1000000,"n.a.") -> 1825 | G9: =IF(AND(ISNUMBER(データ_財務!F24)),データ_財務!F24/1000000,"n.a.") -> 1794 | H9: =IF(AND(ISNUMBER(データ_財務!F25)),データ_財務!F25/1000000,"n.a.") -> 1860 | I9: ='3_Forecast'!I11 -> 1880.5219 | J9: ='3_Forecast'!J11 -> 1964.2499 | K9: ='3_Forecast'!K11 -> 2142.4697
C10: 研究開発費（内数の場合あり） | D10: =IF(AND(ISNUMBER(データ_財務!F26)),データ_財務!F26/1000000,"n.a.") -> 1554 | E10: =IF(AND(ISNUMBER(データ_財務!F27)),データ_財務!F27/1000000,"n.a.") -> 1670 | F10: =IF(AND(ISNUMBER(データ_財務!F28)),データ_財務!F28/1000000,"n.a.") -> 1863 | G10: =IF(AND(ISNUMBER(データ_財務!F29)),データ_財務!F29/1000000,"n.a.") -> 1959 | H10: =IF(AND(ISNUMBER(データ_財務!F30)),データ_財務!F30/1000000,"n.a.") -> 2083 | I10: ='3_Forecast'!I12 -> 2149.1679 | J10: ='3_Forecast'!J12 -> 2203.7926 | K10: ='3_Forecast'!K12 -> 2391.5941
C11: その他営業費用・損益調整（計算値） | D11: =IF(AND(ISNUMBER(D8),ISNUMBER(D9),ISNUMBER(D12),ISNUMBER(D10)),D8-D9-D12-D10,"n.a.") -> 196 | E11: =IF(AND(ISNUMBER(E8),ISNUMBER(E9),ISNUMBER(E12),ISNUMBER(E10)),E8-E9-E12-E10,"n.a.") -> 257 | F11: =IF(AND(ISNUMBER(F8),ISNUMBER(F9),ISNUMBER(F12),ISNUMBER(F10)),F8-F9-F12-F10,"n.a.") -> 0 | G11: =IF(AND(ISNUMBER(G8),ISNUMBER(G9),ISNUMBER(G12),ISNUMBER(G10)),G8-G9-G12-G10,"n.a.") -> -124 | H11: =IF(AND(ISNUMBER(H8),ISNUMBER(H9),ISNUMBER(H12),ISNUMBER(H10)),H8-H9-H12-H10,"n.a.") -> 117 | I11: ='3_Forecast'!I13 -> 0 | J11: ='3_Forecast'!J13 -> 0 | K11: ='3_Forecast'!K13 -> 0
C12: 営業利益 | D12: =IF(AND(ISNUMBER(データ_財務!F31)),データ_財務!F31/1000000,"n.a.") -> 8960 | E12: =IF(AND(ISNUMBER(データ_財務!F32)),データ_財務!F32/1000000,"n.a.") -> 10140 | F12: =IF(AND(ISNUMBER(データ_財務!F33)),データ_財務!F33/1000000,"n.a.") -> 7331 | G12: =IF(AND(ISNUMBER(データ_財務!F34)),データ_財務!F34/1000000,"n.a.") -> 5465 | H12: =IF(AND(ISNUMBER(データ_財務!F35)),データ_財務!F35/1000000,"n.a.") -> 6023 | I12: ='3_Forecast'!I14 -> 9850.353 | J12: ='3_Forecast'!J14 -> 10923.146 | K12: ='3_Forecast'!K14 -> 10537.961
C13: 税引前利益 | D13: =IF(AND(ISNUMBER(データ_財務!F36)),データ_財務!F36/1000000,"n.a.") -> 8919 | E13: =IF(AND(ISNUMBER(データ_財務!F37)),データ_財務!F37/1000000,"n.a.") -> 10032 | F13: =IF(AND(ISNUMBER(データ_財務!F38)),データ_財務!F38/1000000,"n.a.") -> 7418 | G13: =IF(AND(ISNUMBER(データ_財務!F39)),データ_財務!F39/1000000,"n.a.") -> 5453 | H13: =IF(AND(ISNUMBER(データ_財務!F40)),データ_財務!F40/1000000,"n.a.") -> 5710 | I13: ='3_Forecast'!I17 -> 9537.353 | J13: ='3_Forecast'!J17 -> 10610.146 | K13: ='3_Forecast'!K17 -> 10224.961
C14: 法人所得税 | D14: =IF(AND(ISNUMBER(データ_財務!F41)),データ_財務!F41/1000000,"n.a.") -> 1150 | E14: =IF(AND(ISNUMBER(データ_財務!F42)),データ_財務!F42/1000000,"n.a.") -> 1283 | F14: =IF(AND(ISNUMBER(データ_財務!F43)),データ_財務!F43/1000000,"n.a.") -> 908 | G14: =IF(AND(ISNUMBER(データ_財務!F44)),データ_財務!F44/1000000,"n.a.") -> 654 | H14: =IF(AND(ISNUMBER(データ_財務!F45)),データ_財務!F45/1000000,"n.a.") -> 709 | I14: ='3_Forecast'!I18 -> 1144.4824 | J14: ='3_Forecast'!J18 -> 1432.3697 | K14: ='3_Forecast'!K18 -> 1380.3698
C15: 当期利益（非支配持分含む） | D15: =IF(AND(ISNUMBER(データ_財務!F151)),データ_財務!F151/1000000,"n.a.") -> 7769 | E15: =IF(AND(ISNUMBER(データ_財務!F152)),データ_財務!F152/1000000,"n.a.") -> 8749 | F15: =IF(AND(ISNUMBER(データ_財務!F153)),データ_財務!F153/1000000,"n.a.") -> 6510 | G15: =IF(AND(ISNUMBER(データ_財務!F154)),データ_財務!F154/1000000,"n.a.") -> 4799 | H15: =IF(AND(ISNUMBER(データ_財務!F155)),データ_財務!F155/1000000,"n.a.") -> 5001 | I15: ='3_Forecast'!I19 -> 8392.8707 | J15: ='3_Forecast'!J19 -> 9177.7763 | K15: ='3_Forecast'!K19 -> 8844.5916
C16: 非支配持分帰属利益 | D16: =IF(AND(ISNUMBER(データ_財務!F141)),データ_財務!F141/1000000,"n.a.") -> 0 | E16: =IF(AND(ISNUMBER(データ_財務!F142)),データ_財務!F142/1000000,"n.a.") -> 0 | F16: =IF(AND(ISNUMBER(データ_財務!F143)),データ_財務!F143/1000000,"n.a.") -> 0 | G16: =IF(AND(ISNUMBER(データ_財務!F144)),データ_財務!F144/1000000,"n.a.") -> 0 | H16: =IF(AND(ISNUMBER(データ_財務!F145)),データ_財務!F145/1000000,"n.a.") -> 0 | I16: ='3_Forecast'!I20 -> 0 | J16: ='3_Forecast'!J20 -> 0 | K16: ='3_Forecast'!K20 -> 0
C17: 親会社株主帰属利益 | D17: =IF(AND(ISNUMBER(データ_財務!F46)),データ_財務!F46/1000000,"n.a.") -> 7769 | E17: =IF(AND(ISNUMBER(データ_財務!F47)),データ_財務!F47/1000000,"n.a.") -> 8749 | F17: =IF(AND(ISNUMBER(データ_財務!F48)),データ_財務!F48/1000000,"n.a.") -> 6510 | G17: =IF(AND(ISNUMBER(データ_財務!F49)),データ_財務!F49/1000000,"n.a.") -> 4799 | H17: =IF(AND(ISNUMBER(データ_財務!F50)),データ_財務!F50/1000000,"n.a.") -> 5001 | I17: ='3_Forecast'!I21 -> 8392.8707 | J17: ='3_Forecast'!J21 -> 9177.7763 | K17: ='3_Forecast'!K21 -> 8844.5916

Sheet 3_BS
C2: TEXAS INSTRUMENTS INC BS
C4: USD 百万単位。年次・連結実績。n.a. = 未抽出／対象外
C5: 項目 | D5: 2021-12-31 A | E5: 2022-12-31 A | F5: 2023-12-31 A | G5: 2024-12-31 A | H5: 2025-12-31 A | I5: 2026-12-31 E | J5: 2027-12-31 E | K5: 2028-12-31 E
C6: 現金及び預金・現金同等物（BS定義） | D6: =IF(AND(ISNUMBER(データ_財務!F51)),データ_財務!F51/1000000,"n.a.") -> 4631 | E6: =IF(AND(ISNUMBER(データ_財務!F52)),データ_財務!F52/1000000,"n.a.") -> 3050 | F6: =IF(AND(ISNUMBER(データ_財務!F53)),データ_財務!F53/1000000,"n.a.") -> 2964 | G6: =IF(AND(ISNUMBER(データ_財務!F54)),データ_財務!F54/1000000,"n.a.") -> 3200 | H6: =IF(AND(ISNUMBER(データ_財務!F55)),データ_財務!F55/1000000,"n.a.") -> 3225 | I6: ='3_Forecast'!I52 -> 5530.0311 | J6: ='3_Forecast'!J52 -> 9106.0235 | K6: ='3_Forecast'!K52 -> 12353.54
C7: 売上債権 | D7: =IF(AND(ISNUMBER(データ_財務!F56)),データ_財務!F56/1000000,"n.a.") -> 1701 | E7: =IF(AND(ISNUMBER(データ_財務!F57)),データ_財務!F57/1000000,"n.a.") -> 1895 | F7: =IF(AND(ISNUMBER(データ_財務!F58)),データ_財務!F58/1000000,"n.a.") -> 1787 | G7: =IF(AND(ISNUMBER(データ_財務!F59)),データ_財務!F59/1000000,"n.a.") -> 1719 | H7: =IF(AND(ISNUMBER(データ_財務!F60)),データ_財務!F60/1000000,"n.a.") -> 1963 | I7: ='3_Forecast'!I24 -> 2485.3527 | J7: ='3_Forecast'!J24 -> 2659.3274 | K7: ='3_Forecast'!K24 -> 2758.144
C8: 棚卸資産 | D8: =IF(AND(ISNUMBER(データ_財務!F61)),データ_財務!F61/1000000,"n.a.") -> 1910 | E8: =IF(AND(ISNUMBER(データ_財務!F62)),データ_財務!F62/1000000,"n.a.") -> 2757 | F8: =IF(AND(ISNUMBER(データ_財務!F63)),データ_財務!F63/1000000,"n.a.") -> 3999 | G8: =IF(AND(ISNUMBER(データ_財務!F64)),データ_財務!F64/1000000,"n.a.") -> 4527 | H8: =IF(AND(ISNUMBER(データ_財務!F65)),データ_財務!F65/1000000,"n.a.") -> 4804 | I8: ='3_Forecast'!I25 -> 4661.4373 | J8: ='3_Forecast'!J25 -> 4856.4817 | K8: ='3_Forecast'!K25 -> 5377.2749
C9: 流動資産 | D9: =IF(AND(ISNUMBER(データ_財務!F66)),データ_財務!F66/1000000,"n.a.") -> 13685 | E9: =IF(AND(ISNUMBER(データ_財務!F67)),データ_財務!F67/1000000,"n.a.") -> 14021 | F9: =IF(AND(ISNUMBER(データ_財務!F68)),データ_財務!F68/1000000,"n.a.") -> 15122 | G9: =IF(AND(ISNUMBER(データ_財務!F69)),データ_財務!F69/1000000,"n.a.") -> 15026 | H9: =IF(AND(ISNUMBER(データ_財務!F70)),データ_財務!F70/1000000,"n.a.") -> 13750 | I9: ='3_Forecast'!I54 -> 16434.821 | J9: ='3_Forecast'!J54 -> 20379.833 | K9: ='3_Forecast'!K54 -> 24246.959
C10: 有形固定資産 | D10: =IF(AND(ISNUMBER(データ_財務!F71)),データ_財務!F71/1000000,"n.a.") -> 5141 | E10: =IF(AND(ISNUMBER(データ_財務!F72)),データ_財務!F72/1000000,"n.a.") -> 6876 | F10: =IF(AND(ISNUMBER(データ_財務!F73)),データ_財務!F73/1000000,"n.a.") -> 9999 | G10: =IF(AND(ISNUMBER(データ_財務!F74)),データ_財務!F74/1000000,"n.a.") -> 11347 | H10: =IF(AND(ISNUMBER(データ_財務!F75)),データ_財務!F75/1000000,"n.a.") -> 12320 | I10: ='3_Forecast'!I33 -> 13104.246 | J10: ='3_Forecast'!J33 -> 13368.322 | K10: ='3_Forecast'!K33 -> 13439.96
C11: 無形資産（のれんを除く場合あり） | D11: =IF(AND(ISNUMBER(データ_財務!F146)),データ_財務!F146/1000000,"n.a.") -> 85 | E11: =IF(AND(ISNUMBER(データ_財務!F147)),データ_財務!F147/1000000,"n.a.") -> 152 | F11: =IF(AND(ISNUMBER(データ_財務!F148)),データ_財務!F148/1000000,"n.a.") -> 223 | G11: =IF(AND(ISNUMBER(データ_財務!F149)),データ_財務!F149/1000000,"n.a.") -> 257 | H11: =IF(AND(ISNUMBER(データ_財務!F150)),データ_財務!F150/1000000,"n.a.") -> 238 | I11: ='3_Forecast'!I34 -> 253.1502 | J11: ='3_Forecast'!J34 -> 258.25167 | K11: ='3_Forecast'!K34 -> 259.6356
C12: 総資産 | D12: =IF(AND(ISNUMBER(データ_財務!F76)),データ_財務!F76/1000000,"n.a.") -> 24676 | E12: =IF(AND(ISNUMBER(データ_財務!F77)),データ_財務!F77/1000000,"n.a.") -> 27207 | F12: =IF(AND(ISNUMBER(データ_財務!F78)),データ_財務!F78/1000000,"n.a.") -> 32348 | G12: =IF(AND(ISNUMBER(データ_財務!F79)),データ_財務!F79/1000000,"n.a.") -> 35509 | H12: =IF(AND(ISNUMBER(データ_財務!F80)),データ_財務!F80/1000000,"n.a.") -> 34585 | I12: ='3_Forecast'!I56 -> 38069.217 | J12: ='3_Forecast'!J56 -> 42283.406 | K12: ='3_Forecast'!K56 -> 46223.555
C13: 仕入債務 | D13: =IF(AND(ISNUMBER(データ_財務!F81)),データ_財務!F81/1000000,"n.a.") -> 571 | E13: =IF(AND(ISNUMBER(データ_財務!F82)),データ_財務!F82/1000000,"n.a.") -> 851 | F13: =IF(AND(ISNUMBER(データ_財務!F83)),データ_財務!F83/1000000,"n.a.") -> 802 | G13: =IF(AND(ISNUMBER(データ_財務!F84)),データ_財務!F84/1000000,"n.a.") -> 820 | H13: =IF(AND(ISNUMBER(データ_財務!F85)),データ_財務!F85/1000000,"n.a.") -> 756 | I13: ='3_Forecast'!I26 -> 846.34624 | J13: ='3_Forecast'!J26 -> 881.75914 | K13: ='3_Forecast'!K26 -> 976.31612
C14: 流動負債 | D14: =IF(AND(ISNUMBER(データ_財務!F86)),データ_財務!F86/1000000,"n.a.") -> 2569 | E14: =IF(AND(ISNUMBER(データ_財務!F87)),データ_財務!F87/1000000,"n.a.") -> 2985 | F14: =IF(AND(ISNUMBER(データ_財務!F88)),データ_財務!F88/1000000,"n.a.") -> 3320 | G14: =IF(AND(ISNUMBER(データ_財務!F89)),データ_財務!F89/1000000,"n.a.") -> 3643 | H14: =IF(AND(ISNUMBER(データ_財務!F90)),データ_財務!F90/1000000,"n.a.") -> 3159 | I14: ='3_Forecast'!I58 -> 3249.3462 | J14: ='3_Forecast'!J58 -> 3284.7591 | K14: ='3_Forecast'!K58 -> 3379.3161
C15: 負債合計 | D15: =IF(AND(ISNUMBER(データ_財務!F91)),データ_財務!F91/1000000,"n.a.") -> 11343 | E15: =IF(AND(ISNUMBER(データ_財務!F92)),データ_財務!F92/1000000,"n.a.") -> 12630 | F15: =IF(AND(ISNUMBER(データ_財務!F93)),データ_財務!F93/1000000,"n.a.") -> 15451 | G15: =IF(AND(ISNUMBER(データ_財務!F94)),データ_財務!F94/1000000,"n.a.") -> 18606 | H15: =IF(AND(ISNUMBER(データ_財務!F95)),データ_財務!F95/1000000,"n.a.") -> 18312 | I15: ='3_Forecast'!I59 -> 18402.346 | J15: ='3_Forecast'!J59 -> 18437.759 | K15: ='3_Forecast'!K59 -> 18532.316
C16: 資本合計（非支配持分含む） | D16: =IF(AND(ISNUMBER(データ_財務!F96)),データ_財務!F96/1000000,"n.a.") -> 13333 | E16: =IF(AND(ISNUMBER(データ_財務!F97)),データ_財務!F97/1000000,"n.a.") -> 14577 | F16: =IF(AND(ISNUMBER(データ_財務!F98)),データ_財務!F98/1000000,"n.a.") -> 16897 | G16: =IF(AND(ISNUMBER(データ_財務!F99)),データ_財務!F99/1000000,"n.a.") -> 16903 | H16: =IF(AND(ISNUMBER(データ_財務!F100)),データ_財務!F100/1000000,"n.a.") -> 16273 | I16: ='3_Forecast'!I60 -> 19666.871 | J16: ='3_Forecast'!J60 -> 23845.647 | K16: ='3_Forecast'!K60 -> 27691.239

Sheet 3_CF
C2: TEXAS INSTRUMENTS INC CF
C4: USD 百万単位。年次・連結実績。n.a. = 未抽出／対象外
C5: 項目 | D5: 2021-12-31 A | E5: 2022-12-31 A | F5: 2023-12-31 A | G5: 2024-12-31 A | H5: 2025-12-31 A | I5: 2026-12-31 E | J5: 2027-12-31 E | K5: 2028-12-31 E
C6: 営業活動によるCF | D6: =IF(AND(ISNUMBER(データ_財務!F101)),データ_財務!F101/1000000,"n.a.") -> 8756 | E6: =IF(AND(ISNUMBER(データ_財務!F102)),データ_財務!F102/1000000,"n.a.") -> 8720 | F6: =IF(AND(ISNUMBER(データ_財務!F103)),データ_財務!F103/1000000,"n.a.") -> 6420 | G6: =IF(AND(ISNUMBER(データ_財務!F104)),データ_財務!F104/1000000,"n.a.") -> 6318 | H6: =IF(AND(ISNUMBER(データ_財務!F105)),データ_財務!F105/1000000,"n.a.") -> 7153 | I6: ='3_Forecast'!I37 -> 10102.427 | J6: ='3_Forecast'!J37 -> 10970.419 | K6: ='3_Forecast'!K37 -> 10488.636
C7: 減価償却・償却費 | D7: =IF(AND(ISNUMBER(データ_財務!F131)),データ_財務!F131/1000000,"n.a.") -> 954 | E7: =IF(AND(ISNUMBER(データ_財務!F132)),データ_財務!F132/1000000,"n.a.") -> 979 | F7: =IF(AND(ISNUMBER(データ_財務!F133)),データ_財務!F133/1000000,"n.a.") -> 1238 | G7: =IF(AND(ISNUMBER(データ_財務!F134)),データ_財務!F134/1000000,"n.a.") -> 1580 | H7: =IF(AND(ISNUMBER(データ_財務!F135)),データ_財務!F135/1000000,"n.a.") -> 1999 | I7: ='3_Forecast'!I32 -> 1999 | J7: ='3_Forecast'!J32 -> 2126.2489 | K7: ='3_Forecast'!K32 -> 2169.097
C8: 減価償却費（有形資産） | D8: =IF(AND(ISNUMBER(データ_財務!F156)),データ_財務!F156/1000000,"n.a.") -> 755 | E8: =IF(AND(ISNUMBER(データ_財務!F157)),データ_財務!F157/1000000,"n.a.") -> 925 | F8: =IF(AND(ISNUMBER(データ_財務!F158)),データ_財務!F158/1000000,"n.a.") -> 1175 | G8: =IF(AND(ISNUMBER(データ_財務!F159)),データ_財務!F159/1000000,"n.a.") -> 1508 | H8: =IF(AND(ISNUMBER(データ_財務!F160)),データ_財務!F160/1000000,"n.a.") -> 1918 | I8: n.a. | J8: n.a. | K8: n.a.
C9: 無形資産償却費 | D9: =IF(AND(ISNUMBER(データ_財務!F161)),データ_財務!F161/1000000,"n.a.") -> 142 | E9: =IF(AND(ISNUMBER(データ_財務!F162)),データ_財務!F162/1000000,"n.a.") -> 0 | F9: =IF(AND(ISNUMBER(データ_財務!F163)),データ_財務!F163/1000000,"n.a.") -> 0 | G9: n.a. | H9: n.a. | I9: n.a. | J9: n.a. | K9: n.a.
C10: 投資活動によるCF | D10: =IF(AND(ISNUMBER(データ_財務!F106)),データ_財務!F106/1000000,"n.a.") -> -4095 | E10: =IF(AND(ISNUMBER(データ_財務!F107)),データ_財務!F107/1000000,"n.a.") -> -3583 | F10: =IF(AND(ISNUMBER(データ_財務!F108)),データ_財務!F108/1000000,"n.a.") -> -4362 | G10: =IF(AND(ISNUMBER(データ_財務!F109)),データ_財務!F109/1000000,"n.a.") -> -3202 | H10: =IF(AND(ISNUMBER(データ_財務!F110)),データ_財務!F110/1000000,"n.a.") -> -1439 | I10: ='3_Forecast'!I38 -> -2798.3958 | J10: ='3_Forecast'!J38 -> -2395.4268 | K10: ='3_Forecast'!K38 -> -2242.1194
C11: 設備投資支出（正額） | D11: =IF(AND(ISNUMBER(データ_財務!F136)),ABS(データ_財務!F136)/1000000,"n.a.") -> 2462 | E11: =IF(AND(ISNUMBER(データ_財務!F137)),ABS(データ_財務!F137)/1000000,"n.a.") -> 2797 | F11: =IF(AND(ISNUMBER(データ_財務!F138)),ABS(データ_財務!F138)/1000000,"n.a.") -> 5071 | G11: =IF(AND(ISNUMBER(データ_財務!F139)),ABS(データ_財務!F139)/1000000,"n.a.") -> 4820 | H11: =IF(AND(ISNUMBER(データ_財務!F140)),ABS(データ_財務!F140)/1000000,"n.a.") -> 4550 | I11: =IF(AND(ISNUMBER('3_Forecast'!I31),ISNUMBER('3_Assumptions'!D19),'3_Assumptions'!D19>=0,'3_Assumptions'!D19<=1),'3_Forecast'!I31*'3_Assumptions'!D19,"n.a.") -> 2745.3604 | J11: =IF(AND(ISNUMBER('3_Forecast'!J31),ISNUMBER('3_Assumptions'!E19),'3_Assumptions'!E19>=0,'3_Assumptions'!E19<=1),'3_Forecast'!J31*'3_Assumptions'!E19,"n.a.") -> 2350.0285 | K11: =IF(AND(ISNUMBER('3_Forecast'!K31),ISNUMBER('3_Assumptions'!F19),'3_Assumptions'!F19>=0,'3_Assumptions'!F19<=1),'3_Forecast'!K31*'3_Assumptions'!F19,"n.a.") -> 2199.6267
C12: 財務活動によるCF | D12: =IF(AND(ISNUMBER(データ_財務!F111)),データ_財務!F111/1000000,"n.a.") -> -3137 | E12: =IF(AND(ISNUMBER(データ_財務!F112)),データ_財務!F112/1000000,"n.a.") -> -6718 | F12: =IF(AND(ISNUMBER(データ_財務!F113)),データ_財務!F113/1000000,"n.a.") -> -2144 | G12: =IF(AND(ISNUMBER(データ_財務!F114)),データ_財務!F114/1000000,"n.a.") -> -2880 | H12: =IF(AND(ISNUMBER(データ_財務!F115)),データ_財務!F115/1000000,"n.a.") -> -5689 | I12: ='3_Forecast'!I45 -> -4999 | J12: ='3_Forecast'!J45 -> -4999 | K12: ='3_Forecast'!K45 -> -4999
C13: 親会社配当支払額（正額） | D13: =IF(AND(ISNUMBER(データ_財務!F164)),ABS(データ_財務!F164)/1000000,"n.a.") -> 3886 | E13: =IF(AND(ISNUMBER(データ_財務!F165)),ABS(データ_財務!F165)/1000000,"n.a.") -> 4297 | F13: =IF(AND(ISNUMBER(データ_財務!F166)),ABS(データ_財務!F166)/1000000,"n.a.") -> 4557 | G13: =IF(AND(ISNUMBER(データ_財務!F167)),ABS(データ_財務!F167)/1000000,"n.a.") -> 4795 | H13: =IF(AND(ISNUMBER(データ_財務!F168)),ABS(データ_財務!F168)/1000000,"n.a.") -> 4999 | I13: ='3_Forecast'!I39 -> 4999 | J13: ='3_Forecast'!J39 -> 4999 | K13: ='3_Forecast'!K39 -> 4999
C14: 現金同等物の為替換算差額 | D14: =IF(AND(ISNUMBER(データ_財務!F116)),データ_財務!F116/1000000,"n.a.") -> 0 | E14: =IF(AND(ISNUMBER(データ_財務!F117)),データ_財務!F117/1000000,"n.a.") -> 0 | F14: =IF(AND(ISNUMBER(データ_財務!F118)),データ_財務!F118/1000000,"n.a.") -> 0 | G14: =IF(AND(ISNUMBER(データ_財務!F119)),データ_財務!F119/1000000,"n.a.") -> 0 | H14: =IF(AND(ISNUMBER(データ_財務!F120)),データ_財務!F120/1000000,"n.a.") -> 0 | I14: ='3_Forecast'!I46 -> 0 | J14: ='3_Forecast'!J46 -> 0 | K14: ='3_Forecast'!K46 -> 0
C15: 現金同等物の増減（会社発表） | D15: =IF(AND(ISNUMBER(データ_財務!F121)),データ_財務!F121/1000000,"n.a.") -> 1524 | E15: =IF(AND(ISNUMBER(データ_財務!F122)),データ_財務!F122/1000000,"n.a.") -> -1581 | F15: =IF(AND(ISNUMBER(データ_財務!F123)),データ_財務!F123/1000000,"n.a.") -> -86 | G15: =IF(AND(ISNUMBER(データ_財務!F124)),データ_財務!F124/1000000,"n.a.") -> 236 | H15: =IF(AND(ISNUMBER(データ_財務!F125)),データ_財務!F125/1000000,"n.a.") -> 25 | I15: ='3_Forecast'!I47 -> 2305.0311 | J15: ='3_Forecast'!J47 -> 3575.9924 | K15: ='3_Forecast'!K47 -> 3247.5164
C16: 現金同等物の期末残高（CF定義） | D16: =IF(AND(ISNUMBER(データ_財務!F126)),データ_財務!F126/1000000,"n.a.") -> 4631 | E16: =IF(AND(ISNUMBER(データ_財務!F127)),データ_財務!F127/1000000,"n.a.") -> 3050 | F16: =IF(AND(ISNUMBER(データ_財務!F128)),データ_財務!F128/1000000,"n.a.") -> 2964 | G16: =IF(AND(ISNUMBER(データ_財務!F129)),データ_財務!F129/1000000,"n.a.") -> 3200 | H16: =IF(AND(ISNUMBER(データ_財務!F130)),データ_財務!F130/1000000,"n.a.") -> 3225 | I16: ='3_Forecast'!I48 -> 5530.0311 | J16: ='3_Forecast'!J48 -> 9106.0235 | K16: ='3_Forecast'!K48 -> 12353.54

Sheet 3_セグメント売上
C2: TEXAS INSTRUMENTS INC セグメント売上
C4: USD 百万単位。年次・連結実績。n.a. = 未抽出／対象外
C5: 項目 | D5: 2021-12-31 A | E5: 2022-12-31 A | F5: 2023-12-31 A | G5: 2024-12-31 A | H5: 2025-12-31 A | I5: 2026-12-31 E | J5: 2027-12-31 E | K5: 2028-12-31 E
C6: Analog | D6: =IF(AND(ISNUMBER(データ_財務!F213)),データ_財務!F213/1000000,"n.a.") -> 14050 | E6: =IF(AND(ISNUMBER(データ_財務!F202)),データ_財務!F202/1000000,"n.a.") -> 15359 | F6: =IF(AND(ISNUMBER(データ_財務!F175)),データ_財務!F175/1000000,"n.a.") -> 13040 | G6: =IF(AND(ISNUMBER(データ_財務!F172)),データ_財務!F172/1000000,"n.a.") -> 12161 | H6: =IF(AND(ISNUMBER(データ_財務!F169)),データ_財務!F169/1000000,"n.a.") -> 14006 | I6: =IF(AND(ISNUMBER(H6),ISNUMBER('3_Assumptions'!D6),ISNUMBER('3_Assumptions'!D29),'3_Assumptions'!D6>=-1,1+'3_Assumptions'!D6+'3_Assumptions'!D29>=0),H6*(1+'3_Assumptions'!D6+'3_Assumptions'!D29),"n.a.") -> 18291.836 | J6: =IF(AND(ISNUMBER(I6),ISNUMBER('3_Assumptions'!E6),ISNUMBER('3_Assumptions'!E29),'3_Assumptions'!E6>=-1,1+'3_Assumptions'!E6+'3_Assumptions'!E29>=0),I6*(1+'3_Assumptions'!E6+'3_Assumptions'!E29),"n.a.") -> 19572.265 | K6: =IF(AND(ISNUMBER(J6),ISNUMBER('3_Assumptions'!F6),ISNUMBER('3_Assumptions'!F29),'3_Assumptions'!F6>=-1,1+'3_Assumptions'!F6+'3_Assumptions'!F29>=0),J6*(1+'3_Assumptions'!F6+'3_Assumptions'!F29),"n.a.") -> 20355.155
C7: Embedded Processing | D7: =IF(AND(ISNUMBER(データ_財務!F214)),データ_財務!F214/1000000,"n.a.") -> 3049 | E7: =IF(AND(ISNUMBER(データ_財務!F203)),データ_財務!F203/1000000,"n.a.") -> 3261 | F7: =IF(AND(ISNUMBER(データ_財務!F176)),データ_財務!F176/1000000,"n.a.") -> 3368 | G7: =IF(AND(ISNUMBER(データ_財務!F173)),データ_財務!F173/1000000,"n.a.") -> 2533 | H7: =IF(AND(ISNUMBER(データ_財務!F170)),データ_財務!F170/1000000,"n.a.") -> 2697 | I7: =IF(AND(ISNUMBER(H7),ISNUMBER('3_Assumptions'!D6),ISNUMBER('3_Assumptions'!D30),'3_Assumptions'!D6>=-1,1+'3_Assumptions'!D6+'3_Assumptions'!D30>=0),H7*(1+'3_Assumptions'!D6+'3_Assumptions'!D30),"n.a.") -> 3155.49 | J7: =IF(AND(ISNUMBER(I7),ISNUMBER('3_Assumptions'!E6),ISNUMBER('3_Assumptions'!E30),'3_Assumptions'!E6>=-1,1+'3_Assumptions'!E6+'3_Assumptions'!E30>=0),I7*(1+'3_Assumptions'!E6+'3_Assumptions'!E30),"n.a.") -> 3376.3743 | K7: =IF(AND(ISNUMBER(J7),ISNUMBER('3_Assumptions'!F6),ISNUMBER('3_Assumptions'!F30),'3_Assumptions'!F6>=-1,1+'3_Assumptions'!F6+'3_Assumptions'!F30>=0),J7*(1+'3_Assumptions'!F6+'3_Assumptions'!F30),"n.a.") -> 3511.4293
C8: Other | D8: =IF(AND(ISNUMBER(データ_財務!F215)),データ_財務!F215/1000000,"n.a.") -> 1245 | E8: =IF(AND(ISNUMBER(データ_財務!F204)),データ_財務!F204/1000000,"n.a.") -> 1408 | F8: =IF(AND(ISNUMBER(データ_財務!F177)),データ_財務!F177/1000000,"n.a.") -> 1111 | G8: =IF(AND(ISNUMBER(データ_財務!F174)),データ_財務!F174/1000000,"n.a.") -> 947 | H8: =IF(AND(ISNUMBER(データ_財務!F171)),データ_財務!F171/1000000,"n.a.") -> 979 | I8: =IF(AND(ISNUMBER(H8),ISNUMBER('3_Assumptions'!D6),ISNUMBER('3_Assumptions'!D31),'3_Assumptions'!D6>=-1,1+'3_Assumptions'!D6+'3_Assumptions'!D31>=0),H8*(1+'3_Assumptions'!D6+'3_Assumptions'!D31),"n.a.") -> 939.84 | J8: =IF(AND(ISNUMBER(I8),ISNUMBER('3_Assumptions'!E6),ISNUMBER('3_Assumptions'!E31),'3_Assumptions'!E6>=-1,1+'3_Assumptions'!E6+'3_Assumptions'!E31>=0),I8*(1+'3_Assumptions'!E6+'3_Assumptions'!E31),"n.a.") -> 1005.6288 | K8: =IF(AND(ISNUMBER(J8),ISNUMBER('3_Assumptions'!F6),ISNUMBER('3_Assumptions'!F31),'3_Assumptions'!F6>=-1,1+'3_Assumptions'!F6+'3_Assumptions'!F31>=0),J8*(1+'3_Assumptions'!F6+'3_Assumptions'!F31),"n.a.") -> 1045.854
C9: Total revenue | D9: =IF(AND(ISNUMBER(データ_財務!F216)),データ_財務!F216/1000000,"n.a.") -> 18344 | E9: =IF(AND(ISNUMBER(データ_財務!F205)),データ_財務!F205/1000000,"n.a.") -> 20028 | F9: =IF(AND(ISNUMBER(データ_財務!F180)),データ_財務!F180/1000000,"n.a.") -> 17519 | G9: =IF(AND(ISNUMBER(データ_財務!F178)),データ_財務!F178/1000000,"n.a.") -> 15641 | H9: =IF(AND(ISNUMBER(データ_財務!F179)),データ_財務!F179/1000000,"n.a.") -> 17682 | I9: =IF(AND(ISNUMBER('3_セグメント売上'!I6),ISNUMBER('3_セグメント売上'!I7),ISNUMBER('3_セグメント売上'!I8)),'3_セグメント売上'!I6+'3_セグメント売上'!I7+'3_セグメント売上'!I8,"n.a.") -> 22387.166 | J9: =IF(AND(ISNUMBER('3_セグメント売上'!J6),ISNUMBER('3_セグメント売上'!J7),ISNUMBER('3_セグメント売上'!J8)),'3_セグメント売上'!J6+'3_セグメント売上'!J7+'3_セグメント売上'!J8,"n.a.") -> 23954.268 | K9: =IF(AND(ISNUMBER('3_セグメント売上'!K6),ISNUMBER('3_セグメント売上'!K7),ISNUMBER('3_セグメント売上'!K8)),'3_セグメント売上'!K6+'3_セグメント売上'!K7+'3_セグメント売上'!K8,"n.a.") -> 24912.438
C11: 内数を除いた抽出売上合計 | D11: =IF(AND(ISNUMBER(D6),ISNUMBER(D7),ISNUMBER(D8)),D6+D7+D8,"n.a.") -> 18344 | E11: =IF(AND(ISNUMBER(E6),ISNUMBER(E7),ISNUMBER(E8)),E6+E7+E8,"n.a.") -> 20028 | F11: =IF(AND(ISNUMBER(F6),ISNUMBER(F7),ISNUMBER(F8)),F6+F7+F8,"n.a.") -> 17519 | G11: =IF(AND(ISNUMBER(G6),ISNUMBER(G7),ISNUMBER(G8)),G6+G7+G8,"n.a.") -> 15641 | H11: =IF(AND(ISNUMBER(H6),ISNUMBER(H7),ISNUMBER(H8)),H6+H7+H8,"n.a.") -> 17682 | I11: =IF(AND(ISNUMBER('3_セグメント売上'!I6),ISNUMBER('3_セグメント売上'!I7),ISNUMBER('3_セグメント売上'!I8)),'3_セグメント売上'!I6+'3_セグメント売上'!I7+'3_セグメント売上'!I8,"n.a.") -> 22387.166 | J11: =IF(AND(ISNUMBER('3_セグメント売上'!J6),ISNUMBER('3_セグメント売上'!J7),ISNUMBER('3_セグメント売上'!J8)),'3_セグメント売上'!J6+'3_セグメント売上'!J7+'3_セグメント売上'!J8,"n.a.") -> 23954.268 | K11: =IF(AND(ISNUMBER('3_セグメント売上'!K6),ISNUMBER('3_セグメント売上'!K7),ISNUMBER('3_セグメント売上'!K8)),'3_セグメント売上'!K6+'3_セグメント売上'!K7+'3_セグメント売上'!K8,"n.a.") -> 24912.438
C14: 報告セグメントAnalog・Embedded Processing＋Other（報告セグメント外の事業）。10-K表示名

Sheet 3_地域別売上
C2: TEXAS INSTRUMENTS INC 地域別売上
C4: USD 百万単位。年次・連結実績。n.a. = 未抽出／対象外
C5: 項目 | D5: 2021-12-31 A | E5: 2022-12-31 A | F5: 2023-12-31 A | G5: 2024-12-31 A | H5: 2025-12-31 A | I5: 2026-12-31 E | J5: 2027-12-31 E | K5: 2028-12-31 E
C6: United States | D6: =IF(AND(ISNUMBER(データ_財務!F217)),データ_財務!F217/1000000,"n.a.") -> 6237 | E6: =IF(AND(ISNUMBER(データ_財務!F206)),データ_財務!F206/1000000,"n.a.") -> 6609 | F6: =IF(AND(ISNUMBER(データ_財務!F183)),データ_財務!F183/1000000,"n.a.") -> 5814 | G6: =IF(AND(ISNUMBER(データ_財務!F182)),データ_財務!F182/1000000,"n.a.") -> 5957 | H6: =IF(AND(ISNUMBER(データ_財務!F181)),データ_財務!F181/1000000,"n.a.") -> 6763 | I6: =IF(AND(ISNUMBER('3_Forecast'!I8),ISNUMBER('3_Assumptions'!D33),ISNUMBER('3_Assumptions'!D34),ISNUMBER('3_Assumptions'!D35),ISNUMBER('3_Assumptions'!D36),ISNUMBER('3_Assumptions'!D37),ISNUMBER('3_Assumptions'!D38),'3_Assumptions'!D33>=0,'3_Assumptions'!D34>=0,'3_Assumptions'!D35>=0,'3_Assumptions'!D36>=0,'3_Assumptions'!D37>=0,'3_Assumptions'!D38>=0,('3_Assumptions'!D33+'3_Assumptions'!D34+'3_Assumptions'!D35+'3_Assumptions'!D36+'3_Assumptions'!D37+'3_Assumptions'!D38)>0),'3_Forecast'!I8*'3_Assumptions'!D33/('3_Assumptions'!D33+'3_Assumptions'!D34+'3_Assumptions'!D35+'3_Assumptions'!D36+'3_Assumptions'!D37+'3_Assumptions'!D38),"n.a.") -> 8562.6289 | J6: =IF(AND(ISNUMBER('3_Forecast'!J8),ISNUMBER('3_Assumptions'!E33),ISNUMBER('3_Assumptions'!E34),ISNUMBER('3_Assumptions'!E35),ISNUMBER('3_Assumptions'!E36),ISNUMBER('3_Assumptions'!E37),ISNUMBER('3_Assumptions'!E38),'3_Assumptions'!E33>=0,'3_Assumptions'!E34>=0,'3_Assumptions'!E35>=0,'3_Assumptions'!E36>=0,'3_Assumptions'!E37>=0,'3_Assumptions'!E38>=0,('3_Assumptions'!E33+'3_Assumptions'!E34+'3_Assumptions'!E35+'3_Assumptions'!E36+'3_Assumptions'!E37+'3_Assumptions'!E38)>0),'3_Forecast'!J8*'3_Assumptions'!E33/('3_Assumptions'!E33+'3_Assumptions'!E34+'3_Assumptions'!E35+'3_Assumptions'!E36+'3_Assumptions'!E37+'3_Assumptions'!E38),"n.a.") -> 9162.0129 | K6: =IF(AND(ISNUMBER('3_Forecast'!K8),ISNUMBER('3_Assumptions'!F33),ISNUMBER('3_Assumptions'!F34),ISNUMBER('3_Assumptions'!F35),ISNUMBER('3_Assumptions'!F36),ISNUMBER('3_Assumptions'!F37),ISNUMBER('3_Assumptions'!F38),'3_Assumptions'!F33>=0,'3_Assumptions'!F34>=0,'3_Assumptions'!F35>=0,'3_Assumptions'!F36>=0,'3_Assumptions'!F37>=0,'3_Assumptions'!F38>=0,('3_Assumptions'!F33+'3_Assumptions'!F34+'3_Assumptions'!F35+'3_Assumptions'!F36+'3_Assumptions'!F37+'3_Assumptions'!F38)>0),'3_Forecast'!K8*'3_Assumptions'!F33/('3_Assumptions'!F33+'3_Assumptions'!F34+'3_Assumptions'!F35+'3_Assumptions'!F36+'3_Assumptions'!F37+'3_Assumptions'!F38),"n.a.") -> 9528.4934
C7: China | D7: =IF(AND(ISNUMBER(データ_財務!F218)),データ_財務!F218/1000000,"n.a.") -> 4586 | E7: =IF(AND(ISNUMBER(データ_財務!F207)),データ_財務!F207/1000000,"n.a.") -> 4807 | F7: =IF(AND(ISNUMBER(データ_財務!F186)),データ_財務!F186/1000000,"n.a.") -> 3293 | G7: =IF(AND(ISNUMBER(データ_財務!F185)),データ_財務!F185/1000000,"n.a.") -> 3012 | H7: =IF(AND(ISNUMBER(データ_財務!F184)),データ_財務!F184/1000000,"n.a.") -> 3781 | I7: =IF(AND(ISNUMBER('3_Forecast'!I8),ISNUMBER('3_Assumptions'!D33),ISNUMBER('3_Assumptions'!D34),ISNUMBER('3_Assumptions'!D35),ISNUMBER('3_Assumptions'!D36),ISNUMBER('3_Assumptions'!D37),ISNUMBER('3_Assumptions'!D38),'3_Assumptions'!D33>=0,'3_Assumptions'!D34>=0,'3_Assumptions'!D35>=0,'3_Assumptions'!D36>=0,'3_Assumptions'!D37>=0,'3_Assumptions'!D38>=0,('3_Assumptions'!D33+'3_Assumptions'!D34+'3_Assumptions'!D35+'3_Assumptions'!D36+'3_Assumptions'!D37+'3_Assumptions'!D38)>0),'3_Forecast'!I8*'3_Assumptions'!D34/('3_Assumptions'!D33+'3_Assumptions'!D34+'3_Assumptions'!D35+'3_Assumptions'!D36+'3_Assumptions'!D37+'3_Assumptions'!D38),"n.a.") -> 4787.1211 | J7: =IF(AND(ISNUMBER('3_Forecast'!J8),ISNUMBER('3_Assumptions'!E33),ISNUMBER('3_Assumptions'!E34),ISNUMBER('3_Assumptions'!E35),ISNUMBER('3_Assumptions'!E36),ISNUMBER('3_Assumptions'!E37),ISNUMBER('3_Assumptions'!E38),'3_Assumptions'!E33>=0,'3_Assumptions'!E34>=0,'3_Assumptions'!E35>=0,'3_Assumptions'!E36>=0,'3_Assumptions'!E37>=0,'3_Assumptions'!E38>=0,('3_Assumptions'!E33+'3_Assumptions'!E34+'3_Assumptions'!E35+'3_Assumptions'!E36+'3_Assumptions'!E37+'3_Assumptions'!E38)>0),'3_Forecast'!J8*'3_Assumptions'!E34/('3_Assumptions'!E33+'3_Assumptions'!E34+'3_Assumptions'!E35+'3_Assumptions'!E36+'3_Assumptions'!E37+'3_Assumptions'!E38),"n.a.") -> 5122.2195 | K7: =IF(AND(ISNUMBER('3_Forecast'!K8),ISNUMBER('3_Assumptions'!F33),ISNUMBER('3_Assumptions'!F34),ISNUMBER('3_Assumptions'!F35),ISNUMBER('3_Assumptions'!F36),ISNUMBER('3_Assumptions'!F37),ISNUMBER('3_Assumptions'!F38),'3_Assumptions'!F33>=0,'3_Assumptions'!F34>=0,'3_Assumptions'!F35>=0,'3_Assumptions'!F36>=0,'3_Assumptions'!F37>=0,'3_Assumptions'!F38>=0,('3_Assumptions'!F33+'3_Assumptions'!F34+'3_Assumptions'!F35+'3_Assumptions'!F36+'3_Assumptions'!F37+'3_Assumptions'!F38)>0),'3_Forecast'!K8*'3_Assumptions'!F34/('3_Assumptions'!F33+'3_Assumptions'!F34+'3_Assumptions'!F35+'3_Assumptions'!F36+'3_Assumptions'!F37+'3_Assumptions'!F38),"n.a.") -> 5327.1083
C8: Rest of Asia | D8: =IF(AND(ISNUMBER(データ_財務!F219)),データ_財務!F219/1000000,"n.a.") -> 2018 | E8: =IF(AND(ISNUMBER(データ_財務!F208)),データ_財務!F208/1000000,"n.a.") -> 2003 | F8: =IF(AND(ISNUMBER(データ_財務!F189)),データ_財務!F189/1000000,"n.a.") -> 1721 | G8: =IF(AND(ISNUMBER(データ_財務!F188)),データ_財務!F188/1000000,"n.a.") -> 1681 | H8: =IF(AND(ISNUMBER(データ_財務!F187)),データ_財務!F187/1000000,"n.a.") -> 1887 | I8: =IF(AND(ISNUMBER('3_Forecast'!I8),ISNUMBER('3_Assumptions'!D33),ISNUMBER('3_Assumptions'!D34),ISNUMBER('3_Assumptions'!D35),ISNUMBER('3_Assumptions'!D36),ISNUMBER('3_Assumptions'!D37),ISNUMBER('3_Assumptions'!D38),'3_Assumptions'!D33>=0,'3_Assumptions'!D34>=0,'3_Assumptions'!D35>=0,'3_Assumptions'!D36>=0,'3_Assumptions'!D37>=0,'3_Assumptions'!D38>=0,('3_Assumptions'!D33+'3_Assumptions'!D34+'3_Assumptions'!D35+'3_Assumptions'!D36+'3_Assumptions'!D37+'3_Assumptions'!D38)>0),'3_Forecast'!I8*'3_Assumptions'!D35/('3_Assumptions'!D33+'3_Assumptions'!D34+'3_Assumptions'!D35+'3_Assumptions'!D36+'3_Assumptions'!D37+'3_Assumptions'!D38),"n.a.") -> 2389.1292 | J8: =IF(AND(ISNUMBER('3_Forecast'!J8),ISNUMBER('3_Assumptions'!E33),ISNUMBER('3_Assumptions'!E34),ISNUMBER('3_Assumptions'!E35),ISNUMBER('3_Assumptions'!E36),ISNUMBER('3_Assumptions'!E37),ISNUMBER('3_Assumptions'!E38),'3_Assumptions'!E33>=0,'3_Assumptions'!E34>=0,'3_Assumptions'!E35>=0,'3_Assumptions'!E36>=0,'3_Assumptions'!E37>=0,'3_Assumptions'!E38>=0,('3_Assumptions'!E33+'3_Assumptions'!E34+'3_Assumptions'!E35+'3_Assumptions'!E36+'3_Assumptions'!E37+'3_Assumptions'!E38)>0),'3_Forecast'!J8*'3_Assumptions'!E35/('3_Assumptions'!E33+'3_Assumptions'!E34+'3_Assumptions'!E35+'3_Assumptions'!E36+'3_Assumptions'!E37+'3_Assumptions'!E38),"n.a.") -> 2556.3682 | K8: =IF(AND(ISNUMBER('3_Forecast'!K8),ISNUMBER('3_Assumptions'!F33),ISNUMBER('3_Assumptions'!F34),ISNUMBER('3_Assumptions'!F35),ISNUMBER('3_Assumptions'!F36),ISNUMBER('3_Assumptions'!F37),ISNUMBER('3_Assumptions'!F38),'3_Assumptions'!F33>=0,'3_Assumptions'!F34>=0,'3_Assumptions'!F35>=0,'3_Assumptions'!F36>=0,'3_Assumptions'!F37>=0,'3_Assumptions'!F38>=0,('3_Assumptions'!F33+'3_Assumptions'!F34+'3_Assumptions'!F35+'3_Assumptions'!F36+'3_Assumptions'!F37+'3_Assumptions'!F38)>0),'3_Forecast'!K8*'3_Assumptions'!F35/('3_Assumptions'!F33+'3_Assumptions'!F34+'3_Assumptions'!F35+'3_Assumptions'!F36+'3_Assumptions'!F37+'3_Assumptions'!F38),"n.a.") -> 2658.623
C9: Europe, Middle East and Africa | D9: =IF(AND(ISNUMBER(データ_財務!F220)),データ_財務!F220/1000000,"n.a.") -> 3852 | E9: =IF(AND(ISNUMBER(データ_財務!F209)),データ_財務!F209/1000000,"n.a.") -> 4807 | F9: =IF(AND(ISNUMBER(データ_財務!F192)),データ_財務!F192/1000000,"n.a.") -> 4642 | G9: =IF(AND(ISNUMBER(データ_財務!F191)),データ_財務!F191/1000000,"n.a.") -> 3519 | H9: =IF(AND(ISNUMBER(データ_財務!F190)),データ_財務!F190/1000000,"n.a.") -> 3747 | I9: =IF(AND(ISNUMBER('3_Forecast'!I8),ISNUMBER('3_Assumptions'!D33),ISNUMBER('3_Assumptions'!D34),ISNUMBER('3_Assumptions'!D35),ISNUMBER('3_Assumptions'!D36),ISNUMBER('3_Assumptions'!D37),ISNUMBER('3_Assumptions'!D38),'3_Assumptions'!D33>=0,'3_Assumptions'!D34>=0,'3_Assumptions'!D35>=0,'3_Assumptions'!D36>=0,'3_Assumptions'!D37>=0,'3_Assumptions'!D38>=0,('3_Assumptions'!D33+'3_Assumptions'!D34+'3_Assumptions'!D35+'3_Assumptions'!D36+'3_Assumptions'!D37+'3_Assumptions'!D38)>0),'3_Forecast'!I8*'3_Assumptions'!D36/('3_Assumptions'!D33+'3_Assumptions'!D34+'3_Assumptions'!D35+'3_Assumptions'!D36+'3_Assumptions'!D37+'3_Assumptions'!D38),"n.a.") -> 4744.0737 | J9: =IF(AND(ISNUMBER('3_Forecast'!J8),ISNUMBER('3_Assumptions'!E33),ISNUMBER('3_Assumptions'!E34),ISNUMBER('3_Assumptions'!E35),ISNUMBER('3_Assumptions'!E36),ISNUMBER('3_Assumptions'!E37),ISNUMBER('3_Assumptions'!E38),'3_Assumptions'!E33>=0,'3_Assumptions'!E34>=0,'3_Assumptions'!E35>=0,'3_Assumptions'!E36>=0,'3_Assumptions'!E37>=0,'3_Assumptions'!E38>=0,('3_Assumptions'!E33+'3_Assumptions'!E34+'3_Assumptions'!E35+'3_Assumptions'!E36+'3_Assumptions'!E37+'3_Assumptions'!E38)>0),'3_Forecast'!J8*'3_Assumptions'!E36/('3_Assumptions'!E33+'3_Assumptions'!E34+'3_Assumptions'!E35+'3_Assumptions'!E36+'3_Assumptions'!E37+'3_Assumptions'!E38),"n.a.") -> 5076.1588 | K9: =IF(AND(ISNUMBER('3_Forecast'!K8),ISNUMBER('3_Assumptions'!F33),ISNUMBER('3_Assumptions'!F34),ISNUMBER('3_Assumptions'!F35),ISNUMBER('3_Assumptions'!F36),ISNUMBER('3_Assumptions'!F37),ISNUMBER('3_Assumptions'!F38),'3_Assumptions'!F33>=0,'3_Assumptions'!F34>=0,'3_Assumptions'!F35>=0,'3_Assumptions'!F36>=0,'3_Assumptions'!F37>=0,'3_Assumptions'!F38>=0,('3_Assumptions'!F33+'3_Assumptions'!F34+'3_Assumptions'!F35+'3_Assumptions'!F36+'3_Assumptions'!F37+'3_Assumptions'!F38)>0),'3_Forecast'!K8*'3_Assumptions'!F36/('3_Assumptions'!F33+'3_Assumptions'!F34+'3_Assumptions'!F35+'3_Assumptions'!F36+'3_Assumptions'!F37+'3_Assumptions'!F38),"n.a.") -> 5279.2052
C10: Japan | D10: =IF(AND(ISNUMBER(データ_財務!F221)),データ_財務!F221/1000000,"n.a.") -> 1468 | E10: =IF(AND(ISNUMBER(データ_財務!F210)),データ_財務!F210/1000000,"n.a.") -> 1602 | F10: =IF(AND(ISNUMBER(データ_財務!F195)),データ_財務!F195/1000000,"n.a.") -> 1782 | G10: =IF(AND(ISNUMBER(データ_財務!F194)),データ_財務!F194/1000000,"n.a.") -> 1212 | H10: =IF(AND(ISNUMBER(データ_財務!F193)),データ_財務!F193/1000000,"n.a.") -> 1173 | I10: =IF(AND(ISNUMBER('3_Forecast'!I8),ISNUMBER('3_Assumptions'!D33),ISNUMBER('3_Assumptions'!D34),ISNUMBER('3_Assumptions'!D35),ISNUMBER('3_Assumptions'!D36),ISNUMBER('3_Assumptions'!D37),ISNUMBER('3_Assumptions'!D38),'3_Assumptions'!D33>=0,'3_Assumptions'!D34>=0,'3_Assumptions'!D35>=0,'3_Assumptions'!D36>=0,'3_Assumptions'!D37>=0,'3_Assumptions'!D38>=0,('3_Assumptions'!D33+'3_Assumptions'!D34+'3_Assumptions'!D35+'3_Assumptions'!D36+'3_Assumptions'!D37+'3_Assumptions'!D38)>0),'3_Forecast'!I8*'3_Assumptions'!D37/('3_Assumptions'!D33+'3_Assumptions'!D34+'3_Assumptions'!D35+'3_Assumptions'!D36+'3_Assumptions'!D37+'3_Assumptions'!D38),"n.a.") -> 1485.1344 | J10: =IF(AND(ISNUMBER('3_Forecast'!J8),ISNUMBER('3_Assumptions'!E33),ISNUMBER('3_Assumptions'!E34),ISNUMBER('3_Assumptions'!E35),ISNUMBER('3_Assumptions'!E36),ISNUMBER('3_Assumptions'!E37),ISNUMBER('3_Assumptions'!E38),'3_Assumptions'!E33>=0,'3_Assumptions'!E34>=0,'3_Assumptions'!E35>=0,'3_Assumptions'!E36>=0,'3_Assumptions'!E37>=0,'3_Assumptions'!E38>=0,('3_Assumptions'!E33+'3_Assumptions'!E34+'3_Assumptions'!E35+'3_Assumptions'!E36+'3_Assumptions'!E37+'3_Assumptions'!E38)>0),'3_Forecast'!J8*'3_Assumptions'!E37/('3_Assumptions'!E33+'3_Assumptions'!E34+'3_Assumptions'!E35+'3_Assumptions'!E36+'3_Assumptions'!E37+'3_Assumptions'!E38),"n.a.") -> 1589.0938 | K10: =IF(AND(ISNUMBER('3_Forecast'!K8),ISNUMBER('3_Assumptions'!F33),ISNUMBER('3_Assumptions'!F34),ISNUMBER('3_Assumptions'!F35),ISNUMBER('3_Assumptions'!F36),ISNUMBER('3_Assumptions'!F37),ISNUMBER('3_Assumptions'!F38),'3_Assumptions'!F33>=0,'3_Assumptions'!F34>=0,'3_Assumptions'!F35>=0,'3_Assumptions'!F36>=0,'3_Assumptions'!F37>=0,'3_Assumptions'!F38>=0,('3_Assumptions'!F33+'3_Assumptions'!F34+'3_Assumptions'!F35+'3_Assumptions'!F36+'3_Assumptions'!F37+'3_Assumptions'!F38)>0),'3_Forecast'!K8*'3_Assumptions'!F37/('3_Assumptions'!F33+'3_Assumptions'!F34+'3_Assumptions'!F35+'3_Assumptions'!F36+'3_Assumptions'!F37+'3_Assumptions'!F38),"n.a.") -> 1652.6575
C11: Rest of world | D11: =IF(AND(ISNUMBER(データ_財務!F222)),データ_財務!F222/1000000,"n.a.") -> 183 | E11: =IF(AND(ISNUMBER(データ_財務!F211)),データ_財務!F211/1000000,"n.a.") -> 200 | F11: =IF(AND(ISNUMBER(データ_財務!F198)),データ_財務!F198/1000000,"n.a.") -> 267 | G11: =IF(AND(ISNUMBER(データ_財務!F197)),データ_財務!F197/1000000,"n.a.") -> 260 | H11: =IF(AND(ISNUMBER(データ_財務!F196)),データ_財務!F196/1000000,"n.a.") -> 331 | I11: =IF(AND(ISNUMBER('3_Forecast'!I8),ISNUMBER('3_Assumptions'!D33),ISNUMBER('3_Assumptions'!D34),ISNUMBER('3_Assumptions'!D35),ISNUMBER('3_Assumptions'!D36),ISNUMBER('3_Assumptions'!D37),ISNUMBER('3_Assumptions'!D38),'3_Assumptions'!D33>=0,'3_Assumptions'!D34>=0,'3_Assumptions'!D35>=0,'3_Assumptions'!D36>=0,'3_Assumptions'!D37>=0,'3_Assumptions'!D38>=0,('3_Assumptions'!D33+'3_Assumptions'!D34+'3_Assumptions'!D35+'3_Assumptions'!D36+'3_Assumptions'!D37+'3_Assumptions'!D38)>0),'3_Forecast'!I8*'3_Assumptions'!D38/('3_Assumptions'!D33+'3_Assumptions'!D34+'3_Assumptions'!D35+'3_Assumptions'!D36+'3_Assumptions'!D37+'3_Assumptions'!D38),"n.a.") -> 419.07883 | J11: =IF(AND(ISNUMBER('3_Forecast'!J8),ISNUMBER('3_Assumptions'!E33),ISNUMBER('3_Assumptions'!E34),ISNUMBER('3_Assumptions'!E35),ISNUMBER('3_Assumptions'!E36),ISNUMBER('3_Assumptions'!E37),ISNUMBER('3_Assumptions'!E38),'3_Assumptions'!E33>=0,'3_Assumptions'!E34>=0,'3_Assumptions'!E35>=0,'3_Assumptions'!E36>=0,'3_Assumptions'!E37>=0,'3_Assumptions'!E38>=0,('3_Assumptions'!E33+'3_Assumptions'!E34+'3_Assumptions'!E35+'3_Assumptions'!E36+'3_Assumptions'!E37+'3_Assumptions'!E38)>0),'3_Forecast'!J8*'3_Assumptions'!E38/('3_Assumptions'!E33+'3_Assumptions'!E34+'3_Assumptions'!E35+'3_Assumptions'!E36+'3_Assumptions'!E37+'3_Assumptions'!E38),"n.a.") -> 448.41435 | K11: =IF(AND(ISNUMBER('3_Forecast'!K8),ISNUMBER('3_Assumptions'!F33),ISNUMBER('3_Assumptions'!F34),ISNUMBER('3_Assumptions'!F35),ISNUMBER('3_Assumptions'!F36),ISNUMBER('3_Assumptions'!F37),ISNUMBER('3_Assumptions'!F38),'3_Assumptions'!F33>=0,'3_Assumptions'!F34>=0,'3_Assumptions'!F35>=0,'3_Assumptions'!F36>=0,'3_Assumptions'!F37>=0,'3_Assumptions'!F38>=0,('3_Assumptions'!F33+'3_Assumptions'!F34+'3_Assumptions'!F35+'3_Assumptions'!F36+'3_Assumptions'!F37+'3_Assumptions'!F38)>0),'3_Forecast'!K8*'3_Assumptions'!F38/('3_Assumptions'!F33+'3_Assumptions'!F34+'3_Assumptions'!F35+'3_Assumptions'!F36+'3_Assumptions'!F37+'3_Assumptions'!F38),"n.a.") -> 466.35093
C12: Total revenue | D12: =IF(AND(ISNUMBER(データ_財務!F223)),データ_財務!F223/1000000,"n.a.") -> 18344 | E12: =IF(AND(ISNUMBER(データ_財務!F212)),データ_財務!F212/1000000,"n.a.") -> 20028 | F12: =IF(AND(ISNUMBER(データ_財務!F201)),データ_財務!F201/1000000,"n.a.") -> 17519 | G12: =IF(AND(ISNUMBER(データ_財務!F200)),データ_財務!F200/1000000,"n.a.") -> 15641 | H12: =IF(AND(ISNUMBER(データ_財務!F199)),データ_財務!F199/1000000,"n.a.") -> 17682 | I12: ='3_Forecast'!I8 -> 22387.166 | J12: ='3_Forecast'!J8 -> 23954.268 | K12: ='3_Forecast'!K8 -> 24912.438
C14: 内数を除いた抽出売上合計 | D14: =IF(AND(ISNUMBER(D6),ISNUMBER(D7),ISNUMBER(D8),ISNUMBER(D9),ISNUMBER(D10),ISNUMBER(D11)),D6+D7+D8+D9+D10+D11,"n.a.") -> 18344 | E14: =IF(AND(ISNUMBER(E6),ISNUMBER(E7),ISNUMBER(E8),ISNUMBER(E9),ISNUMBER(E10),ISNUMBER(E11)),E6+E7+E8+E9+E10+E11,"n.a.") -> 20028 | F14: =IF(AND(ISNUMBER(F6),ISNUMBER(F7),ISNUMBER(F8),ISNUMBER(F9),ISNUMBER(F10),ISNUMBER(F11)),F6+F7+F8+F9+F10+F11,"n.a.") -> 17519 | G14: =IF(AND(ISNUMBER(G6),ISNUMBER(G7),ISNUMBER(G8),ISNUMBER(G9),ISNUMBER(G10),ISNUMBER(G11)),G6+G7+G8+G9+G10+G11,"n.a.") -> 15641 | H14: =IF(AND(ISNUMBER(H6),ISNUMBER(H7),ISNUMBER(H8),ISNUMBER(H9),ISNUMBER(H10),ISNUMBER(H11)),H6+H7+H8+H9+H10+H11,"n.a.") -> 17682 | I14: =IF(AND(ISNUMBER(I6),ISNUMBER(I7),ISNUMBER(I8),ISNUMBER(I9),ISNUMBER(I10),ISNUMBER(I11)),I6+I7+I8+I9+I10+I11,"n.a.") -> 22387.166 | J14: =IF(AND(ISNUMBER(J6),ISNUMBER(J7),ISNUMBER(J8),ISNUMBER(J9),ISNUMBER(J10),ISNUMBER(J11)),J6+J7+J8+J9+J10+J11,"n.a.") -> 23954.268 | K14: =IF(AND(ISNUMBER(K6),ISNUMBER(K7),ISNUMBER(K8),ISNUMBER(K9),ISNUMBER(K10),ISNUMBER(K11)),K6+K7+K8+K9+K10+K11,"n.a.") -> 24912.438
C17: TI推計：エンドカスタマー本社所在地ベース（出荷先ベースとは別表・混在させない）。内数行なし（ドイツは脚注の比率のみ）

Sheet 3_Forecast
C2: TEXAS INSTRUMENTS INC Forecast
C4: USD 百万単位。年次・連結実績。n.a. = 未抽出／対象外
C5: 項目 | D5: 2021-12-31 A | E5: 2022-12-31 A | F5: 2023-12-31 A | G5: 2024-12-31 A | H5: 2025-12-31 A | I5: 2026-12-31 E | J5: 2027-12-31 E | K5: 2028-12-31 E
C6: 予測期間の日数 | I6: 365 | J6: 365 | K6: 366
C8: 売上高 | H8: ='3_PL'!H6 -> 17682 | I8: =IF(AND(ISNUMBER('3_セグメント売上'!I6),ISNUMBER('3_セグメント売上'!I7),ISNUMBER('3_セグメント売上'!I8)),'3_セグメント売上'!I6+'3_セグメント売上'!I7+'3_セグメント売上'!I8,"n.a.") -> 22387.166 | J8: =IF(AND(ISNUMBER('3_セグメント売上'!J6),ISNUMBER('3_セグメント売上'!J7),ISNUMBER('3_セグメント売上'!J8)),'3_セグメント売上'!J6+'3_セグメント売上'!J7+'3_セグメント売上'!J8,"n.a.") -> 23954.268 | K8: =IF(AND(ISNUMBER('3_セグメント売上'!K6),ISNUMBER('3_セグメント売上'!K7),ISNUMBER('3_セグメント売上'!K8)),'3_セグメント売上'!K6+'3_セグメント売上'!K7+'3_セグメント売上'!K8,"n.a.") -> 24912.438
C9: 売上原価 | H9: ='3_PL'!H7 -> 7599 | I9: =IF(AND(ISNUMBER(I8),ISNUMBER(I10)),I8-I10,"n.a.") -> 8507.1231 | J9: =IF(AND(ISNUMBER(J8),ISNUMBER(J10)),J8-J10,"n.a.") -> 8863.079 | K9: =IF(AND(ISNUMBER(K8),ISNUMBER(K10)),K8-K10,"n.a.") -> 9840.4131
C10: 売上総利益 | H10: ='3_PL'!H8 -> 10083 | I10: =IF(AND(ISNUMBER(I8),ISNUMBER('3_Assumptions'!D7),'3_Assumptions'!D7>=0,'3_Assumptions'!D7<=1),I8*'3_Assumptions'!D7,"n.a.") -> 13880.043 | J10: =IF(AND(ISNUMBER(J8),ISNUMBER('3_Assumptions'!E7),'3_Assumptions'!E7>=0,'3_Assumptions'!E7<=1),J8*'3_Assumptions'!E7,"n.a.") -> 15091.189 | K10: =IF(AND(ISNUMBER(K8),ISNUMBER('3_Assumptions'!F7),'3_Assumptions'!F7>=0,'3_Assumptions'!F7<=1),K8*'3_Assumptions'!F7,"n.a.") -> 15072.025
C11: 販売費及び一般管理費 | H11: ='3_PL'!H9 -> 1860 | I11: =IF(AND(ISNUMBER(I8),ISNUMBER('3_Assumptions'!D8),'3_Assumptions'!D8>=0),I8*'3_Assumptions'!D8,"n.a.") -> 1880.5219 | J11: =IF(AND(ISNUMBER(J8),ISNUMBER('3_Assumptions'!E8),'3_Assumptions'!E8>=0),J8*'3_Assumptions'!E8,"n.a.") -> 1964.2499 | K11: =IF(AND(ISNUMBER(K8),ISNUMBER('3_Assumptions'!F8),'3_Assumptions'!F8>=0),K8*'3_Assumptions'!F8,"n.a.") -> 2142.4697
C12: 別建て研究開発費 | I12: =IF(AND(ISNUMBER(I8),ISNUMBER('3_Assumptions'!D9),'3_Assumptions'!D9>=0),I8*'3_Assumptions'!D9,"n.a.") -> 2149.1679 | J12: =IF(AND(ISNUMBER(J8),ISNUMBER('3_Assumptions'!E9),'3_Assumptions'!E9>=0),J8*'3_Assumptions'!E9,"n.a.") -> 2203.7926 | K12: =IF(AND(ISNUMBER(K8),ISNUMBER('3_Assumptions'!F9),'3_Assumptions'!F9>=0),K8*'3_Assumptions'!F9,"n.a.") -> 2391.5941
C13: その他営業費用（収益は負） | I13: =IF(AND(ISNUMBER(I8),ISNUMBER('3_Assumptions'!D10)),I8*'3_Assumptions'!D10,"n.a.") -> 0 | J13: =IF(AND(ISNUMBER(J8),ISNUMBER('3_Assumptions'!E10)),J8*'3_Assumptions'!E10,"n.a.") -> 0 | K13: =IF(AND(ISNUMBER(K8),ISNUMBER('3_Assumptions'!F10)),K8*'3_Assumptions'!F10,"n.a.") -> 0
C14: 営業利益 | H14: ='3_PL'!H12 -> 6023 | I14: =IF(AND(ISNUMBER(I10),ISNUMBER(I11),ISNUMBER(I12),ISNUMBER(I13)),I10-I11-I12-I13,"n.a.") -> 9850.353 | J14: =IF(AND(ISNUMBER(J10),ISNUMBER(J11),ISNUMBER(J12),ISNUMBER(J13)),J10-J11-J12-J13,"n.a.") -> 10923.146 | K14: =IF(AND(ISNUMBER(K10),ISNUMBER(K11),ISNUMBER(K12),ISNUMBER(K13)),K10-K11-K12-K13,"n.a.") -> 10537.961
C15: 基礎の純営業外損益 | I15: =IF(AND(ISNUMBER('3_Assumptions'!D11)),'3_Assumptions'!D11,"n.a.") -> -313 | J15: =IF(AND(ISNUMBER('3_Assumptions'!E11)),'3_Assumptions'!E11,"n.a.") -> -313 | K15: =IF(AND(ISNUMBER('3_Assumptions'!F11)),'3_Assumptions'!F11,"n.a.") -> -313
C16: 追加借入の利息 | I16: =IF(AND(ISNUMBER(H49),ISNUMBER('3_Assumptions'!D24),'3_Assumptions'!D24>=0,'3_Assumptions'!D24<=1),H49*'3_Assumptions'!D24,"n.a.") -> 0 | J16: =IF(AND(ISNUMBER(I49),ISNUMBER('3_Assumptions'!E24),'3_Assumptions'!E24>=0,'3_Assumptions'!E24<=1),I49*'3_Assumptions'!E24,"n.a.") -> 0 | K16: =IF(AND(ISNUMBER(J49),ISNUMBER('3_Assumptions'!F24),'3_Assumptions'!F24>=0,'3_Assumptions'!F24<=1),J49*'3_Assumptions'!F24,"n.a.") -> 0
C17: 税引前利益 | H17: ='3_PL'!H13 -> 5710 | I17: =IF(AND(ISNUMBER(I14),ISNUMBER(I15),ISNUMBER(I16)),I14+I15-I16,"n.a.") -> 9537.353 | J17: =IF(AND(ISNUMBER(J14),ISNUMBER(J15),ISNUMBER(J16)),J14+J15-J16,"n.a.") -> 10610.146 | K17: =IF(AND(ISNUMBER(K14),ISNUMBER(K15),ISNUMBER(K16)),K14+K15-K16,"n.a.") -> 10224.961
C18: 法人所得税 | H18: ='3_PL'!H14 -> 709 | I18: =IF(AND(ISNUMBER(I17),ISNUMBER('3_Assumptions'!D12),'3_Assumptions'!D12>=0,'3_Assumptions'!D12<=1),MAX(0,I17)*'3_Assumptions'!D12,"n.a.") -> 1144.4824 | J18: =IF(AND(ISNUMBER(J17),ISNUMBER('3_Assumptions'!E12),'3_Assumptions'!E12>=0,'3_Assumptions'!E12<=1),MAX(0,J17)*'3_Assumptions'!E12,"n.a.") -> 1432.3697 | K18: =IF(AND(ISNUMBER(K17),ISNUMBER('3_Assumptions'!F12),'3_Assumptions'!F12>=0,'3_Assumptions'!F12<=1),MAX(0,K17)*'3_Assumptions'!F12,"n.a.") -> 1380.3698
C19: 当期利益（非支配持分含む） | H19: ='3_PL'!H15 -> 5001 | I19: =IF(AND(ISNUMBER(I17),ISNUMBER(I18)),I17-I18,"n.a.") -> 8392.8707 | J19: =IF(AND(ISNUMBER(J17),ISNUMBER(J18)),J17-J18,"n.a.") -> 9177.7763 | K19: =IF(AND(ISNUMBER(K17),ISNUMBER(K18)),K17-K18,"n.a.") -> 8844.5916
C20: 非支配持分帰属利益 | I20: =IF(AND(ISNUMBER(I19),ISNUMBER('3_Assumptions'!D13),'3_Assumptions'!D13>=0,'3_Assumptions'!D13<=1),I19*'3_Assumptions'!D13,"n.a.") -> 0 | J20: =IF(AND(ISNUMBER(J19),ISNUMBER('3_Assumptions'!E13),'3_Assumptions'!E13>=0,'3_Assumptions'!E13<=1),J19*'3_Assumptions'!E13,"n.a.") -> 0 | K20: =IF(AND(ISNUMBER(K19),ISNUMBER('3_Assumptions'!F13),'3_Assumptions'!F13>=0,'3_Assumptions'!F13<=1),K19*'3_Assumptions'!F13,"n.a.") -> 0
C21: 親会社株主帰属利益 | H21: ='3_PL'!H17 -> 5001 | I21: =IF(AND(ISNUMBER(I19),ISNUMBER(I20)),I19-I20,"n.a.") -> 8392.8707 | J21: =IF(AND(ISNUMBER(J19),ISNUMBER(J20)),J19-J20,"n.a.") -> 9177.7763 | K21: =IF(AND(ISNUMBER(K19),ISNUMBER(K20)),K19-K20,"n.a.") -> 8844.5916
C24: 売上債権 | H24: ='3_BS'!H7 -> 1963 | I24: =IF(AND(ISNUMBER(I8),ISNUMBER(I6),ISNUMBER('3_Assumptions'!D14),'3_Assumptions'!D14>=0),I8/I6*'3_Assumptions'!D14,"n.a.") -> 2485.3527 | J24: =IF(AND(ISNUMBER(J8),ISNUMBER(J6),ISNUMBER('3_Assumptions'!E14),'3_Assumptions'!E14>=0),J8/J6*'3_Assumptions'!E14,"n.a.") -> 2659.3274 | K24: =IF(AND(ISNUMBER(K8),ISNUMBER(K6),ISNUMBER('3_Assumptions'!F14),'3_Assumptions'!F14>=0),K8/K6*'3_Assumptions'!F14,"n.a.") -> 2758.144
C25: 棚卸資産 | H25: ='3_BS'!H8 -> 4804 | I25: =IF(AND(ISNUMBER(I9),ISNUMBER(I6),ISNUMBER('3_Assumptions'!D15),'3_Assumptions'!D15>=0),I9/I6*'3_Assumptions'!D15,"n.a.") -> 4661.4373 | J25: =IF(AND(ISNUMBER(J9),ISNUMBER(J6),ISNUMBER('3_Assumptions'!E15),'3_Assumptions'!E15>=0),J9/J6*'3_Assumptions'!E15,"n.a.") -> 4856.4817 | K25: =IF(AND(ISNUMBER(K9),ISNUMBER(K6),ISNUMBER('3_Assumptions'!F15),'3_Assumptions'!F15>=0),K9/K6*'3_Assumptions'!F15,"n.a.") -> 5377.2749
C26: 仕入債務 | H26: ='3_BS'!H13 -> 756 | I26: =IF(AND(ISNUMBER(I9),ISNUMBER(I6),ISNUMBER('3_Assumptions'!D16),'3_Assumptions'!D16>=0),I9/I6*'3_Assumptions'!D16,"n.a.") -> 846.34624 | J26: =IF(AND(ISNUMBER(J9),ISNUMBER(J6),ISNUMBER('3_Assumptions'!E16),'3_Assumptions'!E16>=0),J9/J6*'3_Assumptions'!E16,"n.a.") -> 881.75914 | K26: =IF(AND(ISNUMBER(K9),ISNUMBER(K6),ISNUMBER('3_Assumptions'!F16),'3_Assumptions'!F16>=0),K9/K6*'3_Assumptions'!F16,"n.a.") -> 976.31612
C27: 運転資本増加（AR＋在庫−AP） | I27: =IF(AND(ISNUMBER(I24),ISNUMBER(H24),ISNUMBER(I25),ISNUMBER(H25),ISNUMBER(I26),ISNUMBER(H26)),I24-H24+I25-H25-I26+H26,"n.a.") -> 289.44379 | J27: =IF(AND(ISNUMBER(J24),ISNUMBER(I24),ISNUMBER(J25),ISNUMBER(I25),ISNUMBER(J26),ISNUMBER(I26)),J24-I24+J25-I25-J26+I26,"n.a.") -> 333.60613 | K27: =IF(AND(ISNUMBER(K24),ISNUMBER(J24),ISNUMBER(K25),ISNUMBER(J25),ISNUMBER(K26),ISNUMBER(J26)),K24-J24+K25-J25-K26+J26,"n.a.") -> 525.05284
C30: 期首有形・無形資産 | I30: =IF(AND(ISNUMBER(H33),ISNUMBER(H34)),H33+H34,"n.a.") -> 12558 | J30: =IF(AND(ISNUMBER(I33),ISNUMBER(I34)),I33+I34,"n.a.") -> 13357.396 | K30: =IF(AND(ISNUMBER(J33),ISNUMBER(J34)),J33+J34,"n.a.") -> 13626.574
C31: 有形・無形の現金投資 | I31: =IF(AND(ISNUMBER(I8),ISNUMBER('3_Assumptions'!D17),'3_Assumptions'!D17>=0),I8*'3_Assumptions'!D17,"n.a.") -> 2798.3958 | J31: =IF(AND(ISNUMBER(J8),ISNUMBER('3_Assumptions'!E17),'3_Assumptions'!E17>=0),J8*'3_Assumptions'!E17,"n.a.") -> 2395.4268 | K31: =IF(AND(ISNUMBER(K8),ISNUMBER('3_Assumptions'!F17),'3_Assumptions'!F17>=0),K8*'3_Assumptions'!F17,"n.a.") -> 2242.1194
C32: 減価償却・償却費 | H32: ='3_CF'!H7 -> 1999 | I32: =IF(AND(ISNUMBER(I30),ISNUMBER('3_Assumptions'!D18),'3_Assumptions'!D18>=0,'3_Assumptions'!D18<=1),MIN(I30,I30*'3_Assumptions'!D18),"n.a.") -> 1999 | J32: =IF(AND(ISNUMBER(J30),ISNUMBER('3_Assumptions'!E18),'3_Assumptions'!E18>=0,'3_Assumptions'!E18<=1),MIN(J30,J30*'3_Assumptions'!E18),"n.a.") -> 2126.2489 | K32: =IF(AND(ISNUMBER(K30),ISNUMBER('3_Assumptions'!F18),'3_Assumptions'!F18>=0,'3_Assumptions'!F18<=1),MIN(K30,K30*'3_Assumptions'!F18),"n.a.") -> 2169.097
C33: 期末有形固定資産 | H33: ='3_BS'!H10 -> 12320 | I33: =IF(AND(ISNUMBER(H33),ISNUMBER(I31),ISNUMBER(I32),ISNUMBER('3_Assumptions'!D19),ISNUMBER(I30),'3_Assumptions'!D19>=0,'3_Assumptions'!D19<=1),H33+I31*'3_Assumptions'!D19-IF(I30=0,0,I32*H33/I30),"n.a.") -> 13104.246 | J33: =IF(AND(ISNUMBER(I33),ISNUMBER(J31),ISNUMBER(J32),ISNUMBER('3_Assumptions'!E19),ISNUMBER(J30),'3_Assumptions'!E19>=0,'3_Assumptions'!E19<=1),I33+J31*'3_Assumptions'!E19-IF(J30=0,0,J32*I33/J30),"n.a.") -> 13368.322 | K33: =IF(AND(ISNUMBER(J33),ISNUMBER(K31),ISNUMBER(K32),ISNUMBER('3_Assumptions'!F19),ISNUMBER(K30),'3_Assumptions'!F19>=0,'3_Assumptions'!F19<=1),J33+K31*'3_Assumptions'!F19-IF(K30=0,0,K32*J33/K30),"n.a.") -> 13439.96
C34: 期末無形資産 | H34: ='3_BS'!H11 -> 238 | I34: =IF(AND(ISNUMBER(H34),ISNUMBER(I31),ISNUMBER(I32),ISNUMBER('3_Assumptions'!D19),ISNUMBER(I30),'3_Assumptions'!D19>=0,'3_Assumptions'!D19<=1),H34+I31*(1-'3_Assumptions'!D19)-IF(I30=0,0,I32*H34/I30),"n.a.") -> 253.1502 | J34: =IF(AND(ISNUMBER(I34),ISNUMBER(J31),ISNUMBER(J32),ISNUMBER('3_Assumptions'!E19),ISNUMBER(J30),'3_Assumptions'!E19>=0,'3_Assumptions'!E19<=1),I34+J31*(1-'3_Assumptions'!E19)-IF(J30=0,0,J32*I34/J30),"n.a.") -> 258.25167 | K34: =IF(AND(ISNUMBER(J34),ISNUMBER(K31),ISNUMBER(K32),ISNUMBER('3_Assumptions'!F19),ISNUMBER(K30),'3_Assumptions'!F19>=0,'3_Assumptions'!F19<=1),J34+K31*(1-'3_Assumptions'!F19)-IF(K30=0,0,K32*J34/K30),"n.a.") -> 259.6356
C37: 営業CF | H37: ='3_CF'!H6 -> 7153 | I37: =IF(AND(ISNUMBER(I19),ISNUMBER(I32),ISNUMBER(I27)),I19+I32-I27,"n.a.") -> 10102.427 | J37: =IF(AND(ISNUMBER(J19),ISNUMBER(J32),ISNUMBER(J27)),J19+J32-J27,"n.a.") -> 10970.419 | K37: =IF(AND(ISNUMBER(K19),ISNUMBER(K32),ISNUMBER(K27)),K19+K32-K27,"n.a.") -> 10488.636
C38: 投資CF | H38: ='3_CF'!H10 -> -1439 | I38: =IF(AND(ISNUMBER(I31)),-I31,"n.a.") -> -2798.3958 | J38: =IF(AND(ISNUMBER(J31)),-J31,"n.a.") -> -2395.4268 | K38: =IF(AND(ISNUMBER(K31)),-K31,"n.a.") -> -2242.1194
C39: 親会社株主配当 | I39: =IF(AND(ISNUMBER('3_Assumptions'!D20),'3_Assumptions'!D20>=0),'3_Assumptions'!D20,"n.a.") -> 4999 | J39: =IF(AND(ISNUMBER('3_Assumptions'!E20),'3_Assumptions'!E20>=0),'3_Assumptions'!E20,"n.a.") -> 4999 | K39: =IF(AND(ISNUMBER('3_Assumptions'!F20),'3_Assumptions'!F20>=0),'3_Assumptions'!F20,"n.a.") -> 4999
C40: 非支配株主配当 | I40: =IF(AND(ISNUMBER('3_Assumptions'!D21),'3_Assumptions'!D21>=0),'3_Assumptions'!D21,"n.a.") -> 0 | J40: =IF(AND(ISNUMBER('3_Assumptions'!E21),'3_Assumptions'!E21>=0),'3_Assumptions'!E21,"n.a.") -> 0 | K40: =IF(AND(ISNUMBER('3_Assumptions'!F21),'3_Assumptions'!F21>=0),'3_Assumptions'!F21,"n.a.") -> 0
C41: 計画追加借入 | I41: =IF(AND(ISNUMBER('3_Assumptions'!D22),'3_Assumptions'!D22>=0),'3_Assumptions'!D22,"n.a.") -> 0 | J41: =IF(AND(ISNUMBER('3_Assumptions'!E22),'3_Assumptions'!E22>=0),'3_Assumptions'!E22,"n.a.") -> 0 | K41: =IF(AND(ISNUMBER('3_Assumptions'!F22),'3_Assumptions'!F22>=0),'3_Assumptions'!F22,"n.a.") -> 0
C42: 新株発行 | I42: =IF(AND(ISNUMBER('3_Assumptions'!D23),'3_Assumptions'!D23>=0),'3_Assumptions'!D23,"n.a.") -> 0 | J42: =IF(AND(ISNUMBER('3_Assumptions'!E23),'3_Assumptions'!E23>=0),'3_Assumptions'!E23,"n.a.") -> 0 | K42: =IF(AND(ISNUMBER('3_Assumptions'!F23),'3_Assumptions'!F23>=0),'3_Assumptions'!F23,"n.a.") -> 0
C43: 追加資金調達前の期末現金 | I43: =IF(AND(ISNUMBER(H48),ISNUMBER(I37),ISNUMBER(I38),ISNUMBER(I39),ISNUMBER(I40),ISNUMBER(I41),ISNUMBER(I42)),H48+I37+I38-I39-I40+I41+I42,"n.a.") -> 5530.0311 | J43: =IF(AND(ISNUMBER(I48),ISNUMBER(J37),ISNUMBER(J38),ISNUMBER(J39),ISNUMBER(J40),ISNUMBER(J41),ISNUMBER(J42)),I48+J37+J38-J39-J40+J41+J42,"n.a.") -> 9106.0235 | K43: =IF(AND(ISNUMBER(J48),ISNUMBER(K37),ISNUMBER(K38),ISNUMBER(K39),ISNUMBER(K40),ISNUMBER(K41),ISNUMBER(K42)),J48+K37+K38-K39-K40+K41+K42,"n.a.") -> 12353.54
C44: 最低現金方針による追加借入 | I44: =IF(AND(ISNUMBER('3_Assumptions'!D26),ISNUMBER('3_Assumptions'!D25),ISNUMBER(I43),OR('3_Assumptions'!D26=0,'3_Assumptions'!D26=1),'3_Assumptions'!D25>=0),IF('3_Assumptions'!D26=1,MAX(0,'3_Assumptions'!D25-I43),0),"n.a.") -> 0 | J44: =IF(AND(ISNUMBER('3_Assumptions'!E26),ISNUMBER('3_Assumptions'!E25),ISNUMBER(J43),OR('3_Assumptions'!E26=0,'3_Assumptions'!E26=1),'3_Assumptions'!E25>=0),IF('3_Assumptions'!E26=1,MAX(0,'3_Assumptions'!E25-J43),0),"n.a.") -> 0 | K44: =IF(AND(ISNUMBER('3_Assumptions'!F26),ISNUMBER('3_Assumptions'!F25),ISNUMBER(K43),OR('3_Assumptions'!F26=0,'3_Assumptions'!F26=1),'3_Assumptions'!F25>=0),IF('3_Assumptions'!F26=1,MAX(0,'3_Assumptions'!F25-K43),0),"n.a.") -> 0
C45: 財務CF | H45: ='3_CF'!H12 -> -5689 | I45: =IF(AND(ISNUMBER(I39),ISNUMBER(I40),ISNUMBER(I41),ISNUMBER(I44),ISNUMBER(I42)),-I39-I40+I41+I44+I42,"n.a.") -> -4999 | J45: =IF(AND(ISNUMBER(J39),ISNUMBER(J40),ISNUMBER(J41),ISNUMBER(J44),ISNUMBER(J42)),-J39-J40+J41+J44+J42,"n.a.") -> -4999 | K45: =IF(AND(ISNUMBER(K39),ISNUMBER(K40),ISNUMBER(K41),ISNUMBER(K44),ISNUMBER(K42)),-K39-K40+K41+K44+K42,"n.a.") -> -4999
C46: 為替効果（予測仮定0） | H46: ='3_CF'!H14 -> 0 | I46: 0 | J46: 0 | K46: 0
C47: 現金増減 | H47: ='3_CF'!H15 -> 25 | I47: =IF(AND(ISNUMBER(I37),ISNUMBER(I38),ISNUMBER(I45)),I37+I38+I45,"n.a.") -> 2305.0311 | J47: =IF(AND(ISNUMBER(J37),ISNUMBER(J38),ISNUMBER(J45)),J37+J38+J45,"n.a.") -> 3575.9924 | K47: =IF(AND(ISNUMBER(K37),ISNUMBER(K38),ISNUMBER(K45)),K37+K38+K45,"n.a.") -> 3247.5164
C48: CF期末現金 | H48: ='3_CF'!H16 -> 3225 | I48: =IF(AND(ISNUMBER(H48),ISNUMBER(I47)),H48+I47,"n.a.") -> 5530.0311 | J48: =IF(AND(ISNUMBER(I48),ISNUMBER(J47)),I48+J47,"n.a.") -> 9106.0235 | K48: =IF(AND(ISNUMBER(J48),ISNUMBER(K47)),J48+K47,"n.a.") -> 12353.54
C49: 予測開始後の累積追加借入 | H49: 0 | I49: =IF(AND(ISNUMBER(H49),ISNUMBER(I41),ISNUMBER(I44)),H49+I41+I44,"n.a.") -> 0 | J49: =IF(AND(ISNUMBER(I49),ISNUMBER(J41),ISNUMBER(J44)),I49+J41+J44,"n.a.") -> 0 | K49: =IF(AND(ISNUMBER(J49),ISNUMBER(K41),ISNUMBER(K44)),J49+K41+K44,"n.a.") -> 0
C52: BS現預金（CF定義との差額固定） | H52: ='3_BS'!H6 -> 3225 | I52: =IF(AND(ISNUMBER(I48),ISNUMBER('3_BS'!H6),ISNUMBER('3_CF'!H16)),I48+'3_BS'!H6-'3_CF'!H16,"n.a.") -> 5530.0311 | J52: =IF(AND(ISNUMBER(J48),ISNUMBER('3_BS'!H6),ISNUMBER('3_CF'!H16)),J48+'3_BS'!H6-'3_CF'!H16,"n.a.") -> 9106.0235 | K52: =IF(AND(ISNUMBER(K48),ISNUMBER('3_BS'!H6),ISNUMBER('3_CF'!H16)),K48+'3_BS'!H6-'3_CF'!H16,"n.a.") -> 12353.54
C53: その他流動資産（固定） | I53: =IF(AND(ISNUMBER('3_BS'!H9),ISNUMBER('3_BS'!H6),ISNUMBER('3_BS'!H7),ISNUMBER('3_BS'!H8)),'3_BS'!H9-'3_BS'!H6-'3_BS'!H7-'3_BS'!H8,"n.a.") -> 3758 | J53: =IF(AND(ISNUMBER('3_BS'!H9),ISNUMBER('3_BS'!H6),ISNUMBER('3_BS'!H7),ISNUMBER('3_BS'!H8)),'3_BS'!H9-'3_BS'!H6-'3_BS'!H7-'3_BS'!H8,"n.a.") -> 3758 | K53: =IF(AND(ISNUMBER('3_BS'!H9),ISNUMBER('3_BS'!H6),ISNUMBER('3_BS'!H7),ISNUMBER('3_BS'!H8)),'3_BS'!H9-'3_BS'!H6-'3_BS'!H7-'3_BS'!H8,"n.a.") -> 3758
C54: 流動資産 | H54: ='3_BS'!H9 -> 13750 | I54: =IF(AND(ISNUMBER(I52),ISNUMBER(I24),ISNUMBER(I25),ISNUMBER(I53)),I52+I24+I25+I53,"n.a.") -> 16434.821 | J54: =IF(AND(ISNUMBER(J52),ISNUMBER(J24),ISNUMBER(J25),ISNUMBER(J53)),J52+J24+J25+J53,"n.a.") -> 20379.833 | K54: =IF(AND(ISNUMBER(K52),ISNUMBER(K24),ISNUMBER(K25),ISNUMBER(K53)),K52+K24+K25+K53,"n.a.") -> 24246.959
C55: その他非流動資産（固定） | I55: =IF(AND(ISNUMBER('3_BS'!H12),ISNUMBER('3_BS'!H9),ISNUMBER('3_BS'!H10),ISNUMBER('3_BS'!H11)),'3_BS'!H12-'3_BS'!H9-'3_BS'!H10-'3_BS'!H11,"n.a.") -> 8277 | J55: =IF(AND(ISNUMBER('3_BS'!H12),ISNUMBER('3_BS'!H9),ISNUMBER('3_BS'!H10),ISNUMBER('3_BS'!H11)),'3_BS'!H12-'3_BS'!H9-'3_BS'!H10-'3_BS'!H11,"n.a.") -> 8277 | K55: =IF(AND(ISNUMBER('3_BS'!H12),ISNUMBER('3_BS'!H9),ISNUMBER('3_BS'!H10),ISNUMBER('3_BS'!H11)),'3_BS'!H12-'3_BS'!H9-'3_BS'!H10-'3_BS'!H11,"n.a.") -> 8277
C56: 総資産 | H56: ='3_BS'!H12 -> 34585 | I56: =IF(AND(ISNUMBER(I54),ISNUMBER(I33),ISNUMBER(I34),ISNUMBER(I55)),I54+I33+I34+I55,"n.a.") -> 38069.217 | J56: =IF(AND(ISNUMBER(J54),ISNUMBER(J33),ISNUMBER(J34),ISNUMBER(J55)),J54+J33+J34+J55,"n.a.") -> 42283.406 | K56: =IF(AND(ISNUMBER(K54),ISNUMBER(K33),ISNUMBER(K34),ISNUMBER(K55)),K54+K33+K34+K55,"n.a.") -> 46223.555
C57: その他流動負債（固定） | I57: =IF(AND(ISNUMBER('3_BS'!H14),ISNUMBER('3_BS'!H13)),'3_BS'!H14-'3_BS'!H13,"n.a.") -> 2403 | J57: =IF(AND(ISNUMBER('3_BS'!H14),ISNUMBER('3_BS'!H13)),'3_BS'!H14-'3_BS'!H13,"n.a.") -> 2403 | K57: =IF(AND(ISNUMBER('3_BS'!H14),ISNUMBER('3_BS'!H13)),'3_BS'!H14-'3_BS'!H13,"n.a.") -> 2403
C58: 流動負債 | H58: ='3_BS'!H14 -> 3159 | I58: =IF(AND(ISNUMBER(I26),ISNUMBER(I57)),I26+I57,"n.a.") -> 3249.3462 | J58: =IF(AND(ISNUMBER(J26),ISNUMBER(J57)),J26+J57,"n.a.") -> 3284.7591 | K58: =IF(AND(ISNUMBER(K26),ISNUMBER(K57)),K26+K57,"n.a.") -> 3379.3161
C59: 負債合計 | H59: ='3_BS'!H15 -> 18312 | I59: =IF(AND(ISNUMBER(H59),ISNUMBER(I26),ISNUMBER(H26),ISNUMBER(I41),ISNUMBER(I44)),H59+I26-H26+I41+I44,"n.a.") -> 18402.346 | J59: =IF(AND(ISNUMBER(I59),ISNUMBER(J26),ISNUMBER(I26),ISNUMBER(J41),ISNUMBER(J44)),I59+J26-I26+J41+J44,"n.a.") -> 18437.759 | K59: =IF(AND(ISNUMBER(J59),ISNUMBER(K26),ISNUMBER(J26),ISNUMBER(K41),ISNUMBER(K44)),J59+K26-J26+K41+K44,"n.a.") -> 18532.316
C60: 資本合計 | H60: ='3_BS'!H16 -> 16273 | I60: =IF(AND(ISNUMBER(H60),ISNUMBER(I19),ISNUMBER(I39),ISNUMBER(I40),ISNUMBER(I42)),H60+I19-I39-I40+I42,"n.a.") -> 19666.871 | J60: =IF(AND(ISNUMBER(I60),ISNUMBER(J19),ISNUMBER(J39),ISNUMBER(J40),ISNUMBER(J42)),I60+J19-J39-J40+J42,"n.a.") -> 23845.647 | K60: =IF(AND(ISNUMBER(J60),ISNUMBER(K19),ISNUMBER(K39),ISNUMBER(K40),ISNUMBER(K42)),J60+K19-K39-K40+K42,"n.a.") -> 27691.239
C62: 貸借差額 | I62: =IF(AND(ISNUMBER(I56),ISNUMBER(I59),ISNUMBER(I60)),I56-I59-I60,"n.a.") -> -7.2759576e-12 | J62: =IF(AND(ISNUMBER(J56),ISNUMBER(J59),ISNUMBER(J60)),J56-J59-J60,"n.a.") -> 3.6379788e-12 | K62: =IF(AND(ISNUMBER(K56),ISNUMBER(K59),ISNUMBER(K60)),K56-K59-K60,"n.a.") -> 3.6379788e-12
C63: CF現金−最低現金 | I63: =IF(AND(ISNUMBER(I48),ISNUMBER('3_Assumptions'!D25),'3_Assumptions'!D25>=0),I48-'3_Assumptions'!D25,"n.a.") -> 5530.0311 | J63: =IF(AND(ISNUMBER(J48),ISNUMBER('3_Assumptions'!E25),'3_Assumptions'!E25>=0),J48-'3_Assumptions'!E25,"n.a.") -> 9106.0235 | K63: =IF(AND(ISNUMBER(K48),ISNUMBER('3_Assumptions'!F25),'3_Assumptions'!F25>=0),K48-'3_Assumptions'!F25,"n.a.") -> 12353.54
C64: 現金ロールフォワード差額 | I64: =IF(AND(ISNUMBER(H48),ISNUMBER(I37),ISNUMBER(I38),ISNUMBER(I45),ISNUMBER(I46),ISNUMBER(I48)),H48+I37+I38+I45+I46-I48,"n.a.") -> 0 | J64: =IF(AND(ISNUMBER(I48),ISNUMBER(J37),ISNUMBER(J38),ISNUMBER(J45),ISNUMBER(J46),ISNUMBER(J48)),I48+J37+J38+J45+J46-J48,"n.a.") -> 0 | K64: =IF(AND(ISNUMBER(J48),ISNUMBER(K37),ISNUMBER(K38),ISNUMBER(K45),ISNUMBER(K46),ISNUMBER(K48)),J48+K37+K38+K45+K46-K48,"n.a.") -> 1.8189894e-12

Sheet 3_Assumptions
C2: TEXAS INSTRUMENTS INC Assumptions
C4: USD 百万単位。青字・淡黄色の予測前提を変更。Eはモデル予測。 | M4: シナリオ別入力（report_spec.json の model.assumptions。青字を編集）
C5: 前提 | D5: 2026-12-31 E | E5: 2027-12-31 E | F5: 2028-12-31 E | M5: 変数（spec） | N5: base 1期 | O5: base 2期 | P5: base 3期 | Q5: bull 1期 | R5: bull 2期 | S5: bull 3期 | T5: bear 1期 | U5: bear 2期 | V5: bear 3期 | W5: 0054初期値 1期 | X5: 0054初期値 2期 | Y5: 0054初期値 3期
C6: 売上成長率（全社共通の基準） | D6: =CHOOSE('2_投資判断'!$C$4,$N$6,$Q$6,$T$6) -> 0.266 | E6: =CHOOSE('2_投資判断'!$C$4,$O$6,$R$6,$U$6) -> 0.07 | F6: =CHOOSE('2_投資判断'!$C$4,$P$6,$S$6,$V$6) -> 0.04 | H6: 同一報告書の比較売上前年比。各セグメントの加減を下で設定 | M6: 売上成長率（全社共通の基準） → 売上成長率（全社共通の基準） | N6: 0.266 | O6: 0.07 | P6: 0.04 | Q6: 0.266 | R6: 0.16 | S6: 0.08 | T6: 0.266 | U6: -0.11 | V6: 0 | W6: 0.13049038 | X6: 0.13049038 | Y6: 0.13049038
C7: 売上総利益率 | D7: =CHOOSE('2_投資判断'!$C$4,$N$10,$Q$10,$T$10) -> 0.62 | E7: =CHOOSE('2_投資判断'!$C$4,$O$10,$R$10,$U$10) -> 0.63 | F7: =CHOOSE('2_投資判断'!$C$4,$P$10,$S$10,$V$10) -> 0.605 | H7: 直近期実績 | M7: 成長率加減：Analog → 成長率加減：Analog | N7: 0.04 | O7: 0 | P7: 0 | Q7: 0.04 | R7: 0 | S7: 0 | T7: 0.04 | U7: 0 | V7: 0 | W7: 0 | X7: 0 | Y7: 0
C8: 販管費率 | D8: =CHOOSE('2_投資判断'!$C$4,$N$11,$Q$11,$T$11) -> 0.084 | E8: =CHOOSE('2_投資判断'!$C$4,$O$11,$R$11,$U$11) -> 0.082 | F8: =CHOOSE('2_投資判断'!$C$4,$P$11,$S$11,$V$11) -> 0.086 | H8: 直近期実績。研究開発費の内数を二重加算しない | M8: 成長率加減：Embedded Processing → 成長率加減：Embedded Processing | N8: -0.096 | O8: 0 | P8: 0 | Q8: -0.096 | R8: 0 | S8: 0 | T8: -0.096 | U8: 0 | V8: 0 | W8: 0 | X8: 0 | Y8: 0
C9: 別建て研究開発費率 | D9: =CHOOSE('2_投資判断'!$C$4,$N$12,$Q$12,$T$12) -> 0.096 | E9: =CHOOSE('2_投資判断'!$C$4,$O$12,$R$12,$U$12) -> 0.092 | F9: =CHOOSE('2_投資判断'!$C$4,$P$12,$S$12,$V$12) -> 0.096 | H9: 日本の研究開発費は販管費等の内数として初期値0 | M9: 成長率加減：Other → 成長率加減：Other | N9: -0.306 | O9: 0 | P9: 0 | Q9: -0.306 | R9: 0 | S9: 0 | T9: -0.306 | U9: 0 | V9: 0 | W9: 0 | X9: 0 | Y9: 0
C10: その他営業費用率（収益は負） | D10: 0 | E10: 0 | F10: 0 | H10: 直近3期の残差費用率の中央値 | M10: 売上総利益率 → 売上総利益率 | N10: 0.62 | O10: 0.63 | P10: 0.605 | Q10: 0.62 | R10: 0.65 | S10: 0.635 | T10: 0.62 | U10: 0.58 | V10: 0.58 | W10: 0.57024092 | X10: 0.57024092 | Y10: 0.57024092
C11: 基礎の純営業外損益 | D11: -313 | E11: -313 | F11: -313 | H11: 直近期の税前利益－営業利益。百万単位 | M11: 販管費率 → 販管費率 | N11: 0.084 | O11: 0.082 | P11: 0.086 | Q11: 0.084 | R11: 0.079 | S11: 0.078 | T11: 0.084 | U11: 0.094 | V11: 0.098 | W11: 0.10519172 | X11: 0.10519172 | Y11: 0.10519172
C12: 実効税率 | D12: =CHOOSE('2_投資判断'!$C$4,$N$13,$Q$13,$T$13) -> 0.12 | E12: =CHOOSE('2_投資判断'!$C$4,$O$13,$R$13,$U$13) -> 0.135 | F12: =CHOOSE('2_投資判断'!$C$4,$P$13,$S$13,$V$13) -> 0.135 | H12: 税前黒字かつ0〜100%の観測の直近3件の中央値 | M12: 別建て研究開発費率 → 別建て研究開発費率 | N12: 0.096 | O12: 0.092 | P12: 0.096 | Q12: 0.096 | R12: 0.088 | S12: 0.086 | T12: 0.096 | U12: 0.105 | V12: 0.11 | W12: 0.11780342 | X12: 0.11780342 | Y12: 0.11780342
C13: 非支配持分への利益配分率 | D13: 0 | E13: 0 | F13: 0 | H13: 有効な直近3観測の中央値。非継続事業の将来利益は0 | M13: 実効税率 → 実効税率 | N13: 0.12 | O13: 0.135 | P13: 0.135 | Q13: 0.12 | R13: 0.135 | S13: 0.135 | T13: 0.12 | U13: 0.135 | V13: 0.135 | W13: 0.12240496 | X13: 0.12240496 | Y13: 0.12240496
C14: 売上債権回収日数 | D14: 40.521151 | E14: 40.521151 | F14: 40.521151 | H14: 直近期AR／売上×365 | M14: 棚卸資産回転日数 → 棚卸資産回転日数 | N14: 200 | O14: 200 | P14: 200 | Q14: 200 | R14: 190 | S14: 190 | T14: 200 | U14: 230 | V14: 240 | W14: 230.74878 | X14: 230.74878 | Y14: 230.74878
C15: 棚卸資産回転日数 | D15: =CHOOSE('2_投資判断'!$C$4,$N$14,$Q$14,$T$14) -> 200 | E15: =CHOOSE('2_投資判断'!$C$4,$O$14,$R$14,$U$14) -> 200 | F15: =CHOOSE('2_投資判断'!$C$4,$P$14,$S$14,$V$14) -> 200 | H15: 直近期棚卸／売上原価×365 | M15: 有形・無形の現金投資／売上 → 有形・無形の現金投資／売上 | N15: 0.125 | O15: 0.1 | P15: 0.09 | Q15: 0.125 | R15: 0.1 | S15: 0.09 | T15: 0.125 | U15: 0.11 | V15: 0.1 | W15: 0.25732383 | X15: 0.25732383 | Y15: 0.25732383
C16: 仕入債務支払日数 | D16: 36.312673 | E16: 36.312673 | F16: 36.312673 | H16: 直近期AP／売上原価×365
C17: 有形・無形の現金投資／売上 | D17: =CHOOSE('2_投資判断'!$C$4,$N$15,$Q$15,$T$15) -> 0.125 | E17: =CHOOSE('2_投資判断'!$C$4,$O$15,$R$15,$U$15) -> 0.1 | F17: =CHOOSE('2_投資判断'!$C$4,$P$15,$S$15,$V$15) -> 0.09 | H17: 直近期CFの取得支出。発生主義の設備投資額とは区別 | M17: 注1：上書きした 0054 入力セルは =CHOOSE(シナリオ番号, base, bull, bear) の式（緑字）。シナリオ番号は 2_投資判断 の C4 で切替
C18: 期首償却対象資産の償却率 | D18: 0.1591814 | E18: 0.1591814 | F18: 0.1591814 | H18: 純粋D&A／有形・無形資産。D&A及びその他で代用しない
C19: 現金投資の有形資産配賦比率 | D19: 0.98104794 | E19: 0.98104794 | F19: 0.98104794 | H19: 直近の現金投資配賦。合算開示時は簿価比率。償却は各期首簿価で配賦
C20: 親会社株主への配当支払 | D20: 4999 | E20: 4999 | F20: 4999 | H20: 直近実績額を固定した初期仮定。百万単位
C21: 非支配株主への配当支払 | D21: 0 | E21: 0 | F21: 0 | H21: 直近実績額。未抽出時0の仮定。百万単位
C22: 計画した追加借入 | D22: 0 | E22: 0 | F22: 0 | H22: 既存債務は固定。返済予定はこの版では未モデル化。百万単位
C23: 新株発行による現金調達 | D23: 0 | E23: 0 | F23: 0 | H23: 初期仮定0。百万単位
C24: 追加借入の年利（仮置き） | D24: 0.05 | E24: 0.05 | F24: 0.05 | H24: 初期仮定5%。期首の追加借入残高に適用
C25: 最低現金残高 | D25: 0 | E25: 0 | F25: 0 | H25: 初期仮定0。百万単位
C26: 現金不足時の自動借入（1/0） | D26: 1 | E26: 1 | F26: 1 | H26: 1で最低現金まで明示的に借入。0で負の現金を表示
C29: 成長率加減：Analog | D29: =CHOOSE('2_投資判断'!$C$4,$N$7,$Q$7,$T$7) -> 0.04 | E29: =CHOOSE('2_投資判断'!$C$4,$O$7,$R$7,$U$7) -> 0 | F29: =CHOOSE('2_投資判断'!$C$4,$P$7,$S$7,$V$7) -> 0
C30: 成長率加減：Embedded Processing | D30: =CHOOSE('2_投資判断'!$C$4,$N$8,$Q$8,$T$8) -> -0.096 | E30: =CHOOSE('2_投資判断'!$C$4,$O$8,$R$8,$U$8) -> 0 | F30: =CHOOSE('2_投資判断'!$C$4,$P$8,$S$8,$V$8) -> 0
C31: 成長率加減：Other | D31: =CHOOSE('2_投資判断'!$C$4,$N$9,$Q$9,$T$9) -> -0.306 | E31: =CHOOSE('2_投資判断'!$C$4,$O$9,$R$9,$U$9) -> 0 | F31: =CHOOSE('2_投資判断'!$C$4,$P$9,$S$9,$V$9) -> 0
C33: 地域配分ウェイト：United States | D33: 0.38247936 | E33: 0.38247936 | F33: 0.38247936
C34: 地域配分ウェイト：China | D34: 0.21383328 | E34: 0.21383328 | F34: 0.21383328
C35: 地域配分ウェイト：Rest of Asia | D35: 0.1067187 | E35: 0.1067187 | F35: 0.1067187
C36: 地域配分ウェイト：Europe, Middle East and Africa | D36: 0.21191042 | E36: 0.21191042 | F36: 0.21191042
C37: 地域配分ウェイト：Japan | D37: 0.066338649 | E37: 0.066338649 | F37: 0.066338649
C38: 地域配分ウェイト：Rest of world | D38: 0.018719602 | E38: 0.018719602 | F38: 0.018719602
C42: 売上成長率の初期値は同一報告書の比較売上から算出。売却事業を含む非比較年度へ遡ったCAGRは使わない。比較値が無い場合は0%仮定。
C43: 粗利率・販管費率は直近期。その他営業費用率は直近3期の中央値で、一過性損益を固定しない。
C44: 税率は税引前利益が正かつ税率0〜100%の観測の直近3件の中央値。税率の外れ値は初期値に使わない。
C45: 非支配持分利益率は0〜100%の観測の直近3件の中央値。非継続事業の将来損益はゼロ仮定。
C46: 設備投資は直近の現金投資比率（合算開示時は簿価比率）で配賦し、償却は各期首簿価で配賦。投資は期末発生と仮定。
C47: 親会社・非支配株主配当は直近支払額を固定する初期仮定。その他資産・負債・OCI・M&A・自社株買い・為替効果は固定またはゼロ仮定。
C48: 新規借入の利率5%は仮置き。期首の追加借入残高に適用し、循環参照を避ける。既存借入の純金融損益は直近期の純営業外損益に含めて固定。
C49: 現金不足時は明示した最低現金方針に従い追加借入。自動調達を0にすると負の現金を表示して検出する。
C50: 地域配分は編集可能なウェイトを正規化。内数は別表示し合計へ加えない。

Sheet 計算_DCF
B1: 計算_DCF DCF 理論株価の計算（選択中シナリオ）
B2: TXN Texas Instruments／金額は百万ドル（株価はドル）。青字＝入力、黒字＝計算、緑字＝他シート参照。シナリオは 2_投資判断 の切替セルに連動
B4: 割引率（WACC）・ターミナル成長率
B5: 項目 | C5: 値 | D5: 備考
B6: リスクフリーレート | C6: 0.0513
B7: β | C7: 1.2
B8: 株式リスクプレミアム | C8: 0.042
B9: サイズプレミアム | C9: 0
B10: 株主資本コスト＝rf＋β×ERP＋サイズ | C10: =C6+C7*C8+C9 -> 0.1017
B11: 負債コスト（税引前） | C11: 0.055
B12: 税率（NOPAT・負債節税） | C12: 0.135
B13: 目標負債比率 D/(D+E) | C13: 0.07
B14: WACC | C14: =(1-C13)*C10+C13*C11*(1-C12) -> 0.09791125
B15: ターミナル成長率 g | C15: 0.035
B16: 延長期間（年） | C16: 7 | D16: 列数に連動するため変更は spec で行い再 build
B17: ターミナル価値の方式 | C17: value_driver | D17: バリュードライバー式: TV＝NOPAT_{n+1}×(1−g/RONIC)/(WACC−g)、NOPAT_{n+1}＝NOPAT_n×(1+g)
B18: RONIC（新規投資の税引後資本利益率） | C18: 0.2 | D18: spec dcf.ronic
B20: 株式価値への調整（百万ドル）
B21: 項目 | C21: 値 | D21: 備考
B22: 純有利子負債 | C22: 5413 | D22: spec dcf.net_debt_override
B23: 非支配持分（DCF 用） | C23: 0 | D23: spec dcf.minority_interest
B24: 非支配持分（SOTP 用） | C24: =C23 -> 0 | D24: minority_interest_sotp 未入力：DCF 用を流用
B25: 持分法投資等 | C25: 2163 | D25: spec dcf.equity_investments
B26: 株式数（株） | C26: =データ_株価!$C$7 -> 913247686 | D26: 発行済（outstanding、自己株控除後の流通株式。2026-07-15 時点）。希薄化（RSU・ストックオプション）は反映しない
B27: 金額単位→ドルの倍率 | C27: 1000000 | D27: 0054 は百万ドル単位
B28: 注1：非支配持分は DCF 用（DCF と同じ物差し）と SOTP 用（時価）を使い分ける（詳細は検証シート）
B30: DCF（選択中シナリオ。予測期間は 3_Forecast を直接参照、百万ドル）
B31: DCF（選択中シナリオ） | C31: 2026-12-31 E | D31: 2027-12-31 E | E31: 2028-12-31 E | F31: 延長+1 | G31: 延長+2 | H31: 延長+3 | I31: 延長+4 | J31: 延長+5 | K31: 延長+6 | L31: 延長+7 | M31: ターミナル
B32: 期（年） | C32: 1 | D32: 2 | E32: 3 | F32: 4 | G32: 5 | H32: 6 | I32: 7 | J32: 8 | K32: 9 | L32: 10 | M32: バリュードライバー式
B33: 売上高 | C33: ='3_Forecast'!$I$8 -> 22387.166 | D33: ='3_Forecast'!$J$8 -> 23954.268 | E33: ='3_Forecast'!$K$8 -> 24912.438 | F33: =E33*(1+F34) -> 25891.141 | G33: =F33*(1+G34) -> 26889.8 | H33: =G33*(1+H34) -> 27907.771 | I33: =H33*(1+I34) -> 28944.345 | J33: =I33*(1+J34) -> 29998.746 | K33: =J33*(1+K34) -> 31070.13 | L33: =K33*(1+L34) -> 32157.584
B34: 売上成長率 | C34: =C33/'3_Forecast'!$H$8-1 -> 0.2660992 | D34: =D33/C33-1 -> 0.07 | E34: =E33/D33-1 -> 0.04 | F34: =$E$34+($C$15-$E$34)*(F32-3)/$C$16 -> 0.039285714 | G34: =$E$34+($C$15-$E$34)*(G32-3)/$C$16 -> 0.038571429 | H34: =$E$34+($C$15-$E$34)*(H32-3)/$C$16 -> 0.037857143 | I34: =$E$34+($C$15-$E$34)*(I32-3)/$C$16 -> 0.037142857 | J34: =$E$34+($C$15-$E$34)*(J32-3)/$C$16 -> 0.036428571 | K34: =$E$34+($C$15-$E$34)*(K32-3)/$C$16 -> 0.035714286 | L34: =$E$34+($C$15-$E$34)*(L32-3)/$C$16 -> 0.035
B35: 営業利益 | C35: ='3_Forecast'!$I$14 -> 9850.353 | D35: ='3_Forecast'!$J$14 -> 10923.146 | E35: ='3_Forecast'!$K$14 -> 10537.961 | F35: =F33*$E$36 -> 10951.953 | G35: =G33*$E$36 -> 11374.385 | H35: =H33*$E$36 -> 11804.987 | I35: =I33*$E$36 -> 12243.458 | J35: =J33*$E$36 -> 12689.47 | K35: =K33*$E$36 -> 13142.665 | L35: =L33*$E$36 -> 13602.658
B36: 営業利益率 | C36: =C35/C33 -> 0.44 | D36: =D35/D33 -> 0.456 | E36: =E35/E33 -> 0.423 | F36: =F35/F33 -> 0.423 | G36: =G35/G33 -> 0.423 | H36: =H35/H33 -> 0.423 | I36: =I35/I33 -> 0.423 | J36: =J35/J33 -> 0.423 | ... L36: =L35/L33 -> 0.423
B37: NOPAT（営業利益×(1−税率)） | C37: =C35*(1-$C$12) -> 8520.5554 | D37: =D35*(1-$C$12) -> 9448.5213 | E37: =E35*(1-$C$12) -> 9115.3366 | F37: =F35*(1-$C$12) -> 9473.4391 | G37: =G35*(1-$C$12) -> 9838.8432 | H37: =H35*(1-$C$12) -> 10211.314 | I37: =I35*(1-$C$12) -> 10590.591 | J37: =J35*(1-$C$12) -> 10976.391 | ... L37: =L35*(1-$C$12) -> 11766.299
B38: 減価償却・償却費 | C38: ='3_Forecast'!$I$32 -> 1999 | D38: ='3_Forecast'!$J$32 -> 2126.2489 | E38: ='3_Forecast'!$K$32 -> 2169.097 | F38: =F33*$E$38/$E$33 -> 2254.3116 | G38: =G33*$E$38/$E$33 -> 2341.2636 | H38: =H33*$E$38/$E$33 -> 2429.8971 | I38: =I33*$E$38/$E$33 -> 2520.1505 | J38: =J33*$E$38/$E$33 -> 2611.9559 | K38: =K33*$E$38/$E$33 -> 2705.2401 | L38: =L33*$E$38/$E$33 -> 2799.9235
B39: 設備投資（有形・無形の現金投資） | C39: ='3_Forecast'!$I$31 -> 2798.3958 | D39: ='3_Forecast'!$J$31 -> 2395.4268 | E39: ='3_Forecast'!$K$31 -> 2242.1194 | F39: =F33*($E$39/$E$33+($E$38/$E$33-$E$39/$E$33)*(F32-3)/$C$16) -> 2319.3611 | G39: =G33*($E$39/$E$33+($E$38/$E$33-$E$39/$E$33)*(G32-3)/$C$16) -> 2397.5624 | H39: =H33*($E$39/$E$33+($E$38/$E$33-$E$39/$E$33)*(H32-3)/$C$16) -> 2476.6413 | I39: =I33*($E$39/$E$33+($E$38/$E$33-$E$39/$E$33)*(I32-3)/$C$16) -> 2556.5107 | J39: =J33*($E$39/$E$33+($E$38/$E$33-$E$39/$E$33)*(J32-3)/$C$16) -> 2637.0791 | K39: =K33*($E$39/$E$33+($E$38/$E$33-$E$39/$E$33)*(K32-3)/$C$16) -> 2718.2503 | L39: =L33*($E$39/$E$33+($E$38/$E$33-$E$39/$E$33)*(L32-3)/$C$16) -> 2799.9235
B40: 運転資本増加 | C40: ='3_Forecast'!$I$27 -> 289.44379 | D40: ='3_Forecast'!$J$27 -> 333.60613 | E40: ='3_Forecast'!$K$27 -> 525.05284 | F40: =$C$57*(F33-E33) -> 281.25047 | G40: =$C$57*(G33-F33) -> 286.98505 | H40: =$C$57*(H33-G33) -> 292.53495 | I40: =$C$57*(I33-H33) -> 297.88101 | J40: =$C$57*(J33-I33) -> 303.0039 | K40: =$C$57*(K33-J33) -> 307.88422 | L40: =$C$57*(L33-K33) -> 312.50248
B41: FCF（NOPAT＋償却−投資−運転資本増加） | C41: =C37+C38-C39-C40 -> 7431.7158 | D41: =D37+D38-D39-D40 -> 8845.7374 | E41: =E37+E38-E39-E40 -> 8517.2614 | F41: =F37+F38-F39-F40 -> 9127.1391 | G41: =G37+G38-G39-G40 -> 9495.5593 | H41: =H37+H38-H39-H40 -> 9872.0346 | I41: =I37+I38-I39-I40 -> 10256.35 | J41: =J37+J38-J39-J40 -> 10648.264 | ... L41: =L37+L38-L39-L40 -> 11453.797 | M41: =L37*(1+$C$15)*(1-$C$15/$C$18)/($C$14-$C$15) -> 159700.35
B42: 割引係数 1/(1+WACC)^t | C42: =1/(1+$C$14)^C32 -> 0.91082043 | D42: =1/(1+$C$14)^D32 -> 0.82959386 | E42: =1/(1+$C$14)^E32 -> 0.75561104 | F42: =1/(1+$C$14)^F32 -> 0.68822597 | G42: =1/(1+$C$14)^G32 -> 0.62685028 | H42: =1/(1+$C$14)^H32 -> 0.57094804 | I42: =1/(1+$C$14)^I32 -> 0.52003114 | J42: =1/(1+$C$14)^J32 -> 0.47365499 | ... L42: =1/(1+$C$14)^L32 -> 0.39294127 | M42: =L42 -> 0.39294127
B43: FCF 現在価値 | C43: =C41*C42 -> 6768.9586 | D43: =D41*D42 -> 7338.3694 | E43: =E41*E42 -> 6435.7367 | F43: =F41*F42 -> 6281.5342 | G43: =G41*G42 -> 5952.294 | H43: =H41*H42 -> 5636.4189 | I43: =I41*I42 -> 5333.6213 | J43: =J41*J42 -> 5043.6034 | ... M43: =M41*M42 -> 62752.86
B45: 予測・延長期間 FCF 現在価値合計 | C45: =SUM(C43:L43) -> 58057.264
B46: ターミナル価値 現在価値 | C46: =M43 -> 62752.86
B47: 事業価値（EV） | C47: =C45+C46 -> 120810.12
B48: （−）純有利子負債 | C48: =$C$22 -> 5413
B49: （−）非支配持分 | C49: =$C$23 -> 0
B50: （＋）持分法投資等 | C50: =$C$25 -> 2163
B51: 株式価値 | C51: =C47-C48-C49+C50 -> 117560.12
B52: 発行済株式数（自己株除く、株） | C52: =$C$26 -> 913247686
B53: 理論株価（ドル） | C53: =C51*$C$27/C52 -> 128.72754
B54: ターミナル価値 / EV | C54: =C46/C47 -> 0.51943379
B55: ターミナル価値 現在価値 / 株式価値 | C55: =IF(C51>0,C46/C51,"n.a.（株式価値≦0）") -> 0.53379376
B56: EV が 1% 動いたときの理論株価の変化（%）＝EV/株式価値 | C56: =IF(C51>0,C47/C51,"n.a.（株式価値≦0）") -> 1.0276454
B57: 運転資本 / 売上（3期目、延長期間で固定） | C57: =('3_Forecast'!$K$24+'3_Forecast'!$K$25-'3_Forecast'!$K$26)/$E$33 -> 0.28737062
B59: 注1：延長期間は売上成長率を g へ線形収束、営業利益率・償却/売上・運転資本/売上は 3期目水準、投資/売上は償却/売上へ収束
B60: 注2：期末割引（期中割引・スタブ期間調整なし）
B62: 感応度①：理論株価（ドル） WACC（行）× ターミナル成長率 g（列）
B63: WACC ＼ g | C63: =$C$15+(-0.01) -> 0.025 | D63: =$C$15+(-0.005) -> 0.03 | E63: =$C$15+(0) -> 0.035 | F63: =$C$15+(0.005) -> 0.04 | G63: =$C$15+(0.01) -> 0.045
B64: =$C$14+(-0.01) -> 0.08791125 | C64: =(SUMPRODUCT($C$41:$L$41/(1+$B64)^$C$32:$L$32)+$L$37*(1+C$63)*(1-C$63/$C$18)/($B64-C$63)/(1+$B64)^$L$32-$C$22-$C$23+$C$25)*$C$27/$C$26 -> 142.1517 | D64: =(SUMPRODUCT($C$41:$L$41/(1+$B64)^$C$32:$L$32)+$L$37*(1+D$63)*(1-D$63/$C$18)/($B64-D$63)/(1+$B64)^$L$32-$C$22-$C$23+$C$25)*$C$27/$C$26 -> 146.93256 | E64: =(SUMPRODUCT($C$41:$L$41/(1+$B64)^$C$32:$L$32)+$L$37*(1+E$63)*(1-E$63/$C$18)/($B64-E$63)/(1+$B64)^$L$32-$C$22-$C$23+$C$25)*$C$27/$C$26 -> 152.59077 | F64: =(SUMPRODUCT($C$41:$L$41/(1+$B64)^$C$32:$L$32)+$L$37*(1+F$63)*(1-F$63/$C$18)/($B64-F$63)/(1+$B64)^$L$32-$C$22-$C$23+$C$25)*$C$27/$C$26 -> 159.40101 | G64: =(SUMPRODUCT($C$41:$L$41/(1+$B64)^$C$32:$L$32)+$L$37*(1+G$63)*(1-G$63/$C$18)/($B64-G$63)/(1+$B64)^$L$32-$C$22-$C$23+$C$25)*$C$27/$C$26 -> 167.76599
B65: =$C$14+(-0.005) -> 0.09291125 | C65: =(SUMPRODUCT($C$41:$L$41/(1+$B65)^$C$32:$L$32)+$L$37*(1+C$63)*(1-C$63/$C$18)/($B65-C$63)/(1+$B65)^$L$32-$C$22-$C$23+$C$25)*$C$27/$C$26 -> 131.49393 | D65: =(SUMPRODUCT($C$41:$L$41/(1+$B65)^$C$32:$L$32)+$L$37*(1+D$63)*(1-D$63/$C$18)/($B65-D$63)/(1+$B65)^$L$32-$C$22-$C$23+$C$25)*$C$27/$C$26 -> 135.25553 | E65: =(SUMPRODUCT($C$41:$L$41/(1+$B65)^$C$32:$L$32)+$L$37*(1+E$63)*(1-E$63/$C$18)/($B65-E$63)/(1+$B65)^$L$32-$C$22-$C$23+$C$25)*$C$27/$C$26 -> 139.64379 | F65: =(SUMPRODUCT($C$41:$L$41/(1+$B65)^$C$32:$L$32)+$L$37*(1+F$63)*(1-F$63/$C$18)/($B65-F$63)/(1+$B65)^$L$32-$C$22-$C$23+$C$25)*$C$27/$C$26 -> 144.83638 | G65: =(SUMPRODUCT($C$41:$L$41/(1+$B65)^$C$32:$L$32)+$L$37*(1+G$63)*(1-G$63/$C$18)/($B65-G$63)/(1+$B65)^$L$32-$C$22-$C$23+$C$25)*$C$27/$C$26 -> 151.08512
B66: =$C$14+(0) -> 0.09791125 | C66: =(SUMPRODUCT($C$41:$L$41/(1+$B66)^$C$32:$L$32)+$L$37*(1+C$63)*(1-C$63/$C$18)/($B66-C$63)/(1+$B66)^$L$32-$C$22-$C$23+$C$25)*$C$27/$C$26 -> 122.28895 | D66: =(SUMPRODUCT($C$41:$L$41/(1+$B66)^$C$32:$L$32)+$L$37*(1+D$63)*(1-D$63/$C$18)/($B66-D$63)/(1+$B66)^$L$32-$C$22-$C$23+$C$25)*$C$27/$C$26 -> 125.28054 | E66: =(SUMPRODUCT($C$41:$L$41/(1+$B66)^$C$32:$L$32)+$L$37*(1+E$63)*(1-E$63/$C$18)/($B66-E$63)/(1+$B66)^$L$32-$C$22-$C$23+$C$25)*$C$27/$C$26 -> 128.72754 | F66: =(SUMPRODUCT($C$41:$L$41/(1+$B66)^$C$32:$L$32)+$L$37*(1+F$63)*(1-F$63/$C$18)/($B66-F$63)/(1+$B66)^$L$32-$C$22-$C$23+$C$25)*$C$27/$C$26 -> 132.74789 | G66: =(SUMPRODUCT($C$41:$L$41/(1+$B66)^$C$32:$L$32)+$L$37*(1+G$63)*(1-G$63/$C$18)/($B66-G$63)/(1+$B66)^$L$32-$C$22-$C$23+$C$25)*$C$27/$C$26 -> 137.50416
B67: =$C$14+(0.005) -> 0.10291125 | C67: =(SUMPRODUCT($C$41:$L$41/(1+$B67)^$C$32:$L$32)+$L$37*(1+C$63)*(1-C$63/$C$18)/($B67-C$63)/(1+$B67)^$L$32-$C$22-$C$23+$C$25)*$C$27/$C$26 -> 114.25762 | D67: =(SUMPRODUCT($C$41:$L$41/(1+$B67)^$C$32:$L$32)+$L$37*(1+D$63)*(1-D$63/$C$18)/($B67-D$63)/(1+$B67)^$L$32-$C$22-$C$23+$C$25)*$C$27/$C$26 -> 116.65838 | E67: =(SUMPRODUCT($C$41:$L$41/(1+$B67)^$C$32:$L$32)+$L$37*(1+E$63)*(1-E$63/$C$18)/($B67-E$63)/(1+$B67)^$L$32-$C$22-$C$23+$C$25)*$C$27/$C$26 -> 119.39485 | F67: =(SUMPRODUCT($C$41:$L$41/(1+$B67)^$C$32:$L$32)+$L$37*(1+F$63)*(1-F$63/$C$18)/($B67-F$63)/(1+$B67)^$L$32-$C$22-$C$23+$C$25)*$C$27/$C$26 -> 122.54707 | G67: =(SUMPRODUCT($C$41:$L$41/(1+$B67)^$C$32:$L$32)+$L$37*(1+G$63)*(1-G$63/$C$18)/($B67-G$63)/(1+$B67)^$L$32-$C$22-$C$23+$C$25)*$C$27/$C$26 -> 126.22272
B68: =$C$14+(0.01) -> 0.10791125 | C68: =(SUMPRODUCT($C$41:$L$41/(1+$B68)^$C$32:$L$32)+$L$37*(1+C$63)*(1-C$63/$C$18)/($B68-C$63)/(1+$B68)^$L$32-$C$22-$C$23+$C$25)*$C$27/$C$26 -> 107.18809 | D68: =(SUMPRODUCT($C$41:$L$41/(1+$B68)^$C$32:$L$32)+$L$37*(1+D$63)*(1-D$63/$C$18)/($B68-D$63)/(1+$B68)^$L$32-$C$22-$C$23+$C$25)*$C$27/$C$26 -> 109.12942 | E68: =(SUMPRODUCT($C$41:$L$41/(1+$B68)^$C$32:$L$32)+$L$37*(1+E$63)*(1-E$63/$C$18)/($B68-E$63)/(1+$B68)^$L$32-$C$22-$C$23+$C$25)*$C$27/$C$26 -> 111.32117 | F68: =(SUMPRODUCT($C$41:$L$41/(1+$B68)^$C$32:$L$32)+$L$37*(1+F$63)*(1-F$63/$C$18)/($B68-F$63)/(1+$B68)^$L$32-$C$22-$C$23+$C$25)*$C$27/$C$26 -> 113.81863 | G68: =(SUMPRODUCT($C$41:$L$41/(1+$B68)^$C$32:$L$32)+$L$37*(1+G$63)*(1-G$63/$C$18)/($B68-G$63)/(1+$B68)^$L$32-$C$22-$C$23+$C$25)*$C$27/$C$26 -> 116.69469
B69: 注1：各セルは FCF 行を参照する閉形式 DCF 式（データテーブル機能は使わない）。中央セル＝理論株価
B70: 注2：g はターミナル成長率のみを動かす（延長期間の収束経路は基準 g のまま）
B72: 感応度②：理論株価（ドル） 営業利益率（行、全期間に加減）× 売上成長率（列、全期間に加減）
B73: 3期目営業利益率 ＼ 1期目成長率 | C73: =$C$34+(-0.02) -> 0.2460992 | D73: =$C$34+(-0.01) -> 0.2560992 | E73: =$C$34+(0) -> 0.2660992 | F73: =$C$34+(0.01) -> 0.2760992 | G73: =$C$34+(0.02) -> 0.2860992
B74: =$E$36+(-0.02) -> 0.403 | C74: =(SUMPRODUCT((($C$35:$L$35+(-0.02)*$C$33:$L$33)*(1-$C$12)+$C$38:$L$38-$C$39:$L$39-$C$40:$L$40)*(1+(-0.02))^$C$32:$L$32/(1+$C$14)^$C$32:$L$32)+($L$35+(-0.02)*$L$33)*(1-$C$12)*(1+(-0.02))^$L$32*(1+$C$15)*(1-$C$15/$C$18)/($C$14-$C$15)/(1+$C$14)^$L$32-$C$22-$C$23+$C$25)*$C$27/$C$26 -> 104.56729 | D74: =(SUMPRODUCT((($C$35:$L$35+(-0.02)*$C$33:$L$33)*(1-$C$12)+$C$38:$L$38-$C$39:$L$39-$C$40:$L$40)*(1+(-0.01))^$C$32:$L$32/(1+$C$14)^$C$32:$L$32)+($L$35+(-0.02)*$L$33)*(1-$C$12)*(1+(-0.01))^$L$32*(1+$C$15)*(1-$C$15/$C$18)/($C$14-$C$15)/(1+$C$14)^$L$32-$C$22-$C$23+$C$25)*$C$27/$C$26 -> 113.10604 | E74: =(SUMPRODUCT((($C$35:$L$35+(-0.02)*$C$33:$L$33)*(1-$C$12)+$C$38:$L$38-$C$39:$L$39-$C$40:$L$40)*(1+0)^$C$32:$L$32/(1+$C$14)^$C$32:$L$32)+($L$35+(-0.02)*$L$33)*(1-$C$12)*(1+0)^$L$32*(1+$C$15)*(1-$C$15/$C$18)/($C$14-$C$15)/(1+$C$14)^$L$32-$C$22-$C$23+$C$25)*$C$27/$C$26 -> 122.35305 | F74: =(SUMPRODUCT((($C$35:$L$35+(-0.02)*$C$33:$L$33)*(1-$C$12)+$C$38:$L$38-$C$39:$L$39-$C$40:$L$40)*(1+(0.01))^$C$32:$L$32/(1+$C$14)^$C$32:$L$32)+($L$35+(-0.02)*$L$33)*(1-$C$12)*(1+(0.01))^$L$32*(1+$C$15)*(1-$C$15/$C$18)/($C$14-$C$15)/(1+$C$14)^$L$32-$C$22-$C$23+$C$25)*$C$27/$C$26 -> 132.36366 | G74: =(SUMPRODUCT((($C$35:$L$35+(-0.02)*$C$33:$L$33)*(1-$C$12)+$C$38:$L$38-$C$39:$L$39-$C$40:$L$40)*(1+(0.02))^$C$32:$L$32/(1+$C$14)^$C$32:$L$32)+($L$35+(-0.02)*$L$33)*(1-$C$12)*(1+(0.02))^$L$32*(1+$C$15)*(1-$C$15/$C$18)/($C$14-$C$15)/(1+$C$14)^$L$32-$C$22-$C$23+$C$25)*$C$27/$C$26 -> 143.19708
B75: =$E$36+(-0.01) -> 0.413 | C75: =(SUMPRODUCT((($C$35:$L$35+(-0.01)*$C$33:$L$33)*(1-$C$12)+$C$38:$L$38-$C$39:$L$39-$C$40:$L$40)*(1+(-0.02))^$C$32:$L$32/(1+$C$14)^$C$32:$L$32)+($L$35+(-0.01)*$L$33)*(1-$C$12)*(1+(-0.02))^$L$32*(1+$C$15)*(1-$C$15/$C$18)/($C$14-$C$15)/(1+$C$14)^$L$32-$C$22-$C$23+$C$25)*$C$27/$C$26 -> 107.30802 | D75: =(SUMPRODUCT((($C$35:$L$35+(-0.01)*$C$33:$L$33)*(1-$C$12)+$C$38:$L$38-$C$39:$L$39-$C$40:$L$40)*(1+(-0.01))^$C$32:$L$32/(1+$C$14)^$C$32:$L$32)+($L$35+(-0.01)*$L$33)*(1-$C$12)*(1+(-0.01))^$L$32*(1+$C$15)*(1-$C$15/$C$18)/($C$14-$C$15)/(1+$C$14)^$L$32-$C$22-$C$23+$C$25)*$C$27/$C$26 -> 116.06117 | E75: =(SUMPRODUCT((($C$35:$L$35+(-0.01)*$C$33:$L$33)*(1-$C$12)+$C$38:$L$38-$C$39:$L$39-$C$40:$L$40)*(1+0)^$C$32:$L$32/(1+$C$14)^$C$32:$L$32)+($L$35+(-0.01)*$L$33)*(1-$C$12)*(1+0)^$L$32*(1+$C$15)*(1-$C$15/$C$18)/($C$14-$C$15)/(1+$C$14)^$L$32-$C$22-$C$23+$C$25)*$C$27/$C$26 -> 125.54029 | F75: =(SUMPRODUCT((($C$35:$L$35+(-0.01)*$C$33:$L$33)*(1-$C$12)+$C$38:$L$38-$C$39:$L$39-$C$40:$L$40)*(1+(0.01))^$C$32:$L$32/(1+$C$14)^$C$32:$L$32)+($L$35+(-0.01)*$L$33)*(1-$C$12)*(1+(0.01))^$L$32*(1+$C$15)*(1-$C$15/$C$18)/($C$14-$C$15)/(1+$C$14)^$L$32-$C$22-$C$23+$C$25)*$C$27/$C$26 -> 135.80211 | G75: =(SUMPRODUCT((($C$35:$L$35+(-0.01)*$C$33:$L$33)*(1-$C$12)+$C$38:$L$38-$C$39:$L$39-$C$40:$L$40)*(1+(0.02))^$C$32:$L$32/(1+$C$14)^$C$32:$L$32)+($L$35+(-0.01)*$L$33)*(1-$C$12)*(1+(0.02))^$L$32*(1+$C$15)*(1-$C$15/$C$18)/($C$14-$C$15)/(1+$C$14)^$L$32-$C$22-$C$23+$C$25)*$C$27/$C$26 -> 146.9073
B76: =$E$36+(0) -> 0.423 | C76: =(SUMPRODUCT((($C$35:$L$35+0*$C$33:$L$33)*(1-$C$12)+$C$38:$L$38-$C$39:$L$39-$C$40:$L$40)*(1+(-0.02))^$C$32:$L$32/(1+$C$14)^$C$32:$L$32)+($L$35+0*$L$33)*(1-$C$12)*(1+(-0.02))^$L$32*(1+$C$15)*(1-$C$15/$C$18)/($C$14-$C$15)/(1+$C$14)^$L$32-$C$22-$C$23+$C$25)*$C$27/$C$26 -> 110.04875 | D76: =(SUMPRODUCT((($C$35:$L$35+0*$C$33:$L$33)*(1-$C$12)+$C$38:$L$38-$C$39:$L$39-$C$40:$L$40)*(1+(-0.01))^$C$32:$L$32/(1+$C$14)^$C$32:$L$32)+($L$35+0*$L$33)*(1-$C$12)*(1+(-0.01))^$L$32*(1+$C$15)*(1-$C$15/$C$18)/($C$14-$C$15)/(1+$C$14)^$L$32-$C$22-$C$23+$C$25)*$C$27/$C$26 -> 119.0163 | E76: =(SUMPRODUCT($C$41:$L$41/(1+$C$14)^$C$32:$L$32)+$L$37*(1+$C$15)*(1-$C$15/$C$18)/($C$14-$C$15)/(1+$C$14)^$L$32-$C$22-$C$23+$C$25)*$C$27/$C$26 -> 128.72754 | F76: =(SUMPRODUCT((($C$35:$L$35+0*$C$33:$L$33)*(1-$C$12)+$C$38:$L$38-$C$39:$L$39-$C$40:$L$40)*(1+(0.01))^$C$32:$L$32/(1+$C$14)^$C$32:$L$32)+($L$35+0*$L$33)*(1-$C$12)*(1+(0.01))^$L$32*(1+$C$15)*(1-$C$15/$C$18)/($C$14-$C$15)/(1+$C$14)^$L$32-$C$22-$C$23+$C$25)*$C$27/$C$26 -> 139.24056 | G76: =(SUMPRODUCT((($C$35:$L$35+0*$C$33:$L$33)*(1-$C$12)+$C$38:$L$38-$C$39:$L$39-$C$40:$L$40)*(1+(0.02))^$C$32:$L$32/(1+$C$14)^$C$32:$L$32)+($L$35+0*$L$33)*(1-$C$12)*(1+(0.02))^$L$32*(1+$C$15)*(1-$C$15/$C$18)/($C$14-$C$15)/(1+$C$14)^$L$32-$C$22-$C$23+$C$25)*$C$27/$C$26 -> 150.61752
B77: =$E$36+(0.01) -> 0.433 | C77: =(SUMPRODUCT((($C$35:$L$35+(0.01)*$C$33:$L$33)*(1-$C$12)+$C$38:$L$38-$C$39:$L$39-$C$40:$L$40)*(1+(-0.02))^$C$32:$L$32/(1+$C$14)^$C$32:$L$32)+($L$35+(0.01)*$L$33)*(1-$C$12)*(1+(-0.02))^$L$32*(1+$C$15)*(1-$C$15/$C$18)/($C$14-$C$15)/(1+$C$14)^$L$32-$C$22-$C$23+$C$25)*$C$27/$C$26 -> 112.78948 | D77: =(SUMPRODUCT((($C$35:$L$35+(0.01)*$C$33:$L$33)*(1-$C$12)+$C$38:$L$38-$C$39:$L$39-$C$40:$L$40)*(1+(-0.01))^$C$32:$L$32/(1+$C$14)^$C$32:$L$32)+($L$35+(0.01)*$L$33)*(1-$C$12)*(1+(-0.01))^$L$32*(1+$C$15)*(1-$C$15/$C$18)/($C$14-$C$15)/(1+$C$14)^$L$32-$C$22-$C$23+$C$25)*$C$27/$C$26 -> 121.97144 | E77: =(SUMPRODUCT((($C$35:$L$35+(0.01)*$C$33:$L$33)*(1-$C$12)+$C$38:$L$38-$C$39:$L$39-$C$40:$L$40)*(1+0)^$C$32:$L$32/(1+$C$14)^$C$32:$L$32)+($L$35+(0.01)*$L$33)*(1-$C$12)*(1+0)^$L$32*(1+$C$15)*(1-$C$15/$C$18)/($C$14-$C$15)/(1+$C$14)^$L$32-$C$22-$C$23+$C$25)*$C$27/$C$26 -> 131.91478 | F77: =(SUMPRODUCT((($C$35:$L$35+(0.01)*$C$33:$L$33)*(1-$C$12)+$C$38:$L$38-$C$39:$L$39-$C$40:$L$40)*(1+(0.01))^$C$32:$L$32/(1+$C$14)^$C$32:$L$32)+($L$35+(0.01)*$L$33)*(1-$C$12)*(1+(0.01))^$L$32*(1+$C$15)*(1-$C$15/$C$18)/($C$14-$C$15)/(1+$C$14)^$L$32-$C$22-$C$23+$C$25)*$C$27/$C$26 -> 142.679 | G77: =(SUMPRODUCT((($C$35:$L$35+(0.01)*$C$33:$L$33)*(1-$C$12)+$C$38:$L$38-$C$39:$L$39-$C$40:$L$40)*(1+(0.02))^$C$32:$L$32/(1+$C$14)^$C$32:$L$32)+($L$35+(0.01)*$L$33)*(1-$C$12)*(1+(0.02))^$L$32*(1+$C$15)*(1-$C$15/$C$18)/($C$14-$C$15)/(1+$C$14)^$L$32-$C$22-$C$23+$C$25)*$C$27/$C$26 -> 154.32774
B78: =$E$36+(0.02) -> 0.443 | C78: =(SUMPRODUCT((($C$35:$L$35+(0.02)*$C$33:$L$33)*(1-$C$12)+$C$38:$L$38-$C$39:$L$39-$C$40:$L$40)*(1+(-0.02))^$C$32:$L$32/(1+$C$14)^$C$32:$L$32)+($L$35+(0.02)*$L$33)*(1-$C$12)*(1+(-0.02))^$L$32*(1+$C$15)*(1-$C$15/$C$18)/($C$14-$C$15)/(1+$C$14)^$L$32-$C$22-$C$23+$C$25)*$C$27/$C$26 -> 115.53021 | D78: =(SUMPRODUCT((($C$35:$L$35+(0.02)*$C$33:$L$33)*(1-$C$12)+$C$38:$L$38-$C$39:$L$39-$C$40:$L$40)*(1+(-0.01))^$C$32:$L$32/(1+$C$14)^$C$32:$L$32)+($L$35+(0.02)*$L$33)*(1-$C$12)*(1+(-0.01))^$L$32*(1+$C$15)*(1-$C$15/$C$18)/($C$14-$C$15)/(1+$C$14)^$L$32-$C$22-$C$23+$C$25)*$C$27/$C$26 -> 124.92657 | E78: =(SUMPRODUCT((($C$35:$L$35+(0.02)*$C$33:$L$33)*(1-$C$12)+$C$38:$L$38-$C$39:$L$39-$C$40:$L$40)*(1+0)^$C$32:$L$32/(1+$C$14)^$C$32:$L$32)+($L$35+(0.02)*$L$33)*(1-$C$12)*(1+0)^$L$32*(1+$C$15)*(1-$C$15/$C$18)/($C$14-$C$15)/(1+$C$14)^$L$32-$C$22-$C$23+$C$25)*$C$27/$C$26 -> 135.10202 | F78: =(SUMPRODUCT((($C$35:$L$35+(0.02)*$C$33:$L$33)*(1-$C$12)+$C$38:$L$38-$C$39:$L$39-$C$40:$L$40)*(1+(0.01))^$C$32:$L$32/(1+$C$14)^$C$32:$L$32)+($L$35+(0.02)*$L$33)*(1-$C$12)*(1+(0.01))^$L$32*(1+$C$15)*(1-$C$15/$C$18)/($C$14-$C$15)/(1+$C$14)^$L$32-$C$22-$C$23+$C$25)*$C$27/$C$26 -> 146.11745 | G78: =(SUMPRODUCT((($C$35:$L$35+(0.02)*$C$33:$L$33)*(1-$C$12)+$C$38:$L$38-$C$39:$L$39-$C$40:$L$40)*(1+(0.02))^$C$32:$L$32/(1+$C$14)^$C$32:$L$32)+($L$35+(0.02)*$L$33)*(1-$C$12)*(1+(0.02))^$L$32*(1+$C$15)*(1-$C$15/$C$18)/($C$14-$C$15)/(1+$C$14)^$L$32-$C$22-$C$23+$C$25)*$C$27/$C$26 -> 158.03795
B79: 注1：営業利益率を全期間で一律加減し、売上を (1+Δg)^t 倍（償却・投資・運転資本も同率）とする近似。中央セルは厳密に理論株価

Sheet 計算_シナリオ
B1: 計算_シナリオ シナリオ別の並列計算（base / bull / bear）
B2: 0054 Forecast の計算（セグメント売上→営業利益→運転資本→償却ロール）を各シナリオの仮定で複製。選択中シナリオの FCF が 計算_DCF と一致することを検証シートで確認
B3: シナリオ別理論株価と確率加重期待値（ドル）
B4: シナリオ | C4: 確率 | D4: 理論株価
B5: base（ベース） | C5: 0.5 | D5: =$C$67 -> 128.72754
B6: bull（強気） | C6: 0.25 | D6: =$C$128 -> 173.24516
B7: bear（弱気） | C7: 0.25 | D7: =$C$189 -> 84.838548
B8: 確率加重期待値（各シナリオを0ドルで下限処理） | C8: =SUM(C5:C7) -> 1 | D8: =C5*MAX(0,D5)+C6*MAX(0,D6)+C7*MAX(0,D7) -> 128.8847
B9: 注1：確率加重は各シナリオを0ドルで下限処理（株主の有限責任）。上の理論株価は下限処理前の値
B13: シナリオ: base（ベース）
B14: 項目（0054 の計算を複製、百万ドル） | C14: 2026-12-31 E | D14: 2027-12-31 E | E14: 2028-12-31 E
B15: 全社成長率 | C15: ='3_Assumptions'!$N$6 -> 0.266 | D15: ='3_Assumptions'!$O$6 -> 0.07 | E15: ='3_Assumptions'!$P$6 -> 0.04
B16: 成長率加減：Analog | C16: ='3_Assumptions'!$N$7 -> 0.04 | D16: ='3_Assumptions'!$O$7 -> 0 | E16: ='3_Assumptions'!$P$7 -> 0
B17: 売上：Analog | C17: ='3_セグメント売上'!$H$6*(1+C15+C16) -> 18291.836 | D17: =C17*(1+D15+D16) -> 19572.265 | E17: =D17*(1+E15+E16) -> 20355.155
B18: 成長率加減：Embedded Processing | C18: ='3_Assumptions'!$N$8 -> -0.096 | D18: ='3_Assumptions'!$O$8 -> 0 | E18: ='3_Assumptions'!$P$8 -> 0
B19: 売上：Embedded Processing | C19: ='3_セグメント売上'!$H$7*(1+C15+C18) -> 3155.49 | D19: =C19*(1+D15+D18) -> 3376.3743 | E19: =D19*(1+E15+E18) -> 3511.4293
B20: 成長率加減：Other | C20: ='3_Assumptions'!$N$9 -> -0.306 | D20: ='3_Assumptions'!$O$9 -> 0 | E20: ='3_Assumptions'!$P$9 -> 0
B21: 売上：Other | C21: ='3_セグメント売上'!$H$8*(1+C15+C20) -> 939.84 | D21: =C21*(1+D15+D20) -> 1005.6288 | E21: =D21*(1+E15+E20) -> 1045.854
B22: 売上高 | C22: =C17+C19+C21 -> 22387.166 | D22: =D17+D19+D21 -> 23954.268 | E22: =E17+E19+E21 -> 24912.438
B23: 売上総利益率 | C23: ='3_Assumptions'!$N$10 -> 0.62 | D23: ='3_Assumptions'!$O$10 -> 0.63 | E23: ='3_Assumptions'!$P$10 -> 0.605
B24: 販管費率 | C24: ='3_Assumptions'!$N$11 -> 0.084 | D24: ='3_Assumptions'!$O$11 -> 0.082 | E24: ='3_Assumptions'!$P$11 -> 0.086
B25: 別建て研究開発費率 | C25: ='3_Assumptions'!$N$12 -> 0.096 | D25: ='3_Assumptions'!$O$12 -> 0.092 | E25: ='3_Assumptions'!$P$12 -> 0.096
B26: その他営業費用率 | C26: ='3_Assumptions'!$D$10 -> 0 | D26: ='3_Assumptions'!$E$10 -> 0 | E26: ='3_Assumptions'!$F$10 -> 0
B27: 営業利益 | C27: =C22*(C23-C24-C25-C26) -> 9850.353 | D27: =D22*(D23-D24-D25-D26) -> 10923.146 | E27: =E22*(E23-E24-E25-E26) -> 10537.961
B28: 売上原価 | C28: =C22*(1-C23) -> 8507.1231 | D28: =D22*(1-D23) -> 8863.079 | E28: =E22*(1-E23) -> 9840.4131
B29: 予測期間の日数 | C29: ='3_Forecast'!$I$6 -> 365 | D29: ='3_Forecast'!$J$6 -> 365 | E29: ='3_Forecast'!$K$6 -> 366
B30: 売上債権回収日数 | C30: ='3_Assumptions'!$D$14 -> 40.521151 | D30: ='3_Assumptions'!$E$14 -> 40.521151 | E30: ='3_Assumptions'!$F$14 -> 40.521151
B31: 棚卸資産回転日数 | C31: ='3_Assumptions'!$N$14 -> 200 | D31: ='3_Assumptions'!$O$14 -> 200 | E31: ='3_Assumptions'!$P$14 -> 200
B32: 仕入債務支払日数 | C32: ='3_Assumptions'!$D$16 -> 36.312673 | D32: ='3_Assumptions'!$E$16 -> 36.312673 | E32: ='3_Assumptions'!$F$16 -> 36.312673
B33: 売上債権 | C33: =C22/C29*C30 -> 2485.3527 | D33: =D22/D29*D30 -> 2659.3274 | E33: =E22/E29*E30 -> 2758.144
B34: 棚卸資産 | C34: =C28/C29*C31 -> 4661.4373 | D34: =D28/D29*D31 -> 4856.4817 | E34: =E28/E29*E31 -> 5377.2749
B35: 仕入債務 | C35: =C28/C29*C32 -> 846.34624 | D35: =D28/D29*D32 -> 881.75914 | E35: =E28/E29*E32 -> 976.31612
B36: 運転資本（AR＋在庫−AP） | C36: =C33+C34-C35 -> 6300.4438 | D36: =D33+D34-D35 -> 6634.0499 | E36: =E33+E34-E35 -> 7159.1028
B37: 運転資本増加 | C37: =C36-('3_Forecast'!$H$24+'3_Forecast'!$H$25-'3_Forecast'!$H$26) -> 289.44379 | D37: =D36-C36 -> 333.60613 | E37: =E36-D36 -> 525.05284
B38: 期首有形・無形資産 | C38: ='3_Forecast'!$H$33+'3_Forecast'!$H$34 -> 12558 | D38: =C43 -> 13357.396 | E38: =D43 -> 13626.574
B39: 期首償却対象資産の償却率 | C39: ='3_Assumptions'!$D$18 -> 0.1591814 | D39: ='3_Assumptions'!$E$18 -> 0.1591814 | E39: ='3_Assumptions'!$F$18 -> 0.1591814
B40: 減価償却・償却費 | C40: =MIN(C38,C38*C39) -> 1999 | D40: =MIN(D38,D38*D39) -> 2126.2489 | E40: =MIN(E38,E38*E39) -> 2169.097
B41: 有形・無形の現金投資／売上 | C41: ='3_Assumptions'!$N$15 -> 0.125 | D41: ='3_Assumptions'!$O$15 -> 0.1 | E41: ='3_Assumptions'!$P$15 -> 0.09
B42: 有形・無形の現金投資 | C42: =C22*C41 -> 2798.3958 | D42: =D22*D41 -> 2395.4268 | E42: =E22*E41 -> 2242.1194
B43: 期末有形・無形資産 | C43: =C38+C42-C40 -> 13357.396 | D43: =D38+D42-D40 -> 13626.574 | E43: =E38+E42-E40 -> 13699.596
B45: DCF（base） | C45: 2026-12-31 E | D45: 2027-12-31 E | E45: 2028-12-31 E | F45: 延長+1 | G45: 延長+2 | H45: 延長+3 | I45: 延長+4 | J45: 延長+5 | K45: 延長+6 | L45: 延長+7 | M45: ターミナル
B46: 期（年） | C46: 1 | D46: 2 | E46: 3 | F46: 4 | G46: 5 | H46: 6 | I46: 7 | J46: 8 | K46: 9 | L46: 10 | M46: バリュードライバー式
B47: 売上高 | C47: =C22 -> 22387.166 | D47: =D22 -> 23954.268 | E47: =E22 -> 24912.438 | F47: =E47*(1+F48) -> 25891.141 | G47: =F47*(1+G48) -> 26889.8 | H47: =G47*(1+H48) -> 27907.771 | I47: =H47*(1+I48) -> 28944.345 | J47: =I47*(1+J48) -> 29998.746 | K47: =J47*(1+K48) -> 31070.13 | L47: =K47*(1+L48) -> 32157.584
B48: 売上成長率 | C48: =C47/'3_Forecast'!$H$8-1 -> 0.2660992 | D48: =D47/C47-1 -> 0.07 | E48: =E47/D47-1 -> 0.04 | F48: =$E$48+(計算_DCF!$C$15-$E$48)*(F46-3)/計算_DCF!$C$16 -> 0.039285714 | G48: =$E$48+(計算_DCF!$C$15-$E$48)*(G46-3)/計算_DCF!$C$16 -> 0.038571429 | H48: =$E$48+(計算_DCF!$C$15-$E$48)*(H46-3)/計算_DCF!$C$16 -> 0.037857143 | I48: =$E$48+(計算_DCF!$C$15-$E$48)*(I46-3)/計算_DCF!$C$16 -> 0.037142857 | J48: =$E$48+(計算_DCF!$C$15-$E$48)*(J46-3)/計算_DCF!$C$16 -> 0.036428571 | K48: =$E$48+(計算_DCF!$C$15-$E$48)*(K46-3)/計算_DCF!$C$16 -> 0.035714286 | L48: =$E$48+(計算_DCF!$C$15-$E$48)*(L46-3)/計算_DCF!$C$16 -> 0.035
B49: 営業利益 | C49: =C27 -> 9850.353 | D49: =D27 -> 10923.146 | E49: =E27 -> 10537.961 | F49: =F47*$E$50 -> 10951.953 | G49: =G47*$E$50 -> 11374.385 | H49: =H47*$E$50 -> 11804.987 | I49: =I47*$E$50 -> 12243.458 | J49: =J47*$E$50 -> 12689.47 | K49: =K47*$E$50 -> 13142.665 | L49: =L47*$E$50 -> 13602.658
B50: 営業利益率 | C50: =C49/C47 -> 0.44 | D50: =D49/D47 -> 0.456 | E50: =E49/E47 -> 0.423 | F50: =F49/F47 -> 0.423 | G50: =G49/G47 -> 0.423 | H50: =H49/H47 -> 0.423 | I50: =I49/I47 -> 0.423 | J50: =J49/J47 -> 0.423 | ... L50: =L49/L47 -> 0.423
B51: NOPAT（営業利益×(1−税率)） | C51: =C49*(1-計算_DCF!$C$12) -> 8520.5554 | D51: =D49*(1-計算_DCF!$C$12) -> 9448.5213 | E51: =E49*(1-計算_DCF!$C$12) -> 9115.3366 | F51: =F49*(1-計算_DCF!$C$12) -> 9473.4391 | G51: =G49*(1-計算_DCF!$C$12) -> 9838.8432 | H51: =H49*(1-計算_DCF!$C$12) -> 10211.314 | I51: =I49*(1-計算_DCF!$C$12) -> 10590.591 | J51: =J49*(1-計算_DCF!$C$12) -> 10976.391 | ... L51: =L49*(1-計算_DCF!$C$12) -> 11766.299
B52: 減価償却・償却費 | C52: =C40 -> 1999 | D52: =D40 -> 2126.2489 | E52: =E40 -> 2169.097 | F52: =F47*$E$52/$E$47 -> 2254.3116 | G52: =G47*$E$52/$E$47 -> 2341.2636 | H52: =H47*$E$52/$E$47 -> 2429.8971 | I52: =I47*$E$52/$E$47 -> 2520.1505 | J52: =J47*$E$52/$E$47 -> 2611.9559 | K52: =K47*$E$52/$E$47 -> 2705.2401 | L52: =L47*$E$52/$E$47 -> 2799.9235
B53: 設備投資（有形・無形の現金投資） | C53: =C42 -> 2798.3958 | D53: =D42 -> 2395.4268 | E53: =E42 -> 2242.1194 | F53: =F47*($E$53/$E$47+($E$52/$E$47-$E$53/$E$47)*(F46-3)/計算_DCF!$C$16) -> 2319.3611 | G53: =G47*($E$53/$E$47+($E$52/$E$47-$E$53/$E$47)*(G46-3)/計算_DCF!$C$16) -> 2397.5624 | H53: =H47*($E$53/$E$47+($E$52/$E$47-$E$53/$E$47)*(H46-3)/計算_DCF!$C$16) -> 2476.6413 | I53: =I47*($E$53/$E$47+($E$52/$E$47-$E$53/$E$47)*(I46-3)/計算_DCF!$C$16) -> 2556.5107 | J53: =J47*($E$53/$E$47+($E$52/$E$47-$E$53/$E$47)*(J46-3)/計算_DCF!$C$16) -> 2637.0791 | K53: =K47*($E$53/$E$47+($E$52/$E$47-$E$53/$E$47)*(K46-3)/計算_DCF!$C$16) -> 2718.2503 | L53: =L47*($E$53/$E$47+($E$52/$E$47-$E$53/$E$47)*(L46-3)/計算_DCF!$C$16) -> 2799.9235
B54: 運転資本増加 | C54: =C37 -> 289.44379 | D54: =D37 -> 333.60613 | E54: =E37 -> 525.05284 | F54: =$C$71*(F47-E47) -> 281.25047 | G54: =$C$71*(G47-F47) -> 286.98505 | H54: =$C$71*(H47-G47) -> 292.53495 | I54: =$C$71*(I47-H47) -> 297.88101 | J54: =$C$71*(J47-I47) -> 303.0039 | K54: =$C$71*(K47-J47) -> 307.88422 | L54: =$C$71*(L47-K47) -> 312.50248
B55: FCF（NOPAT＋償却−投資−運転資本増加） | C55: =C51+C52-C53-C54 -> 7431.7158 | D55: =D51+D52-D53-D54 -> 8845.7374 | E55: =E51+E52-E53-E54 -> 8517.2614 | F55: =F51+F52-F53-F54 -> 9127.1391 | G55: =G51+G52-G53-G54 -> 9495.5593 | H55: =H51+H52-H53-H54 -> 9872.0346 | I55: =I51+I52-I53-I54 -> 10256.35 | J55: =J51+J52-J53-J54 -> 10648.264 | ... L55: =L51+L52-L53-L54 -> 11453.797 | M55: =L51*(1+計算_DCF!$C$15)*(1-計算_DCF!$C$15/計算_DCF!$C$18)/(計算_DCF!$C$14-計算_DCF!$C$15) -> 159700.35
B56: 割引係数 1/(1+WACC)^t | C56: =1/(1+計算_DCF!$C$14)^C46 -> 0.91082043 | D56: =1/(1+計算_DCF!$C$14)^D46 -> 0.82959386 | E56: =1/(1+計算_DCF!$C$14)^E46 -> 0.75561104 | F56: =1/(1+計算_DCF!$C$14)^F46 -> 0.68822597 | G56: =1/(1+計算_DCF!$C$14)^G46 -> 0.62685028 | H56: =1/(1+計算_DCF!$C$14)^H46 -> 0.57094804 | I56: =1/(1+計算_DCF!$C$14)^I46 -> 0.52003114 | J56: =1/(1+計算_DCF!$C$14)^J46 -> 0.47365499 | ... L56: =1/(1+計算_DCF!$C$14)^L46 -> 0.39294127 | M56: =L56 -> 0.39294127
B57: FCF 現在価値 | C57: =C55*C56 -> 6768.9586 | D57: =D55*D56 -> 7338.3694 | E57: =E55*E56 -> 6435.7367 | F57: =F55*F56 -> 6281.5342 | G57: =G55*G56 -> 5952.294 | H57: =H55*H56 -> 5636.4189 | I57: =I55*I56 -> 5333.6213 | J57: =J55*J56 -> 5043.6034 | ... M57: =M55*M56 -> 62752.86
B59: 予測・延長期間 FCF 現在価値合計 | C59: =SUM(C57:L57) -> 58057.264
B60: ターミナル価値 現在価値 | C60: =M57 -> 62752.86
B61: 事業価値（EV） | C61: =C59+C60 -> 120810.12
B62: （−）純有利子負債 | C62: =計算_DCF!$C$22 -> 5413
B63: （−）非支配持分 | C63: =計算_DCF!$C$23 -> 0
B64: （＋）持分法投資等 | C64: =計算_DCF!$C$25 -> 2163
B65: 株式価値 | C65: =C61-C62-C63+C64 -> 117560.12
B66: 発行済株式数（自己株除く、株） | C66: =計算_DCF!$C$26 -> 913247686
B67: 理論株価（ドル） | C67: =C65*計算_DCF!$C$27/C66 -> 128.72754
B68: ターミナル価値 / EV | C68: =C60/C61 -> 0.51943379
B69: ターミナル価値 現在価値 / 株式価値 | C69: =IF(C65>0,C60/C65,"n.a.（株式価値≦0）") -> 0.53379376
B70: EV が 1% 動いたときの理論株価の変化（%）＝EV/株式価値 | C70: =IF(C65>0,C61/C65,"n.a.（株式価値≦0）") -> 1.0276454
B71: 運転資本 / 売上（3期目、延長期間で固定） | C71: =(E36)/$E$47 -> 0.28737062
B74: シナリオ: bull（強気）
B75: 項目（0054 の計算を複製、百万ドル） | C75: 2026-12-31 E | D75: 2027-12-31 E | E75: 2028-12-31 E
B76: 全社成長率 | C76: ='3_Assumptions'!$Q$6 -> 0.266 | D76: ='3_Assumptions'!$R$6 -> 0.16 | E76: ='3_Assumptions'!$S$6 -> 0.08
B77: 成長率加減：Analog | C77: ='3_Assumptions'!$Q$7 -> 0.04 | D77: ='3_Assumptions'!$R$7 -> 0 | E77: ='3_Assumptions'!$S$7 -> 0
B78: 売上：Analog | C78: ='3_セグメント売上'!$H$6*(1+C76+C77) -> 18291.836 | D78: =C78*(1+D76+D77) -> 21218.53 | E78: =D78*(1+E76+E77) -> 22916.012
B79: 成長率加減：Embedded Processing | C79: ='3_Assumptions'!$Q$8 -> -0.096 | D79: ='3_Assumptions'!$R$8 -> 0 | E79: ='3_Assumptions'!$S$8 -> 0
B80: 売上：Embedded Processing | C80: ='3_セグメント売上'!$H$7*(1+C76+C79) -> 3155.49 | D80: =C80*(1+D76+D79) -> 3660.3684 | E80: =D80*(1+E76+E79) -> 3953.1979
B81: 成長率加減：Other | C81: ='3_Assumptions'!$Q$9 -> -0.306 | D81: ='3_Assumptions'!$R$9 -> 0 | E81: ='3_Assumptions'!$S$9 -> 0
B82: 売上：Other | C82: ='3_セグメント売上'!$H$8*(1+C76+C81) -> 939.84 | D82: =C82*(1+D76+D81) -> 1090.2144 | E82: =D82*(1+E76+E81) -> 1177.4316
B83: 売上高 | C83: =C78+C80+C82 -> 22387.166 | D83: =D78+D80+D82 -> 25969.113 | E83: =E78+E80+E82 -> 28046.642
B84: 売上総利益率 | C84: ='3_Assumptions'!$Q$10 -> 0.62 | D84: ='3_Assumptions'!$R$10 -> 0.65 | E84: ='3_Assumptions'!$S$10 -> 0.635
B85: 販管費率 | C85: ='3_Assumptions'!$Q$11 -> 0.084 | D85: ='3_Assumptions'!$R$11 -> 0.079 | E85: ='3_Assumptions'!$S$11 -> 0.078
B86: 別建て研究開発費率 | C86: ='3_Assumptions'!$Q$12 -> 0.096 | D86: ='3_Assumptions'!$R$12 -> 0.088 | E86: ='3_Assumptions'!$S$12 -> 0.086
B87: その他営業費用率 | C87: ='3_Assumptions'!$D$10 -> 0 | D87: ='3_Assumptions'!$E$10 -> 0 | E87: ='3_Assumptions'!$F$10 -> 0
B88: 営業利益 | C88: =C83*(C84-C85-C86-C87) -> 9850.353 | D88: =D83*(D84-D85-D86-D87) -> 12543.081 | E88: =E83*(E84-E85-E86-E87) -> 13209.968
B89: 売上原価 | C89: =C83*(1-C84) -> 8507.1231 | D89: =D83*(1-D84) -> 9089.1894 | E89: =E83*(1-E84) -> 10237.024
B90: 予測期間の日数 | C90: ='3_Forecast'!$I$6 -> 365 | D90: ='3_Forecast'!$J$6 -> 365 | E90: ='3_Forecast'!$K$6 -> 366
B91: 売上債権回収日数 | C91: ='3_Assumptions'!$D$14 -> 40.521151 | D91: ='3_Assumptions'!$E$14 -> 40.521151 | E91: ='3_Assumptions'!$F$14 -> 40.521151
B92: 棚卸資産回転日数 | C92: ='3_Assumptions'!$Q$14 -> 200 | D92: ='3_Assumptions'!$R$14 -> 190 | E92: ='3_Assumptions'!$S$14 -> 190
B93: 仕入債務支払日数 | C93: ='3_Assumptions'!$D$16 -> 36.312673 | D93: ='3_Assumptions'!$E$16 -> 36.312673 | E93: ='3_Assumptions'!$F$16 -> 36.312673
B94: 売上債権 | C94: =C83/C90*C91 -> 2485.3527 | D94: =D83/D90*D91 -> 2883.0092 | E94: =E83/E90*E91 -> 3105.1427
B95: 棚卸資産 | C95: =C89/C90*C92 -> 4661.4373 | D95: =D89/D90*D92 -> 4731.3589 | E95: =E89/E90*E92 -> 5314.3022
B96: 仕入債務 | C96: =C89/C90*C93 -> 846.34624 | D96: =D89/D90*D93 -> 904.25414 | E96: =E89/E90*E93 -> 1015.6659
B97: 運転資本（AR＋在庫−AP） | C97: =C94+C95-C96 -> 6300.4438 | D97: =D94+D95-D96 -> 6710.1139 | E97: =E94+E95-E96 -> 7403.7789
B98: 運転資本増加 | C98: =C97-('3_Forecast'!$H$24+'3_Forecast'!$H$25-'3_Forecast'!$H$26) -> 289.44379 | D98: =D97-C97 -> 409.67009 | E98: =E97-D97 -> 693.66506
B99: 期首有形・無形資産 | C99: ='3_Forecast'!$H$33+'3_Forecast'!$H$34 -> 12558 | D99: =C104 -> 13357.396 | E99: =D104 -> 13828.058
B100: 期首償却対象資産の償却率 | C100: ='3_Assumptions'!$D$18 -> 0.1591814 | D100: ='3_Assumptions'!$E$18 -> 0.1591814 | E100: ='3_Assumptions'!$F$18 -> 0.1591814
B101: 減価償却・償却費 | C101: =MIN(C99,C99*C100) -> 1999 | D101: =MIN(D99,D99*D100) -> 2126.2489 | E101: =MIN(E99,E99*E100) -> 2201.1696
B102: 有形・無形の現金投資／売上 | C102: ='3_Assumptions'!$Q$15 -> 0.125 | D102: ='3_Assumptions'!$R$15 -> 0.1 | E102: ='3_Assumptions'!$S$15 -> 0.09
B103: 有形・無形の現金投資 | C103: =C83*C102 -> 2798.3958 | D103: =D83*D102 -> 2596.9113 | E103: =E83*E102 -> 2524.1977
B104: 期末有形・無形資産 | C104: =C99+C103-C101 -> 13357.396 | D104: =D99+D103-D101 -> 13828.058 | E104: =E99+E103-E101 -> 14151.086
B106: DCF（bull） | C106: 2026-12-31 E | D106: 2027-12-31 E | E106: 2028-12-31 E | F106: 延長+1 | G106: 延長+2 | H106: 延長+3 | I106: 延長+4 | J106: 延長+5 | K106: 延長+6 | L106: 延長+7 | M106: ターミナル
B107: 期（年） | C107: 1 | D107: 2 | E107: 3 | F107: 4 | G107: 5 | H107: 6 | I107: 7 | J107: 8 | K107: 9 | L107: 10 | M107: バリュードライバー式
B108: 売上高 | C108: =C83 -> 22387.166 | D108: =D83 -> 25969.113 | E108: =E83 -> 28046.642 | F108: =E108*(1+F109) -> 30110.073 | G108: =F108*(1+G109) -> 32131.749 | H108: =G108*(1+H109) -> 34082.606 | I108: =H108*(1+I109) -> 35932.804 | J108: =I108*(1+J109) -> 37652.446 | K108: =J108*(1+K109) -> 39212.333 | L108: =K108*(1+L109) -> 40584.764
...

Sheet データ_株価
B1: データ_株価（market.json）
B2: 出所：株価・出来高・S&P500 は Yahoo Finance（yfinance 1.4.1、auto_adjust=False）、財務は SEC EDGAR companyfacts（XBRL）と 8-K 決算リリース（EX-99）、為替は FRED DEXJPUS。取得日 2026-10-23。【通貨】金額は米ドル（USD、1ドル単位）。株価はドル。adv60_jpy のみ円（DEXJPUS で換算）。【PIT】月末tの EPS・BPS・純有利子負債・EBITDA は、提出日（filed）の翌日<=t のファクトのみから作成（決算期末日基準の先取りなし）。同一期間が複数回提出された場合は t 時点で最新の提出値。8-K EX-99 の値も提出日の翌日から使用。【eps_actual_ttm】希薄化後 EPS の直近 4 四半期合計（3か月値が無い期は同一期首の累計差。Q4＝通期−9か月累計）。【会社予想】米国企業は通期の会社予想 EPS・配当を開示しないため eps_forecast・per_forecast・dps_forecast は null（アナリスト予想は使わない）。PER は実績 TTM（per_actual）。【div_yield】宣言配当/株の直近 4 四半期合計÷株価（実績 TTM。予想ではない）。【bps】株主資本（StockholdersEquity、親会社持分）÷発行済株式数（dei:EntityCommonStockSharesOutstanding、表紙記載日時点。米国開示の発行済は自己株控除後の流通株式）。【mcap】株価×同株式数。treasury_shares は null（控除済みのため）。【price】close は yfinance の分割調整済み終値（配当未調整）、adj_close は配当も調整。【ev_ebitda】EV＝時価総額＋有利子負債（長期債務の固定＋1年内返済、短期借入/CP があれば加算）−現金同等物−短期投資、EBITDA＝営業利益 TTM＋減価償却 TTM（XBRL タグは DepreciationDepletionAndAmortization→DepreciationAndAmortization→Depreciation の順で最初に TTM が組めたもの。対象の採用タグ: Depreciation）。リース負債・非支配持分・持分法投資は加減しない。【adv60】直近 60 営業日の close×volume の平均（ドル。取引所公表の売買代金ではなく近似）。adv60_jpy＝adv60×DEXJPUS（158.0 円/ドル、2026-10-16）。【peers】同定義で最新営業日の値（最新 10-Q/10-K の後に決算 8-K があれば EX-99 で補完）。roe＝純利益 TTM／株主資本（期末と 1 年前の平均、無ければ期末）、op_margin＝営業利益 TTM／売上 TTM、sales_growth＝売上 TTM の前年比。 【取れなかった項目/注意】TXN: 2026-10-23 は取引時間中の未確定バーのため除外 / ^GSPC: 2026-10-23 は取引時間中の未確定バーのため除外 / 8-K EX-99（0000097476-26-000165、提出 2026-10-21、有効 翌日）で 2026-09-30 期の値を補完: rev,op,ni,eps,dps,da_dep,cash,sti,debt_cur,debt_nc,equity／未検出 stb / ADI: 2026-10-23 は取引時間中の未確定バーのため除外 / MCHP: 2026-10-23 は取引時間中の未確定バーのため除外 / NXPI: 2026-10-23 は取引時間中の未確定バーのため除外 / peer NXPI: companyfacts 未反映の定期報告あり [('10-Q', '2026-07-28')]（XBRL API の反映遅れ） / 8-K EX-99: 期末表記 June 28 が想定 June 30 と不一致のため補完しない（52/53週決算等） / ON: 2026-10-23 は取引時間中の未確定バーのため除外 / peer ON: null=div_yield / STM: 2026-10-23 は取引時間中の未確定バーのため除外 / peer STM: null=per_actual,roe,op_margin,sales_growth,ev_ebitda（20-F 提出の外国企業（us-gaap）: companyfacts は年次のみ・四半期は 6-K で XBRL 無し → TTM 不可。年次値での代替はしていない） / MPWR: 2026-10-23 は取引時間中の未確定バーのため除外 / peer MPWR: null=ev_ebitda（有利子負債タグなし: 負債タグなし。無借金でも 0 と推定せず null）
B4: スナップショット | C4: 値 | D4: 単位 | F4: 月 | G4: 終値 | H4: 終値（調整後） | I4: S&P500 | J4: 対S&P500相対（期初=100） | L4: 月 | M4: PER（予想） | N4: PER（実績） | O4: PBR | P4: 配当利回り | Q4: EV/EBITDA | R4: 株価 | T4: 日付 | U4: 終値 | V4: 終値（調整後） | W4: 出来高 | X4: S&P500
B5: 基準日 | C5: 2026-10-22 | F5: 2021-10 | G5: 187.48 | H5: 163.7214 | I5: 4605.3799 | J5: 100 | L5: 2021-10 | N5: 24.066752 | O5: 14.249252 | P5: 0.021762322 | Q5: 19.000517 | R5: 187.48 | T5: 2021-10-25 | U5: 200.2 | V5: 173.75932 | W5: 4254900 | X5: 4566.48
B6: 株価（終値） | C6: 279.5 | D6: ドル | F6: 2021-11 | G6: 192.37 | H6: 167.9917 | I6: 4567 | J6: 103.4706 | L6: 2021-11 | N6: 24.694479 | O6: 14.620912 | P6: 0.021209129 | Q6: 19.502021 | R6: 192.37 | T6: 2021-10-26 | U6: 196.98 | V6: 170.96461 | W6: 5837500 | X6: 4574.79
B7: 発行済株式数（自己株控除後） | C7: 913247686 | D7: 株 | F7: 2021-12 | G7: 188.47 | H7: 164.586 | I7: 4766.1802 | J7: 97.1365 | L7: 2021-12 | N7: 24.193838 | O7: 14.324496 | P7: 0.021648008 | Q7: 19.102049 | R7: 188.47 | T7: 2021-10-27 | U7: 187.10001 | V7: 162.38945 | W7: 10365500 | X7: 4551.6802
B8: 自己株式数 | C8: n.a. | D8: 株 | F8: 2022-01 | G8: 179.49 | H8: 157.782 | I8: 4515.5498 | J8: 98.2894 | L8: 2022-01 | N8: 23.041079 | O8: 13.64198 | P8: 0.022731071 | Q8: 18.181088 | R8: 179.49001 | T8: 2021-10-28 | U8: 187.87 | V8: 163.05775 | W8: 5123000 | X8: 4596.4199
B9: 時価総額 | C9: 255252728237 | D9: ドル | F9: 2022-02 | G9: 169.99 | H9: 149.4309 | I9: 4373.9399 | J9: 96.101 | L9: 2022-02 | N9: 20.579904 | O9: 11.774827 | P9: 0.024766162 | Q9: 15.954274 | R9: 169.99001 | T9: 2021-10-29 | U9: 187.48 | V9: 163.72139 | W9: 4552200 | X9: 4605.3799
B10: 売買代金 60日平均 | C10: 1.6762836e+09 | D10: ドル | F10: 2022-03 | G10: 183.48 | H10: 161.2894 | I10: 4530.4102 | J10: 100.1448 | L10: 2022-03 | N10: 22.213075 | O10: 12.709249 | P10: 0.022945281 | Q10: 17.236687 | R10: 183.48 | T10: 2021-11-01 | U10: 187.47 | V10: 163.71272 | W10: 4203900 | X10: 4613.6699
B11: 売買代金 60日平均（円換算 158.0円/ドル、2026-10-16） | C11: 2.648528e+11 | D11: 円（換算） | F11: 2022-04 | G11: 170.25 | H11: 149.6595 | I11: 4131.9302 | J11: 101.8852 | L11: 2022-04 | N11: 19.479405 | O11: 11.200206 | P11: 0.025491924 | Q11: 14.95273 | R11: 170.25 | T11: 2021-11-02 | U11: 189.34 | V11: 165.34575 | W11: 4009600 | X11: 4630.6499
B12: 純有利子負債 | C12: 5413000000 | D12: ドル | F12: 2022-05 | G12: 176.76 | H12: 156.4387 | I12: 4132.1499 | J12: 106.4947 | L12: 2022-05 | N12: 20.224256 | O12: 11.628478 | P12: 0.024553067 | Q12: 15.532179 | R12: 176.75999 | T12: 2021-11-03 | U12: 189.19 | V12: 165.21471 | W12: 3666900 | X12: 4660.5698
B13: PER（予想） | C13: n.a. | D13: 倍 | F13: 2022-06 | G13: 153.65 | H13: 135.9855 | I13: 3785.3799 | J13: 101.0516 | L13: 2022-06 | N13: 17.580091 | O13: 10.108144 | P13: 0.028246015 | Q13: 13.47518 | R13: 153.64999 | T13: 2021-11-04 | U13: 191.11 | V13: 166.89142 | W13: 4828000 | X13: 4680.0601
B14: PER（実績TTM） | C14: 36.251621 | D14: 倍 | F14: 2022-07 | G14: 178.89 | H14: 159.3666 | I14: 4130.29 | J14: 108.5367 | L14: 2022-07 | N14: 19.57221 | O14: 11.599 | P14: 0.024987423 | Q14: 14.873097 | R14: 178.89 | T14: 2021-11-05 | U14: 193.39999 | V14: 168.89122 | W14: 4510500 | X14: 4697.5298
B15: PBR | C15: 13.304807 | D15: 倍 | F15: 2022-08 | G15: 165.21 | H15: 147.1796 | I15: 3955 | J15: 104.6794 | L15: 2022-08 | N15: 18.075493 | O15: 10.712007 | P15: 0.027056472 | Q15: 13.727719 | R15: 165.21001 | T15: 2021-11-08 | U15: 192.36 | V15: 167.98303 | W15: 5213900 | X15: 4701.7002
B16: 配当利回り（実績TTM） | C16: 0.020322004 | F16: 2022-09 | G16: 154.78 | H16: 137.8878 | I16: 3585.6201 | J16: 108.1737 | L16: 2022-09 | N16: 16.934354 | O16: 10.035738 | P16: 0.0288797 | Q16: 12.854451 | R16: 154.78 | T16: 2021-11-09 | U16: 190.78999 | V16: 166.612 | W16: 4314700 | X16: 4685.25
B17: EV/EBITDA | C17: 24.487152 | D17: 倍 | F17: 2022-10 | G17: 160.63 | H17: 144.2404 | I17: 3871.98 | J17: 104.7885 | L17: 2022-10 | N17: 16.837527 | O17: 10.049166 | P17: 0.02863724 | Q17: 12.750617 | R17: 160.63 | T17: 2021-11-10 | U17: 187.02 | V17: 163.31975 | W17: 4304600 | X17: 4646.71
F18: 2022-11 | G18: 180.46 | H18: 162.047 | I18: 4080.1101 | J18: 111.7196 | L18: 2022-11 | N18: 18.916143 | O18: 11.28975 | P18: 0.025490412 | Q18: 14.337247 | R18: 180.46001 | T18: 2021-11-11 | U18: 188.60001 | V18: 164.69949 | W18: 2554800 | X18: 4649.27
B19: 発行済株式数は米国開示の outstanding（自己株控除後の流通株式）。自己株式数は控除済みのため空欄 | F19: 2022-12 | G19: 165.22 | H19: 148.362 | I19: 3839.5 | J19: 108.6947 | L19: 2022-12 | N19: 17.318658 | O19: 10.33632 | P19: 0.027841665 | Q19: 13.11787 | R19: 165.22 | T19: 2021-11-12 | U19: 190.08 | V19: 165.99196 | W19: 3121700 | X19: 4682.8501
F20: 2023-01 | G20: 177.21 | H20: 160.2627 | I20: 4076.6001 | J20: 110.5845 | L20: 2023-01 | N20: 18.575472 | O20: 11.086426 | P20: 0.025957902 | Q20: 14.07721 | R20: 177.21001 | T20: 2021-11-15 | U20: 189.23 | V20: 165.24963 | W20: 2985200 | X20: 4682.7998
F21: 2023-02 | G21: 171.45 | H21: 155.0536 | I21: 3970.1499 | J21: 109.8588 | L21: 2023-02 | N21: 18.219978 | O21: 10.658502 | P21: 0.027354914 | Q21: 14.011476 | R21: 171.45 | T21: 2021-11-16 | U21: 188.52 | V21: 164.62968 | W21: 3312000 | X21: 4700.8999
F22: 2023-03 | G22: 186.01 | H22: 168.2211 | I22: 4109.3101 | J22: 115.152 | L22: 2023-03 | N22: 19.767268 | O22: 11.563651 | P22: 0.025213699 | Q22: 15.203916 | R22: 186.00999 | T22: 2021-11-17 | U22: 189.57001 | V22: 165.5466 | W22: 4167800 | X22: 4688.6699
F23: 2023-04 | G23: 167.2 | H23: 151.21 | I23: 4169.48 | J23: 102.0137 | L23: 2023-04 | N23: 18.765432 | O23: 9.9560272 | P23: 0.028588517 | Q23: 14.507259 | R23: 167.2 | T23: 2021-11-18 | U23: 193.47 | V23: 168.95238 | W23: 4677300 | X23: 4704.54
F24: 2023-05 | G24: 173.88 | H24: 158.4618 | I24: 4179.8301 | J24: 106.6415 | L24: 2023-05 | N24: 19.515152 | O24: 10.353792 | P24: 0.027490222 | Q24: 15.084645 | R24: 173.88 | T24: 2021-11-19 | U24: 195.16 | V24: 170.42819 | W24: 5129100 | X24: 4697.96
F25: 2023-06 | G25: 180.02 | H25: 164.0574 | I25: 4450.3799 | J25: 103.6952 | L25: 2023-06 | N25: 20.204265 | O25: 10.719402 | P25: 0.026552605 | Q25: 15.615356 | R25: 180.02 | T25: 2021-11-22 | U25: 192.5 | V25: 168.10527 | W25: 4712300 | X25: 4682.9399
F26: 2023-07 | G26: 180 | H26: 165.1917 | I26: 4588.96 | J26: 101.2591 | L26: 2023-07 | N26: 21.608643 | O26: 10.25307 | P26: 0.027055556 | Q26: 16.833293 | R26: 180 | T26: 2021-11-23 | U26: 192.64 | V26: 168.22758 | W26: 4881400 | X26: 4690.7002
F27: 2023-08 | G27: 168.06 | H27: 154.234 | I27: 4507.6602 | J27: 96.2474 | L27: 2023-08 | N27: 20.17527 | O27: 9.5729497 | P27: 0.028977746 | Q27: 15.727959 | R27: 168.06 | T27: 2021-11-24 | U27: 193.60001 | V27: 169.06587 | W27: 6494000 | X27: 4701.46
F28: 2023-09 | G28: 159.01 | H28: 145.9285 | I28: 4288.0498 | J28: 95.7283 | L28: 2023-09 | N28: 19.088835 | O28: 9.057448 | P28: 0.030627006 | Q28: 14.890163 | R28: 159.00999 | T28: 2021-11-26 | U28: 188.25999 | V28: 164.40259 | W28: 3324900 | X28: 4594.6201
F29: 2023-10 | G29: 142.01 | H29: 131.5218 | I29: 4193.7998 | J29: 88.2165 | L29: 2023-10 | N29: 18.418936 | O29: 7.7550393 | P29: 0.034927119 | Q29: 14.461002 | R29: 142.00999 | T29: 2021-11-29 | U29: 194.38 | V29: 169.74704 | W29: 4576200 | X29: 4655.27
F30: 2023-11 | G30: 152.71 | H30: 141.4315 | I30: 4567.7998 | J30: 87.0962 | L30: 2023-11 | N30: 19.806745 | O30: 8.3393574 | P30: 0.032479862 | Q30: 15.531716 | R30: 152.71001 | T30: 2021-11-30 | U30: 192.37 | V30: 167.99174 | W30: 8775600 | X30: 4567
F31: 2023-12 | G31: 170.46 | H31: 157.8706 | I31: 4769.8301 | J31: 93.1018 | L31: 2023-12 | N31: 22.10895 | O31: 9.3086691 | P31: 0.029097734 | Q31: 17.307897 | R31: 170.46001 | T31: 2021-12-01 | U31: 191.75999 | V31: 167.45908 | W31: 7279100 | X31: 4513.04
... F65: 2026-10 | G65: 279.5 | H65: 279.5 | I65: 7663.4302 | J65: 102.5932 | L65: 2026-10 | N65: 36.251621 | O65: 13.304807 | P65: 0.020322004 | Q65: 24.487152 | R65: 279.5 | T65: 2022-01-20 | U65: 173.45 | V65: 151.46941 | W65: 6057800 | X65: 4482.73
T66: 2022-01-21 | U66: 175.64 | V66: 153.38187 | W66: 11527900 | X66: 4397.9399
T67: 2022-01-24 | U67: 178.34 | V67: 155.73972 | W67: 11717600 | X67: 4410.1299
T68: 2022-01-25 | U68: 173.96001 | V68: 151.91478 | W68: 8157600 | X68: 4356.4502
T69: 2022-01-26 | U69: 178.33 | V69: 155.73097 | W69: 12852700 | X69: 4349.9302
T70: 2022-01-27 | U70: 174.81 | V70: 152.65706 | W70: 6752900 | X70: 4326.5098
T71: 2022-01-28 | U71: 177.28999 | V71: 155.84802 | W71: 7322100 | X71: 4431.8501
T72: 2022-01-31 | U72: 179.49001 | V72: 157.78198 | W72: 6980800 | X72: 4515.5498
T73: 2022-02-01 | U73: 181.28999 | V73: 159.36426 | W73: 6233700 | X73: 4546.54
T74: 2022-02-02 | U74: 187.84 | V74: 165.12206 | W74: 8993800 | X74: 4589.3799
T75: 2022-02-03 | U75: 175.59 | V75: 154.35361 | W75: 11691400 | X75: 4477.4399
T76: 2022-02-04 | U76: 171.42 | V76: 150.68796 | W76: 11408600 | X76: 4500.5298
T77: 2022-02-07 | U77: 169.95 | V77: 149.39577 | W77: 6418900 | X77: 4483.8701
... T1258: 2026-10-22 | U1258: 279.5 | V1258: 279.5 | W1258: 13865800 | X1258: 7663.4302

Sheet データ_類似企業
B1: データ_類似企業（market.json peers）
B2: 対象企業の行はスナップショット。対象の ROE・営業利益率・売上成長率は market.json snapshot に無ければ n.a.
B4: コード | C4: 社名 | D4: 株価（ドル） | E4: 時価総額（ドル） | F4: PER（実績TTM） | G4: PBR | H4: ROE | I4: 営業利益率 | J4: 売上成長率 | K4: EV/EBITDA | L4: 配当利回り（実績TTM） | M4: 基準日 | N4: 出所 | Q4: ポジショニング図（名称） | R4: 売上高 前年同期比（%、各社の直近四半期） | S4: 売上総利益率（%、GAAP／IFRS、各社の直近四半期）
B5: TXN | C5: Texas Instruments（対象） | D5: 279.5 | E5: 255252728237 | F5: 36.251621 | G5: 13.304807 | H5: 0.39724115 | I5: 0.40763748 | J5: 0.20271053 | K5: 24.487152 | L5: 0.020322004 | M5: 2026-10-22 | N5: market.json snapshot | Q5: TXN（2026年7〜9月期） | R5: 28 | S5: 64.2
B6: ADI | C6: ANALOG DEVICES INC | D6: 385.76001 | E6: 1.8692598e+11 | F6: 45.814728 | G6: 5.5714152 | H6: 0.12227095 | I6: 0.35549467 | J6: 0.33648002 | K6: 36.171556 | L6: 0.010835753 | M6: 2026-10-22 | N6: yfinance（株価）・SEC companyfacts（財務、TTM・PIT）［us-gaap・直近四半期末 2026-08-01・BS 2026-08-01・株数 2026-08-01］ | Q6: ADI（FQ3'26、〜2026/8/1） | R6: 40 | S6: 67.3
B7: MCHP | C7: MICROCHIP TECHNOLOGY INC | D7: 74.519997 | E7: 4.0465006e+10 | F7: 109.58823 | G7: 6.2726718 | H7: 0.071896063 | I7: 0.15516467 | J7: 0.2092875 | K7: 30.995445 | L7: 0.024422975 | M7: 2026-10-22 | N7: yfinance（株価）・SEC companyfacts（財務、TTM・PIT）［us-gaap・直近四半期末 2026-06-30・BS 2026-06-30・株数 2026-07-28］ | Q7: MCHP（FQ1'27、〜2026/6/30） | R7: 38 | S7: 63.2
B8: NXPI | C8: NXP Semiconductors N.V. | D8: 237.78999 | E8: 6.0035096e+10 | F8: 22.755023 | G8: 5.4941975 | H8: 0.26203763 | I8: 0.30352755 | J8: 0.023695529 | K8: 15.126559 | L8: 0.017057068 | M8: 2026-10-22 | N8: yfinance（株価）・SEC companyfacts（財務、TTM・PIT）［us-gaap・直近四半期末 2026-03-29・BS 2026-03-29・株数 2026-04-24］ | Q8: NXPI（2026年4〜6月期） | R8: 19 | S8: 57.3
B9: ON | C9: ON SEMICONDUCTOR CORP | D9: 73.230003 | E9: 2.8509299e+10 | F9: 47.245163 | G9: 3.9493674 | H9: 0.083142584 | I9: 0.10805447 | J9: -0.03141214 | K9: 19.946679 | L9: n.a. | M9: 2026-10-22 | N9: yfinance（株価）・SEC companyfacts（財務、TTM・PIT）［us-gaap・直近四半期末 2026-07-03・BS 2026-07-03・株数 2026-07-29］ | Q9: STM（2026年4〜6月期） | R9: 26 | S9: 34.8
B10: STM | C10: STMicroelectronics N.V. | D10: 44.09 | E10: 3.9185788e+10 | F10: n.a. | G10: 2.1979912 | H10: n.a. | I10: n.a. | J10: n.a. | K10: n.a. | L10: 0.0081651168 | M10: 2026-10-22 | N10: yfinance（株価）・SEC companyfacts（財務、TTM・PIT）［us-gaap・直近四半期末 n.a.・BS 2025-12-31・株数 2025-12-31］ | Q10: ON（2026年4〜6月期） | R10: 9 | S10: 38.4
B11: MPWR | C11: MONOLITHIC POWER SYSTEMS, INC. | D11: 1167.9301 | E11: 5.7395587e+10 | F11: 71.345758 | G11: 14.734105 | H11: 0.22572879 | I11: 0.28723484 | J11: 0.28666322 | K11: n.a. | L11: 0.0060962555 | M11: 2026-10-22 | N11: yfinance（株価）・SEC companyfacts（財務、TTM・PIT）［us-gaap・直近四半期末 2026-06-30・BS 2026-06-30・株数 2026-07-29］ | Q11: MPWR（2026年4〜6月期） | R11: 47.6 | S11: 55.2
Q12: 参考：Infineon（FY26 Q3、二次） | R12: 13 | S12: 40.8
Q13: 参考：Renesas（2026年4〜6月期、二次） | R13: 24.8 | S13: 58.6

Sheet データ_セグメント
B1: データ_セグメント（セグメント構成比グラフの元データ）
B2: 推計利益＝会社開示のセグメント利益（op_profit、百万ドル）。利益構成比＝推計利益÷セグメント合計（調整額を除く）
B4: セグメント | C4: 売上構成比 | D4: 営業利益率 | E4: 営業利益（開示、百万ドル） | F4: 推計利益（百万ドル） | G4: 利益構成比 | H4: 出所 | I4: グラフ表示名
B5: Analog（アナログ） | C5: 0.792 | D5: 0.386 | E5: 5412 | F5: =E5 -> 5412 | G5: =IF(AND(ISNUMBER(F5),ISNUMBER($F$8),$F$8>0),F5/$F$8,"n.a.") -> 0.89855554 | H5: F1-S1,F1-S2,F1-S6 | I5: Analog
B6: Embedded Processing（組込みプロセッサ） | C6: 0.153 | D6: 0.113 | E6: 304 | F6: =E6 -> 304 | G6: =IF(AND(ISNUMBER(F6),ISNUMBER($F$8),$F$8>0),F6/$F$8,"n.a.") -> 0.050473186 | H6: F1-S1,F1-S2,F1-S3 | I6: Embedded Processing
B7: Other（その他） | C7: 0.055 | D7: 0.314 | E7: 307 | F7: =E7 -> 307 | G7: =IF(AND(ISNUMBER(F7),ISNUMBER($F$8),$F$8>0),F7/$F$8,"n.a.") -> 0.050971277 | H7: F1-S1,F1-S2 | I7: Other
B8: 合計 | C8: =SUM(C5:C7) -> 1 | F8: =SUM(F5:F7) -> 6023 | G8: =SUM(G5:G7) -> 1
B10: 注1：利益構成比は会社開示のセグメント利益（op_profit）。赤字セグメントは負の構成比になる。合計が 0 以下なら n.a.
B11: 注2：売上構成比の合計が 100% に満たない場合、不足分を「その他・調整（差分）」として売上構成比グラフに含める

Sheet データ_市況
B1: データ_市況（⑦ 関連市況の元データ）
B2: 各系列の出所は 1_企業分析 ⑦ の表と 出典 シートを参照。時点の昇順
B3: 指数／月次 | E3: 指数(2017=100)／月次 | H3: 百万台(年率)／月次 | K3: 指数(2017=100)／月次 | N3: 百万ドル／月次
B4: 時点 | C4: 米国PPI 半導体・関連デバイス製造（NSA, 1998/12=100） | D4: 軸ラベル | E4: 時点 | F4: 米国鉱工業生産 半導体・その他電子部品（NAICS3344, SA, 2017=100） | G4: 軸ラベル | H4: 時点 | I4: 米国軽自動車販売台数（乗用車+軽トラック, SAAR） | J4: 軸ラベル | K4: 時点 | L4: 米国鉱工業生産 製造業（SA, 2017=100） | M4: 軸ラベル | N4: 時点 | O4: 米国製造業新規受注 コンピュータ・電子製品（SA） | P4: 軸ラベル
B5: 2021-09 | C5: 29.978 | D5: 2021/09 | E5: 2021-09 | F5: 118.1095 | G5: 2021/09 | H5: 2021-09 | I5: 12.287 | J5: 2021/09 | K5: 2021-09 | L5: 97.0654 | M5: 2021/09 | N5: 2021-09 | O5: 23426 | P5: 2021/09
B6: 2021-10 | C6: 29.758 | D6: 2021/10 | E6: 2021-10 | F6: 119.9345 | G6: 2021/10 | H6: 2021-10 | I6: 12.775 | J6: 2021/10 | K6: 2021-10 | L6: 98.4333 | M6: 2021/10 | N6: 2021-10 | O6: 23258 | P6: 2021/10
B7: 2021-11 | C7: 29.98 | D7: 2021/11 | E7: 2021-11 | F7: 122.4168 | G7: 2021/11 | H7: 2021-11 | I7: 12.954 | J7: 2021/11 | K7: 2021-11 | L7: 99.0146 | M7: 2021/11 | N7: 2021-11 | O7: 24365 | P7: 2021/11
B8: 2021-12 | C8: 30.08 | D8: 2021/12 | E8: 2021-12 | F8: 124.7074 | G8: 2021/12 | H8: 2021-12 | I8: 12.681 | J8: 2021/12 | K8: 2021-12 | L8: 98.897 | M8: 2021/12 | N8: 2021-12 | O8: 24000 | P8: 2021/12
B9: 2022-01 | C9: 30.382 | D9: 2022/01 | E9: 2022-01 | F9: 125.773 | G9: 2022/01 | H9: 2022-01 | I9: 14.683 | J9: 2022/01 | K9: 2022-01 | L9: 97.9535 | M9: 2022/01 | N9: 2022-01 | O9: 24951 | P9: 2022/01
B10: 2022-02 | C10: 30.356 | D10: 2022/02 | E10: 2022-02 | F10: 128.9521 | G10: 2022/02 | H10: 2022-02 | I10: 13.736 | J10: 2022/02 | K10: 2022-02 | L10: 98.5223 | M10: 2022/02 | N10: 2022-02 | O10: 24829 | P10: 2022/02
B11: 2022-03 | C11: 30.527 | D11: 2022/03 | E11: 2022-03 | F11: 129.5542 | G11: 2022/03 | H11: 2022-03 | I11: 13.66 | J11: 2022/03 | K11: 2022-03 | L11: 98.9704 | M11: 2022/03 | N11: 2022-03 | O11: 24866 | P11: 2022/03
B12: 2022-04 | C12: 30.717 | D12: 2022/04 | E12: 2022-04 | F12: 127.9384 | G12: 2022/04 | H12: 2022-04 | I12: 14.113 | J12: 2022/04 | K12: 2022-04 | L12: 98.9204 | M12: 2022/04 | N12: 2022-04 | O12: 25011 | P12: 2022/04
B13: 2022-05 | C13: 30.858 | D13: 2022/05 | E13: 2022-05 | F13: 128.77 | G13: 2022/05 | H13: 2022-05 | I13: 12.853 | J13: 2022/05 | K13: 2022-05 | L13: 98.4799 | M13: 2022/05 | N13: 2022-05 | O13: 25136 | P13: 2022/05
B14: 2022-06 | C14: 31.044 | D14: 2022/06 | E14: 2022-06 | F14: 131.2495 | G14: 2022/06 | H14: 2022-06 | I14: 13.348 | J14: 2022/06 | K14: 2022-06 | L14: 97.9383 | M14: 2022/06 | N14: 2022-06 | O14: 25024 | P14: 2022/06
B15: 2022-07 | C15: 30.998 | D15: 2022/07 | E15: 2022-07 | F15: 131.7061 | G15: 2022/07 | H15: 2022-07 | I15: 13.307 | J15: 2022/07 | K15: 2022-07 | L15: 98.0214 | M15: 2022/07 | N15: 2022-07 | O15: 25470 | P15: 2022/07
B16: 2022-08 | C16: 30.879 | D16: 2022/08 | E16: 2022-08 | F16: 132.8333 | G16: 2022/08 | H16: 2022-08 | I16: 13.588 | J16: 2022/08 | K16: 2022-08 | L16: 98.0019 | M16: 2022/08 | N16: 2022-08 | O16: 25449 | P16: 2022/08
... B64: 2026-08 | C64: 28.541 | D64: 2026/08 | E64: 2026-08 | F64: 194.5212 | G64: 2026/08 | H64: 2026-08 | I64: 16.567 | J64: 2026/08 | K64: 2026-08 | L64: 99.1776 | M64: 2026/08 | N64: 2026-08 | O64: 30868 | P64: 2026/08
B65: 2026-09 | C65: 28.801 | D65: 2026/09 | E65: 2026-09 | F65: 198.6335 | G65: 2026/09 | H65: 2026-09 | I65: 15.982 | J65: 2026/09 | K65: 2026-09 | L65: 99.4361 | M65: 2026/09

Sheet データ_財務
C2: 会社発表値と出典
C3: 金額は原単位。発表値を保持し、換算・符号調整は各シートで計算。
C5: 項目 | D5: 期間開始 | E5: 期間終了 | F5: 原数値 | G5: 通貨 | H5: 提出日時 | I5: タグ・表位置 | J5: 原本URL | K5: 変換
C6: 売上高 | D6: 2021-01-01 | E6: 2021-12-31 | F6: 18344000000 | G6: USD | H6: 2024-02-02 | I6: RevenueFromContractWithCustomerExcludingAssessedTax | 0000097476-24-000007 | J6: https://www.sec.gov/Archives/edgar/data/97476/000009747624000007/0000097476-24-000007-index.html | K6: identity
C7: 売上高 | D7: 2022-01-01 | E7: 2022-12-31 | F7: 20028000000 | G7: USD | H7: 2025-02-14 | I7: RevenueFromContractWithCustomerExcludingAssessedTax | 0000097476-25-000007 | J7: https://www.sec.gov/Archives/edgar/data/97476/000009747625000007/0000097476-25-000007-index.html | K7: identity
C8: 売上高 | D8: 2023-01-01 | E8: 2023-12-31 | F8: 17519000000 | G8: USD | H8: 2026-02-06 | I8: RevenueFromContractWithCustomerExcludingAssessedTax | 0000097476-26-000059 | J8: https://www.sec.gov/Archives/edgar/data/97476/000009747626000059/0000097476-26-000059-index.html | K8: identity
C9: 売上高 | D9: 2024-01-01 | E9: 2024-12-31 | F9: 15641000000 | G9: USD | H9: 2026-02-06 | I9: RevenueFromContractWithCustomerExcludingAssessedTax | 0000097476-26-000059 | J9: https://www.sec.gov/Archives/edgar/data/97476/000009747626000059/0000097476-26-000059-index.html | K9: identity
C10: 売上高 | D10: 2025-01-01 | E10: 2025-12-31 | F10: 17682000000 | G10: USD | H10: 2026-02-06 | I10: RevenueFromContractWithCustomerExcludingAssessedTax | 0000097476-26-000059 | J10: https://www.sec.gov/Archives/edgar/data/97476/000009747626000059/0000097476-26-000059-index.html | K10: identity
C11: 売上原価 | D11: 2021-01-01 | E11: 2021-12-31 | F11: 5968000000 | G11: USD | H11: 2024-02-02 | I11: CostOfGoodsAndServicesSold | 0000097476-24-000007 | J11: https://www.sec.gov/Archives/edgar/data/97476/000009747624000007/0000097476-24-000007-index.html | K11: identity
C12: 売上原価 | D12: 2022-01-01 | E12: 2022-12-31 | F12: 6257000000 | G12: USD | H12: 2025-02-14 | I12: CostOfGoodsAndServicesSold | 0000097476-25-000007 | J12: https://www.sec.gov/Archives/edgar/data/97476/000009747625000007/0000097476-25-000007-index.html | K12: identity
C13: 売上原価 | D13: 2023-01-01 | E13: 2023-12-31 | F13: 6500000000 | G13: USD | H13: 2026-02-06 | I13: CostOfGoodsAndServicesSold | 0000097476-26-000059 | J13: https://www.sec.gov/Archives/edgar/data/97476/000009747626000059/0000097476-26-000059-index.html | K13: identity
C14: 売上原価 | D14: 2024-01-01 | E14: 2024-12-31 | F14: 6547000000 | G14: USD | H14: 2026-02-06 | I14: CostOfGoodsAndServicesSold | 0000097476-26-000059 | J14: https://www.sec.gov/Archives/edgar/data/97476/000009747626000059/0000097476-26-000059-index.html | K14: identity
C15: 売上原価 | D15: 2025-01-01 | E15: 2025-12-31 | F15: 7599000000 | G15: USD | H15: 2026-02-06 | I15: CostOfGoodsAndServicesSold | 0000097476-26-000059 | J15: https://www.sec.gov/Archives/edgar/data/97476/000009747626000059/0000097476-26-000059-index.html | K15: identity
C16: 売上総利益 | D16: 2021-01-01 | E16: 2021-12-31 | F16: 12376000000 | G16: USD | H16: 2024-02-02 | I16: GrossProfit | 0000097476-24-000007 | J16: https://www.sec.gov/Archives/edgar/data/97476/000009747624000007/0000097476-24-000007-index.html | K16: identity
C17: 売上総利益 | D17: 2022-01-01 | E17: 2022-12-31 | F17: 13771000000 | G17: USD | H17: 2025-02-14 | I17: GrossProfit | 0000097476-25-000007 | J17: https://www.sec.gov/Archives/edgar/data/97476/000009747625000007/0000097476-25-000007-index.html | K17: identity
... C50: 親会社株主帰属利益 | D50: 2025-01-01 | E50: 2025-12-31 | F50: 5001000000 | G50: USD | H50: 2026-02-06 | I50: NetIncomeLoss | 0000097476-26-000059 | J50: https://www.sec.gov/Archives/edgar/data/97476/000009747626000059/0000097476-26-000059-index.html | K50: identity
C51: 現金及び預金・現金同等物（BS定義） | E51: 2021-12-31 | F51: 4631000000 | G51: USD | H51: 2023-02-03 | I51: CashAndCashEquivalentsAtCarryingValue | 0000097476-23-000007 | J51: https://www.sec.gov/Archives/edgar/data/97476/000009747623000007/0000097476-23-000007-index.html | K51: identity
C52: 現金及び預金・現金同等物（BS定義） | E52: 2022-12-31 | F52: 3050000000 | G52: USD | H52: 2024-02-02 | I52: CashAndCashEquivalentsAtCarryingValue | 0000097476-24-000007 | J52: https://www.sec.gov/Archives/edgar/data/97476/000009747624000007/0000097476-24-000007-index.html | K52: identity
C53: 現金及び預金・現金同等物（BS定義） | E53: 2023-12-31 | F53: 2964000000 | G53: USD | H53: 2025-02-14 | I53: CashAndCashEquivalentsAtCarryingValue | 0000097476-25-000007 | J53: https://www.sec.gov/Archives/edgar/data/97476/000009747625000007/0000097476-25-000007-index.html | K53: identity
C54: 現金及び預金・現金同等物（BS定義） | E54: 2024-12-31 | F54: 3200000000 | G54: USD | H54: 2026-02-06 | I54: CashAndCashEquivalentsAtCarryingValue | 0000097476-26-000059 | J54: https://www.sec.gov/Archives/edgar/data/97476/000009747626000059/0000097476-26-000059-index.html | K54: identity
C55: 現金及び預金・現金同等物（BS定義） | E55: 2025-12-31 | F55: 3225000000 | G55: USD | H55: 2026-02-06 | I55: CashAndCashEquivalentsAtCarryingValue | 0000097476-26-000059 | J55: https://www.sec.gov/Archives/edgar/data/97476/000009747626000059/0000097476-26-000059-index.html | K55: identity
C56: 売上債権 | E56: 2021-12-31 | F56: 1701000000 | G56: USD | H56: 2023-02-03 | I56: AccountsReceivableNetCurrent | 0000097476-23-000007 | J56: https://www.sec.gov/Archives/edgar/data/97476/000009747623000007/0000097476-23-000007-index.html | K56: identity
C57: 売上債権 | E57: 2022-12-31 | F57: 1895000000 | G57: USD | H57: 2024-02-02 | I57: AccountsReceivableNetCurrent | 0000097476-24-000007 | J57: https://www.sec.gov/Archives/edgar/data/97476/000009747624000007/0000097476-24-000007-index.html | K57: identity
C58: 売上債権 | E58: 2023-12-31 | F58: 1787000000 | G58: USD | H58: 2025-02-14 | I58: AccountsReceivableNetCurrent | 0000097476-25-000007 | J58: https://www.sec.gov/Archives/edgar/data/97476/000009747625000007/0000097476-25-000007-index.html | K58: identity
C59: 売上債権 | E59: 2024-12-31 | F59: 1719000000 | G59: USD | H59: 2026-02-06 | I59: AccountsReceivableNetCurrent | 0000097476-26-000059 | J59: https://www.sec.gov/Archives/edgar/data/97476/000009747626000059/0000097476-26-000059-index.html | K59: identity
C60: 売上債権 | E60: 2025-12-31 | F60: 1963000000 | G60: USD | H60: 2026-02-06 | I60: AccountsReceivableNetCurrent | 0000097476-26-000059 | J60: https://www.sec.gov/Archives/edgar/data/97476/000009747626000059/0000097476-26-000059-index.html | K60: identity
C61: 棚卸資産 | E61: 2021-12-31 | F61: 1910000000 | G61: USD | H61: 2023-02-03 | I61: InventoryNet | 0000097476-23-000007 | J61: https://www.sec.gov/Archives/edgar/data/97476/000009747623000007/0000097476-23-000007-index.html | K61: identity
C62: 棚卸資産 | E62: 2022-12-31 | F62: 2757000000 | G62: USD | H62: 2024-02-02 | I62: InventoryNet | 0000097476-24-000007 | J62: https://www.sec.gov/Archives/edgar/data/97476/000009747624000007/0000097476-24-000007-index.html | K62: identity
... C100: 資本合計（非支配持分含む） | E100: 2025-12-31 | F100: 16273000000 | G100: USD | H100: 2026-02-06 | I100: StockholdersEquity | c-6 | J100: https://www.sec.gov/Archives/edgar/data/97476/000009747626000059/txn-20251231.htm | K100: identity
C101: 営業活動によるCF | D101: 2021-01-01 | E101: 2021-12-31 | F101: 8756000000 | G101: USD | H101: 2024-02-02 | I101: NetCashProvidedByUsedInOperatingActivities | 0000097476-24-000007 | J101: https://www.sec.gov/Archives/edgar/data/97476/000009747624000007/0000097476-24-000007-index.html | K101: identity
C102: 営業活動によるCF | D102: 2022-01-01 | E102: 2022-12-31 | F102: 8720000000 | G102: USD | H102: 2025-02-14 | I102: NetCashProvidedByUsedInOperatingActivities | 0000097476-25-000007 | J102: https://www.sec.gov/Archives/edgar/data/97476/000009747625000007/0000097476-25-000007-index.html | K102: identity
C103: 営業活動によるCF | D103: 2023-01-01 | E103: 2023-12-31 | F103: 6420000000 | G103: USD | H103: 2026-02-06 | I103: NetCashProvidedByUsedInOperatingActivities | 0000097476-26-000059 | J103: https://www.sec.gov/Archives/edgar/data/97476/000009747626000059/0000097476-26-000059-index.html | K103: identity
C104: 営業活動によるCF | D104: 2024-01-01 | E104: 2024-12-31 | F104: 6318000000 | G104: USD | H104: 2026-02-06 | I104: NetCashProvidedByUsedInOperatingActivities | 0000097476-26-000059 | J104: https://www.sec.gov/Archives/edgar/data/97476/000009747626000059/0000097476-26-000059-index.html | K104: identity
C105: 営業活動によるCF | D105: 2025-01-01 | E105: 2025-12-31 | F105: 7153000000 | G105: USD | H105: 2026-02-06 | I105: NetCashProvidedByUsedInOperatingActivities | 0000097476-26-000059 | J105: https://www.sec.gov/Archives/edgar/data/97476/000009747626000059/0000097476-26-000059-index.html | K105: identity
C106: 投資活動によるCF | D106: 2021-01-01 | E106: 2021-12-31 | F106: -4095000000 | G106: USD | H106: 2024-02-02 | I106: NetCashProvidedByUsedInInvestingActivities | 0000097476-24-000007 | J106: https://www.sec.gov/Archives/edgar/data/97476/000009747624000007/0000097476-24-000007-index.html | K106: identity
C107: 投資活動によるCF | D107: 2022-01-01 | E107: 2022-12-31 | F107: -3583000000 | G107: USD | H107: 2025-02-14 | I107: NetCashProvidedByUsedInInvestingActivities | 0000097476-25-000007 | J107: https://www.sec.gov/Archives/edgar/data/97476/000009747625000007/0000097476-25-000007-index.html | K107: identity
C108: 投資活動によるCF | D108: 2023-01-01 | E108: 2023-12-31 | F108: -4362000000 | G108: USD | H108: 2026-02-06 | I108: NetCashProvidedByUsedInInvestingActivities | 0000097476-26-000059 | J108: https://www.sec.gov/Archives/edgar/data/97476/000009747626000059/0000097476-26-000059-index.html | K108: identity
C109: 投資活動によるCF | D109: 2024-01-01 | E109: 2024-12-31 | F109: -3202000000 | G109: USD | H109: 2026-02-06 | I109: NetCashProvidedByUsedInInvestingActivities | 0000097476-26-000059 | J109: https://www.sec.gov/Archives/edgar/data/97476/000009747626000059/0000097476-26-000059-index.html | K109: identity
C110: 投資活動によるCF | D110: 2025-01-01 | E110: 2025-12-31 | F110: -1439000000 | G110: USD | H110: 2026-02-06 | I110: NetCashProvidedByUsedInInvestingActivities | 0000097476-26-000059 | J110: https://www.sec.gov/Archives/edgar/data/97476/000009747626000059/0000097476-26-000059-index.html | K110: identity
C111: 財務活動によるCF | D111: 2021-01-01 | E111: 2021-12-31 | F111: -3137000000 | G111: USD | H111: 2024-02-02 | I111: NetCashProvidedByUsedInFinancingActivities | 0000097476-24-000007 | J111: https://www.sec.gov/Archives/edgar/data/97476/000009747624000007/0000097476-24-000007-index.html | K111: identity
C112: 財務活動によるCF | D112: 2022-01-01 | E112: 2022-12-31 | F112: -6718000000 | G112: USD | H112: 2025-02-14 | I112: NetCashProvidedByUsedInFinancingActivities | 0000097476-25-000007 | J112: https://www.sec.gov/Archives/edgar/data/97476/000009747625000007/0000097476-25-000007-index.html | K112: identity
... C125: 現金同等物の増減（会社発表） | D125: 2025-01-01 | E125: 2025-12-31 | F125: 25000000 | G125: USD | H125: 2026-02-06 | I125: CashCashEquivalentsRestrictedCashAndRestrictedCashEquivalentsPeriodIncreaseDecreaseIncludingExchangeRateEffect | c-1 | J125: https://www.sec.gov/Archives/edgar/data/97476/000009747626000059/txn-20251231.htm | K125: identity
C126: 現金同等物の期末残高（CF定義） | E126: 2021-12-31 | F126: 4631000000 | G126: USD | H126: 2023-02-03 | I126: CashAndCashEquivalentsAtCarryingValue | 0000097476-23-000007 | J126: https://www.sec.gov/Archives/edgar/data/97476/000009747623000007/0000097476-23-000007-index.html | K126: identity
C127: 現金同等物の期末残高（CF定義） | E127: 2022-12-31 | F127: 3050000000 | G127: USD | H127: 2024-02-02 | I127: CashAndCashEquivalentsAtCarryingValue | 0000097476-24-000007 | J127: https://www.sec.gov/Archives/edgar/data/97476/000009747624000007/0000097476-24-000007-index.html | K127: identity
C128: 現金同等物の期末残高（CF定義） | E128: 2023-12-31 | F128: 2964000000 | G128: USD | H128: 2025-02-14 | I128: CashAndCashEquivalentsAtCarryingValue | 0000097476-25-000007 | J128: https://www.sec.gov/Archives/edgar/data/97476/000009747625000007/0000097476-25-000007-index.html | K128: identity
C129: 現金同等物の期末残高（CF定義） | E129: 2024-12-31 | F129: 3200000000 | G129: USD | H129: 2026-02-06 | I129: CashAndCashEquivalentsAtCarryingValue | 0000097476-26-000059 | J129: https://www.sec.gov/Archives/edgar/data/97476/000009747626000059/0000097476-26-000059-index.html | K129: identity
C130: 現金同等物の期末残高（CF定義） | E130: 2025-12-31 | F130: 3225000000 | G130: USD | H130: 2026-02-06 | I130: CashAndCashEquivalentsAtCarryingValue | 0000097476-26-000059 | J130: https://www.sec.gov/Archives/edgar/data/97476/000009747626000059/0000097476-26-000059-index.html | K130: identity
C131: 減価償却・償却費 | D131: 2021-01-01 | E131: 2021-12-31 | F131: 954000000 | G131: USD | H131: 2024-02-02 | I131: TXNPresentedDepreciationAndAmortization | c-5: CF表示値の合計 Depreciation 755＋Amortization of capitalized software 57＋Amortization of acquisition-related intangibles 142 | J131: https://www.sec.gov/Archives/edgar/data/97476/000009747624000007/txn-20231231.htm | K131: identity
C132: 減価償却・償却費 | D132: 2022-01-01 | E132: 2022-12-31 | F132: 979000000 | G132: USD | H132: 2025-02-14 | I132: TXNPresentedDepreciationAndAmortization | c-5: CF表示値の合計 Depreciation 925＋Amortization of capitalized software 54 | J132: https://www.sec.gov/Archives/edgar/data/97476/000009747625000007/txn-20241231.htm | K132: identity
C133: 減価償却・償却費 | D133: 2023-01-01 | E133: 2023-12-31 | F133: 1238000000 | G133: USD | H133: 2026-02-06 | I133: TXNPresentedDepreciationAndAmortization | c-5: CF表示値の合計 Depreciation 1175＋Amortization of capitalized software 63 | J133: https://www.sec.gov/Archives/edgar/data/97476/000009747626000059/txn-20251231.htm | K133: identity
C134: 減価償却・償却費 | D134: 2024-01-01 | E134: 2024-12-31 | F134: 1580000000 | G134: USD | H134: 2026-02-06 | I134: TXNPresentedDepreciationAndAmortization | c-4: CF表示値の合計 Depreciation 1508＋Amortization of capitalized software 72 | J134: https://www.sec.gov/Archives/edgar/data/97476/000009747626000059/txn-20251231.htm | K134: identity
C135: 減価償却・償却費 | D135: 2025-01-01 | E135: 2025-12-31 | F135: 1999000000 | G135: USD | H135: 2026-02-06 | I135: TXNPresentedDepreciationAndAmortization | c-1: CF表示値の合計 Depreciation 1918＋Amortization of capitalized software 81 | J135: https://www.sec.gov/Archives/edgar/data/97476/000009747626000059/txn-20251231.htm | K135: identity
C136: 設備投資支出（正額） | D136: 2021-01-01 | E136: 2021-12-31 | F136: 2462000000 | G136: USD | H136: 2024-02-02 | I136: PaymentsToAcquirePropertyPlantAndEquipment | 0000097476-24-000007 | J136: https://www.sec.gov/Archives/edgar/data/97476/000009747624000007/0000097476-24-000007-index.html | K136: absolute
C137: 設備投資支出（正額） | D137: 2022-01-01 | E137: 2022-12-31 | F137: 2797000000 | G137: USD | H137: 2025-02-14 | I137: PaymentsToAcquirePropertyPlantAndEquipment | 0000097476-25-000007 | J137: https://www.sec.gov/Archives/edgar/data/97476/000009747625000007/0000097476-25-000007-index.html | K137: absolute
C138: 設備投資支出（正額） | D138: 2023-01-01 | E138: 2023-12-31 | F138: 5071000000 | G138: USD | H138: 2026-02-06 | I138: PaymentsToAcquirePropertyPlantAndEquipment | 0000097476-26-000059 | J138: https://www.sec.gov/Archives/edgar/data/97476/000009747626000059/0000097476-26-000059-index.html | K138: absolute
C139: 設備投資支出（正額） | D139: 2024-01-01 | E139: 2024-12-31 | F139: 4820000000 | G139: USD | H139: 2026-02-06 | I139: PaymentsToAcquirePropertyPlantAndEquipment | 0000097476-26-000059 | J139: https://www.sec.gov/Archives/edgar/data/97476/000009747626000059/0000097476-26-000059-index.html | K139: absolute
C140: 設備投資支出（正額） | D140: 2025-01-01 | E140: 2025-12-31 | F140: 4550000000 | G140: USD | H140: 2026-02-06 | I140: PaymentsToAcquirePropertyPlantAndEquipment | 0000097476-26-000059 | J140: https://www.sec.gov/Archives/edgar/data/97476/000009747626000059/0000097476-26-000059-index.html | K140: absolute
C141: 非支配持分帰属利益 | D141: 2021-01-01 | E141: 2021-12-31 | F141: 0 | G141: USD | H141: 2023-02-03 | I141: TXNNoncontrollingInterestNotPresented | i4318962e5e42482e8147add103655653_D20210101-20211231: Net income単一表示・非支配持分の区分表示なし | J141: https://www.sec.gov/Archives/edgar/data/97476/000009747623000007/txn-20221231.htm | K141: identity
C142: 非支配持分帰属利益 | D142: 2022-01-01 | E142: 2022-12-31 | F142: 0 | G142: USD | H142: 2024-02-02 | I142: TXNNoncontrollingInterestNotPresented | c-4: Net income単一表示・非支配持分の区分表示なし | J142: https://www.sec.gov/Archives/edgar/data/97476/000009747624000007/txn-20231231.htm | K142: identity
... C145: 非支配持分帰属利益 | D145: 2025-01-01 | E145: 2025-12-31 | F145: 0 | G145: USD | H145: 2026-02-06 | I145: TXNNoncontrollingInterestNotPresented | c-1: Net income単一表示・非支配持分の区分表示なし | J145: https://www.sec.gov/Archives/edgar/data/97476/000009747626000059/txn-20251231.htm | K145: identity
C146: 無形資産（のれんを除く場合あり） | E146: 2021-12-31 | F146: 85000000 | G146: USD | H146: 2023-02-03 | I146: CapitalizedComputerSoftwareNet | ie846fa343e4f4bf1bc19f8ade4f4d6b0_I20211231 | J146: https://www.sec.gov/Archives/edgar/data/97476/000009747623000007/txn-20221231.htm | K146: identity
C147: 無形資産（のれんを除く場合あり） | E147: 2022-12-31 | F147: 152000000 | G147: USD | H147: 2024-02-02 | I147: CapitalizedComputerSoftwareNet | c-7 | J147: https://www.sec.gov/Archives/edgar/data/97476/000009747624000007/txn-20231231.htm | K147: identity
C148: 無形資産（のれんを除く場合あり） | E148: 2023-12-31 | F148: 223000000 | G148: USD | H148: 2025-02-14 | I148: CapitalizedComputerSoftwareNet | c-7 | J148: https://www.sec.gov/Archives/edgar/data/97476/000009747625000007/txn-20241231.htm | K148: identity
C149: 無形資産（のれんを除く場合あり） | E149: 2024-12-31 | F149: 257000000 | G149: USD | H149: 2026-02-06 | I149: CapitalizedComputerSoftwareNet | c-7 | J149: https://www.sec.gov/Archives/edgar/data/97476/000009747626000059/txn-20251231.htm | K149: identity
C150: 無形資産（のれんを除く場合あり） | E150: 2025-12-31 | F150: 238000000 | G150: USD | H150: 2026-02-06 | I150: CapitalizedComputerSoftwareNet | c-6 | J150: https://www.sec.gov/Archives/edgar/data/97476/000009747626000059/txn-20251231.htm | K150: identity
C151: 当期利益（非支配持分含む） | D151: 2021-01-01 | E151: 2021-12-31 | F151: 7769000000 | G151: USD | H151: 2024-02-02 | I151: NetIncomeLoss | 0000097476-24-000007 | J151: https://www.sec.gov/Archives/edgar/data/97476/000009747624000007/0000097476-24-000007-index.html | K151: identity
C152: 当期利益（非支配持分含む） | D152: 2022-01-01 | E152: 2022-12-31 | F152: 8749000000 | G152: USD | H152: 2025-02-14 | I152: NetIncomeLoss | 0000097476-25-000007 | J152: https://www.sec.gov/Archives/edgar/data/97476/000009747625000007/0000097476-25-000007-index.html | K152: identity
C153: 当期利益（非支配持分含む） | D153: 2023-01-01 | E153: 2023-12-31 | F153: 6510000000 | G153: USD | H153: 2026-02-06 | I153: NetIncomeLoss | 0000097476-26-000059 | J153: https://www.sec.gov/Archives/edgar/data/97476/000009747626000059/0000097476-26-000059-index.html | K153: identity
C154: 当期利益（非支配持分含む） | D154: 2024-01-01 | E154: 2024-12-31 | F154: 4799000000 | G154: USD | H154: 2026-02-06 | I154: NetIncomeLoss | 0000097476-26-000059 | J154: https://www.sec.gov/Archives/edgar/data/97476/000009747626000059/0000097476-26-000059-index.html | K154: identity
C155: 当期利益（非支配持分含む） | D155: 2025-01-01 | E155: 2025-12-31 | F155: 5001000000 | G155: USD | H155: 2026-02-06 | I155: NetIncomeLoss | 0000097476-26-000059 | J155: https://www.sec.gov/Archives/edgar/data/97476/000009747626000059/0000097476-26-000059-index.html | K155: identity
C156: 減価償却費（有形資産） | D156: 2021-01-01 | E156: 2021-12-31 | F156: 755000000 | G156: USD | H156: 2024-02-02 | I156: Depreciation | 0000097476-24-000007 | J156: https://www.sec.gov/Archives/edgar/data/97476/000009747624000007/0000097476-24-000007-index.html | K156: identity
C157: 減価償却費（有形資産） | D157: 2022-01-01 | E157: 2022-12-31 | F157: 925000000 | G157: USD | H157: 2025-02-14 | I157: Depreciation | 0000097476-25-000007 | J157: https://www.sec.gov/Archives/edgar/data/97476/000009747625000007/0000097476-25-000007-index.html | K157: identity
C158: 減価償却費（有形資産） | D158: 2023-01-01 | E158: 2023-12-31 | F158: 1175000000 | G158: USD | H158: 2026-02-06 | I158: Depreciation | 0000097476-26-000059 | J158: https://www.sec.gov/Archives/edgar/data/97476/000009747626000059/0000097476-26-000059-index.html | K158: identity
C159: 減価償却費（有形資産） | D159: 2024-01-01 | E159: 2024-12-31 | F159: 1508000000 | G159: USD | H159: 2026-02-06 | I159: Depreciation | 0000097476-26-000059 | J159: https://www.sec.gov/Archives/edgar/data/97476/000009747626000059/0000097476-26-000059-index.html | K159: identity
C160: 減価償却費（有形資産） | D160: 2025-01-01 | E160: 2025-12-31 | F160: 1918000000 | G160: USD | H160: 2026-02-06 | I160: Depreciation | 0000097476-26-000059 | J160: https://www.sec.gov/Archives/edgar/data/97476/000009747626000059/0000097476-26-000059-index.html | K160: identity
C161: 無形資産償却費 | D161: 2021-01-01 | E161: 2021-12-31 | F161: 142000000 | G161: USD | H161: 2024-02-02 | I161: AmortizationOfIntangibleAssets | 0000097476-24-000007 | J161: https://www.sec.gov/Archives/edgar/data/97476/000009747624000007/0000097476-24-000007-index.html | K161: identity
C162: 無形資産償却費 | D162: 2022-01-01 | E162: 2022-12-31 | F162: 0 | G162: USD | H162: 2024-02-02 | I162: AmortizationOfIntangibleAssets | 0000097476-24-000007 | J162: https://www.sec.gov/Archives/edgar/data/97476/000009747624000007/0000097476-24-000007-index.html | K162: identity
... C168: 親会社配当支払額（正額） | D168: 2025-01-01 | E168: 2025-12-31 | F168: 4999000000 | G168: USD | H168: 2026-02-06 | I168: PaymentsOfDividends | 0000097476-26-000059 | J168: https://www.sec.gov/Archives/edgar/data/97476/000009747626000059/0000097476-26-000059-index.html | K168: absolute
C169: Analog | E169: 2025-12-31 | F169: 14006000000 | G169: USD | H169: 2026-02-06 | I169: RevenueFromContractWithCustomerExcludingAssessedTax | c-42 | StatementBusinessSegmentsAxis=AnalogMember | J169: https://www.sec.gov/Archives/edgar/data/97476/000009747626000059/txn-20251231.htm | K169: identity
C170: Embedded Processing | E170: 2025-12-31 | F170: 2697000000 | G170: USD | H170: 2026-02-06 | I170: RevenueFromContractWithCustomerExcludingAssessedTax | c-43 | StatementBusinessSegmentsAxis=EmbeddedProcessingMember | J170: https://www.sec.gov/Archives/edgar/data/97476/000009747626000059/txn-20251231.htm | K170: identity
C171: Other | E171: 2025-12-31 | F171: 979000000 | G171: USD | H171: 2026-02-06 | I171: RevenueFromContractWithCustomerExcludingAssessedTax | c-44 | StatementBusinessSegmentsAxis=AllOtherSegmentsMember | J171: https://www.sec.gov/Archives/edgar/data/97476/000009747626000059/txn-20251231.htm | K171: identity
C172: Analog | E172: 2024-12-31 | F172: 12161000000 | G172: USD | H172: 2026-02-06 | I172: RevenueFromContractWithCustomerExcludingAssessedTax | c-45 | StatementBusinessSegmentsAxis=AnalogMember | J172: https://www.sec.gov/Archives/edgar/data/97476/000009747626000059/txn-20251231.htm | K172: identity
C173: Embedded Processing | E173: 2024-12-31 | F173: 2533000000 | G173: USD | H173: 2026-02-06 | I173: RevenueFromContractWithCustomerExcludingAssessedTax | c-46 | StatementBusinessSegmentsAxis=EmbeddedProcessingMember | J173: https://www.sec.gov/Archives/edgar/data/97476/000009747626000059/txn-20251231.htm | K173: identity
C174: Other | E174: 2024-12-31 | F174: 947000000 | G174: USD | H174: 2026-02-06 | I174: RevenueFromContractWithCustomerExcludingAssessedTax | c-47 | StatementBusinessSegmentsAxis=AllOtherSegmentsMember | J174: https://www.sec.gov/Archives/edgar/data/97476/000009747626000059/txn-20251231.htm | K174: identity
C175: Analog | E175: 2023-12-31 | F175: 13040000000 | G175: USD | H175: 2026-02-06 | I175: RevenueFromContractWithCustomerExcludingAssessedTax | c-48 | StatementBusinessSegmentsAxis=AnalogMember | J175: https://www.sec.gov/Archives/edgar/data/97476/000009747626000059/txn-20251231.htm | K175: identity
C176: Embedded Processing | E176: 2023-12-31 | F176: 3368000000 | G176: USD | H176: 2026-02-06 | I176: RevenueFromContractWithCustomerExcludingAssessedTax | c-49 | StatementBusinessSegmentsAxis=EmbeddedProcessingMember | J176: https://www.sec.gov/Archives/edgar/data/97476/000009747626000059/txn-20251231.htm | K176: identity
C177: Other | E177: 2023-12-31 | F177: 1111000000 | G177: USD | H177: 2026-02-06 | I177: RevenueFromContractWithCustomerExcludingAssessedTax | c-50 | StatementBusinessSegmentsAxis=AllOtherSegmentsMember | J177: https://www.sec.gov/Archives/edgar/data/97476/000009747626000059/txn-20251231.htm | K177: identity
C178: Total revenue | E178: 2024-12-31 | F178: 15641000000 | G178: USD | H178: 2026-02-06 | I178: RevenueFromContractWithCustomerExcludingAssessedTax | c-4 | J178: https://www.sec.gov/Archives/edgar/data/97476/000009747626000059/txn-20251231.htm | K178: identity
C179: Total revenue | E179: 2025-12-31 | F179: 17682000000 | G179: USD | H179: 2026-02-06 | I179: RevenueFromContractWithCustomerExcludingAssessedTax | c-1 | J179: https://www.sec.gov/Archives/edgar/data/97476/000009747626000059/txn-20251231.htm | K179: identity
C180: Total revenue | E180: 2023-12-31 | F180: 17519000000 | G180: USD | H180: 2026-02-06 | I180: RevenueFromContractWithCustomerExcludingAssessedTax | c-5 | J180: https://www.sec.gov/Archives/edgar/data/97476/000009747626000059/txn-20251231.htm | K180: identity
... C223: Total revenue | E223: 2021-12-31 | F223: 18344000000 | G223: USD | H223: 2024-02-02 | I223: RevenueFromContractWithCustomerExcludingAssessedTax | c-71 | ConcentrationRiskByTypeAxis=GeographicConcentrationRiskMember | J223: https://www.sec.gov/Archives/edgar/data/97476/000009747624000007/txn-20231231.htm | K223: identity

Sheet データ_整合検査
C2: 財務・注記の整合性検査
C4: USD 百万単位。年次・連結実績。n.a. = 未抽出／対象外
C5: 項目 | D5: 2021-12-31 A | E5: 2022-12-31 A | F5: 2023-12-31 A | G5: 2024-12-31 A | H5: 2025-12-31 A | I5: 2026-12-31 E | J5: 2027-12-31 E | K5: 2028-12-31 E
C6: 貸借差額（総資産−負債−資本） | D6: =IF(AND(ISNUMBER('3_BS'!D12),ISNUMBER('3_BS'!D15),ISNUMBER('3_BS'!D16)),'3_BS'!D12-'3_BS'!D15-'3_BS'!D16,"n.a.") -> 0 | E6: =IF(AND(ISNUMBER('3_BS'!E12),ISNUMBER('3_BS'!E15),ISNUMBER('3_BS'!E16)),'3_BS'!E12-'3_BS'!E15-'3_BS'!E16,"n.a.") -> 0 | F6: =IF(AND(ISNUMBER('3_BS'!F12),ISNUMBER('3_BS'!F15),ISNUMBER('3_BS'!F16)),'3_BS'!F12-'3_BS'!F15-'3_BS'!F16,"n.a.") -> 0 | G6: =IF(AND(ISNUMBER('3_BS'!G12),ISNUMBER('3_BS'!G15),ISNUMBER('3_BS'!G16)),'3_BS'!G12-'3_BS'!G15-'3_BS'!G16,"n.a.") -> 0 | H6: =IF(AND(ISNUMBER('3_BS'!H12),ISNUMBER('3_BS'!H15),ISNUMBER('3_BS'!H16)),'3_BS'!H12-'3_BS'!H15-'3_BS'!H16,"n.a.") -> 0 | I6: ='3_Forecast'!I62 -> -7.2759576e-12 | J6: ='3_Forecast'!J62 -> 3.6379788e-12 | K6: ='3_Forecast'!K62 -> 3.6379788e-12
C7: 売上総利益差額 | D7: =IF(AND(ISNUMBER('3_PL'!D6),ISNUMBER('3_PL'!D7),ISNUMBER('3_PL'!D8)),'3_PL'!D6-'3_PL'!D7-'3_PL'!D8,"n.a.") -> 0 | E7: =IF(AND(ISNUMBER('3_PL'!E6),ISNUMBER('3_PL'!E7),ISNUMBER('3_PL'!E8)),'3_PL'!E6-'3_PL'!E7-'3_PL'!E8,"n.a.") -> 0 | F7: =IF(AND(ISNUMBER('3_PL'!F6),ISNUMBER('3_PL'!F7),ISNUMBER('3_PL'!F8)),'3_PL'!F6-'3_PL'!F7-'3_PL'!F8,"n.a.") -> 0 | G7: =IF(AND(ISNUMBER('3_PL'!G6),ISNUMBER('3_PL'!G7),ISNUMBER('3_PL'!G8)),'3_PL'!G6-'3_PL'!G7-'3_PL'!G8,"n.a.") -> 0 | H7: =IF(AND(ISNUMBER('3_PL'!H6),ISNUMBER('3_PL'!H7),ISNUMBER('3_PL'!H8)),'3_PL'!H6-'3_PL'!H7-'3_PL'!H8,"n.a.") -> 0 | I7: =IF(AND(ISNUMBER('3_Forecast'!I8),ISNUMBER('3_Forecast'!I9),ISNUMBER('3_Forecast'!I10)),'3_Forecast'!I8-'3_Forecast'!I9-'3_Forecast'!I10,"n.a.") -> 0 | J7: =IF(AND(ISNUMBER('3_Forecast'!J8),ISNUMBER('3_Forecast'!J9),ISNUMBER('3_Forecast'!J10)),'3_Forecast'!J8-'3_Forecast'!J9-'3_Forecast'!J10,"n.a.") -> 0 | K7: =IF(AND(ISNUMBER('3_Forecast'!K8),ISNUMBER('3_Forecast'!K9),ISNUMBER('3_Forecast'!K10)),'3_Forecast'!K8-'3_Forecast'!K9-'3_Forecast'!K10,"n.a.") -> 0
C8: CF増減差額 | D8: =IF(AND(ISNUMBER('3_CF'!D6),ISNUMBER('3_CF'!D10),ISNUMBER('3_CF'!D12),ISNUMBER('3_CF'!D14),ISNUMBER('3_CF'!D15)),'3_CF'!D6+'3_CF'!D10+'3_CF'!D12+'3_CF'!D14-'3_CF'!D15,"n.a.") -> 0 | E8: =IF(AND(ISNUMBER('3_CF'!E6),ISNUMBER('3_CF'!E10),ISNUMBER('3_CF'!E12),ISNUMBER('3_CF'!E14),ISNUMBER('3_CF'!E15)),'3_CF'!E6+'3_CF'!E10+'3_CF'!E12+'3_CF'!E14-'3_CF'!E15,"n.a.") -> 0 | F8: =IF(AND(ISNUMBER('3_CF'!F6),ISNUMBER('3_CF'!F10),ISNUMBER('3_CF'!F12),ISNUMBER('3_CF'!F14),ISNUMBER('3_CF'!F15)),'3_CF'!F6+'3_CF'!F10+'3_CF'!F12+'3_CF'!F14-'3_CF'!F15,"n.a.") -> 0 | G8: =IF(AND(ISNUMBER('3_CF'!G6),ISNUMBER('3_CF'!G10),ISNUMBER('3_CF'!G12),ISNUMBER('3_CF'!G14),ISNUMBER('3_CF'!G15)),'3_CF'!G6+'3_CF'!G10+'3_CF'!G12+'3_CF'!G14-'3_CF'!G15,"n.a.") -> 0 | H8: =IF(AND(ISNUMBER('3_CF'!H6),ISNUMBER('3_CF'!H10),ISNUMBER('3_CF'!H12),ISNUMBER('3_CF'!H14),ISNUMBER('3_CF'!H15)),'3_CF'!H6+'3_CF'!H10+'3_CF'!H12+'3_CF'!H14-'3_CF'!H15,"n.a.") -> 0 | I8: ='3_Forecast'!I64 -> 0 | J8: ='3_Forecast'!J64 -> 0 | K8: ='3_Forecast'!K64 -> 1.8189894e-12
C10: セグメント売上合計 − 連結売上高 | D10: =IF(AND(ISNUMBER('3_セグメント売上'!D11),ISNUMBER('3_PL'!D6)),'3_セグメント売上'!D11-'3_PL'!D6,"n.a.") -> 0 | E10: =IF(AND(ISNUMBER('3_セグメント売上'!E11),ISNUMBER('3_PL'!E6)),'3_セグメント売上'!E11-'3_PL'!E6,"n.a.") -> 0 | F10: =IF(AND(ISNUMBER('3_セグメント売上'!F11),ISNUMBER('3_PL'!F6)),'3_セグメント売上'!F11-'3_PL'!F6,"n.a.") -> 0 | G10: =IF(AND(ISNUMBER('3_セグメント売上'!G11),ISNUMBER('3_PL'!G6)),'3_セグメント売上'!G11-'3_PL'!G6,"n.a.") -> 0 | H10: =IF(AND(ISNUMBER('3_セグメント売上'!H11),ISNUMBER('3_PL'!H6)),'3_セグメント売上'!H11-'3_PL'!H6,"n.a.") -> 0 | I10: =IF(AND(ISNUMBER('3_セグメント売上'!I11),ISNUMBER('3_Forecast'!I8)),'3_セグメント売上'!I11-'3_Forecast'!I8,"n.a.") -> 0 | J10: =IF(AND(ISNUMBER('3_セグメント売上'!J11),ISNUMBER('3_Forecast'!J8)),'3_セグメント売上'!J11-'3_Forecast'!J8,"n.a.") -> 0 | K10: =IF(AND(ISNUMBER('3_セグメント売上'!K11),ISNUMBER('3_Forecast'!K8)),'3_セグメント売上'!K11-'3_Forecast'!K8,"n.a.") -> 0
C11: 地域別売上合計 − 連結売上高 | D11: =IF(AND(ISNUMBER('3_地域別売上'!D14),ISNUMBER('3_PL'!D6)),'3_地域別売上'!D14-'3_PL'!D6,"n.a.") -> 0 | E11: =IF(AND(ISNUMBER('3_地域別売上'!E14),ISNUMBER('3_PL'!E6)),'3_地域別売上'!E14-'3_PL'!E6,"n.a.") -> 0 | F11: =IF(AND(ISNUMBER('3_地域別売上'!F14),ISNUMBER('3_PL'!F6)),'3_地域別売上'!F14-'3_PL'!F6,"n.a.") -> 0 | G11: =IF(AND(ISNUMBER('3_地域別売上'!G14),ISNUMBER('3_PL'!G6)),'3_地域別売上'!G14-'3_PL'!G6,"n.a.") -> 0 | H11: =IF(AND(ISNUMBER('3_地域別売上'!H14),ISNUMBER('3_PL'!H6)),'3_地域別売上'!H14-'3_PL'!H6,"n.a.") -> 0 | I11: =IF(AND(ISNUMBER('3_地域別売上'!I14),ISNUMBER('3_Forecast'!I8)),'3_地域別売上'!I14-'3_Forecast'!I8,"n.a.") -> 0 | J11: =IF(AND(ISNUMBER('3_地域別売上'!J14),ISNUMBER('3_Forecast'!J8)),'3_地域別売上'!J14-'3_Forecast'!J8,"n.a.") -> 3.6379788e-12 | K11: =IF(AND(ISNUMBER('3_地域別売上'!K14),ISNUMBER('3_Forecast'!K8)),'3_地域別売上'!K14-'3_Forecast'!K8,"n.a.") -> -3.6379788e-12
C15: n.a.：前提不足または計算値のため独立照合不可。0は一致。
C16: 差額の単位は百万。5超を強調。元資料の丸め・範囲差を確認。
C17: CF現金とBS現預金の差を埋めるプラグは作成しません。

Sheet 出典
B1: 出典一覧
B2: 記述の右端「出所」列の ID に対応。一次＝会社開示・公的統計の原本、二次＝それ以外（出所列に「※二次」）
B4: ID | C4: 種別 | D4: 一次/二次 | E4: 発行者 | F4: タイトル | G4: 発行日 | H4: 取得日 | I4: 頁 | J4: URL | K4: 引用（短い）
B5: D0-S1 | C5: 決算短信 | D5: 一次 | E5: Texas Instruments Incorporated (SEC EDGAR) | F5: TI reports third quarter 2026 financial results and shareholder returns (8-K Exhibit 99) | G5: 2026-10-21 | H5: 2026-10-23 | I5: p.4 Consolidated Balance Sheets (Sep 30, 2026); p.3 income statement, p.5-6 supplemental | J5: https://www.sec.gov/Archives/edgar/data/97476/000009747626000165/q32026txnex99-eredgar.htm
B6: D0-S2 | C6: 決算短信 | D6: 一次 | E6: Texas Instruments Incorporated (SEC EDGAR) | F6: Form 10-Q for the quarter ended June 30, 2026 | G6: 2026-07-24 | H6: 2026-10-23 | I6: cover p.1 (shares 913,247,686 at 2026-07-15); Note 4 investments p.10; Note 6 debt p.13 | J6: https://www.sec.gov/Archives/edgar/data/97476/000009747626000152/txn-20260630.htm
B7: D0-S3 | C7: その他 | D7: 一次 | E7: U.S. SEC | F7: SEC EDGAR submissions API for CIK 0000097476 (filing list check: no Q3 2026 10-Q as of 2026-10-23) | G7: 2026-10-23 | H7: 2026-10-23 | I7: recent filings list | J7: https://data.sec.gov/submissions/CIK0000097476.json
B8: D0-S4 | C8: 決算短信 | D8: 一次 | E8: Texas Instruments / SEC | F8: Texas Instruments Form 10-Q（2026-06-30）CHIPS 関連受取債権 流動 $1,005M＋長期 $1,158M | G8: 2026-07-24 | H8: 2026-10-23 | I8: BS 注記（F6-S3 と同一資料） | J8: https://www.sec.gov/cgi-bin/browse-edgar?action=getcompany&CIK=0000097476&type=10-Q
B9: F1-S1 | C9: 有価証券報告書 | D9: 一次 | E9: Texas Instruments / SEC | F9: Texas Instruments Form 10-K FY2025 (Item 1 事業・市場、MD&Aセグメント、セグメント情報、地域別売上) | G9: 2026-02-06 | H9: 2026-10-23 | I9: p.2-8(Item1)、p.9(リスク)、p.21-22(MD&A)、p.32-33(セグメント・地域) | J9: https://www.sec.gov/Archives/edgar/data/97476/000009747626000059/txn-20251231.htm | K9: more than 80% of our revenue was direct
B10: F1-S2 | C10: 決算短信 | D10: 一次 | E10: Texas Instruments / SEC | F10: TI reports third quarter 2026 financial results (8-K Exhibit 99) | G10: 2026-10-21 | H10: 2026-10-23 | I10: p.1-7 | J10: https://www.sec.gov/Archives/edgar/data/97476/000009747626000165/q32026txnex99-eredgar.htm
B11: F1-S3 | C11: 決算短信 | D11: 一次 | E11: Texas Instruments / SEC | F11: Texas Instruments Form 10-Q for the quarter ended 2026-06-30 | G11: 2026-07-24 | H11: 2026-10-23 | I11: p.18-20(事業・製造・MD&A)、Silicon Labs買収注記 | J11: https://www.sec.gov/Archives/edgar/data/97476/000009747626000152/txn-20260630.htm
B12: F1-S4 | C12: 決算短信 | D12: 一次 | E12: Texas Instruments / SEC | F12: TI increases dividend 7% to $1.52 per share (8-K Exhibit 99) | G12: 2026-09-17 | H12: 2026-10-23 | I12: p.1 | J12: https://www.sec.gov/Archives/edgar/data/97476/000095010326014118/dp253473_ex99.htm
B13: F1-S5 | C13: 決算短信 | D13: 一次 | E13: Texas Instruments / Silicon Labs / SEC | F13: Texas Instruments to acquire Silicon Labs (8-K Exhibit 99.1) | G13: 2026-02-04 | H13: 2026-10-23 | I13: p.1-2 | J13: https://www.sec.gov/Archives/edgar/data/97476/000119312526036727/d100130dex991.htm
B14: F1-S6 | C14: 報道 | D14: 二次 | E14: The Motley Fool (決算コール書き起こし、二次) | F14: Texas Instruments (TXN) Q3 2026 Earnings Call Transcript | G14: 2026-10-21 | H14: 2026-10-23 | I14: プリペアド・リマークス、Q&A | J14: https://www.fool.com/earnings/call-transcripts/2026/10/21/texas-instruments-txn-q3-2026-earnings-call-transcript/
B15: F1-S7 | C15: 報道 | D15: 二次 | E15: Boardroom Alpha (SEC提出書類の転載、原本はSilicon Labs 8-K accession 0001193125-26-237879) | F15: Silicon Labs 8-K (HSR待機期間満了) 2026-05-26 ※閲覧は転載ミラー経由 | G15: 2026-05-26 | H15: 2026-10-23 | I15: Item 8.01 | J15: https://www.boardroomalpha.com/sec/slab-8-k-2026-05-26-0001193125-26-237879
B16: F2-S1 | C16: 決算短信 | D16: 一次 | E16: Texas Instruments / SEC | F16: Texas Instruments 8-K Exhibit 99.1 Q3 2026 earnings release | G16: 2026-10-21 | H16: 2026-10-23 | I16: Statements of income, segment table | J16: https://www.sec.gov/Archives/edgar/data/0000097476/000009747626000165/q32026txnex99-eredgar.htm
B17: F2-S2 | C17: 決算短信 | D17: 一次 | E17: Analog Devices / SEC | F17: Analog Devices 8-K Exhibit 99.1 Fiscal Q3 2026 results | G17: 2026-08-19 | H17: 2026-10-23 | I17: Revenue by end market, gross margin | J17: https://www.sec.gov/Archives/edgar/data/0000006281/000000628126000072/adi3q26exhibit991earnings.htm
B18: F2-S3 | C18: 決算短信 | D18: 一次 | E18: Microchip Technology / SEC | F18: Microchip Technology 8-K Exhibit 99.1 Q1 FY2027 results | G18: 2026-08 | H18: 2026-10-23 | I18: Net sales and gross margin table | J18: https://www.sec.gov/Archives/edgar/data/0000827054/000082705426000037/exhibit991q1fy27.htm
B19: F2-S4 | C19: 決算短信 | D19: 二次 | E19: NXP Semiconductors / SEC | F19: NXP Semiconductors 8-K Exhibit 99.1 Q2 2026 results | G19: 2026-07 | H19: 2026-10-23 | I19: Summary table（本文は検索要約で確認、原文の再確認は未） | J19: https://www.sec.gov/Archives/edgar/data/0001413447/000141344726000044/nxp2q26exhibit991.htm
B20: F2-S5 | C20: 決算短信 | D20: 一次 | E20: onsemi / SEC | F20: onsemi 8-K Exhibit 99.1 Q2 2026 results | G20: 2026-08-03 | H20: 2026-10-23 | I20: Revenue and gross margin | J20: https://www.sec.gov/Archives/edgar/data/0001097864/000114036126030989/ef20079200_ex99-1.htm
B21: F2-S6 | C21: 決算短信 | D21: 一次 | E21: STMicroelectronics / SEC | F21: STMicroelectronics Form 6-K Q2 2026 earnings press release | G21: 2026-07-23 | H21: 2026-10-23 | I21: Q2 results, segment table, Q3 outlook | J21: https://www.sec.gov/Archives/edgar/data/0000932787/000093278726000052/c3403c-q226earningspressre.htm
... B23: F2-S8 | C23: 決算説明資料 | D23: 二次 | E23: The Motley Fool ほか（二次） | F23: Texas Instruments Q3 2026 earnings call transcript（要約経由） | G23: 2026-10-21 | H23: 2026-10-23 | I23: Q&A、価格・設備投資・中国の発言（要約。原文の逐語確認は未） | J23: https://www.fool.com/earnings/call-transcripts/2026/10/21/texas-instruments-txn-q3-2026-earnings-call-transcript/
B24: F2-S9 | C24: 報道 | D24: 二次 | E24: TrendForce News | F24: ADI reportedly set to raise prices again in September（流通情報） | G24: 2026-08-13 | H24: 2026-10-23 | J24: https://www.trendforce.com/news/2026/08/13/news-adi-reportedly-set-to-raise-prices-again-on-september-with-military-chips-facing-up-to-30-hike/
B25: F2-S10 | C25: その他 | D25: 二次 | E25: China SCIO（Ministry of Commerce announcement No.27 of 2025 の報道） | F25: China launches anti-dumping probe into certain US analog IC chips | G25: 2025-09-14 | H25: 2026-10-23 | J25: http://english.scio.gov.cn/m/pressroom/2025-09/14/content_118077750.html
B26: F2-S11 | C26: 報道 | D26: 二次 | E26: Infineon press release（転載） | F26: Infineon Q3 FY2026 concluded with record sales driven by strong AI business | G26: 2026-08-05 | H26: 2026-10-23 | J26: https://www.placera.se/pressmeddelanden/infineon-technologies-infineon-technolgies-ag-q3-fy-2026-concluded-with-record-sales-driven-by-strong-ai-business-further-significant-increase-in-revenue-and-margin-expected-in-q4-fy-2026-20260805
B27: F2-S12 | C27: 報道 | D27: 二次 | E27: Evertiq | F27: Infineon opens EUR 5 billion Smart Power Fab in Dresden | G27: 2026-07-02 | H27: 2026-10-23 | J27: https://evertiq.com/design/2026-07-02-infineon-opens-5-billion-smart-power-fab-in-dresden
B28: F2-S13 | C28: 報道 | D28: 二次 | E28: Business Wire（転載。数値は検索要約で確認） | F28: Renesas Reports Financial Results for the Second Quarter Ended June 30, 2026 | G28: 2026-07-30 | H28: 2026-10-23 | J28: https://secure.businesswire.com/news/home/20260730481394/en/Renesas-Reports-Financial-Results-for-the-Second-Quarter-Ended-June-30-2026
B29: F2-S14 | C29: 報道 | D29: 二次 | E29: GlobeNewswire | F29: STMicroelectronics announces timing for third quarter 2026 earnings release | G29: 2026-10-05 | H29: 2026-10-23 | J29: https://www.globenewswire.com/news-release/2026/10/05/3374171/0/en/index.html
B30: F2-S15 | C30: 外部コンサル | D30: 二次 | E30: GM Insights ほか（市場調査サイト、出典不明瞭） | F30: Analog semiconductors market share（TXN約17.8〜19%・ADI約13.5%、情報源間で不一致） | G30: 2025 | H30: 2026-10-23 | J30: https://gminsights.com/industry-analysis/analog-semiconductors-market/market-share
B31: F2-S16 | C31: その他 | D31: 二次 | E31: investment-org context（過去調査、10-K を二次引用） | F31: TXN 製品・戦略・歴史調査（既知） | G31: 2026-10-17 | H31: 2026-10-23 | I31: 300mm、規模の経済の節 | J31: D:\開発用フォルダ\investment-org\context\stocks\TXN_Texas-Instruments\research_20261017_products-strategy-history.md
B32: F3-S1 | C32: その他 | D32: 一次 | E32: Texas Instruments / SEC EDGAR | F32: TI 8-K (Item 5.02) 2020-08-18: Haviv Ilan elected COO | G32: 2020-08-18 | H32: 2026-10-23 | I32: Item 5.02 | J32: https://www.sec.gov/Archives/edgar/data/97476/000119312520223640/d97776d8k.htm
B33: F3-S2 | C33: その他 | D33: 一次 | E33: Texas Instruments / SEC EDGAR | F33: TI 8-K (Item 5.02) 2021-12-07: Ilan elected to Board | G33: 2021-12-07 | H33: 2026-10-23 | I33: Item 5.02 | J33: https://www.sec.gov/Archives/edgar/data/97476/000119312521350324/d444198d8k.htm
B34: F3-S3 | C34: その他 | D34: 一次 | E34: Texas Instruments / SEC EDGAR | F34: TI 8-K (Item 5.02) 2023-01-20: Ilan appointed President and CEO effective 2023-04-01 | G34: 2023-01-20 | H34: 2026-10-23 | I34: Item 5.02 | J34: https://www.sec.gov/Archives/edgar/data/97476/000119312523011991/d398525d8k.htm
B35: F3-S4 | C35: その他 | D35: 一次 | E35: Texas Instruments / SEC EDGAR | F35: TI 8-K (Items 5.02/7.01) 2025-10-16: Templeton to retire 2025-12-31, Ilan to become Chairman | G35: 2025-10-16 | H35: 2026-10-23 | I35: Item 5.02 | J35: https://www.sec.gov/Archives/edgar/data/97476/000095010325013275/dp235861_8k.htm
B36: F3-S5 | C36: その他 | D36: 一次 | E36: Texas Instruments / SEC EDGAR | F36: TI 8-K (Item 5.02) 2026-06-02: Julie Knecht to succeed Rafael Lizardi as CFO effective 2026-08-01 | G36: 2026-06-02 | H36: 2026-10-23 | I36: Item 5.02 | J36: https://www.sec.gov/Archives/edgar/data/97476/000095010326008325/dp247795_8k.htm
B37: F3-S6 | C37: その他 | D37: 一次 | E37: Texas Instruments / SEC EDGAR | F37: TI 8-K (Item 5.02) 2026-03-25: SVP Hagop Kozanian to retire 2026-08-31 | G37: 2026-03-25 | H37: 2026-10-23 | I37: Item 5.02 | J37: https://www.sec.gov/Archives/edgar/data/97476/000119312526124057/d136885d8k.htm
B38: F3-S7 | C38: その他 | D38: 一次 | E38: Texas Instruments / SEC EDGAR | F38: TI 2026 Proxy Statement (DEF 14A) | G38: 2026-03-04 | H38: 2026-10-23 | I38: p.9, 22-32, 46-47, 55-56 | J38: https://www.sec.gov/Archives/edgar/data/97476/000009747626000078/txn-20260303.htm
B39: F3-S8 | C39: その他 | D39: 一次 | E39: Texas Instruments / SEC EDGAR | F39: TI 8-K (Item 5.07) 2026-04-17: 2026 annual meeting vote results | G39: 2026-04-17 | H39: 2026-10-23 | I39: Item 5.07 | J39: https://www.sec.gov/Archives/edgar/data/97476/000009747626000094/txn-20260416.htm
B40: F3-S9 | C40: 有価証券報告書 | D40: 一次 | E40: Texas Instruments / SEC EDGAR | F40: TI Form 10-K FY2025 | G40: 2026-02-06 | H40: 2026-10-23 | I40: Item 1 Strategy; Item 7 MD&A (capex outlook, CHIPS Act) | J40: https://www.sec.gov/Archives/edgar/data/97476/000009747626000059/txn-20251231.htm
B41: F3-S10 | C41: 有価証券報告書 | D41: 一次 | E41: Texas Instruments / SEC EDGAR | F41: TI Form 10-K FY2024 (CHIPS Act expectation; elevated capex) | G41: 2025-02-14 | H41: 2026-10-23 | I41: Item 7 MD&A | J41: https://www.sec.gov/Archives/edgar/data/97476/000009747625000007/txn-20241231.htm
B42: F3-S11 | C42: 有価証券報告書 | D42: 一次 | E42: Texas Instruments / SEC EDGAR | F42: TI Form 10-K FY2021 (capital expenditures to increase) | G42: 2022-02-04 | H42: 2026-10-23 | I42: Item 1 Strategy | J42: https://www.sec.gov/Archives/edgar/data/97476/000009747622000009/txn-20211231.htm
... B49: F3-S18 | C49: 有価証券報告書 | D49: 一次 | E49: SEC EDGAR (data.sec.gov) | F49: SEC XBRL company facts (CIK 0000097476): FY2021-2025 income, cash flow, balance sheet items (自己算出の元データ) | G49: 2026-10-23 | H49: 2026-10-23 | I49: us-gaap tags | J49: https://data.sec.gov/api/xbrl/companyfacts/CIK0000097476.json
B50: F3-S19 | C50: 報道 | D50: 二次 | E50: Yahoo Finance (MarketBeat 要約) | F50: Summary of TI Capital Management call 2026-02-24 (via MarketBeat, Yahoo Finance) - capex $2-3B, FCF/share >$8, inventory 150-250 days, Silicon Labs return criteria | G50: 2026-02-25 | H50: 2026-10-23 | J50: https://finance.yahoo.com/news/texas-instruments-slashes-2026-capex-101721209.html
B51: F3-S20 | C51: 報道 | D51: 二次 | E51: TSI Network | F51: Report on TI off-cycle capital management update: 2026 capex $2-5B, FCF/share $8-12 (TI IR deck itself returned HTTP 403, not retrieved) | G51: 2025-01-20 | H51: 2026-10-23 | J51: https://www.tsinetwork.ca/daily-advice/dividend-stocks/texas-instruments-cuts-spending-boosts-cash-flow-projections-through-2026
B52: F3-S21 | C52: 決算短信 | D52: 一次 | E52: Texas Instruments / SEC EDGAR | F52: TI 8-K 2026-02-04 Ex.99.1: Silicon Labs acquisition announcement ($231/share, EV about $7.5B) | G52: 2026-02-04 | H52: 2026-10-23 | I52: p.1 | J52: https://www.sec.gov/Archives/edgar/data/97476/000119312526036727/d100130dex991.htm
B53: F4-S1 | C53: 決算短信 | D53: 一次 | E53: Texas Instruments / SEC | F53: Texas Instruments 8-K Ex.99 Q3 2026 results (2026-10-21) | G53: 2026-10-21 | H53: 2026-10-23 | I53: pp.1-6 | J53: https://www.sec.gov/Archives/edgar/data/0000097476/000009747626000165/q32026txnex99-eredgar.htm
B54: F4-S2 | C54: 決算説明資料 | D54: 二次 | E54: Motley Fool | F54: TXN Q3 2026 earnings call transcript (Motley Fool, 2026-10-21) | G54: 2026-10-21 | H54: 2026-10-23 | J54: https://www.fool.com/earnings/call-transcripts/2026/10/21/texas-instruments-txn-q3-2026-earnings-call-transcript/
B55: F4-S3 | C55: 報道 | D55: 二次 | E55: Yahoo Finance | F55: Texas Instruments Q3 Earnings Call Highlights (Yahoo Finance) | G55: 2026-10-21 | H55: 2026-10-23 | J55: https://finance.yahoo.com/markets/stocks/articles/texas-instruments-q3-earnings-call-230316199.html
B56: F4-S4 | C56: その他 | D56: 二次 | E56: Yahoo Finance | F56: Yahoo Finance chart API TXN daily price/volume 2021-01-04 to 2026-10-23 | G56: 2026-10-23 | H56: 2026-10-23 | J56: https://query1.finance.yahoo.com/v8/finance/chart/TXN
B57: F4-S5 | C57: 決算短信 | D57: 一次 | E57: Texas Instruments / SEC | F57: Texas Instruments 10-Q for quarter ended 2026-06-30 | G57: 2026-07-24 | H57: 2026-10-23 | I57: Debt note; Note 9 Silicon Labs | J57: https://www.sec.gov/Archives/edgar/data/0000097476/000009747626000152/txn-20260630.htm
